Workbook
Name p_moneda: PARAMETROS!$B$6
Name p_horas_jornada: PARAMETROS!$B$7
Name p_factor_productividad: PARAMETROS!$B$8
Name p_dias_backlog_max: PARAMETROS!$B$11
Name p_dias_backlog_min: PARAMETROS!$B$12
Name p_meta_adherencia: PARAMETROS!$B$13
Name p_meta_ratio_prev_corr: PARAMETROS!$B$14
Name p_ruta_base_checklists: PARAMETROS!$B$16
Name p_top_tareas: PARAMETROS!$B$17
Name p_nombre_empresa: PARAMETROS!$B$4
Name p_nombre_planta: PARAMETROS!$B$5
Name p_dias_laborables_base: PARAMETROS!$B$18
Name p_base_semanal_horas: PARAMETROS!$B$19
Name p_semana_referencia: PARAMETROS!$B$20
Name p_tolerancia_horas_bono: PARAMETROS!$B$21
Name p_anio_presupuesto: PARAMETROS!$B$22
Name p_tolerancia_desviacion_presupuesto: PARAMETROS!$B$23
Name p_fecha_datos: PARAMETROS!$B$24
Name p_meta_pct_predictivo: PARAMETROS!$B$25
Name p_meta_pct_preventivo: PARAMETROS!$B$26
Name p_meta_pct_correctivo_programado: PARAMETROS!$B$27
Name p_meta_pct_emergencia: PARAMETROS!$B$28
Name lista_no_disponible: PARAMETROS!$G$5:$G$6
Name lista_dias: PARAMETROS!$I$5:$I$11
Name lista_tecnicos: TECNICOS!$K$4:$K$19
Name patronHabil: CALENDARIO!$B$5:$B$11
Name cal_fechas: CALENDARIO!$I$5:$I$764
Name cal_habil: CALENDARIO!$J$5:$J$764
Name lista_semanas_plan: PLAN_SEMANAL!$X$3:$X$60
Name lista_turnos: CAT_TURNOS!$G$4:$G$9
Name lista_f_turno: =PARAMETROS!$K$5:INDEX(PARAMETROS!$K$5:$K$24,MAX(1,COUNTIF(PARAMETROS!$K$5:$K$24,"?*")))
Name lista_f_area: =PARAMETROS!$L$5:INDEX(PARAMETROS!$L$5:$L$30,MAX(1,COUNTIF(PARAMETROS!$L$5:$L$30,"?*")))
Name lista_areas: =PARAMETROS!$M$5:INDEX(PARAMETROS!$M$5:$M$29,MAX(1,COUNTIF(PARAMETROS!$M$5:$M$29,"?*")))
Name lista_f_coordinador: =PARAMETROS!$N$5:INDEX(PARAMETROS!$N$5:$N$30,MAX(1,COUNTIF(PARAMETROS!$N$5:$N$30,"?*")))
Name lista_f_subarea: =PARAMETROS!$O$5:INDEX(PARAMETROS!$O$5:$O$30,MAX(1,COUNTIF(PARAMETROS!$O$5:$O$30,"?*")))
Name lista_subareas: =PARAMETROS!$P$5:INDEX(PARAMETROS!$P$5:$P$29,MAX(1,COUNTIF(PARAMETROS!$P$5:$P$29,"?*")))
Name lista_f_especialidad: =PARAMETROS!$Q$5:INDEX(PARAMETROS!$Q$5:$Q$25,MAX(1,COUNTIF(PARAMETROS!$Q$5:$Q$25,"?*")))
Name lista_esp_propias: =PARAMETROS!$R$5:INDEX(PARAMETROS!$R$5:$R$24,MAX(1,COUNTIF(PARAMETROS!$R$5:$R$24,"?*")))
Name lista_ceco: =PARAMETROS!$S$5:INDEX(PARAMETROS!$S$5:$S$29,MAX(1,COUNTIF(PARAMETROS!$S$5:$S$29,"?*")))
Name lista_puestos: =PARAMETROS!$T$5:INDEX(PARAMETROS!$T$5:$T$24,MAX(1,COUNTIF(PARAMETROS!$T$5:$T$24,"?*")))
Name lista_actividades: =PARAMETROS!$U$5:INDEX(PARAMETROS!$U$5:$U$27,MAX(1,COUNTIF(PARAMETROS!$U$5:$U$27,"?*")))
Name lista_tipos_ot: =PARAMETROS!$V$5:INDEX(PARAMETROS!$V$5:$V$24,MAX(1,COUNTIF(PARAMETROS!$V$5:$V$24,"?*")))
Name lista_supervisores: =PARAMETROS!$W$5:INDEX(PARAMETROS!$W$5:$W$22,MAX(1,COUNTIF(PARAMETROS!$W$5:$W$22,"?*")))
Name lista_motivos_ausencia: =PARAMETROS!$X$5:INDEX(PARAMETROS!$X$5:$X$22,MAX(1,COUNTIF(PARAMETROS!$X$5:$X$22,"?*")))
Name lista_meses_dash: DASHBOARD!$X$3:$X$20

Sheet DASHBOARD
A1: ="TABLERO DE MANTENIMIENTO — "&p_nombre_planta&" · "&p_nombre_empresa
A2: Solo lectura: cada indicador se lee de su hoja de origen (botonera de abajo). El selector ofrece el calendario completo, no solo los meses con datos: un mes sin datos sale en BLANCO (blanco = no hay dato; cero = hubo trabajo y no se cumplió). Las metas de mix son convención de industria, NO una norma; se ajustan en PARAMETROS. | X2: meses con datos (validación) — no editar
A3: Mes: | B3: 2026-07 | D3: ="Fecha de datos: "&TEXT(p_fecha_datos,"yyyy-mm-dd")&" · "&IF($B$3=YEAR(p_fecha_datos)&"-"&TEXT(MONTH(p_fecha_datos),"00"),"MES EN CURSO: incluye hasta el "&TEXT(p_fecha_datos-1,"yyyy-mm-dd")&" (ni el día de la fecha de datos ni los posteriores entran)",IF($B$3<YEAR(p_fecha_datos)&"-"&TEXT(MONTH(p_fecha_datos),"00"),"mes cerrado: incluye el mes completo","mes futuro: muestra lo PLANIFICADO del mes completo")) | X3: 2025-10
A4: =HYPERLINK("#PLAN_SEMANAL!A1","▸ PLAN SEMANAL") | C4: =HYPERLINK("#ADHERENCIA!A1","▸ ADHERENCIA") | E4: =HYPERLINK("#PERFIL_HH!A1","▸ PERFIL HH") | G4: =HYPERLINK("#BACKLOG!A1","▸ BACKLOG") | I4: =HYPERLINK("#PRESUPUESTO!A1","▸ PRESUPUESTO") | K4: =HYPERLINK("#ORDENES!A1","▸ ORDENES") | M4: =HYPERLINK("#VALIDACION!A1","▸ VALIDACION") | X4: 2025-11
X5: 2025-12
A6: 1 · ADHERENCIA AL PROGRAMA | G6: 2 · % CARGA DE CAPACIDAD | M6: 3 · SEMANAS DE BACKLOG | X6: 2026-01
A7: =IFERROR(INDEX(ADHERENCIA!$E$134:$E$151,MATCH($B$3,ADHERENCIA!$A$134:$A$151,0)),"") | G7: =IFERROR(INDEX(PERFIL_HH!$L$373:$L$390,MATCH($B$3,PERFIL_HH!$A$373:$A$390,0)),"") | M7: =IFERROR(INDEX(BACKLOG!$F$34:$F$51,MATCH($B$3,BACKLOG!$A$34:$A$51,0)),"") | X7: 2026-02
X8: 2026-03
A9: ="meta "&TEXT(p_meta_adherencia,"0%")&" · REGLA-7, solo días hábiles" | G9: ="capacidad PRODUCTIVA = disponible × "&TEXT(p_factor_productividad,"0%")&" · no es el 100 % del tiempo de presencia" | M9: HH pendientes al corte ÷ capacidad productiva de una semana | X9: 2026-04
A10: origen: ADHERENCIA › MES A MES | G10: origen: PERFIL_HH › MES A MES | M10: origen: BACKLOG › AL CORTE (el detalle por tramos, en la hoja) | X10: 2026-05
X11: 2026-06
A12: 4 · EJECUCIÓN OPEX (acumulada) | G12: 5 · CUMPLIMIENTO DE LUBRICACIÓN | M12: 6 · CUMPLIMIENTO DE CALIBRACIONES | X12: 2026-07
A13: =IF(VALUE(LEFT($B$3,4))<>p_anio_presupuesto,"",IF(SUMPRODUCT(({1,2,3,4,5,6,7,8,9,10,11,12}<=VALUE(RIGHT($B$3,2)))*(PRESUPUESTO!$C$30:$N$30))=0,"",SUMPRODUCT(({1,2,3,4,5,6,7,8,9,10,11,12}<=VALUE(RIGHT($B$3,2)))*(PRESUPUESTO!$C$43:$N$43))/SUMPRODUCT(({1,2,3,4,5,6,7,8,9,10,11,12}<=VALUE(RIGHT($B$3,2)))*(PRESUPUESTO!$C$30:$N$30)))) | G13: =IFERROR(INDEX(ADHERENCIA!$M$134:$M$151,MATCH($B$3,ADHERENCIA!$A$134:$A$151,0)),"") | M13: =IFERROR(INDEX(ADHERENCIA!$I$134:$I$151,MATCH($B$3,ADHERENCIA!$A$134:$A$151,0)),"") | X13: 2026-08
X14: 2026-09
A15: ="real ÷ presupuesto, enero → mes elegido · tolerancia "&TEXT(p_tolerancia_desviacion_presupuesto,"0%") | G15: ="lubricacion cerradas ÷ programadas del mes · vencidas: "&$G$17 | M15: ="calibracion cerradas ÷ programadas del mes · vencidas: "&$M$17 | X15: 2026-10
A16: origen: PRESUPUESTO › filas TOTAL GENERAL | G16: origen: ADHERENCIA › MES A MES (rubro lubricacion) | M16: origen: ADHERENCIA › MES A MES (rubro calibracion) | X16: 2026-11
G17: =IFERROR(INDEX(ADHERENCIA!$N$134:$N$151,MATCH($B$3,ADHERENCIA!$A$134:$A$151,0)),"") | H17: ← lubricacion vencidas al corte (celda de apoyo del semáforo) | M17: =IFERROR(INDEX(ADHERENCIA!$J$134:$J$151,MATCH($B$3,ADHERENCIA!$A$134:$A$151,0)),"") | N17: ← calibracion vencidas al corte (celda de apoyo del semáforo) | X17: 2026-12
X18: 2027-01
X19: 2027-02
X20: 2027-03
J33: C · MIX DE MANTENIMIENTO — real vs meta (la meta se compara contra el % por HORAS)
J34: clase | K34: % real (horas) | L34: % meta | M34: desviación (pp) | N34: % real (conteo) | O34: horas | P34: órdenes
J35: predictivo | K35: =IF(N(IFERROR(INDEX(ADHERENCIA!$AA$134:$AA$151,MATCH($B$3,ADHERENCIA!$A$134:$A$151,0)),""))=0,"",$O35/IFERROR(INDEX(ADHERENCIA!$AA$134:$AA$151,MATCH($B$3,ADHERENCIA!$A$134:$A$151,0)),"")) | L35: =p_meta_pct_predictivo/100 | M35: =IF($K35="","",($K35-$L35)*100) | N35: =IF(N(IFERROR(INDEX(ADHERENCIA!$T$134:$T$151,MATCH($B$3,ADHERENCIA!$A$134:$A$151,0)),""))=0,"",$P35/IFERROR(INDEX(ADHERENCIA!$T$134:$T$151,MATCH($B$3,ADHERENCIA!$A$134:$A$151,0)),"")) | O35: =IFERROR(INDEX(ADHERENCIA!$V$134:$V$151,MATCH($B$3,ADHERENCIA!$A$134:$A$151,0)),"") | P35: =IFERROR(INDEX(ADHERENCIA!$O$134:$O$151,MATCH($B$3,ADHERENCIA!$A$134:$A$151,0)),"")
J36: preventivo | K36: =IF(N(IFERROR(INDEX(ADHERENCIA!$AA$134:$AA$151,MATCH($B$3,ADHERENCIA!$A$134:$A$151,0)),""))=0,"",$O36/IFERROR(INDEX(ADHERENCIA!$AA$134:$AA$151,MATCH($B$3,ADHERENCIA!$A$134:$A$151,0)),"")) | L36: =p_meta_pct_preventivo/100 | M36: =IF($K36="","",($K36-$L36)*100) | N36: =IF(N(IFERROR(INDEX(ADHERENCIA!$T$134:$T$151,MATCH($B$3,ADHERENCIA!$A$134:$A$151,0)),""))=0,"",$P36/IFERROR(INDEX(ADHERENCIA!$T$134:$T$151,MATCH($B$3,ADHERENCIA!$A$134:$A$151,0)),"")) | O36: =IFERROR(INDEX(ADHERENCIA!$W$134:$W$151,MATCH($B$3,ADHERENCIA!$A$134:$A$151,0)),"") | P36: =IFERROR(INDEX(ADHERENCIA!$P$134:$P$151,MATCH($B$3,ADHERENCIA!$A$134:$A$151,0)),"")
J37: correctivo_programado | K37: =IF(N(IFERROR(INDEX(ADHERENCIA!$AA$134:$AA$151,MATCH($B$3,ADHERENCIA!$A$134:$A$151,0)),""))=0,"",$O37/IFERROR(INDEX(ADHERENCIA!$AA$134:$AA$151,MATCH($B$3,ADHERENCIA!$A$134:$A$151,0)),"")) | L37: =p_meta_pct_correctivo_programado/100 | M37: =IF($K37="","",($K37-$L37)*100) | N37: =IF(N(IFERROR(INDEX(ADHERENCIA!$T$134:$T$151,MATCH($B$3,ADHERENCIA!$A$134:$A$151,0)),""))=0,"",$P37/IFERROR(INDEX(ADHERENCIA!$T$134:$T$151,MATCH($B$3,ADHERENCIA!$A$134:$A$151,0)),"")) | O37: =IFERROR(INDEX(ADHERENCIA!$X$134:$X$151,MATCH($B$3,ADHERENCIA!$A$134:$A$151,0)),"") | P37: =IFERROR(INDEX(ADHERENCIA!$Q$134:$Q$151,MATCH($B$3,ADHERENCIA!$A$134:$A$151,0)),"")
J38: emergencia | K38: =IF(N(IFERROR(INDEX(ADHERENCIA!$AA$134:$AA$151,MATCH($B$3,ADHERENCIA!$A$134:$A$151,0)),""))=0,"",$O38/IFERROR(INDEX(ADHERENCIA!$AA$134:$AA$151,MATCH($B$3,ADHERENCIA!$A$134:$A$151,0)),"")) | L38: =p_meta_pct_emergencia/100 | M38: =IF($K38="","",($K38-$L38)*100) | N38: =IF(N(IFERROR(INDEX(ADHERENCIA!$T$134:$T$151,MATCH($B$3,ADHERENCIA!$A$134:$A$151,0)),""))=0,"",$P38/IFERROR(INDEX(ADHERENCIA!$T$134:$T$151,MATCH($B$3,ADHERENCIA!$A$134:$A$151,0)),"")) | O38: =IFERROR(INDEX(ADHERENCIA!$Y$134:$Y$151,MATCH($B$3,ADHERENCIA!$A$134:$A$151,0)),"") | P38: =IFERROR(INDEX(ADHERENCIA!$R$134:$R$151,MATCH($B$3,ADHERENCIA!$A$134:$A$151,0)),"")
J39: SIN CLASIFICAR | K39: =IF(N(IFERROR(INDEX(ADHERENCIA!$AA$134:$AA$151,MATCH($B$3,ADHERENCIA!$A$134:$A$151,0)),""))=0,"",$O39/IFERROR(INDEX(ADHERENCIA!$AA$134:$AA$151,MATCH($B$3,ADHERENCIA!$A$134:$A$151,0)),"")) | L39: =0 | M39: =IF($K39="","",($K39-$L39)*100) | N39: =IF(N(IFERROR(INDEX(ADHERENCIA!$T$134:$T$151,MATCH($B$3,ADHERENCIA!$A$134:$A$151,0)),""))=0,"",$P39/IFERROR(INDEX(ADHERENCIA!$T$134:$T$151,MATCH($B$3,ADHERENCIA!$A$134:$A$151,0)),"")) | O39: =IFERROR(INDEX(ADHERENCIA!$Z$134:$Z$151,MATCH($B$3,ADHERENCIA!$A$134:$A$151,0)),"") | P39: =IFERROR(INDEX(ADHERENCIA!$S$134:$S$151,MATCH($B$3,ADHERENCIA!$A$134:$A$151,0)),"")
J40: TOTAL (control) | K40: =IF(N(IFERROR(INDEX(ADHERENCIA!$AA$134:$AA$151,MATCH($B$3,ADHERENCIA!$A$134:$A$151,0)),""))=0,"",SUM($K$35:$K$39)) | L40: =SUM($L$35:$L$39) | N40: =IF(N(IFERROR(INDEX(ADHERENCIA!$T$134:$T$151,MATCH($B$3,ADHERENCIA!$A$134:$A$151,0)),""))=0,"",SUM($N$35:$N$39)) | O40: =SUM($O$35:$O$39) | P40: =SUM($P$35:$P$39)
J41: DIFERENCIA vs el mes (debe ser 0) | O41: =ROUND($O40-N(IFERROR(INDEX(ADHERENCIA!$AA$134:$AA$151,MATCH($B$3,ADHERENCIA!$A$134:$A$151,0)),"")),6) | P41: =$P40-N(IFERROR(INDEX(ADHERENCIA!$T$134:$T$151,MATCH($B$3,ADHERENCIA!$A$134:$A$151,0)),""))
J42: =PARAMETROS!$B$29
J43: RUBRO (calibración, lubricación) es etiqueta transversal: NO entra en este mix, se mide en sus tarjetas.
A51: BLOQUES DE DATOS DE LOS GRÁFICOS — se leen de las hojas fuente y responden al mes seleccionado. No editar.
A52: A · cumplimiento semanal del mes elegido
A53: semana | B53: adherencia | C53: meta
A54: =IF((DATE(VALUE(LEFT($B$3,4)),VALUE(RIGHT($B$3,2)),1)-WEEKDAY(DATE(VALUE(LEFT($B$3,4)),VALUE(RIGHT($B$3,2)),1),2)+1+0)>DATE(VALUE(LEFT($B$3,4)),VALUE(RIGHT($B$3,2))+1,0),"",YEAR((DATE(VALUE(LEFT($B$3,4)),VALUE(RIGHT($B$3,2)),1)-WEEKDAY(DATE(VALUE(LEFT($B$3,4)),VALUE(RIGHT($B$3,2)),1),2)+1+0)+4-WEEKDAY((DATE(VALUE(LEFT($B$3,4)),VALUE(RIGHT($B$3,2)),1)-WEEKDAY(DATE(VALUE(LEFT($B$3,4)),VALUE(RIGHT($B$3,2)),1),2)+1+0),2))&"-S"&TEXT(_xlfn.ISOWEEKNUM((DATE(VALUE(LEFT($B$3,4)),VALUE(RIGHT($B$3,2)),1)-WEEKDAY(DATE(VALUE(LEFT($B$3,4)),VALUE(RIGHT($B$3,2)),1),2)+1+0)),"00")) | B54: =IF($A54="","",IFERROR(INDEX(ADHERENCIA!$D$5:$D$64,MATCH($A54,ADHERENCIA!$A$5:$A$64,0)),"")) | C54: =IF($A54="","",p_meta_adherencia)
A55: =IF((DATE(VALUE(LEFT($B$3,4)),VALUE(RIGHT($B$3,2)),1)-WEEKDAY(DATE(VALUE(LEFT($B$3,4)),VALUE(RIGHT($B$3,2)),1),2)+1+7)>DATE(VALUE(LEFT($B$3,4)),VALUE(RIGHT($B$3,2))+1,0),"",YEAR((DATE(VALUE(LEFT($B$3,4)),VALUE(RIGHT($B$3,2)),1)-WEEKDAY(DATE(VALUE(LEFT($B$3,4)),VALUE(RIGHT($B$3,2)),1),2)+1+7)+4-WEEKDAY((DATE(VALUE(LEFT($B$3,4)),VALUE(RIGHT($B$3,2)),1)-WEEKDAY(DATE(VALUE(LEFT($B$3,4)),VALUE(RIGHT($B$3,2)),1),2)+1+7),2))&"-S"&TEXT(_xlfn.ISOWEEKNUM((DATE(VALUE(LEFT($B$3,4)),VALUE(RIGHT($B$3,2)),1)-WEEKDAY(DATE(VALUE(LEFT($B$3,4)),VALUE(RIGHT($B$3,2)),1),2)+1+7)),"00")) | B55: =IF($A55="","",IFERROR(INDEX(ADHERENCIA!$D$5:$D$64,MATCH($A55,ADHERENCIA!$A$5:$A$64,0)),"")) | C55: =IF($A55="","",p_meta_adherencia)
A56: =IF((DATE(VALUE(LEFT($B$3,4)),VALUE(RIGHT($B$3,2)),1)-WEEKDAY(DATE(VALUE(LEFT($B$3,4)),VALUE(RIGHT($B$3,2)),1),2)+1+14)>DATE(VALUE(LEFT($B$3,4)),VALUE(RIGHT($B$3,2))+1,0),"",YEAR((DATE(VALUE(LEFT($B$3,4)),VALUE(RIGHT($B$3,2)),1)-WEEKDAY(DATE(VALUE(LEFT($B$3,4)),VALUE(RIGHT($B$3,2)),1),2)+1+14)+4-WEEKDAY((DATE(VALUE(LEFT($B$3,4)),VALUE(RIGHT($B$3,2)),1)-WEEKDAY(DATE(VALUE(LEFT($B$3,4)),VALUE(RIGHT($B$3,2)),1),2)+1+14),2))&"-S"&TEXT(_xlfn.ISOWEEKNUM((DATE(VALUE(LEFT($B$3,4)),VALUE(RIGHT($B$3,2)),1)-WEEKDAY(DATE(VALUE(LEFT($B$3,4)),VALUE(RIGHT($B$3,2)),1),2)+1+14)),"00")) | B56: =IF($A56="","",IFERROR(INDEX(ADHERENCIA!$D$5:$D$64,MATCH($A56,ADHERENCIA!$A$5:$A$64,0)),"")) | C56: =IF($A56="","",p_meta_adherencia)
A57: =IF((DATE(VALUE(LEFT($B$3,4)),VALUE(RIGHT($B$3,2)),1)-WEEKDAY(DATE(VALUE(LEFT($B$3,4)),VALUE(RIGHT($B$3,2)),1),2)+1+21)>DATE(VALUE(LEFT($B$3,4)),VALUE(RIGHT($B$3,2))+1,0),"",YEAR((DATE(VALUE(LEFT($B$3,4)),VALUE(RIGHT($B$3,2)),1)-WEEKDAY(DATE(VALUE(LEFT($B$3,4)),VALUE(RIGHT($B$3,2)),1),2)+1+21)+4-WEEKDAY((DATE(VALUE(LEFT($B$3,4)),VALUE(RIGHT($B$3,2)),1)-WEEKDAY(DATE(VALUE(LEFT($B$3,4)),VALUE(RIGHT($B$3,2)),1),2)+1+21),2))&"-S"&TEXT(_xlfn.ISOWEEKNUM((DATE(VALUE(LEFT($B$3,4)),VALUE(RIGHT($B$3,2)),1)-WEEKDAY(DATE(VALUE(LEFT($B$3,4)),VALUE(RIGHT($B$3,2)),1),2)+1+21)),"00")) | B57: =IF($A57="","",IFERROR(INDEX(ADHERENCIA!$D$5:$D$64,MATCH($A57,ADHERENCIA!$A$5:$A$64,0)),"")) | C57: =IF($A57="","",p_meta_adherencia)
A58: =IF((DATE(VALUE(LEFT($B$3,4)),VALUE(RIGHT($B$3,2)),1)-WEEKDAY(DATE(VALUE(LEFT($B$3,4)),VALUE(RIGHT($B$3,2)),1),2)+1+28)>DATE(VALUE(LEFT($B$3,4)),VALUE(RIGHT($B$3,2))+1,0),"",YEAR((DATE(VALUE(LEFT($B$3,4)),VALUE(RIGHT($B$3,2)),1)-WEEKDAY(DATE(VALUE(LEFT($B$3,4)),VALUE(RIGHT($B$3,2)),1),2)+1+28)+4-WEEKDAY((DATE(VALUE(LEFT($B$3,4)),VALUE(RIGHT($B$3,2)),1)-WEEKDAY(DATE(VALUE(LEFT($B$3,4)),VALUE(RIGHT($B$3,2)),1),2)+1+28),2))&"-S"&TEXT(_xlfn.ISOWEEKNUM((DATE(VALUE(LEFT($B$3,4)),VALUE(RIGHT($B$3,2)),1)-WEEKDAY(DATE(VALUE(LEFT($B$3,4)),VALUE(RIGHT($B$3,2)),1),2)+1+28)),"00")) | B58: =IF($A58="","",IFERROR(INDEX(ADHERENCIA!$D$5:$D$64,MATCH($A58,ADHERENCIA!$A$5:$A$64,0)),"")) | C58: =IF($A58="","",p_meta_adherencia)
A59: =IF((DATE(VALUE(LEFT($B$3,4)),VALUE(RIGHT($B$3,2)),1)-WEEKDAY(DATE(VALUE(LEFT($B$3,4)),VALUE(RIGHT($B$3,2)),1),2)+1+35)>DATE(VALUE(LEFT($B$3,4)),VALUE(RIGHT($B$3,2))+1,0),"",YEAR((DATE(VALUE(LEFT($B$3,4)),VALUE(RIGHT($B$3,2)),1)-WEEKDAY(DATE(VALUE(LEFT($B$3,4)),VALUE(RIGHT($B$3,2)),1),2)+1+35)+4-WEEKDAY((DATE(VALUE(LEFT($B$3,4)),VALUE(RIGHT($B$3,2)),1)-WEEKDAY(DATE(VALUE(LEFT($B$3,4)),VALUE(RIGHT($B$3,2)),1),2)+1+35),2))&"-S"&TEXT(_xlfn.ISOWEEKNUM((DATE(VALUE(LEFT($B$3,4)),VALUE(RIGHT($B$3,2)),1)-WEEKDAY(DATE(VALUE(LEFT($B$3,4)),VALUE(RIGHT($B$3,2)),1),2)+1+35)),"00")) | B59: =IF($A59="","",IFERROR(INDEX(ADHERENCIA!$D$5:$D$64,MATCH($A59,ADHERENCIA!$A$5:$A$64,0)),"")) | C59: =IF($A59="","",p_meta_adherencia)
A60: B · carga vs capacidad productiva por especialidad (agregado; el detalle individual vive en SEGUIMIENTO_HH)
A61: especialidad | B61: planificada | C61: capacidad productiva
A62: MEC | B62: =IFERROR(INDEX(PERFIL_HH!$D$373:$D$390,MATCH($B$3,PERFIL_HH!$A$373:$A$390,0)),"") | C62: =IFERROR(INDEX(PERFIL_HH!$E$373:$E$390,MATCH($B$3,PERFIL_HH!$A$373:$A$390,0)),"")
A63: ELE | B63: =IFERROR(INDEX(PERFIL_HH!$F$373:$F$390,MATCH($B$3,PERFIL_HH!$A$373:$A$390,0)),"") | C63: =IFERROR(INDEX(PERFIL_HH!$G$373:$G$390,MATCH($B$3,PERFIL_HH!$A$373:$A$390,0)),"")
A64: AUT | B64: =IFERROR(INDEX(PERFIL_HH!$H$373:$H$390,MATCH($B$3,PERFIL_HH!$A$373:$A$390,0)),"") | C64: =IFERROR(INDEX(PERFIL_HH!$I$373:$I$390,MATCH($B$3,PERFIL_HH!$A$373:$A$390,0)),"")
A79: D · OPEX plan vs real por mes (fijo y variable) — hasta el mes elegido
A80: mes | B80: plan fijo | C80: plan variable | D80: real fijo | E80: real variable
A81: ene | B81: =IF(1>VALUE(RIGHT($B$3,2)),"",PRESUPUESTO!$C$28) | C81: =IF(1>VALUE(RIGHT($B$3,2)),"",PRESUPUESTO!$C$29) | D81: =IF(1>VALUE(RIGHT($B$3,2)),"",PRESUPUESTO!$C$41) | E81: =IF(1>VALUE(RIGHT($B$3,2)),"",PRESUPUESTO!$C$42)
A82: feb | B82: =IF(2>VALUE(RIGHT($B$3,2)),"",PRESUPUESTO!$D$28) | C82: =IF(2>VALUE(RIGHT($B$3,2)),"",PRESUPUESTO!$D$29) | D82: =IF(2>VALUE(RIGHT($B$3,2)),"",PRESUPUESTO!$D$41) | E82: =IF(2>VALUE(RIGHT($B$3,2)),"",PRESUPUESTO!$D$42)
A83: mar | B83: =IF(3>VALUE(RIGHT($B$3,2)),"",PRESUPUESTO!$E$28) | C83: =IF(3>VALUE(RIGHT($B$3,2)),"",PRESUPUESTO!$E$29) | D83: =IF(3>VALUE(RIGHT($B$3,2)),"",PRESUPUESTO!$E$41) | E83: =IF(3>VALUE(RIGHT($B$3,2)),"",PRESUPUESTO!$E$42)
A84: abr | B84: =IF(4>VALUE(RIGHT($B$3,2)),"",PRESUPUESTO!$F$28) | C84: =IF(4>VALUE(RIGHT($B$3,2)),"",PRESUPUESTO!$F$29) | D84: =IF(4>VALUE(RIGHT($B$3,2)),"",PRESUPUESTO!$F$41) | E84: =IF(4>VALUE(RIGHT($B$3,2)),"",PRESUPUESTO!$F$42)
A85: may | B85: =IF(5>VALUE(RIGHT($B$3,2)),"",PRESUPUESTO!$G$28) | C85: =IF(5>VALUE(RIGHT($B$3,2)),"",PRESUPUESTO!$G$29) | D85: =IF(5>VALUE(RIGHT($B$3,2)),"",PRESUPUESTO!$G$41) | E85: =IF(5>VALUE(RIGHT($B$3,2)),"",PRESUPUESTO!$G$42)
A86: jun | B86: =IF(6>VALUE(RIGHT($B$3,2)),"",PRESUPUESTO!$H$28) | C86: =IF(6>VALUE(RIGHT($B$3,2)),"",PRESUPUESTO!$H$29) | D86: =IF(6>VALUE(RIGHT($B$3,2)),"",PRESUPUESTO!$H$41) | E86: =IF(6>VALUE(RIGHT($B$3,2)),"",PRESUPUESTO!$H$42)
A87: jul | B87: =IF(7>VALUE(RIGHT($B$3,2)),"",PRESUPUESTO!$I$28) | C87: =IF(7>VALUE(RIGHT($B$3,2)),"",PRESUPUESTO!$I$29) | D87: =IF(7>VALUE(RIGHT($B$3,2)),"",PRESUPUESTO!$I$41) | E87: =IF(7>VALUE(RIGHT($B$3,2)),"",PRESUPUESTO!$I$42)
A88: ago | B88: =IF(8>VALUE(RIGHT($B$3,2)),"",PRESUPUESTO!$J$28) | C88: =IF(8>VALUE(RIGHT($B$3,2)),"",PRESUPUESTO!$J$29) | D88: =IF(8>VALUE(RIGHT($B$3,2)),"",PRESUPUESTO!$J$41) | E88: =IF(8>VALUE(RIGHT($B$3,2)),"",PRESUPUESTO!$J$42)
A89: sep | B89: =IF(9>VALUE(RIGHT($B$3,2)),"",PRESUPUESTO!$K$28) | C89: =IF(9>VALUE(RIGHT($B$3,2)),"",PRESUPUESTO!$K$29) | D89: =IF(9>VALUE(RIGHT($B$3,2)),"",PRESUPUESTO!$K$41) | E89: =IF(9>VALUE(RIGHT($B$3,2)),"",PRESUPUESTO!$K$42)
A90: oct | B90: =IF(10>VALUE(RIGHT($B$3,2)),"",PRESUPUESTO!$L$28) | C90: =IF(10>VALUE(RIGHT($B$3,2)),"",PRESUPUESTO!$L$29) | D90: =IF(10>VALUE(RIGHT($B$3,2)),"",PRESUPUESTO!$L$41) | E90: =IF(10>VALUE(RIGHT($B$3,2)),"",PRESUPUESTO!$L$42)
A91: nov | B91: =IF(11>VALUE(RIGHT($B$3,2)),"",PRESUPUESTO!$M$28) | C91: =IF(11>VALUE(RIGHT($B$3,2)),"",PRESUPUESTO!$M$29) | D91: =IF(11>VALUE(RIGHT($B$3,2)),"",PRESUPUESTO!$M$41) | E91: =IF(11>VALUE(RIGHT($B$3,2)),"",PRESUPUESTO!$M$42)
A92: dic | B92: =IF(12>VALUE(RIGHT($B$3,2)),"",PRESUPUESTO!$N$28) | C92: =IF(12>VALUE(RIGHT($B$3,2)),"",PRESUPUESTO!$N$29) | D92: =IF(12>VALUE(RIGHT($B$3,2)),"",PRESUPUESTO!$N$41) | E92: =IF(12>VALUE(RIGHT($B$3,2)),"",PRESUPUESTO!$N$42)
A94: E · lubricación por semana del mes elegido
A95: semana | B95: programadas | C95: cerradas
A96: =IF($A54="","",$A54) | B96: =IF($A96="","",IFERROR(INDEX(ADHERENCIA!$D$155:$D$214,MATCH($A96,ADHERENCIA!$A$155:$A$214,0)),"")) | C96: =IF($A96="","",IFERROR(INDEX(ADHERENCIA!$E$155:$E$214,MATCH($A96,ADHERENCIA!$A$155:$A$214,0)),""))
A97: =IF($A55="","",$A55) | B97: =IF($A97="","",IFERROR(INDEX(ADHERENCIA!$D$155:$D$214,MATCH($A97,ADHERENCIA!$A$155:$A$214,0)),"")) | C97: =IF($A97="","",IFERROR(INDEX(ADHERENCIA!$E$155:$E$214,MATCH($A97,ADHERENCIA!$A$155:$A$214,0)),""))
A98: =IF($A56="","",$A56) | B98: =IF($A98="","",IFERROR(INDEX(ADHERENCIA!$D$155:$D$214,MATCH($A98,ADHERENCIA!$A$155:$A$214,0)),"")) | C98: =IF($A98="","",IFERROR(INDEX(ADHERENCIA!$E$155:$E$214,MATCH($A98,ADHERENCIA!$A$155:$A$214,0)),""))
A99: =IF($A57="","",$A57) | B99: =IF($A99="","",IFERROR(INDEX(ADHERENCIA!$D$155:$D$214,MATCH($A99,ADHERENCIA!$A$155:$A$214,0)),"")) | C99: =IF($A99="","",IFERROR(INDEX(ADHERENCIA!$E$155:$E$214,MATCH($A99,ADHERENCIA!$A$155:$A$214,0)),""))
A100: =IF($A58="","",$A58) | B100: =IF($A100="","",IFERROR(INDEX(ADHERENCIA!$D$155:$D$214,MATCH($A100,ADHERENCIA!$A$155:$A$214,0)),"")) | C100: =IF($A100="","",IFERROR(INDEX(ADHERENCIA!$E$155:$E$214,MATCH($A100,ADHERENCIA!$A$155:$A$214,0)),""))
A101: =IF($A59="","",$A59) | B101: =IF($A101="","",IFERROR(INDEX(ADHERENCIA!$D$155:$D$214,MATCH($A101,ADHERENCIA!$A$155:$A$214,0)),"")) | C101: =IF($A101="","",IFERROR(INDEX(ADHERENCIA!$E$155:$E$214,MATCH($A101,ADHERENCIA!$A$155:$A$214,0)),""))

Sheet INSTRUCTIVO
A1: INSTRUCTIVO — cómo se usa MantPlan
A2: =HYPERLINK("#DASHBOARD!A1","◂ VOLVER AL TABLERO")
A3: Versión 3.6.0 · generado 2026-07-27 · ARCHIVO DE PLANTILLA: trae 8 órdenes de EJEMPLO que hay que borrar.
A6: A. QUÉ ES Y QUÉ NO ES
A7: Sirve para PROGRAMAR y CONTROLAR la semana de mantenimiento: repartir el trabajo entre los técnicos, ver si la carga cabe en las horas disponibles, medir si se cumplió lo programado y seguir el gasto contra el presupuesto.
A8: NO genera órdenes de trabajo: las órdenes salen de su ERP/CMMS y se pegan aquí.
A9: NO sustituye al ERP/CMMS: no guarda historial, no cierra órdenes, no notifica.
A10: NO analiza confiabilidad: no calcula MTBF, MTTR ni criticidad (ver el punto G).
A11: NO gestiona almacén: no conoce stock, reservas ni consumo de repuestos.
A13: B. ANTES DE EMPEZAR — configuración, una sola vez
A14: 1. PARAMETROS — nombre de empresa y planta, moneda, horas de jornada, factor de productividad, metas de adherencia y de mix, y la fecha de datos.
A15: 2. Catálogos (hojas CAT_*, ocultas: clic derecho en una pestaña → Mostrar) — mapee los códigos de SU ERP: centros de costo, puestos de trabajo, actividades, tipos de OT, estados del ERP, supervisores y turnos. Es lo único que hay que traducir.
A16: 3. TECNICOS — reemplace el roster de ejemplo por su gente. `rotativo` = sí si entra al ciclo de turnos; `orden_rotacion` = su posición de arranque (1..N, sin repetir dentro de la misma especialidad y área); `activo` = no lo saca de las listas, de la capacidad y del ciclo sin borrarlo.
A17: 4. CALENDARIO — marque el patrón semanal y cargue feriados y paros de planta.
... A56: MOTOR: las 10 reglas de negocio viven en las fórmulas y no cambian entre empresas. CATÁLOGOS: lo que sí cambia. PARAMETROS: lo que se ajusta. Sin macros, sin enlaces externos y sin ningún código de empresa dentro de una fórmula: por eso adaptarlo a otra planta es editar catálogos, no programar. El detalle de cada decisión está en MANUAL.md, junto al archivo.

Sheet PLAN_SEMANAL
A1: PLAN SEMANAL — el gráfico de carga y la grilla responden a los mismos selectores. "(todos)" desactiva un criterio; "-" significa vacío.
A2: =HYPERLINK("#DASHBOARD!A1","◂ VOLVER AL TABLERO") | P2: datos del gráfico de carga — no editar | X2: semanas con datos (validación) — no editar
A3: semana: | B3: 2026-S31 | C3: día: | D3: (todos) | E3: turno: | F3: (todos) | G3: coordinador: | H3: (todos) | I3: área: | J3: (todos) | K3: especialidad: | L3: (todos) | M3: sub-área: | N3: (todos) | P3: tecnico | Q3: especialidad | R3: etiqueta | S3: hha_seleccion | T3: dentro_capacidad | U3: sobreasignacion | V3: capacidad | X3: (todos)
P4: Carlos Pérez | Q4: MEC | R4: =IF(OR($B$3="(todos)",$D$3="(todos)"),$P4,$P4&" ("&_xlfn.XLOOKUP($B$3&"|"&$D$3&"|"&$P4,tblAsignaciones[clave],tblAsignaciones[turno],"")&")") | S4: =IF(AND($L$3<>"(todos)",$Q4<>$L$3),NA(),SUMIFS(tblOrdenes[horas_efectivas],tblOrdenes[tecnico_asignado],$P4,tblOrdenes[semana],IF($B$3="(todos)","*",$B$3),tblOrdenes[dia_semana],IF($D$3="(todos)","*",$D$3),tblOrdenes[turno_asignado],IF($F$3="(todos)","*",$F$3),tblOrdenes[coordinador],IF($H$3="(todos)","*",$H$3),tblOrdenes[area],IF($J$3="(todos)","*",$J$3),tblOrdenes[sub_area],IF($N$3="(todos)","*",$N$3))) | T4: =IF(ISNA($S4),NA(),MIN($S4,$V4)) | U4: =IF(ISNA($S4),NA(),MAX(0,$S4-$V4)) | V4: =IF(AND($L$3<>"(todos)",$Q4<>$L$3),NA(),p_factor_productividad*SUMIFS(tblAsignaciones[horas_disponibles],tblAsignaciones[tecnico],$P4,tblAsignaciones[semana],IF($B$3="(todos)","*",$B$3),tblAsignaciones[dia],IF($D$3="(todos)","*",$D$3))) | X4: 2025-S51
A5: órdenes: | B5: =COUNTIFS($A$26:$A$1225,IF($B$3="(todos)","*",$B$3),$B$26:$B$1225,IF($D$3="(todos)","*",$D$3),$C$26:$C$1225,IF($F$3="(todos)","*",$F$3),$D$26:$D$1225,IF($H$3="(todos)","*",$H$3),$E$26:$E$1225,IF($J$3="(todos)","*",$J$3),$F$26:$F$1225,IF($L$3="(todos)","*",$L$3),$G$26:$G$1225,IF($N$3="(todos)","*",$N$3)) | C5: HH: | D5: =SUMIFS($L$26:$L$1225,$A$26:$A$1225,IF($B$3="(todos)","*",$B$3),$B$26:$B$1225,IF($D$3="(todos)","*",$D$3),$C$26:$C$1225,IF($F$3="(todos)","*",$F$3),$D$26:$D$1225,IF($H$3="(todos)","*",$H$3),$E$26:$E$1225,IF($J$3="(todos)","*",$J$3),$F$26:$F$1225,IF($L$3="(todos)","*",$L$3),$G$26:$G$1225,IF($N$3="(todos)","*",$N$3)) | P5: María Gómez | Q5: MEC | R5: =IF(OR($B$3="(todos)",$D$3="(todos)"),$P5,$P5&" ("&_xlfn.XLOOKUP($B$3&"|"&$D$3&"|"&$P5,tblAsignaciones[clave],tblAsignaciones[turno],"")&")") | S5: =IF(AND($L$3<>"(todos)",$Q5<>$L$3),NA(),SUMIFS(tblOrdenes[horas_efectivas],tblOrdenes[tecnico_asignado],$P5,tblOrdenes[semana],IF($B$3="(todos)","*",$B$3),tblOrdenes[dia_semana],IF($D$3="(todos)","*",$D$3),tblOrdenes[turno_asignado],IF($F$3="(todos)","*",$F$3),tblOrdenes[coordinador],IF($H$3="(todos)","*",$H$3),tblOrdenes[area],IF($J$3="(todos)","*",$J$3),tblOrdenes[sub_area],IF($N$3="(todos)","*",$N$3))) | T5: =IF(ISNA($S5),NA(),MIN($S5,$V5)) | U5: =IF(ISNA($S5),NA(),MAX(0,$S5-$V5)) | V5: =IF(AND($L$3<>"(todos)",$Q5<>$L$3),NA(),p_factor_productividad*SUMIFS(tblAsignaciones[horas_disponibles],tblAsignaciones[tecnico],$P5,tblAsignaciones[semana],IF($B$3="(todos)","*",$B$3),tblAsignaciones[dia],IF($D$3="(todos)","*",$D$3))) | X5: 2025-S52
P6: Luis Rodríguez | Q6: MEC | R6: =IF(OR($B$3="(todos)",$D$3="(todos)"),$P6,$P6&" ("&_xlfn.XLOOKUP($B$3&"|"&$D$3&"|"&$P6,tblAsignaciones[clave],tblAsignaciones[turno],"")&")") | S6: =IF(AND($L$3<>"(todos)",$Q6<>$L$3),NA(),SUMIFS(tblOrdenes[horas_efectivas],tblOrdenes[tecnico_asignado],$P6,tblOrdenes[semana],IF($B$3="(todos)","*",$B$3),tblOrdenes[dia_semana],IF($D$3="(todos)","*",$D$3),tblOrdenes[turno_asignado],IF($F$3="(todos)","*",$F$3),tblOrdenes[coordinador],IF($H$3="(todos)","*",$H$3),tblOrdenes[area],IF($J$3="(todos)","*",$J$3),tblOrdenes[sub_area],IF($N$3="(todos)","*",$N$3))) | T6: =IF(ISNA($S6),NA(),MIN($S6,$V6)) | U6: =IF(ISNA($S6),NA(),MAX(0,$S6-$V6)) | V6: =IF(AND($L$3<>"(todos)",$Q6<>$L$3),NA(),p_factor_productividad*SUMIFS(tblAsignaciones[horas_disponibles],tblAsignaciones[tecnico],$P6,tblAsignaciones[semana],IF($B$3="(todos)","*",$B$3),tblAsignaciones[dia],IF($D$3="(todos)","*",$D$3))) | X6: 2026-S01
P7: Miguel Martínez | Q7: MEC | R7: =IF(OR($B$3="(todos)",$D$3="(todos)"),$P7,$P7&" ("&_xlfn.XLOOKUP($B$3&"|"&$D$3&"|"&$P7,tblAsignaciones[clave],tblAsignaciones[turno],"")&")") | S7: =IF(AND($L$3<>"(todos)",$Q7<>$L$3),NA(),SUMIFS(tblOrdenes[horas_efectivas],tblOrdenes[tecnico_asignado],$P7,tblOrdenes[semana],IF($B$3="(todos)","*",$B$3),tblOrdenes[dia_semana],IF($D$3="(todos)","*",$D$3),tblOrdenes[turno_asignado],IF($F$3="(todos)","*",$F$3),tblOrdenes[coordinador],IF($H$3="(todos)","*",$H$3),tblOrdenes[area],IF($J$3="(todos)","*",$J$3),tblOrdenes[sub_area],IF($N$3="(todos)","*",$N$3))) | T7: =IF(ISNA($S7),NA(),MIN($S7,$V7)) | U7: =IF(ISNA($S7),NA(),MAX(0,$S7-$V7)) | V7: =IF(AND($L$3<>"(todos)",$Q7<>$L$3),NA(),p_factor_productividad*SUMIFS(tblAsignaciones[horas_disponibles],tblAsignaciones[tecnico],$P7,tblAsignaciones[semana],IF($B$3="(todos)","*",$B$3),tblAsignaciones[dia],IF($D$3="(todos)","*",$D$3))) | X7: 2026-S02
P8: Ana Sánchez | Q8: MEC | R8: =IF(OR($B$3="(todos)",$D$3="(todos)"),$P8,$P8&" ("&_xlfn.XLOOKUP($B$3&"|"&$D$3&"|"&$P8,tblAsignaciones[clave],tblAsignaciones[turno],"")&")") | S8: =IF(AND($L$3<>"(todos)",$Q8<>$L$3),NA(),SUMIFS(tblOrdenes[horas_efectivas],tblOrdenes[tecnico_asignado],$P8,tblOrdenes[semana],IF($B$3="(todos)","*",$B$3),tblOrdenes[dia_semana],IF($D$3="(todos)","*",$D$3),tblOrdenes[turno_asignado],IF($F$3="(todos)","*",$F$3),tblOrdenes[coordinador],IF($H$3="(todos)","*",$H$3),tblOrdenes[area],IF($J$3="(todos)","*",$J$3),tblOrdenes[sub_area],IF($N$3="(todos)","*",$N$3))) | T8: =IF(ISNA($S8),NA(),MIN($S8,$V8)) | U8: =IF(ISNA($S8),NA(),MAX(0,$S8-$V8)) | V8: =IF(AND($L$3<>"(todos)",$Q8<>$L$3),NA(),p_factor_productividad*SUMIFS(tblAsignaciones[horas_disponibles],tblAsignaciones[tecnico],$P8,tblAsignaciones[semana],IF($B$3="(todos)","*",$B$3),tblAsignaciones[dia],IF($D$3="(todos)","*",$D$3))) | X8: 2026-S03
P9: David Torres | Q9: MEC | R9: =IF(OR($B$3="(todos)",$D$3="(todos)"),$P9,$P9&" ("&_xlfn.XLOOKUP($B$3&"|"&$D$3&"|"&$P9,tblAsignaciones[clave],tblAsignaciones[turno],"")&")") | S9: =IF(AND($L$3<>"(todos)",$Q9<>$L$3),NA(),SUMIFS(tblOrdenes[horas_efectivas],tblOrdenes[tecnico_asignado],$P9,tblOrdenes[semana],IF($B$3="(todos)","*",$B$3),tblOrdenes[dia_semana],IF($D$3="(todos)","*",$D$3),tblOrdenes[turno_asignado],IF($F$3="(todos)","*",$F$3),tblOrdenes[coordinador],IF($H$3="(todos)","*",$H$3),tblOrdenes[area],IF($J$3="(todos)","*",$J$3),tblOrdenes[sub_area],IF($N$3="(todos)","*",$N$3))) | T9: =IF(ISNA($S9),NA(),MIN($S9,$V9)) | U9: =IF(ISNA($S9),NA(),MAX(0,$S9-$V9)) | V9: =IF(AND($L$3<>"(todos)",$Q9<>$L$3),NA(),p_factor_productividad*SUMIFS(tblAsignaciones[horas_disponibles],tblAsignaciones[tecnico],$P9,tblAsignaciones[semana],IF($B$3="(todos)","*",$B$3),tblAsignaciones[dia],IF($D$3="(todos)","*",$D$3))) | X9: 2026-S04
P10: Francisco Ramírez | Q10: MEC | R10: =IF(OR($B$3="(todos)",$D$3="(todos)"),$P10,$P10&" ("&_xlfn.XLOOKUP($B$3&"|"&$D$3&"|"&$P10,tblAsignaciones[clave],tblAsignaciones[turno],"")&")") | S10: =IF(AND($L$3<>"(todos)",$Q10<>$L$3),NA(),SUMIFS(tblOrdenes[horas_efectivas],tblOrdenes[tecnico_asignado],$P10,tblOrdenes[semana],IF($B$3="(todos)","*",$B$3),tblOrdenes[dia_semana],IF($D$3="(todos)","*",$D$3),tblOrdenes[turno_asignado],IF($F$3="(todos)","*",$F$3),tblOrdenes[coordinador],IF($H$3="(todos)","*",$H$3),tblOrdenes[area],IF($J$3="(todos)","*",$J$3),tblOrdenes[sub_area],IF($N$3="(todos)","*",$N$3))) | T10: =IF(ISNA($S10),NA(),MIN($S10,$V10)) | U10: =IF(ISNA($S10),NA(),MAX(0,$S10-$V10)) | V10: =IF(AND($L$3<>"(todos)",$Q10<>$L$3),NA(),p_factor_productividad*SUMIFS(tblAsignaciones[horas_disponibles],tblAsignaciones[tecnico],$P10,tblAsignaciones[semana],IF($B$3="(todos)","*",$B$3),tblAsignaciones[dia],IF($D$3="(todos)","*",$D$3))) | X10: 2026-S05
P11: Jorge Díaz | Q11: ELE | R11: =IF(OR($B$3="(todos)",$D$3="(todos)"),$P11,$P11&" ("&_xlfn.XLOOKUP($B$3&"|"&$D$3&"|"&$P11,tblAsignaciones[clave],tblAsignaciones[turno],"")&")") | S11: =IF(AND($L$3<>"(todos)",$Q11<>$L$3),NA(),SUMIFS(tblOrdenes[horas_efectivas],tblOrdenes[tecnico_asignado],$P11,tblOrdenes[semana],IF($B$3="(todos)","*",$B$3),tblOrdenes[dia_semana],IF($D$3="(todos)","*",$D$3),tblOrdenes[turno_asignado],IF($F$3="(todos)","*",$F$3),tblOrdenes[coordinador],IF($H$3="(todos)","*",$H$3),tblOrdenes[area],IF($J$3="(todos)","*",$J$3),tblOrdenes[sub_area],IF($N$3="(todos)","*",$N$3))) | T11: =IF(ISNA($S11),NA(),MIN($S11,$V11)) | U11: =IF(ISNA($S11),NA(),MAX(0,$S11-$V11)) | V11: =IF(AND($L$3<>"(todos)",$Q11<>$L$3),NA(),p_factor_productividad*SUMIFS(tblAsignaciones[horas_disponibles],tblAsignaciones[tecnico],$P11,tblAsignaciones[semana],IF($B$3="(todos)","*",$B$3),tblAsignaciones[dia],IF($D$3="(todos)","*",$D$3))) | X11: 2026-S06
P12: Roberto Castro | Q12: ELE | R12: =IF(OR($B$3="(todos)",$D$3="(todos)"),$P12,$P12&" ("&_xlfn.XLOOKUP($B$3&"|"&$D$3&"|"&$P12,tblAsignaciones[clave],tblAsignaciones[turno],"")&")") | S12: =IF(AND($L$3<>"(todos)",$Q12<>$L$3),NA(),SUMIFS(tblOrdenes[horas_efectivas],tblOrdenes[tecnico_asignado],$P12,tblOrdenes[semana],IF($B$3="(todos)","*",$B$3),tblOrdenes[dia_semana],IF($D$3="(todos)","*",$D$3),tblOrdenes[turno_asignado],IF($F$3="(todos)","*",$F$3),tblOrdenes[coordinador],IF($H$3="(todos)","*",$H$3),tblOrdenes[area],IF($J$3="(todos)","*",$J$3),tblOrdenes[sub_area],IF($N$3="(todos)","*",$N$3))) | T12: =IF(ISNA($S12),NA(),MIN($S12,$V12)) | U12: =IF(ISNA($S12),NA(),MAX(0,$S12-$V12)) | V12: =IF(AND($L$3<>"(todos)",$Q12<>$L$3),NA(),p_factor_productividad*SUMIFS(tblAsignaciones[horas_disponibles],tblAsignaciones[tecnico],$P12,tblAsignaciones[semana],IF($B$3="(todos)","*",$B$3),tblAsignaciones[dia],IF($D$3="(todos)","*",$D$3))) | X12: 2026-S07
P13: Laura Morales | Q13: ELE | R13: =IF(OR($B$3="(todos)",$D$3="(todos)"),$P13,$P13&" ("&_xlfn.XLOOKUP($B$3&"|"&$D$3&"|"&$P13,tblAsignaciones[clave],tblAsignaciones[turno],"")&")") | S13: =IF(AND($L$3<>"(todos)",$Q13<>$L$3),NA(),SUMIFS(tblOrdenes[horas_efectivas],tblOrdenes[tecnico_asignado],$P13,tblOrdenes[semana],IF($B$3="(todos)","*",$B$3),tblOrdenes[dia_semana],IF($D$3="(todos)","*",$D$3),tblOrdenes[turno_asignado],IF($F$3="(todos)","*",$F$3),tblOrdenes[coordinador],IF($H$3="(todos)","*",$H$3),tblOrdenes[area],IF($J$3="(todos)","*",$J$3),tblOrdenes[sub_area],IF($N$3="(todos)","*",$N$3))) | T13: =IF(ISNA($S13),NA(),MIN($S13,$V13)) | U13: =IF(ISNA($S13),NA(),MAX(0,$S13-$V13)) | V13: =IF(AND($L$3<>"(todos)",$Q13<>$L$3),NA(),p_factor_productividad*SUMIFS(tblAsignaciones[horas_disponibles],tblAsignaciones[tecnico],$P13,tblAsignaciones[semana],IF($B$3="(todos)","*",$B$3),tblAsignaciones[dia],IF($D$3="(todos)","*",$D$3))) | X13: 2026-S08
P14: Ricardo Ortiz | Q14: ELE | R14: =IF(OR($B$3="(todos)",$D$3="(todos)"),$P14,$P14&" ("&_xlfn.XLOOKUP($B$3&"|"&$D$3&"|"&$P14,tblAsignaciones[clave],tblAsignaciones[turno],"")&")") | S14: =IF(AND($L$3<>"(todos)",$Q14<>$L$3),NA(),SUMIFS(tblOrdenes[horas_efectivas],tblOrdenes[tecnico_asignado],$P14,tblOrdenes[semana],IF($B$3="(todos)","*",$B$3),tblOrdenes[dia_semana],IF($D$3="(todos)","*",$D$3),tblOrdenes[turno_asignado],IF($F$3="(todos)","*",$F$3),tblOrdenes[coordinador],IF($H$3="(todos)","*",$H$3),tblOrdenes[area],IF($J$3="(todos)","*",$J$3),tblOrdenes[sub_area],IF($N$3="(todos)","*",$N$3))) | T14: =IF(ISNA($S14),NA(),MIN($S14,$V14)) | U14: =IF(ISNA($S14),NA(),MAX(0,$S14-$V14)) | V14: =IF(AND($L$3<>"(todos)",$Q14<>$L$3),NA(),p_factor_productividad*SUMIFS(tblAsignaciones[horas_disponibles],tblAsignaciones[tecnico],$P14,tblAsignaciones[semana],IF($B$3="(todos)","*",$B$3),tblAsignaciones[dia],IF($D$3="(todos)","*",$D$3))) | X14: 2026-S09
P15: Eduardo Silva | Q15: ELE | R15: =IF(OR($B$3="(todos)",$D$3="(todos)"),$P15,$P15&" ("&_xlfn.XLOOKUP($B$3&"|"&$D$3&"|"&$P15,tblAsignaciones[clave],tblAsignaciones[turno],"")&")") | S15: =IF(AND($L$3<>"(todos)",$Q15<>$L$3),NA(),SUMIFS(tblOrdenes[horas_efectivas],tblOrdenes[tecnico_asignado],$P15,tblOrdenes[semana],IF($B$3="(todos)","*",$B$3),tblOrdenes[dia_semana],IF($D$3="(todos)","*",$D$3),tblOrdenes[turno_asignado],IF($F$3="(todos)","*",$F$3),tblOrdenes[coordinador],IF($H$3="(todos)","*",$H$3),tblOrdenes[area],IF($J$3="(todos)","*",$J$3),tblOrdenes[sub_area],IF($N$3="(todos)","*",$N$3))) | T15: =IF(ISNA($S15),NA(),MIN($S15,$V15)) | U15: =IF(ISNA($S15),NA(),MAX(0,$S15-$V15)) | V15: =IF(AND($L$3<>"(todos)",$Q15<>$L$3),NA(),p_factor_productividad*SUMIFS(tblAsignaciones[horas_disponibles],tblAsignaciones[tecnico],$P15,tblAsignaciones[semana],IF($B$3="(todos)","*",$B$3),tblAsignaciones[dia],IF($D$3="(todos)","*",$D$3))) | X15: 2026-S10
P16: Gabriela Rojas | Q16: ELE | R16: =IF(OR($B$3="(todos)",$D$3="(todos)"),$P16,$P16&" ("&_xlfn.XLOOKUP($B$3&"|"&$D$3&"|"&$P16,tblAsignaciones[clave],tblAsignaciones[turno],"")&")") | S16: =IF(AND($L$3<>"(todos)",$Q16<>$L$3),NA(),SUMIFS(tblOrdenes[horas_efectivas],tblOrdenes[tecnico_asignado],$P16,tblOrdenes[semana],IF($B$3="(todos)","*",$B$3),tblOrdenes[dia_semana],IF($D$3="(todos)","*",$D$3),tblOrdenes[turno_asignado],IF($F$3="(todos)","*",$F$3),tblOrdenes[coordinador],IF($H$3="(todos)","*",$H$3),tblOrdenes[area],IF($J$3="(todos)","*",$J$3),tblOrdenes[sub_area],IF($N$3="(todos)","*",$N$3))) | T16: =IF(ISNA($S16),NA(),MIN($S16,$V16)) | U16: =IF(ISNA($S16),NA(),MAX(0,$S16-$V16)) | V16: =IF(AND($L$3<>"(todos)",$Q16<>$L$3),NA(),p_factor_productividad*SUMIFS(tblAsignaciones[horas_disponibles],tblAsignaciones[tecnico],$P16,tblAsignaciones[semana],IF($B$3="(todos)","*",$B$3),tblAsignaciones[dia],IF($D$3="(todos)","*",$D$3))) | X16: 2026-S11
P17: Fernando Mendoza | Q17: ELE | R17: =IF(OR($B$3="(todos)",$D$3="(todos)"),$P17,$P17&" ("&_xlfn.XLOOKUP($B$3&"|"&$D$3&"|"&$P17,tblAsignaciones[clave],tblAsignaciones[turno],"")&")") | S17: =IF(AND($L$3<>"(todos)",$Q17<>$L$3),NA(),SUMIFS(tblOrdenes[horas_efectivas],tblOrdenes[tecnico_asignado],$P17,tblOrdenes[semana],IF($B$3="(todos)","*",$B$3),tblOrdenes[dia_semana],IF($D$3="(todos)","*",$D$3),tblOrdenes[turno_asignado],IF($F$3="(todos)","*",$F$3),tblOrdenes[coordinador],IF($H$3="(todos)","*",$H$3),tblOrdenes[area],IF($J$3="(todos)","*",$J$3),tblOrdenes[sub_area],IF($N$3="(todos)","*",$N$3))) | T17: =IF(ISNA($S17),NA(),MIN($S17,$V17)) | U17: =IF(ISNA($S17),NA(),MAX(0,$S17-$V17)) | V17: =IF(AND($L$3<>"(todos)",$Q17<>$L$3),NA(),p_factor_productividad*SUMIFS(tblAsignaciones[horas_disponibles],tblAsignaciones[tecnico],$P17,tblAsignaciones[semana],IF($B$3="(todos)","*",$B$3),tblAsignaciones[dia],IF($D$3="(todos)","*",$D$3))) | X17: 2026-S12
... P19: Daniela Medina | Q19: AUT | R19: =IF(OR($B$3="(todos)",$D$3="(todos)"),$P19,$P19&" ("&_xlfn.XLOOKUP($B$3&"|"&$D$3&"|"&$P19,tblAsignaciones[clave],tblAsignaciones[turno],"")&")") | S19: =IF(AND($L$3<>"(todos)",$Q19<>$L$3),NA(),SUMIFS(tblOrdenes[horas_efectivas],tblOrdenes[tecnico_asignado],$P19,tblOrdenes[semana],IF($B$3="(todos)","*",$B$3),tblOrdenes[dia_semana],IF($D$3="(todos)","*",$D$3),tblOrdenes[turno_asignado],IF($F$3="(todos)","*",$F$3),tblOrdenes[coordinador],IF($H$3="(todos)","*",$H$3),tblOrdenes[area],IF($J$3="(todos)","*",$J$3),tblOrdenes[sub_area],IF($N$3="(todos)","*",$N$3))) | T19: =IF(ISNA($S19),NA(),MIN($S19,$V19)) | U19: =IF(ISNA($S19),NA(),MAX(0,$S19-$V19)) | V19: =IF(AND($L$3<>"(todos)",$Q19<>$L$3),NA(),p_factor_productividad*SUMIFS(tblAsignaciones[horas_disponibles],tblAsignaciones[tecnico],$P19,tblAsignaciones[semana],IF($B$3="(todos)","*",$B$3),tblAsignaciones[dia],IF($D$3="(todos)","*",$D$3))) | X19: 2026-S14
X20: 2026-S15
X21: 2026-S16
X22: 2026-S17
X23: 2026-S18
X24: 2026-S19
A25: semana | B25: dia | C25: turno | D25: coordinador | E25: area | F25: especialidad | G25: sub_area | H25: tecnico | I25: id_operacion | J25: descripcion_operacion | K25: equipo | L25: horas | M25: estado | N25: en_plan | X25: 2026-S20
A26: =IF('ORDENES'!$A4="","",IF('ORDENES'!$O4="","-",'ORDENES'!$O4)) | B26: =IF('ORDENES'!$A4="","",IF('ORDENES'!$S4="","-",'ORDENES'!$S4)) | C26: =IF('ORDENES'!$A4="","",IF('ORDENES'!$AI4="","-",'ORDENES'!$AI4)) | D26: =IF('ORDENES'!$A4="","",IF('ORDENES'!$AA4="","-",'ORDENES'!$AA4)) | E26: =IF('ORDENES'!$A4="","",IF('ORDENES'!$Y4="","-",'ORDENES'!$Y4)) | F26: =IF('ORDENES'!$A4="","",IF('ORDENES'!$AB4="","-",'ORDENES'!$AB4)) | G26: =IF('ORDENES'!$A4="","",IF('ORDENES'!$Z4="","-",'ORDENES'!$Z4)) | H26: =IF('ORDENES'!$A4="","",IF('ORDENES'!$AH4="","-",'ORDENES'!$AH4)) | I26: =IF('ORDENES'!$A4="","",IF('ORDENES'!$AU4="","-",'ORDENES'!$AU4)) | J26: =IF('ORDENES'!$A4="","",IF('ORDENES'!$D4="","-",'ORDENES'!$D4)) | K26: =IF('ORDENES'!$A4="","",IF('ORDENES'!$E4="","-",'ORDENES'!$E4)) | L26: =IF('ORDENES'!$A4="","",IF('ORDENES'!$M4="",0,'ORDENES'!$M4)) | M26: =IF('ORDENES'!$A4="","",IF('ORDENES'!$N4="","-",'ORDENES'!$N4)) | N26: =IF('ORDENES'!$A4="","",'ORDENES'!$AG4) | X26: 2026-S21
A27: =IF('ORDENES'!$A5="","",IF('ORDENES'!$O5="","-",'ORDENES'!$O5)) | B27: =IF('ORDENES'!$A5="","",IF('ORDENES'!$S5="","-",'ORDENES'!$S5)) | C27: =IF('ORDENES'!$A5="","",IF('ORDENES'!$AI5="","-",'ORDENES'!$AI5)) | D27: =IF('ORDENES'!$A5="","",IF('ORDENES'!$AA5="","-",'ORDENES'!$AA5)) | E27: =IF('ORDENES'!$A5="","",IF('ORDENES'!$Y5="","-",'ORDENES'!$Y5)) | F27: =IF('ORDENES'!$A5="","",IF('ORDENES'!$AB5="","-",'ORDENES'!$AB5)) | G27: =IF('ORDENES'!$A5="","",IF('ORDENES'!$Z5="","-",'ORDENES'!$Z5)) | H27: =IF('ORDENES'!$A5="","",IF('ORDENES'!$AH5="","-",'ORDENES'!$AH5)) | I27: =IF('ORDENES'!$A5="","",IF('ORDENES'!$AU5="","-",'ORDENES'!$AU5)) | J27: =IF('ORDENES'!$A5="","",IF('ORDENES'!$D5="","-",'ORDENES'!$D5)) | K27: =IF('ORDENES'!$A5="","",IF('ORDENES'!$E5="","-",'ORDENES'!$E5)) | L27: =IF('ORDENES'!$A5="","",IF('ORDENES'!$M5="",0,'ORDENES'!$M5)) | M27: =IF('ORDENES'!$A5="","",IF('ORDENES'!$N5="","-",'ORDENES'!$N5)) | N27: =IF('ORDENES'!$A5="","",'ORDENES'!$AG5) | X27: 2026-S22
A28: =IF('ORDENES'!$A6="","",IF('ORDENES'!$O6="","-",'ORDENES'!$O6)) | B28: =IF('ORDENES'!$A6="","",IF('ORDENES'!$S6="","-",'ORDENES'!$S6)) | C28: =IF('ORDENES'!$A6="","",IF('ORDENES'!$AI6="","-",'ORDENES'!$AI6)) | D28: =IF('ORDENES'!$A6="","",IF('ORDENES'!$AA6="","-",'ORDENES'!$AA6)) | E28: =IF('ORDENES'!$A6="","",IF('ORDENES'!$Y6="","-",'ORDENES'!$Y6)) | F28: =IF('ORDENES'!$A6="","",IF('ORDENES'!$AB6="","-",'ORDENES'!$AB6)) | G28: =IF('ORDENES'!$A6="","",IF('ORDENES'!$Z6="","-",'ORDENES'!$Z6)) | H28: =IF('ORDENES'!$A6="","",IF('ORDENES'!$AH6="","-",'ORDENES'!$AH6)) | I28: =IF('ORDENES'!$A6="","",IF('ORDENES'!$AU6="","-",'ORDENES'!$AU6)) | J28: =IF('ORDENES'!$A6="","",IF('ORDENES'!$D6="","-",'ORDENES'!$D6)) | K28: =IF('ORDENES'!$A6="","",IF('ORDENES'!$E6="","-",'ORDENES'!$E6)) | L28: =IF('ORDENES'!$A6="","",IF('ORDENES'!$M6="",0,'ORDENES'!$M6)) | M28: =IF('ORDENES'!$A6="","",IF('ORDENES'!$N6="","-",'ORDENES'!$N6)) | N28: =IF('ORDENES'!$A6="","",'ORDENES'!$AG6) | X28: 2026-S23
A29: =IF('ORDENES'!$A7="","",IF('ORDENES'!$O7="","-",'ORDENES'!$O7)) | B29: =IF('ORDENES'!$A7="","",IF('ORDENES'!$S7="","-",'ORDENES'!$S7)) | C29: =IF('ORDENES'!$A7="","",IF('ORDENES'!$AI7="","-",'ORDENES'!$AI7)) | D29: =IF('ORDENES'!$A7="","",IF('ORDENES'!$AA7="","-",'ORDENES'!$AA7)) | E29: =IF('ORDENES'!$A7="","",IF('ORDENES'!$Y7="","-",'ORDENES'!$Y7)) | F29: =IF('ORDENES'!$A7="","",IF('ORDENES'!$AB7="","-",'ORDENES'!$AB7)) | G29: =IF('ORDENES'!$A7="","",IF('ORDENES'!$Z7="","-",'ORDENES'!$Z7)) | H29: =IF('ORDENES'!$A7="","",IF('ORDENES'!$AH7="","-",'ORDENES'!$AH7)) | I29: =IF('ORDENES'!$A7="","",IF('ORDENES'!$AU7="","-",'ORDENES'!$AU7)) | J29: =IF('ORDENES'!$A7="","",IF('ORDENES'!$D7="","-",'ORDENES'!$D7)) | K29: =IF('ORDENES'!$A7="","",IF('ORDENES'!$E7="","-",'ORDENES'!$E7)) | L29: =IF('ORDENES'!$A7="","",IF('ORDENES'!$M7="",0,'ORDENES'!$M7)) | M29: =IF('ORDENES'!$A7="","",IF('ORDENES'!$N7="","-",'ORDENES'!$N7)) | N29: =IF('ORDENES'!$A7="","",'ORDENES'!$AG7) | X29: 2026-S24
A30: =IF('ORDENES'!$A8="","",IF('ORDENES'!$O8="","-",'ORDENES'!$O8)) | B30: =IF('ORDENES'!$A8="","",IF('ORDENES'!$S8="","-",'ORDENES'!$S8)) | C30: =IF('ORDENES'!$A8="","",IF('ORDENES'!$AI8="","-",'ORDENES'!$AI8)) | D30: =IF('ORDENES'!$A8="","",IF('ORDENES'!$AA8="","-",'ORDENES'!$AA8)) | E30: =IF('ORDENES'!$A8="","",IF('ORDENES'!$Y8="","-",'ORDENES'!$Y8)) | F30: =IF('ORDENES'!$A8="","",IF('ORDENES'!$AB8="","-",'ORDENES'!$AB8)) | G30: =IF('ORDENES'!$A8="","",IF('ORDENES'!$Z8="","-",'ORDENES'!$Z8)) | H30: =IF('ORDENES'!$A8="","",IF('ORDENES'!$AH8="","-",'ORDENES'!$AH8)) | I30: =IF('ORDENES'!$A8="","",IF('ORDENES'!$AU8="","-",'ORDENES'!$AU8)) | J30: =IF('ORDENES'!$A8="","",IF('ORDENES'!$D8="","-",'ORDENES'!$D8)) | K30: =IF('ORDENES'!$A8="","",IF('ORDENES'!$E8="","-",'ORDENES'!$E8)) | L30: =IF('ORDENES'!$A8="","",IF('ORDENES'!$M8="",0,'ORDENES'!$M8)) | M30: =IF('ORDENES'!$A8="","",IF('ORDENES'!$N8="","-",'ORDENES'!$N8)) | N30: =IF('ORDENES'!$A8="","",'ORDENES'!$AG8) | X30: 2026-S25
A31: =IF('ORDENES'!$A9="","",IF('ORDENES'!$O9="","-",'ORDENES'!$O9)) | B31: =IF('ORDENES'!$A9="","",IF('ORDENES'!$S9="","-",'ORDENES'!$S9)) | C31: =IF('ORDENES'!$A9="","",IF('ORDENES'!$AI9="","-",'ORDENES'!$AI9)) | D31: =IF('ORDENES'!$A9="","",IF('ORDENES'!$AA9="","-",'ORDENES'!$AA9)) | E31: =IF('ORDENES'!$A9="","",IF('ORDENES'!$Y9="","-",'ORDENES'!$Y9)) | F31: =IF('ORDENES'!$A9="","",IF('ORDENES'!$AB9="","-",'ORDENES'!$AB9)) | G31: =IF('ORDENES'!$A9="","",IF('ORDENES'!$Z9="","-",'ORDENES'!$Z9)) | H31: =IF('ORDENES'!$A9="","",IF('ORDENES'!$AH9="","-",'ORDENES'!$AH9)) | I31: =IF('ORDENES'!$A9="","",IF('ORDENES'!$AU9="","-",'ORDENES'!$AU9)) | J31: =IF('ORDENES'!$A9="","",IF('ORDENES'!$D9="","-",'ORDENES'!$D9)) | K31: =IF('ORDENES'!$A9="","",IF('ORDENES'!$E9="","-",'ORDENES'!$E9)) | L31: =IF('ORDENES'!$A9="","",IF('ORDENES'!$M9="",0,'ORDENES'!$M9)) | M31: =IF('ORDENES'!$A9="","",IF('ORDENES'!$N9="","-",'ORDENES'!$N9)) | N31: =IF('ORDENES'!$A9="","",'ORDENES'!$AG9) | X31: 2026-S26
A32: =IF('ORDENES'!$A10="","",IF('ORDENES'!$O10="","-",'ORDENES'!$O10)) | B32: =IF('ORDENES'!$A10="","",IF('ORDENES'!$S10="","-",'ORDENES'!$S10)) | C32: =IF('ORDENES'!$A10="","",IF('ORDENES'!$AI10="","-",'ORDENES'!$AI10)) | D32: =IF('ORDENES'!$A10="","",IF('ORDENES'!$AA10="","-",'ORDENES'!$AA10)) | E32: =IF('ORDENES'!$A10="","",IF('ORDENES'!$Y10="","-",'ORDENES'!$Y10)) | F32: =IF('ORDENES'!$A10="","",IF('ORDENES'!$AB10="","-",'ORDENES'!$AB10)) | G32: =IF('ORDENES'!$A10="","",IF('ORDENES'!$Z10="","-",'ORDENES'!$Z10)) | H32: =IF('ORDENES'!$A10="","",IF('ORDENES'!$AH10="","-",'ORDENES'!$AH10)) | I32: =IF('ORDENES'!$A10="","",IF('ORDENES'!$AU10="","-",'ORDENES'!$AU10)) | J32: =IF('ORDENES'!$A10="","",IF('ORDENES'!$D10="","-",'ORDENES'!$D10)) | K32: =IF('ORDENES'!$A10="","",IF('ORDENES'!$E10="","-",'ORDENES'!$E10)) | L32: =IF('ORDENES'!$A10="","",IF('ORDENES'!$M10="",0,'ORDENES'!$M10)) | M32: =IF('ORDENES'!$A10="","",IF('ORDENES'!$N10="","-",'ORDENES'!$N10)) | N32: =IF('ORDENES'!$A10="","",'ORDENES'!$AG10) | X32: 2026-S27
A33: =IF('ORDENES'!$A11="","",IF('ORDENES'!$O11="","-",'ORDENES'!$O11)) | B33: =IF('ORDENES'!$A11="","",IF('ORDENES'!$S11="","-",'ORDENES'!$S11)) | C33: =IF('ORDENES'!$A11="","",IF('ORDENES'!$AI11="","-",'ORDENES'!$AI11)) | D33: =IF('ORDENES'!$A11="","",IF('ORDENES'!$AA11="","-",'ORDENES'!$AA11)) | E33: =IF('ORDENES'!$A11="","",IF('ORDENES'!$Y11="","-",'ORDENES'!$Y11)) | F33: =IF('ORDENES'!$A11="","",IF('ORDENES'!$AB11="","-",'ORDENES'!$AB11)) | G33: =IF('ORDENES'!$A11="","",IF('ORDENES'!$Z11="","-",'ORDENES'!$Z11)) | H33: =IF('ORDENES'!$A11="","",IF('ORDENES'!$AH11="","-",'ORDENES'!$AH11)) | I33: =IF('ORDENES'!$A11="","",IF('ORDENES'!$AU11="","-",'ORDENES'!$AU11)) | J33: =IF('ORDENES'!$A11="","",IF('ORDENES'!$D11="","-",'ORDENES'!$D11)) | K33: =IF('ORDENES'!$A11="","",IF('ORDENES'!$E11="","-",'ORDENES'!$E11)) | L33: =IF('ORDENES'!$A11="","",IF('ORDENES'!$M11="",0,'ORDENES'!$M11)) | M33: =IF('ORDENES'!$A11="","",IF('ORDENES'!$N11="","-",'ORDENES'!$N11)) | N33: =IF('ORDENES'!$A11="","",'ORDENES'!$AG11) | X33: 2026-S28
A34: =IF('ORDENES'!$A12="","",IF('ORDENES'!$O12="","-",'ORDENES'!$O12)) | B34: =IF('ORDENES'!$A12="","",IF('ORDENES'!$S12="","-",'ORDENES'!$S12)) | C34: =IF('ORDENES'!$A12="","",IF('ORDENES'!$AI12="","-",'ORDENES'!$AI12)) | D34: =IF('ORDENES'!$A12="","",IF('ORDENES'!$AA12="","-",'ORDENES'!$AA12)) | E34: =IF('ORDENES'!$A12="","",IF('ORDENES'!$Y12="","-",'ORDENES'!$Y12)) | F34: =IF('ORDENES'!$A12="","",IF('ORDENES'!$AB12="","-",'ORDENES'!$AB12)) | G34: =IF('ORDENES'!$A12="","",IF('ORDENES'!$Z12="","-",'ORDENES'!$Z12)) | H34: =IF('ORDENES'!$A12="","",IF('ORDENES'!$AH12="","-",'ORDENES'!$AH12)) | I34: =IF('ORDENES'!$A12="","",IF('ORDENES'!$AU12="","-",'ORDENES'!$AU12)) | J34: =IF('ORDENES'!$A12="","",IF('ORDENES'!$D12="","-",'ORDENES'!$D12)) | K34: =IF('ORDENES'!$A12="","",IF('ORDENES'!$E12="","-",'ORDENES'!$E12)) | L34: =IF('ORDENES'!$A12="","",IF('ORDENES'!$M12="",0,'ORDENES'!$M12)) | M34: =IF('ORDENES'!$A12="","",IF('ORDENES'!$N12="","-",'ORDENES'!$N12)) | N34: =IF('ORDENES'!$A12="","",'ORDENES'!$AG12) | X34: 2026-S29
A35: =IF('ORDENES'!$A13="","",IF('ORDENES'!$O13="","-",'ORDENES'!$O13)) | B35: =IF('ORDENES'!$A13="","",IF('ORDENES'!$S13="","-",'ORDENES'!$S13)) | C35: =IF('ORDENES'!$A13="","",IF('ORDENES'!$AI13="","-",'ORDENES'!$AI13)) | D35: =IF('ORDENES'!$A13="","",IF('ORDENES'!$AA13="","-",'ORDENES'!$AA13)) | E35: =IF('ORDENES'!$A13="","",IF('ORDENES'!$Y13="","-",'ORDENES'!$Y13)) | F35: =IF('ORDENES'!$A13="","",IF('ORDENES'!$AB13="","-",'ORDENES'!$AB13)) | G35: =IF('ORDENES'!$A13="","",IF('ORDENES'!$Z13="","-",'ORDENES'!$Z13)) | H35: =IF('ORDENES'!$A13="","",IF('ORDENES'!$AH13="","-",'ORDENES'!$AH13)) | I35: =IF('ORDENES'!$A13="","",IF('ORDENES'!$AU13="","-",'ORDENES'!$AU13)) | J35: =IF('ORDENES'!$A13="","",IF('ORDENES'!$D13="","-",'ORDENES'!$D13)) | K35: =IF('ORDENES'!$A13="","",IF('ORDENES'!$E13="","-",'ORDENES'!$E13)) | L35: =IF('ORDENES'!$A13="","",IF('ORDENES'!$M13="",0,'ORDENES'!$M13)) | M35: =IF('ORDENES'!$A13="","",IF('ORDENES'!$N13="","-",'ORDENES'!$N13)) | N35: =IF('ORDENES'!$A13="","",'ORDENES'!$AG13) | X35: 2026-S30
A36: =IF('ORDENES'!$A14="","",IF('ORDENES'!$O14="","-",'ORDENES'!$O14)) | B36: =IF('ORDENES'!$A14="","",IF('ORDENES'!$S14="","-",'ORDENES'!$S14)) | C36: =IF('ORDENES'!$A14="","",IF('ORDENES'!$AI14="","-",'ORDENES'!$AI14)) | D36: =IF('ORDENES'!$A14="","",IF('ORDENES'!$AA14="","-",'ORDENES'!$AA14)) | E36: =IF('ORDENES'!$A14="","",IF('ORDENES'!$Y14="","-",'ORDENES'!$Y14)) | F36: =IF('ORDENES'!$A14="","",IF('ORDENES'!$AB14="","-",'ORDENES'!$AB14)) | G36: =IF('ORDENES'!$A14="","",IF('ORDENES'!$Z14="","-",'ORDENES'!$Z14)) | H36: =IF('ORDENES'!$A14="","",IF('ORDENES'!$AH14="","-",'ORDENES'!$AH14)) | I36: =IF('ORDENES'!$A14="","",IF('ORDENES'!$AU14="","-",'ORDENES'!$AU14)) | J36: =IF('ORDENES'!$A14="","",IF('ORDENES'!$D14="","-",'ORDENES'!$D14)) | K36: =IF('ORDENES'!$A14="","",IF('ORDENES'!$E14="","-",'ORDENES'!$E14)) | L36: =IF('ORDENES'!$A14="","",IF('ORDENES'!$M14="",0,'ORDENES'!$M14)) | M36: =IF('ORDENES'!$A14="","",IF('ORDENES'!$N14="","-",'ORDENES'!$N14)) | N36: =IF('ORDENES'!$A14="","",'ORDENES'!$AG14) | X36: 2026-S31
A37: =IF('ORDENES'!$A15="","",IF('ORDENES'!$O15="","-",'ORDENES'!$O15)) | B37: =IF('ORDENES'!$A15="","",IF('ORDENES'!$S15="","-",'ORDENES'!$S15)) | C37: =IF('ORDENES'!$A15="","",IF('ORDENES'!$AI15="","-",'ORDENES'!$AI15)) | D37: =IF('ORDENES'!$A15="","",IF('ORDENES'!$AA15="","-",'ORDENES'!$AA15)) | E37: =IF('ORDENES'!$A15="","",IF('ORDENES'!$Y15="","-",'ORDENES'!$Y15)) | F37: =IF('ORDENES'!$A15="","",IF('ORDENES'!$AB15="","-",'ORDENES'!$AB15)) | G37: =IF('ORDENES'!$A15="","",IF('ORDENES'!$Z15="","-",'ORDENES'!$Z15)) | H37: =IF('ORDENES'!$A15="","",IF('ORDENES'!$AH15="","-",'ORDENES'!$AH15)) | I37: =IF('ORDENES'!$A15="","",IF('ORDENES'!$AU15="","-",'ORDENES'!$AU15)) | J37: =IF('ORDENES'!$A15="","",IF('ORDENES'!$D15="","-",'ORDENES'!$D15)) | K37: =IF('ORDENES'!$A15="","",IF('ORDENES'!$E15="","-",'ORDENES'!$E15)) | L37: =IF('ORDENES'!$A15="","",IF('ORDENES'!$M15="",0,'ORDENES'!$M15)) | M37: =IF('ORDENES'!$A15="","",IF('ORDENES'!$N15="","-",'ORDENES'!$N15)) | N37: =IF('ORDENES'!$A15="","",'ORDENES'!$AG15) | X37: 2026-S32
... A60: =IF('ORDENES'!$A38="","",IF('ORDENES'!$O38="","-",'ORDENES'!$O38)) | B60: =IF('ORDENES'!$A38="","",IF('ORDENES'!$S38="","-",'ORDENES'!$S38)) | C60: =IF('ORDENES'!$A38="","",IF('ORDENES'!$AI38="","-",'ORDENES'!$AI38)) | D60: =IF('ORDENES'!$A38="","",IF('ORDENES'!$AA38="","-",'ORDENES'!$AA38)) | E60: =IF('ORDENES'!$A38="","",IF('ORDENES'!$Y38="","-",'ORDENES'!$Y38)) | F60: =IF('ORDENES'!$A38="","",IF('ORDENES'!$AB38="","-",'ORDENES'!$AB38)) | G60: =IF('ORDENES'!$A38="","",IF('ORDENES'!$Z38="","-",'ORDENES'!$Z38)) | H60: =IF('ORDENES'!$A38="","",IF('ORDENES'!$AH38="","-",'ORDENES'!$AH38)) | I60: =IF('ORDENES'!$A38="","",IF('ORDENES'!$AU38="","-",'ORDENES'!$AU38)) | J60: =IF('ORDENES'!$A38="","",IF('ORDENES'!$D38="","-",'ORDENES'!$D38)) | K60: =IF('ORDENES'!$A38="","",IF('ORDENES'!$E38="","-",'ORDENES'!$E38)) | L60: =IF('ORDENES'!$A38="","",IF('ORDENES'!$M38="",0,'ORDENES'!$M38)) | M60: =IF('ORDENES'!$A38="","",IF('ORDENES'!$N38="","-",'ORDENES'!$N38)) | N60: =IF('ORDENES'!$A38="","",'ORDENES'!$AG38) | X60: 2027-S02
A61: =IF('ORDENES'!$A39="","",IF('ORDENES'!$O39="","-",'ORDENES'!$O39)) | B61: =IF('ORDENES'!$A39="","",IF('ORDENES'!$S39="","-",'ORDENES'!$S39)) | C61: =IF('ORDENES'!$A39="","",IF('ORDENES'!$AI39="","-",'ORDENES'!$AI39)) | D61: =IF('ORDENES'!$A39="","",IF('ORDENES'!$AA39="","-",'ORDENES'!$AA39)) | E61: =IF('ORDENES'!$A39="","",IF('ORDENES'!$Y39="","-",'ORDENES'!$Y39)) | F61: =IF('ORDENES'!$A39="","",IF('ORDENES'!$AB39="","-",'ORDENES'!$AB39)) | G61: =IF('ORDENES'!$A39="","",IF('ORDENES'!$Z39="","-",'ORDENES'!$Z39)) | H61: =IF('ORDENES'!$A39="","",IF('ORDENES'!$AH39="","-",'ORDENES'!$AH39)) | I61: =IF('ORDENES'!$A39="","",IF('ORDENES'!$AU39="","-",'ORDENES'!$AU39)) | J61: =IF('ORDENES'!$A39="","",IF('ORDENES'!$D39="","-",'ORDENES'!$D39)) | K61: =IF('ORDENES'!$A39="","",IF('ORDENES'!$E39="","-",'ORDENES'!$E39)) | L61: =IF('ORDENES'!$A39="","",IF('ORDENES'!$M39="",0,'ORDENES'!$M39)) | M61: =IF('ORDENES'!$A39="","",IF('ORDENES'!$N39="","-",'ORDENES'!$N39)) | N61: =IF('ORDENES'!$A39="","",'ORDENES'!$AG39)
A62: =IF('ORDENES'!$A40="","",IF('ORDENES'!$O40="","-",'ORDENES'!$O40)) | B62: =IF('ORDENES'!$A40="","",IF('ORDENES'!$S40="","-",'ORDENES'!$S40)) | C62: =IF('ORDENES'!$A40="","",IF('ORDENES'!$AI40="","-",'ORDENES'!$AI40)) | D62: =IF('ORDENES'!$A40="","",IF('ORDENES'!$AA40="","-",'ORDENES'!$AA40)) | E62: =IF('ORDENES'!$A40="","",IF('ORDENES'!$Y40="","-",'ORDENES'!$Y40)) | F62: =IF('ORDENES'!$A40="","",IF('ORDENES'!$AB40="","-",'ORDENES'!$AB40)) | G62: =IF('ORDENES'!$A40="","",IF('ORDENES'!$Z40="","-",'ORDENES'!$Z40)) | H62: =IF('ORDENES'!$A40="","",IF('ORDENES'!$AH40="","-",'ORDENES'!$AH40)) | I62: =IF('ORDENES'!$A40="","",IF('ORDENES'!$AU40="","-",'ORDENES'!$AU40)) | J62: =IF('ORDENES'!$A40="","",IF('ORDENES'!$D40="","-",'ORDENES'!$D40)) | K62: =IF('ORDENES'!$A40="","",IF('ORDENES'!$E40="","-",'ORDENES'!$E40)) | L62: =IF('ORDENES'!$A40="","",IF('ORDENES'!$M40="",0,'ORDENES'!$M40)) | M62: =IF('ORDENES'!$A40="","",IF('ORDENES'!$N40="","-",'ORDENES'!$N40)) | N62: =IF('ORDENES'!$A40="","",'ORDENES'!$AG40)
A63: =IF('ORDENES'!$A41="","",IF('ORDENES'!$O41="","-",'ORDENES'!$O41)) | B63: =IF('ORDENES'!$A41="","",IF('ORDENES'!$S41="","-",'ORDENES'!$S41)) | C63: =IF('ORDENES'!$A41="","",IF('ORDENES'!$AI41="","-",'ORDENES'!$AI41)) | D63: =IF('ORDENES'!$A41="","",IF('ORDENES'!$AA41="","-",'ORDENES'!$AA41)) | E63: =IF('ORDENES'!$A41="","",IF('ORDENES'!$Y41="","-",'ORDENES'!$Y41)) | F63: =IF('ORDENES'!$A41="","",IF('ORDENES'!$AB41="","-",'ORDENES'!$AB41)) | G63: =IF('ORDENES'!$A41="","",IF('ORDENES'!$Z41="","-",'ORDENES'!$Z41)) | H63: =IF('ORDENES'!$A41="","",IF('ORDENES'!$AH41="","-",'ORDENES'!$AH41)) | I63: =IF('ORDENES'!$A41="","",IF('ORDENES'!$AU41="","-",'ORDENES'!$AU41)) | J63: =IF('ORDENES'!$A41="","",IF('ORDENES'!$D41="","-",'ORDENES'!$D41)) | K63: =IF('ORDENES'!$A41="","",IF('ORDENES'!$E41="","-",'ORDENES'!$E41)) | L63: =IF('ORDENES'!$A41="","",IF('ORDENES'!$M41="",0,'ORDENES'!$M41)) | M63: =IF('ORDENES'!$A41="","",IF('ORDENES'!$N41="","-",'ORDENES'!$N41)) | N63: =IF('ORDENES'!$A41="","",'ORDENES'!$AG41)
A64: =IF('ORDENES'!$A42="","",IF('ORDENES'!$O42="","-",'ORDENES'!$O42)) | B64: =IF('ORDENES'!$A42="","",IF('ORDENES'!$S42="","-",'ORDENES'!$S42)) | C64: =IF('ORDENES'!$A42="","",IF('ORDENES'!$AI42="","-",'ORDENES'!$AI42)) | D64: =IF('ORDENES'!$A42="","",IF('ORDENES'!$AA42="","-",'ORDENES'!$AA42)) | E64: =IF('ORDENES'!$A42="","",IF('ORDENES'!$Y42="","-",'ORDENES'!$Y42)) | F64: =IF('ORDENES'!$A42="","",IF('ORDENES'!$AB42="","-",'ORDENES'!$AB42)) | G64: =IF('ORDENES'!$A42="","",IF('ORDENES'!$Z42="","-",'ORDENES'!$Z42)) | H64: =IF('ORDENES'!$A42="","",IF('ORDENES'!$AH42="","-",'ORDENES'!$AH42)) | I64: =IF('ORDENES'!$A42="","",IF('ORDENES'!$AU42="","-",'ORDENES'!$AU42)) | J64: =IF('ORDENES'!$A42="","",IF('ORDENES'!$D42="","-",'ORDENES'!$D42)) | K64: =IF('ORDENES'!$A42="","",IF('ORDENES'!$E42="","-",'ORDENES'!$E42)) | L64: =IF('ORDENES'!$A42="","",IF('ORDENES'!$M42="",0,'ORDENES'!$M42)) | M64: =IF('ORDENES'!$A42="","",IF('ORDENES'!$N42="","-",'ORDENES'!$N42)) | N64: =IF('ORDENES'!$A42="","",'ORDENES'!$AG42)
A65: =IF('ORDENES'!$A43="","",IF('ORDENES'!$O43="","-",'ORDENES'!$O43)) | B65: =IF('ORDENES'!$A43="","",IF('ORDENES'!$S43="","-",'ORDENES'!$S43)) | C65: =IF('ORDENES'!$A43="","",IF('ORDENES'!$AI43="","-",'ORDENES'!$AI43)) | D65: =IF('ORDENES'!$A43="","",IF('ORDENES'!$AA43="","-",'ORDENES'!$AA43)) | E65: =IF('ORDENES'!$A43="","",IF('ORDENES'!$Y43="","-",'ORDENES'!$Y43)) | F65: =IF('ORDENES'!$A43="","",IF('ORDENES'!$AB43="","-",'ORDENES'!$AB43)) | G65: =IF('ORDENES'!$A43="","",IF('ORDENES'!$Z43="","-",'ORDENES'!$Z43)) | H65: =IF('ORDENES'!$A43="","",IF('ORDENES'!$AH43="","-",'ORDENES'!$AH43)) | I65: =IF('ORDENES'!$A43="","",IF('ORDENES'!$AU43="","-",'ORDENES'!$AU43)) | J65: =IF('ORDENES'!$A43="","",IF('ORDENES'!$D43="","-",'ORDENES'!$D43)) | K65: =IF('ORDENES'!$A43="","",IF('ORDENES'!$E43="","-",'ORDENES'!$E43)) | L65: =IF('ORDENES'!$A43="","",IF('ORDENES'!$M43="",0,'ORDENES'!$M43)) | M65: =IF('ORDENES'!$A43="","",IF('ORDENES'!$N43="","-",'ORDENES'!$N43)) | N65: =IF('ORDENES'!$A43="","",'ORDENES'!$AG43)
A66: =IF('ORDENES'!$A44="","",IF('ORDENES'!$O44="","-",'ORDENES'!$O44)) | B66: =IF('ORDENES'!$A44="","",IF('ORDENES'!$S44="","-",'ORDENES'!$S44)) | C66: =IF('ORDENES'!$A44="","",IF('ORDENES'!$AI44="","-",'ORDENES'!$AI44)) | D66: =IF('ORDENES'!$A44="","",IF('ORDENES'!$AA44="","-",'ORDENES'!$AA44)) | E66: =IF('ORDENES'!$A44="","",IF('ORDENES'!$Y44="","-",'ORDENES'!$Y44)) | F66: =IF('ORDENES'!$A44="","",IF('ORDENES'!$AB44="","-",'ORDENES'!$AB44)) | G66: =IF('ORDENES'!$A44="","",IF('ORDENES'!$Z44="","-",'ORDENES'!$Z44)) | H66: =IF('ORDENES'!$A44="","",IF('ORDENES'!$AH44="","-",'ORDENES'!$AH44)) | I66: =IF('ORDENES'!$A44="","",IF('ORDENES'!$AU44="","-",'ORDENES'!$AU44)) | J66: =IF('ORDENES'!$A44="","",IF('ORDENES'!$D44="","-",'ORDENES'!$D44)) | K66: =IF('ORDENES'!$A44="","",IF('ORDENES'!$E44="","-",'ORDENES'!$E44)) | L66: =IF('ORDENES'!$A44="","",IF('ORDENES'!$M44="",0,'ORDENES'!$M44)) | M66: =IF('ORDENES'!$A44="","",IF('ORDENES'!$N44="","-",'ORDENES'!$N44)) | N66: =IF('ORDENES'!$A44="","",'ORDENES'!$AG44)
A67: =IF('ORDENES'!$A45="","",IF('ORDENES'!$O45="","-",'ORDENES'!$O45)) | B67: =IF('ORDENES'!$A45="","",IF('ORDENES'!$S45="","-",'ORDENES'!$S45)) | C67: =IF('ORDENES'!$A45="","",IF('ORDENES'!$AI45="","-",'ORDENES'!$AI45)) | D67: =IF('ORDENES'!$A45="","",IF('ORDENES'!$AA45="","-",'ORDENES'!$AA45)) | E67: =IF('ORDENES'!$A45="","",IF('ORDENES'!$Y45="","-",'ORDENES'!$Y45)) | F67: =IF('ORDENES'!$A45="","",IF('ORDENES'!$AB45="","-",'ORDENES'!$AB45)) | G67: =IF('ORDENES'!$A45="","",IF('ORDENES'!$Z45="","-",'ORDENES'!$Z45)) | H67: =IF('ORDENES'!$A45="","",IF('ORDENES'!$AH45="","-",'ORDENES'!$AH45)) | I67: =IF('ORDENES'!$A45="","",IF('ORDENES'!$AU45="","-",'ORDENES'!$AU45)) | J67: =IF('ORDENES'!$A45="","",IF('ORDENES'!$D45="","-",'ORDENES'!$D45)) | K67: =IF('ORDENES'!$A45="","",IF('ORDENES'!$E45="","-",'ORDENES'!$E45)) | L67: =IF('ORDENES'!$A45="","",IF('ORDENES'!$M45="",0,'ORDENES'!$M45)) | M67: =IF('ORDENES'!$A45="","",IF('ORDENES'!$N45="","-",'ORDENES'!$N45)) | N67: =IF('ORDENES'!$A45="","",'ORDENES'!$AG45)
A68: =IF('ORDENES'!$A46="","",IF('ORDENES'!$O46="","-",'ORDENES'!$O46)) | B68: =IF('ORDENES'!$A46="","",IF('ORDENES'!$S46="","-",'ORDENES'!$S46)) | C68: =IF('ORDENES'!$A46="","",IF('ORDENES'!$AI46="","-",'ORDENES'!$AI46)) | D68: =IF('ORDENES'!$A46="","",IF('ORDENES'!$AA46="","-",'ORDENES'!$AA46)) | E68: =IF('ORDENES'!$A46="","",IF('ORDENES'!$Y46="","-",'ORDENES'!$Y46)) | F68: =IF('ORDENES'!$A46="","",IF('ORDENES'!$AB46="","-",'ORDENES'!$AB46)) | G68: =IF('ORDENES'!$A46="","",IF('ORDENES'!$Z46="","-",'ORDENES'!$Z46)) | H68: =IF('ORDENES'!$A46="","",IF('ORDENES'!$AH46="","-",'ORDENES'!$AH46)) | I68: =IF('ORDENES'!$A46="","",IF('ORDENES'!$AU46="","-",'ORDENES'!$AU46)) | J68: =IF('ORDENES'!$A46="","",IF('ORDENES'!$D46="","-",'ORDENES'!$D46)) | K68: =IF('ORDENES'!$A46="","",IF('ORDENES'!$E46="","-",'ORDENES'!$E46)) | L68: =IF('ORDENES'!$A46="","",IF('ORDENES'!$M46="",0,'ORDENES'!$M46)) | M68: =IF('ORDENES'!$A46="","",IF('ORDENES'!$N46="","-",'ORDENES'!$N46)) | N68: =IF('ORDENES'!$A46="","",'ORDENES'!$AG46)
A69: =IF('ORDENES'!$A47="","",IF('ORDENES'!$O47="","-",'ORDENES'!$O47)) | B69: =IF('ORDENES'!$A47="","",IF('ORDENES'!$S47="","-",'ORDENES'!$S47)) | C69: =IF('ORDENES'!$A47="","",IF('ORDENES'!$AI47="","-",'ORDENES'!$AI47)) | D69: =IF('ORDENES'!$A47="","",IF('ORDENES'!$AA47="","-",'ORDENES'!$AA47)) | E69: =IF('ORDENES'!$A47="","",IF('ORDENES'!$Y47="","-",'ORDENES'!$Y47)) | F69: =IF('ORDENES'!$A47="","",IF('ORDENES'!$AB47="","-",'ORDENES'!$AB47)) | G69: =IF('ORDENES'!$A47="","",IF('ORDENES'!$Z47="","-",'ORDENES'!$Z47)) | H69: =IF('ORDENES'!$A47="","",IF('ORDENES'!$AH47="","-",'ORDENES'!$AH47)) | I69: =IF('ORDENES'!$A47="","",IF('ORDENES'!$AU47="","-",'ORDENES'!$AU47)) | J69: =IF('ORDENES'!$A47="","",IF('ORDENES'!$D47="","-",'ORDENES'!$D47)) | K69: =IF('ORDENES'!$A47="","",IF('ORDENES'!$E47="","-",'ORDENES'!$E47)) | L69: =IF('ORDENES'!$A47="","",IF('ORDENES'!$M47="",0,'ORDENES'!$M47)) | M69: =IF('ORDENES'!$A47="","",IF('ORDENES'!$N47="","-",'ORDENES'!$N47)) | N69: =IF('ORDENES'!$A47="","",'ORDENES'!$AG47)
A70: =IF('ORDENES'!$A48="","",IF('ORDENES'!$O48="","-",'ORDENES'!$O48)) | B70: =IF('ORDENES'!$A48="","",IF('ORDENES'!$S48="","-",'ORDENES'!$S48)) | C70: =IF('ORDENES'!$A48="","",IF('ORDENES'!$AI48="","-",'ORDENES'!$AI48)) | D70: =IF('ORDENES'!$A48="","",IF('ORDENES'!$AA48="","-",'ORDENES'!$AA48)) | E70: =IF('ORDENES'!$A48="","",IF('ORDENES'!$Y48="","-",'ORDENES'!$Y48)) | F70: =IF('ORDENES'!$A48="","",IF('ORDENES'!$AB48="","-",'ORDENES'!$AB48)) | G70: =IF('ORDENES'!$A48="","",IF('ORDENES'!$Z48="","-",'ORDENES'!$Z48)) | H70: =IF('ORDENES'!$A48="","",IF('ORDENES'!$AH48="","-",'ORDENES'!$AH48)) | I70: =IF('ORDENES'!$A48="","",IF('ORDENES'!$AU48="","-",'ORDENES'!$AU48)) | J70: =IF('ORDENES'!$A48="","",IF('ORDENES'!$D48="","-",'ORDENES'!$D48)) | K70: =IF('ORDENES'!$A48="","",IF('ORDENES'!$E48="","-",'ORDENES'!$E48)) | L70: =IF('ORDENES'!$A48="","",IF('ORDENES'!$M48="",0,'ORDENES'!$M48)) | M70: =IF('ORDENES'!$A48="","",IF('ORDENES'!$N48="","-",'ORDENES'!$N48)) | N70: =IF('ORDENES'!$A48="","",'ORDENES'!$AG48)
A71: =IF('ORDENES'!$A49="","",IF('ORDENES'!$O49="","-",'ORDENES'!$O49)) | B71: =IF('ORDENES'!$A49="","",IF('ORDENES'!$S49="","-",'ORDENES'!$S49)) | C71: =IF('ORDENES'!$A49="","",IF('ORDENES'!$AI49="","-",'ORDENES'!$AI49)) | D71: =IF('ORDENES'!$A49="","",IF('ORDENES'!$AA49="","-",'ORDENES'!$AA49)) | E71: =IF('ORDENES'!$A49="","",IF('ORDENES'!$Y49="","-",'ORDENES'!$Y49)) | F71: =IF('ORDENES'!$A49="","",IF('ORDENES'!$AB49="","-",'ORDENES'!$AB49)) | G71: =IF('ORDENES'!$A49="","",IF('ORDENES'!$Z49="","-",'ORDENES'!$Z49)) | H71: =IF('ORDENES'!$A49="","",IF('ORDENES'!$AH49="","-",'ORDENES'!$AH49)) | I71: =IF('ORDENES'!$A49="","",IF('ORDENES'!$AU49="","-",'ORDENES'!$AU49)) | J71: =IF('ORDENES'!$A49="","",IF('ORDENES'!$D49="","-",'ORDENES'!$D49)) | K71: =IF('ORDENES'!$A49="","",IF('ORDENES'!$E49="","-",'ORDENES'!$E49)) | L71: =IF('ORDENES'!$A49="","",IF('ORDENES'!$M49="",0,'ORDENES'!$M49)) | M71: =IF('ORDENES'!$A49="","",IF('ORDENES'!$N49="","-",'ORDENES'!$N49)) | N71: =IF('ORDENES'!$A49="","",'ORDENES'!$AG49)
A72: =IF('ORDENES'!$A50="","",IF('ORDENES'!$O50="","-",'ORDENES'!$O50)) | B72: =IF('ORDENES'!$A50="","",IF('ORDENES'!$S50="","-",'ORDENES'!$S50)) | C72: =IF('ORDENES'!$A50="","",IF('ORDENES'!$AI50="","-",'ORDENES'!$AI50)) | D72: =IF('ORDENES'!$A50="","",IF('ORDENES'!$AA50="","-",'ORDENES'!$AA50)) | E72: =IF('ORDENES'!$A50="","",IF('ORDENES'!$Y50="","-",'ORDENES'!$Y50)) | F72: =IF('ORDENES'!$A50="","",IF('ORDENES'!$AB50="","-",'ORDENES'!$AB50)) | G72: =IF('ORDENES'!$A50="","",IF('ORDENES'!$Z50="","-",'ORDENES'!$Z50)) | H72: =IF('ORDENES'!$A50="","",IF('ORDENES'!$AH50="","-",'ORDENES'!$AH50)) | I72: =IF('ORDENES'!$A50="","",IF('ORDENES'!$AU50="","-",'ORDENES'!$AU50)) | J72: =IF('ORDENES'!$A50="","",IF('ORDENES'!$D50="","-",'ORDENES'!$D50)) | K72: =IF('ORDENES'!$A50="","",IF('ORDENES'!$E50="","-",'ORDENES'!$E50)) | L72: =IF('ORDENES'!$A50="","",IF('ORDENES'!$M50="",0,'ORDENES'!$M50)) | M72: =IF('ORDENES'!$A50="","",IF('ORDENES'!$N50="","-",'ORDENES'!$N50)) | N72: =IF('ORDENES'!$A50="","",'ORDENES'!$AG50)
... A1225: =IF('ORDENES'!$A1203="","",IF('ORDENES'!$O1203="","-",'ORDENES'!$O1203)) | B1225: =IF('ORDENES'!$A1203="","",IF('ORDENES'!$S1203="","-",'ORDENES'!$S1203)) | C1225: =IF('ORDENES'!$A1203="","",IF('ORDENES'!$AI1203="","-",'ORDENES'!$AI1203)) | D1225: =IF('ORDENES'!$A1203="","",IF('ORDENES'!$AA1203="","-",'ORDENES'!$AA1203)) | E1225: =IF('ORDENES'!$A1203="","",IF('ORDENES'!$Y1203="","-",'ORDENES'!$Y1203)) | F1225: =IF('ORDENES'!$A1203="","",IF('ORDENES'!$AB1203="","-",'ORDENES'!$AB1203)) | G1225: =IF('ORDENES'!$A1203="","",IF('ORDENES'!$Z1203="","-",'ORDENES'!$Z1203)) | H1225: =IF('ORDENES'!$A1203="","",IF('ORDENES'!$AH1203="","-",'ORDENES'!$AH1203)) | I1225: =IF('ORDENES'!$A1203="","",IF('ORDENES'!$AU1203="","-",'ORDENES'!$AU1203)) | J1225: =IF('ORDENES'!$A1203="","",IF('ORDENES'!$D1203="","-",'ORDENES'!$D1203)) | K1225: =IF('ORDENES'!$A1203="","",IF('ORDENES'!$E1203="","-",'ORDENES'!$E1203)) | L1225: =IF('ORDENES'!$A1203="","",IF('ORDENES'!$M1203="",0,'ORDENES'!$M1203)) | M1225: =IF('ORDENES'!$A1203="","",IF('ORDENES'!$N1203="","-",'ORDENES'!$N1203)) | N1225: =IF('ORDENES'!$A1203="","",'ORDENES'!$AG1203)

Sheet ADHERENCIA
A1: ADHERENCIA (REGLA-7) — rojo < 90 %, amarillo 90–95 %, verde > 95 %. Solo días hábiles: las órdenes en día no laborable no penalizan (se reportan en VALIDACION).
A2: =HYPERLINK("#DASHBOARD!A1","◂ VOLVER AL TABLERO")
A3: POR SEMANA (serie derivada de los datos, hasta 60)
A4: valor | B4: total_ot | C4: cerradas | D4: adherencia_conteo | E4: hh_total | F4: hh_cerradas | G4: adherencia_horas | H4: meta
A5: ='PERFIL_HH'!$O$4 | B5: =COUNTIFS(tblOrdenes[semana],$A5,tblOrdenes[es_habil],"sí") | C5: =COUNTIFS(tblOrdenes[semana],$A5,tblOrdenes[estado],"Cerrada",tblOrdenes[es_habil],"sí") | D5: =IF(B5=0,"",C5/B5) | E5: =SUMIFS(tblOrdenes[horas_efectivas],tblOrdenes[semana],$A5,tblOrdenes[es_habil],"sí") | F5: =SUMIFS(tblOrdenes[horas_efectivas],tblOrdenes[semana],$A5,tblOrdenes[estado],"Cerrada",tblOrdenes[es_habil],"sí") | G5: =IF(E5=0,"",F5/E5) | H5: =p_meta_adherencia
A6: ='PERFIL_HH'!$O$5 | B6: =COUNTIFS(tblOrdenes[semana],$A6,tblOrdenes[es_habil],"sí") | C6: =COUNTIFS(tblOrdenes[semana],$A6,tblOrdenes[estado],"Cerrada",tblOrdenes[es_habil],"sí") | D6: =IF(B6=0,"",C6/B6) | E6: =SUMIFS(tblOrdenes[horas_efectivas],tblOrdenes[semana],$A6,tblOrdenes[es_habil],"sí") | F6: =SUMIFS(tblOrdenes[horas_efectivas],tblOrdenes[semana],$A6,tblOrdenes[estado],"Cerrada",tblOrdenes[es_habil],"sí") | G6: =IF(E6=0,"",F6/E6) | H6: =p_meta_adherencia
A7: ='PERFIL_HH'!$O$6 | B7: =COUNTIFS(tblOrdenes[semana],$A7,tblOrdenes[es_habil],"sí") | C7: =COUNTIFS(tblOrdenes[semana],$A7,tblOrdenes[estado],"Cerrada",tblOrdenes[es_habil],"sí") | D7: =IF(B7=0,"",C7/B7) | E7: =SUMIFS(tblOrdenes[horas_efectivas],tblOrdenes[semana],$A7,tblOrdenes[es_habil],"sí") | F7: =SUMIFS(tblOrdenes[horas_efectivas],tblOrdenes[semana],$A7,tblOrdenes[estado],"Cerrada",tblOrdenes[es_habil],"sí") | G7: =IF(E7=0,"",F7/E7) | H7: =p_meta_adherencia
A8: ='PERFIL_HH'!$O$7 | B8: =COUNTIFS(tblOrdenes[semana],$A8,tblOrdenes[es_habil],"sí") | C8: =COUNTIFS(tblOrdenes[semana],$A8,tblOrdenes[estado],"Cerrada",tblOrdenes[es_habil],"sí") | D8: =IF(B8=0,"",C8/B8) | E8: =SUMIFS(tblOrdenes[horas_efectivas],tblOrdenes[semana],$A8,tblOrdenes[es_habil],"sí") | F8: =SUMIFS(tblOrdenes[horas_efectivas],tblOrdenes[semana],$A8,tblOrdenes[estado],"Cerrada",tblOrdenes[es_habil],"sí") | G8: =IF(E8=0,"",F8/E8) | H8: =p_meta_adherencia
A9: ='PERFIL_HH'!$O$8 | B9: =COUNTIFS(tblOrdenes[semana],$A9,tblOrdenes[es_habil],"sí") | C9: =COUNTIFS(tblOrdenes[semana],$A9,tblOrdenes[estado],"Cerrada",tblOrdenes[es_habil],"sí") | D9: =IF(B9=0,"",C9/B9) | E9: =SUMIFS(tblOrdenes[horas_efectivas],tblOrdenes[semana],$A9,tblOrdenes[es_habil],"sí") | F9: =SUMIFS(tblOrdenes[horas_efectivas],tblOrdenes[semana],$A9,tblOrdenes[estado],"Cerrada",tblOrdenes[es_habil],"sí") | G9: =IF(E9=0,"",F9/E9) | H9: =p_meta_adherencia
A10: ='PERFIL_HH'!$O$9 | B10: =COUNTIFS(tblOrdenes[semana],$A10,tblOrdenes[es_habil],"sí") | C10: =COUNTIFS(tblOrdenes[semana],$A10,tblOrdenes[estado],"Cerrada",tblOrdenes[es_habil],"sí") | D10: =IF(B10=0,"",C10/B10) | E10: =SUMIFS(tblOrdenes[horas_efectivas],tblOrdenes[semana],$A10,tblOrdenes[es_habil],"sí") | F10: =SUMIFS(tblOrdenes[horas_efectivas],tblOrdenes[semana],$A10,tblOrdenes[estado],"Cerrada",tblOrdenes[es_habil],"sí") | G10: =IF(E10=0,"",F10/E10) | H10: =p_meta_adherencia
A11: ='PERFIL_HH'!$O$10 | B11: =COUNTIFS(tblOrdenes[semana],$A11,tblOrdenes[es_habil],"sí") | C11: =COUNTIFS(tblOrdenes[semana],$A11,tblOrdenes[estado],"Cerrada",tblOrdenes[es_habil],"sí") | D11: =IF(B11=0,"",C11/B11) | E11: =SUMIFS(tblOrdenes[horas_efectivas],tblOrdenes[semana],$A11,tblOrdenes[es_habil],"sí") | F11: =SUMIFS(tblOrdenes[horas_efectivas],tblOrdenes[semana],$A11,tblOrdenes[estado],"Cerrada",tblOrdenes[es_habil],"sí") | G11: =IF(E11=0,"",F11/E11) | H11: =p_meta_adherencia
A12: ='PERFIL_HH'!$O$11 | B12: =COUNTIFS(tblOrdenes[semana],$A12,tblOrdenes[es_habil],"sí") | C12: =COUNTIFS(tblOrdenes[semana],$A12,tblOrdenes[estado],"Cerrada",tblOrdenes[es_habil],"sí") | D12: =IF(B12=0,"",C12/B12) | E12: =SUMIFS(tblOrdenes[horas_efectivas],tblOrdenes[semana],$A12,tblOrdenes[es_habil],"sí") | F12: =SUMIFS(tblOrdenes[horas_efectivas],tblOrdenes[semana],$A12,tblOrdenes[estado],"Cerrada",tblOrdenes[es_habil],"sí") | G12: =IF(E12=0,"",F12/E12) | H12: =p_meta_adherencia
A13: ='PERFIL_HH'!$O$12 | B13: =COUNTIFS(tblOrdenes[semana],$A13,tblOrdenes[es_habil],"sí") | C13: =COUNTIFS(tblOrdenes[semana],$A13,tblOrdenes[estado],"Cerrada",tblOrdenes[es_habil],"sí") | D13: =IF(B13=0,"",C13/B13) | E13: =SUMIFS(tblOrdenes[horas_efectivas],tblOrdenes[semana],$A13,tblOrdenes[es_habil],"sí") | F13: =SUMIFS(tblOrdenes[horas_efectivas],tblOrdenes[semana],$A13,tblOrdenes[estado],"Cerrada",tblOrdenes[es_habil],"sí") | G13: =IF(E13=0,"",F13/E13) | H13: =p_meta_adherencia
A14: ='PERFIL_HH'!$O$13 | B14: =COUNTIFS(tblOrdenes[semana],$A14,tblOrdenes[es_habil],"sí") | C14: =COUNTIFS(tblOrdenes[semana],$A14,tblOrdenes[estado],"Cerrada",tblOrdenes[es_habil],"sí") | D14: =IF(B14=0,"",C14/B14) | E14: =SUMIFS(tblOrdenes[horas_efectivas],tblOrdenes[semana],$A14,tblOrdenes[es_habil],"sí") | F14: =SUMIFS(tblOrdenes[horas_efectivas],tblOrdenes[semana],$A14,tblOrdenes[estado],"Cerrada",tblOrdenes[es_habil],"sí") | G14: =IF(E14=0,"",F14/E14) | H14: =p_meta_adherencia
A15: ='PERFIL_HH'!$O$14 | B15: =COUNTIFS(tblOrdenes[semana],$A15,tblOrdenes[es_habil],"sí") | C15: =COUNTIFS(tblOrdenes[semana],$A15,tblOrdenes[estado],"Cerrada",tblOrdenes[es_habil],"sí") | D15: =IF(B15=0,"",C15/B15) | E15: =SUMIFS(tblOrdenes[horas_efectivas],tblOrdenes[semana],$A15,tblOrdenes[es_habil],"sí") | F15: =SUMIFS(tblOrdenes[horas_efectivas],tblOrdenes[semana],$A15,tblOrdenes[estado],"Cerrada",tblOrdenes[es_habil],"sí") | G15: =IF(E15=0,"",F15/E15) | H15: =p_meta_adherencia
A16: ='PERFIL_HH'!$O$15 | B16: =COUNTIFS(tblOrdenes[semana],$A16,tblOrdenes[es_habil],"sí") | C16: =COUNTIFS(tblOrdenes[semana],$A16,tblOrdenes[estado],"Cerrada",tblOrdenes[es_habil],"sí") | D16: =IF(B16=0,"",C16/B16) | E16: =SUMIFS(tblOrdenes[horas_efectivas],tblOrdenes[semana],$A16,tblOrdenes[es_habil],"sí") | F16: =SUMIFS(tblOrdenes[horas_efectivas],tblOrdenes[semana],$A16,tblOrdenes[estado],"Cerrada",tblOrdenes[es_habil],"sí") | G16: =IF(E16=0,"",F16/E16) | H16: =p_meta_adherencia
A17: ='PERFIL_HH'!$O$16 | B17: =COUNTIFS(tblOrdenes[semana],$A17,tblOrdenes[es_habil],"sí") | C17: =COUNTIFS(tblOrdenes[semana],$A17,tblOrdenes[estado],"Cerrada",tblOrdenes[es_habil],"sí") | D17: =IF(B17=0,"",C17/B17) | E17: =SUMIFS(tblOrdenes[horas_efectivas],tblOrdenes[semana],$A17,tblOrdenes[es_habil],"sí") | F17: =SUMIFS(tblOrdenes[horas_efectivas],tblOrdenes[semana],$A17,tblOrdenes[estado],"Cerrada",tblOrdenes[es_habil],"sí") | G17: =IF(E17=0,"",F17/E17) | H17: =p_meta_adherencia
A18: ='PERFIL_HH'!$O$17 | B18: =COUNTIFS(tblOrdenes[semana],$A18,tblOrdenes[es_habil],"sí") | C18: =COUNTIFS(tblOrdenes[semana],$A18,tblOrdenes[estado],"Cerrada",tblOrdenes[es_habil],"sí") | D18: =IF(B18=0,"",C18/B18) | E18: =SUMIFS(tblOrdenes[horas_efectivas],tblOrdenes[semana],$A18,tblOrdenes[es_habil],"sí") | F18: =SUMIFS(tblOrdenes[horas_efectivas],tblOrdenes[semana],$A18,tblOrdenes[estado],"Cerrada",tblOrdenes[es_habil],"sí") | G18: =IF(E18=0,"",F18/E18) | H18: =p_meta_adherencia
A19: ='PERFIL_HH'!$O$18 | B19: =COUNTIFS(tblOrdenes[semana],$A19,tblOrdenes[es_habil],"sí") | C19: =COUNTIFS(tblOrdenes[semana],$A19,tblOrdenes[estado],"Cerrada",tblOrdenes[es_habil],"sí") | D19: =IF(B19=0,"",C19/B19) | E19: =SUMIFS(tblOrdenes[horas_efectivas],tblOrdenes[semana],$A19,tblOrdenes[es_habil],"sí") | F19: =SUMIFS(tblOrdenes[horas_efectivas],tblOrdenes[semana],$A19,tblOrdenes[estado],"Cerrada",tblOrdenes[es_habil],"sí") | G19: =IF(E19=0,"",F19/E19) | H19: =p_meta_adherencia
A20: ='PERFIL_HH'!$O$19 | B20: =COUNTIFS(tblOrdenes[semana],$A20,tblOrdenes[es_habil],"sí") | C20: =COUNTIFS(tblOrdenes[semana],$A20,tblOrdenes[estado],"Cerrada",tblOrdenes[es_habil],"sí") | D20: =IF(B20=0,"",C20/B20) | E20: =SUMIFS(tblOrdenes[horas_efectivas],tblOrdenes[semana],$A20,tblOrdenes[es_habil],"sí") | F20: =SUMIFS(tblOrdenes[horas_efectivas],tblOrdenes[semana],$A20,tblOrdenes[estado],"Cerrada",tblOrdenes[es_habil],"sí") | G20: =IF(E20=0,"",F20/E20) | H20: =p_meta_adherencia
A21: ='PERFIL_HH'!$O$20 | B21: =COUNTIFS(tblOrdenes[semana],$A21,tblOrdenes[es_habil],"sí") | C21: =COUNTIFS(tblOrdenes[semana],$A21,tblOrdenes[estado],"Cerrada",tblOrdenes[es_habil],"sí") | D21: =IF(B21=0,"",C21/B21) | E21: =SUMIFS(tblOrdenes[horas_efectivas],tblOrdenes[semana],$A21,tblOrdenes[es_habil],"sí") | F21: =SUMIFS(tblOrdenes[horas_efectivas],tblOrdenes[semana],$A21,tblOrdenes[estado],"Cerrada",tblOrdenes[es_habil],"sí") | G21: =IF(E21=0,"",F21/E21) | H21: =p_meta_adherencia
A22: ='PERFIL_HH'!$O$21 | B22: =COUNTIFS(tblOrdenes[semana],$A22,tblOrdenes[es_habil],"sí") | C22: =COUNTIFS(tblOrdenes[semana],$A22,tblOrdenes[estado],"Cerrada",tblOrdenes[es_habil],"sí") | D22: =IF(B22=0,"",C22/B22) | E22: =SUMIFS(tblOrdenes[horas_efectivas],tblOrdenes[semana],$A22,tblOrdenes[es_habil],"sí") | F22: =SUMIFS(tblOrdenes[horas_efectivas],tblOrdenes[semana],$A22,tblOrdenes[estado],"Cerrada",tblOrdenes[es_habil],"sí") | G22: =IF(E22=0,"",F22/E22) | H22: =p_meta_adherencia
A23: ='PERFIL_HH'!$O$22 | B23: =COUNTIFS(tblOrdenes[semana],$A23,tblOrdenes[es_habil],"sí") | C23: =COUNTIFS(tblOrdenes[semana],$A23,tblOrdenes[estado],"Cerrada",tblOrdenes[es_habil],"sí") | D23: =IF(B23=0,"",C23/B23) | E23: =SUMIFS(tblOrdenes[horas_efectivas],tblOrdenes[semana],$A23,tblOrdenes[es_habil],"sí") | F23: =SUMIFS(tblOrdenes[horas_efectivas],tblOrdenes[semana],$A23,tblOrdenes[estado],"Cerrada",tblOrdenes[es_habil],"sí") | G23: =IF(E23=0,"",F23/E23) | H23: =p_meta_adherencia
A24: ='PERFIL_HH'!$O$23 | B24: =COUNTIFS(tblOrdenes[semana],$A24,tblOrdenes[es_habil],"sí") | C24: =COUNTIFS(tblOrdenes[semana],$A24,tblOrdenes[estado],"Cerrada",tblOrdenes[es_habil],"sí") | D24: =IF(B24=0,"",C24/B24) | E24: =SUMIFS(tblOrdenes[horas_efectivas],tblOrdenes[semana],$A24,tblOrdenes[es_habil],"sí") | F24: =SUMIFS(tblOrdenes[horas_efectivas],tblOrdenes[semana],$A24,tblOrdenes[estado],"Cerrada",tblOrdenes[es_habil],"sí") | G24: =IF(E24=0,"",F24/E24) | H24: =p_meta_adherencia
A25: ='PERFIL_HH'!$O$24 | B25: =COUNTIFS(tblOrdenes[semana],$A25,tblOrdenes[es_habil],"sí") | C25: =COUNTIFS(tblOrdenes[semana],$A25,tblOrdenes[estado],"Cerrada",tblOrdenes[es_habil],"sí") | D25: =IF(B25=0,"",C25/B25) | E25: =SUMIFS(tblOrdenes[horas_efectivas],tblOrdenes[semana],$A25,tblOrdenes[es_habil],"sí") | F25: =SUMIFS(tblOrdenes[horas_efectivas],tblOrdenes[semana],$A25,tblOrdenes[estado],"Cerrada",tblOrdenes[es_habil],"sí") | G25: =IF(E25=0,"",F25/E25) | H25: =p_meta_adherencia
A26: ='PERFIL_HH'!$O$25 | B26: =COUNTIFS(tblOrdenes[semana],$A26,tblOrdenes[es_habil],"sí") | C26: =COUNTIFS(tblOrdenes[semana],$A26,tblOrdenes[estado],"Cerrada",tblOrdenes[es_habil],"sí") | D26: =IF(B26=0,"",C26/B26) | E26: =SUMIFS(tblOrdenes[horas_efectivas],tblOrdenes[semana],$A26,tblOrdenes[es_habil],"sí") | F26: =SUMIFS(tblOrdenes[horas_efectivas],tblOrdenes[semana],$A26,tblOrdenes[estado],"Cerrada",tblOrdenes[es_habil],"sí") | G26: =IF(E26=0,"",F26/E26) | H26: =p_meta_adherencia
A27: ='PERFIL_HH'!$O$26 | B27: =COUNTIFS(tblOrdenes[semana],$A27,tblOrdenes[es_habil],"sí") | C27: =COUNTIFS(tblOrdenes[semana],$A27,tblOrdenes[estado],"Cerrada",tblOrdenes[es_habil],"sí") | D27: =IF(B27=0,"",C27/B27) | E27: =SUMIFS(tblOrdenes[horas_efectivas],tblOrdenes[semana],$A27,tblOrdenes[es_habil],"sí") | F27: =SUMIFS(tblOrdenes[horas_efectivas],tblOrdenes[semana],$A27,tblOrdenes[estado],"Cerrada",tblOrdenes[es_habil],"sí") | G27: =IF(E27=0,"",F27/E27) | H27: =p_meta_adherencia
A28: ='PERFIL_HH'!$O$27 | B28: =COUNTIFS(tblOrdenes[semana],$A28,tblOrdenes[es_habil],"sí") | C28: =COUNTIFS(tblOrdenes[semana],$A28,tblOrdenes[estado],"Cerrada",tblOrdenes[es_habil],"sí") | D28: =IF(B28=0,"",C28/B28) | E28: =SUMIFS(tblOrdenes[horas_efectivas],tblOrdenes[semana],$A28,tblOrdenes[es_habil],"sí") | F28: =SUMIFS(tblOrdenes[horas_efectivas],tblOrdenes[semana],$A28,tblOrdenes[estado],"Cerrada",tblOrdenes[es_habil],"sí") | G28: =IF(E28=0,"",F28/E28) | H28: =p_meta_adherencia
A29: ='PERFIL_HH'!$O$28 | B29: =COUNTIFS(tblOrdenes[semana],$A29,tblOrdenes[es_habil],"sí") | C29: =COUNTIFS(tblOrdenes[semana],$A29,tblOrdenes[estado],"Cerrada",tblOrdenes[es_habil],"sí") | D29: =IF(B29=0,"",C29/B29) | E29: =SUMIFS(tblOrdenes[horas_efectivas],tblOrdenes[semana],$A29,tblOrdenes[es_habil],"sí") | F29: =SUMIFS(tblOrdenes[horas_efectivas],tblOrdenes[semana],$A29,tblOrdenes[estado],"Cerrada",tblOrdenes[es_habil],"sí") | G29: =IF(E29=0,"",F29/E29) | H29: =p_meta_adherencia
A30: ='PERFIL_HH'!$O$29 | B30: =COUNTIFS(tblOrdenes[semana],$A30,tblOrdenes[es_habil],"sí") | C30: =COUNTIFS(tblOrdenes[semana],$A30,tblOrdenes[estado],"Cerrada",tblOrdenes[es_habil],"sí") | D30: =IF(B30=0,"",C30/B30) | E30: =SUMIFS(tblOrdenes[horas_efectivas],tblOrdenes[semana],$A30,tblOrdenes[es_habil],"sí") | F30: =SUMIFS(tblOrdenes[horas_efectivas],tblOrdenes[semana],$A30,tblOrdenes[estado],"Cerrada",tblOrdenes[es_habil],"sí") | G30: =IF(E30=0,"",F30/E30) | H30: =p_meta_adherencia
A31: ='PERFIL_HH'!$O$30 | B31: =COUNTIFS(tblOrdenes[semana],$A31,tblOrdenes[es_habil],"sí") | C31: =COUNTIFS(tblOrdenes[semana],$A31,tblOrdenes[estado],"Cerrada",tblOrdenes[es_habil],"sí") | D31: =IF(B31=0,"",C31/B31) | E31: =SUMIFS(tblOrdenes[horas_efectivas],tblOrdenes[semana],$A31,tblOrdenes[es_habil],"sí") | F31: =SUMIFS(tblOrdenes[horas_efectivas],tblOrdenes[semana],$A31,tblOrdenes[estado],"Cerrada",tblOrdenes[es_habil],"sí") | G31: =IF(E31=0,"",F31/E31) | H31: =p_meta_adherencia
A32: ='PERFIL_HH'!$O$31 | B32: =COUNTIFS(tblOrdenes[semana],$A32,tblOrdenes[es_habil],"sí") | C32: =COUNTIFS(tblOrdenes[semana],$A32,tblOrdenes[estado],"Cerrada",tblOrdenes[es_habil],"sí") | D32: =IF(B32=0,"",C32/B32) | E32: =SUMIFS(tblOrdenes[horas_efectivas],tblOrdenes[semana],$A32,tblOrdenes[es_habil],"sí") | F32: =SUMIFS(tblOrdenes[horas_efectivas],tblOrdenes[semana],$A32,tblOrdenes[estado],"Cerrada",tblOrdenes[es_habil],"sí") | G32: =IF(E32=0,"",F32/E32) | H32: =p_meta_adherencia
A33: ='PERFIL_HH'!$O$32 | B33: =COUNTIFS(tblOrdenes[semana],$A33,tblOrdenes[es_habil],"sí") | C33: =COUNTIFS(tblOrdenes[semana],$A33,tblOrdenes[estado],"Cerrada",tblOrdenes[es_habil],"sí") | D33: =IF(B33=0,"",C33/B33) | E33: =SUMIFS(tblOrdenes[horas_efectivas],tblOrdenes[semana],$A33,tblOrdenes[es_habil],"sí") | F33: =SUMIFS(tblOrdenes[horas_efectivas],tblOrdenes[semana],$A33,tblOrdenes[estado],"Cerrada",tblOrdenes[es_habil],"sí") | G33: =IF(E33=0,"",F33/E33) | H33: =p_meta_adherencia
A34: ='PERFIL_HH'!$O$33 | B34: =COUNTIFS(tblOrdenes[semana],$A34,tblOrdenes[es_habil],"sí") | C34: =COUNTIFS(tblOrdenes[semana],$A34,tblOrdenes[estado],"Cerrada",tblOrdenes[es_habil],"sí") | D34: =IF(B34=0,"",C34/B34) | E34: =SUMIFS(tblOrdenes[horas_efectivas],tblOrdenes[semana],$A34,tblOrdenes[es_habil],"sí") | F34: =SUMIFS(tblOrdenes[horas_efectivas],tblOrdenes[semana],$A34,tblOrdenes[estado],"Cerrada",tblOrdenes[es_habil],"sí") | G34: =IF(E34=0,"",F34/E34) | H34: =p_meta_adherencia
A35: ='PERFIL_HH'!$O$34 | B35: =COUNTIFS(tblOrdenes[semana],$A35,tblOrdenes[es_habil],"sí") | C35: =COUNTIFS(tblOrdenes[semana],$A35,tblOrdenes[estado],"Cerrada",tblOrdenes[es_habil],"sí") | D35: =IF(B35=0,"",C35/B35) | E35: =SUMIFS(tblOrdenes[horas_efectivas],tblOrdenes[semana],$A35,tblOrdenes[es_habil],"sí") | F35: =SUMIFS(tblOrdenes[horas_efectivas],tblOrdenes[semana],$A35,tblOrdenes[estado],"Cerrada",tblOrdenes[es_habil],"sí") | G35: =IF(E35=0,"",F35/E35) | H35: =p_meta_adherencia
A36: ='PERFIL_HH'!$O$35 | B36: =COUNTIFS(tblOrdenes[semana],$A36,tblOrdenes[es_habil],"sí") | C36: =COUNTIFS(tblOrdenes[semana],$A36,tblOrdenes[estado],"Cerrada",tblOrdenes[es_habil],"sí") | D36: =IF(B36=0,"",C36/B36) | E36: =SUMIFS(tblOrdenes[horas_efectivas],tblOrdenes[semana],$A36,tblOrdenes[es_habil],"sí") | F36: =SUMIFS(tblOrdenes[horas_efectivas],tblOrdenes[semana],$A36,tblOrdenes[estado],"Cerrada",tblOrdenes[es_habil],"sí") | G36: =IF(E36=0,"",F36/E36) | H36: =p_meta_adherencia
A37: ='PERFIL_HH'!$O$36 | B37: =COUNTIFS(tblOrdenes[semana],$A37,tblOrdenes[es_habil],"sí") | C37: =COUNTIFS(tblOrdenes[semana],$A37,tblOrdenes[estado],"Cerrada",tblOrdenes[es_habil],"sí") | D37: =IF(B37=0,"",C37/B37) | E37: =SUMIFS(tblOrdenes[horas_efectivas],tblOrdenes[semana],$A37,tblOrdenes[es_habil],"sí") | F37: =SUMIFS(tblOrdenes[horas_efectivas],tblOrdenes[semana],$A37,tblOrdenes[estado],"Cerrada",tblOrdenes[es_habil],"sí") | G37: =IF(E37=0,"",F37/E37) | H37: =p_meta_adherencia
A38: ='PERFIL_HH'!$O$37 | B38: =COUNTIFS(tblOrdenes[semana],$A38,tblOrdenes[es_habil],"sí") | C38: =COUNTIFS(tblOrdenes[semana],$A38,tblOrdenes[estado],"Cerrada",tblOrdenes[es_habil],"sí") | D38: =IF(B38=0,"",C38/B38) | E38: =SUMIFS(tblOrdenes[horas_efectivas],tblOrdenes[semana],$A38,tblOrdenes[es_habil],"sí") | F38: =SUMIFS(tblOrdenes[horas_efectivas],tblOrdenes[semana],$A38,tblOrdenes[estado],"Cerrada",tblOrdenes[es_habil],"sí") | G38: =IF(E38=0,"",F38/E38) | H38: =p_meta_adherencia
A39: ='PERFIL_HH'!$O$38 | B39: =COUNTIFS(tblOrdenes[semana],$A39,tblOrdenes[es_habil],"sí") | C39: =COUNTIFS(tblOrdenes[semana],$A39,tblOrdenes[estado],"Cerrada",tblOrdenes[es_habil],"sí") | D39: =IF(B39=0,"",C39/B39) | E39: =SUMIFS(tblOrdenes[horas_efectivas],tblOrdenes[semana],$A39,tblOrdenes[es_habil],"sí") | F39: =SUMIFS(tblOrdenes[horas_efectivas],tblOrdenes[semana],$A39,tblOrdenes[estado],"Cerrada",tblOrdenes[es_habil],"sí") | G39: =IF(E39=0,"",F39/E39) | H39: =p_meta_adherencia
A40: ='PERFIL_HH'!$O$39 | B40: =COUNTIFS(tblOrdenes[semana],$A40,tblOrdenes[es_habil],"sí") | C40: =COUNTIFS(tblOrdenes[semana],$A40,tblOrdenes[estado],"Cerrada",tblOrdenes[es_habil],"sí") | D40: =IF(B40=0,"",C40/B40) | E40: =SUMIFS(tblOrdenes[horas_efectivas],tblOrdenes[semana],$A40,tblOrdenes[es_habil],"sí") | F40: =SUMIFS(tblOrdenes[horas_efectivas],tblOrdenes[semana],$A40,tblOrdenes[estado],"Cerrada",tblOrdenes[es_habil],"sí") | G40: =IF(E40=0,"",F40/E40) | H40: =p_meta_adherencia
A41: ='PERFIL_HH'!$O$40 | B41: =COUNTIFS(tblOrdenes[semana],$A41,tblOrdenes[es_habil],"sí") | C41: =COUNTIFS(tblOrdenes[semana],$A41,tblOrdenes[estado],"Cerrada",tblOrdenes[es_habil],"sí") | D41: =IF(B41=0,"",C41/B41) | E41: =SUMIFS(tblOrdenes[horas_efectivas],tblOrdenes[semana],$A41,tblOrdenes[es_habil],"sí") | F41: =SUMIFS(tblOrdenes[horas_efectivas],tblOrdenes[semana],$A41,tblOrdenes[estado],"Cerrada",tblOrdenes[es_habil],"sí") | G41: =IF(E41=0,"",F41/E41) | H41: =p_meta_adherencia
A42: ='PERFIL_HH'!$O$41 | B42: =COUNTIFS(tblOrdenes[semana],$A42,tblOrdenes[es_habil],"sí") | C42: =COUNTIFS(tblOrdenes[semana],$A42,tblOrdenes[estado],"Cerrada",tblOrdenes[es_habil],"sí") | D42: =IF(B42=0,"",C42/B42) | E42: =SUMIFS(tblOrdenes[horas_efectivas],tblOrdenes[semana],$A42,tblOrdenes[es_habil],"sí") | F42: =SUMIFS(tblOrdenes[horas_efectivas],tblOrdenes[semana],$A42,tblOrdenes[estado],"Cerrada",tblOrdenes[es_habil],"sí") | G42: =IF(E42=0,"",F42/E42) | H42: =p_meta_adherencia
A43: ='PERFIL_HH'!$O$42 | B43: =COUNTIFS(tblOrdenes[semana],$A43,tblOrdenes[es_habil],"sí") | C43: =COUNTIFS(tblOrdenes[semana],$A43,tblOrdenes[estado],"Cerrada",tblOrdenes[es_habil],"sí") | D43: =IF(B43=0,"",C43/B43) | E43: =SUMIFS(tblOrdenes[horas_efectivas],tblOrdenes[semana],$A43,tblOrdenes[es_habil],"sí") | F43: =SUMIFS(tblOrdenes[horas_efectivas],tblOrdenes[semana],$A43,tblOrdenes[estado],"Cerrada",tblOrdenes[es_habil],"sí") | G43: =IF(E43=0,"",F43/E43) | H43: =p_meta_adherencia
A44: ='PERFIL_HH'!$O$43 | B44: =COUNTIFS(tblOrdenes[semana],$A44,tblOrdenes[es_habil],"sí") | C44: =COUNTIFS(tblOrdenes[semana],$A44,tblOrdenes[estado],"Cerrada",tblOrdenes[es_habil],"sí") | D44: =IF(B44=0,"",C44/B44) | E44: =SUMIFS(tblOrdenes[horas_efectivas],tblOrdenes[semana],$A44,tblOrdenes[es_habil],"sí") | F44: =SUMIFS(tblOrdenes[horas_efectivas],tblOrdenes[semana],$A44,tblOrdenes[estado],"Cerrada",tblOrdenes[es_habil],"sí") | G44: =IF(E44=0,"",F44/E44) | H44: =p_meta_adherencia
A45: ='PERFIL_HH'!$O$44 | B45: =COUNTIFS(tblOrdenes[semana],$A45,tblOrdenes[es_habil],"sí") | C45: =COUNTIFS(tblOrdenes[semana],$A45,tblOrdenes[estado],"Cerrada",tblOrdenes[es_habil],"sí") | D45: =IF(B45=0,"",C45/B45) | E45: =SUMIFS(tblOrdenes[horas_efectivas],tblOrdenes[semana],$A45,tblOrdenes[es_habil],"sí") | F45: =SUMIFS(tblOrdenes[horas_efectivas],tblOrdenes[semana],$A45,tblOrdenes[estado],"Cerrada",tblOrdenes[es_habil],"sí") | G45: =IF(E45=0,"",F45/E45) | H45: =p_meta_adherencia
A46: ='PERFIL_HH'!$O$45 | B46: =COUNTIFS(tblOrdenes[semana],$A46,tblOrdenes[es_habil],"sí") | C46: =COUNTIFS(tblOrdenes[semana],$A46,tblOrdenes[estado],"Cerrada",tblOrdenes[es_habil],"sí") | D46: =IF(B46=0,"",C46/B46) | E46: =SUMIFS(tblOrdenes[horas_efectivas],tblOrdenes[semana],$A46,tblOrdenes[es_habil],"sí") | F46: =SUMIFS(tblOrdenes[horas_efectivas],tblOrdenes[semana],$A46,tblOrdenes[estado],"Cerrada",tblOrdenes[es_habil],"sí") | G46: =IF(E46=0,"",F46/E46) | H46: =p_meta_adherencia
A47: ='PERFIL_HH'!$O$46 | B47: =COUNTIFS(tblOrdenes[semana],$A47,tblOrdenes[es_habil],"sí") | C47: =COUNTIFS(tblOrdenes[semana],$A47,tblOrdenes[estado],"Cerrada",tblOrdenes[es_habil],"sí") | D47: =IF(B47=0,"",C47/B47) | E47: =SUMIFS(tblOrdenes[horas_efectivas],tblOrdenes[semana],$A47,tblOrdenes[es_habil],"sí") | F47: =SUMIFS(tblOrdenes[horas_efectivas],tblOrdenes[semana],$A47,tblOrdenes[estado],"Cerrada",tblOrdenes[es_habil],"sí") | G47: =IF(E47=0,"",F47/E47) | H47: =p_meta_adherencia
A48: ='PERFIL_HH'!$O$47 | B48: =COUNTIFS(tblOrdenes[semana],$A48,tblOrdenes[es_habil],"sí") | C48: =COUNTIFS(tblOrdenes[semana],$A48,tblOrdenes[estado],"Cerrada",tblOrdenes[es_habil],"sí") | D48: =IF(B48=0,"",C48/B48) | E48: =SUMIFS(tblOrdenes[horas_efectivas],tblOrdenes[semana],$A48,tblOrdenes[es_habil],"sí") | F48: =SUMIFS(tblOrdenes[horas_efectivas],tblOrdenes[semana],$A48,tblOrdenes[estado],"Cerrada",tblOrdenes[es_habil],"sí") | G48: =IF(E48=0,"",F48/E48) | H48: =p_meta_adherencia
A49: ='PERFIL_HH'!$O$48 | B49: =COUNTIFS(tblOrdenes[semana],$A49,tblOrdenes[es_habil],"sí") | C49: =COUNTIFS(tblOrdenes[semana],$A49,tblOrdenes[estado],"Cerrada",tblOrdenes[es_habil],"sí") | D49: =IF(B49=0,"",C49/B49) | E49: =SUMIFS(tblOrdenes[horas_efectivas],tblOrdenes[semana],$A49,tblOrdenes[es_habil],"sí") | F49: =SUMIFS(tblOrdenes[horas_efectivas],tblOrdenes[semana],$A49,tblOrdenes[estado],"Cerrada",tblOrdenes[es_habil],"sí") | G49: =IF(E49=0,"",F49/E49) | H49: =p_meta_adherencia
A50: ='PERFIL_HH'!$O$49 | B50: =COUNTIFS(tblOrdenes[semana],$A50,tblOrdenes[es_habil],"sí") | C50: =COUNTIFS(tblOrdenes[semana],$A50,tblOrdenes[estado],"Cerrada",tblOrdenes[es_habil],"sí") | D50: =IF(B50=0,"",C50/B50) | E50: =SUMIFS(tblOrdenes[horas_efectivas],tblOrdenes[semana],$A50,tblOrdenes[es_habil],"sí") | F50: =SUMIFS(tblOrdenes[horas_efectivas],tblOrdenes[semana],$A50,tblOrdenes[estado],"Cerrada",tblOrdenes[es_habil],"sí") | G50: =IF(E50=0,"",F50/E50) | H50: =p_meta_adherencia
A51: ='PERFIL_HH'!$O$50 | B51: =COUNTIFS(tblOrdenes[semana],$A51,tblOrdenes[es_habil],"sí") | C51: =COUNTIFS(tblOrdenes[semana],$A51,tblOrdenes[estado],"Cerrada",tblOrdenes[es_habil],"sí") | D51: =IF(B51=0,"",C51/B51) | E51: =SUMIFS(tblOrdenes[horas_efectivas],tblOrdenes[semana],$A51,tblOrdenes[es_habil],"sí") | F51: =SUMIFS(tblOrdenes[horas_efectivas],tblOrdenes[semana],$A51,tblOrdenes[estado],"Cerrada",tblOrdenes[es_habil],"sí") | G51: =IF(E51=0,"",F51/E51) | H51: =p_meta_adherencia
A52: ='PERFIL_HH'!$O$51 | B52: =COUNTIFS(tblOrdenes[semana],$A52,tblOrdenes[es_habil],"sí") | C52: =COUNTIFS(tblOrdenes[semana],$A52,tblOrdenes[estado],"Cerrada",tblOrdenes[es_habil],"sí") | D52: =IF(B52=0,"",C52/B52) | E52: =SUMIFS(tblOrdenes[horas_efectivas],tblOrdenes[semana],$A52,tblOrdenes[es_habil],"sí") | F52: =SUMIFS(tblOrdenes[horas_efectivas],tblOrdenes[semana],$A52,tblOrdenes[estado],"Cerrada",tblOrdenes[es_habil],"sí") | G52: =IF(E52=0,"",F52/E52) | H52: =p_meta_adherencia
A53: ='PERFIL_HH'!$O$52 | B53: =COUNTIFS(tblOrdenes[semana],$A53,tblOrdenes[es_habil],"sí") | C53: =COUNTIFS(tblOrdenes[semana],$A53,tblOrdenes[estado],"Cerrada",tblOrdenes[es_habil],"sí") | D53: =IF(B53=0,"",C53/B53) | E53: =SUMIFS(tblOrdenes[horas_efectivas],tblOrdenes[semana],$A53,tblOrdenes[es_habil],"sí") | F53: =SUMIFS(tblOrdenes[horas_efectivas],tblOrdenes[semana],$A53,tblOrdenes[estado],"Cerrada",tblOrdenes[es_habil],"sí") | G53: =IF(E53=0,"",F53/E53) | H53: =p_meta_adherencia
A54: ='PERFIL_HH'!$O$53 | B54: =COUNTIFS(tblOrdenes[semana],$A54,tblOrdenes[es_habil],"sí") | C54: =COUNTIFS(tblOrdenes[semana],$A54,tblOrdenes[estado],"Cerrada",tblOrdenes[es_habil],"sí") | D54: =IF(B54=0,"",C54/B54) | E54: =SUMIFS(tblOrdenes[horas_efectivas],tblOrdenes[semana],$A54,tblOrdenes[es_habil],"sí") | F54: =SUMIFS(tblOrdenes[horas_efectivas],tblOrdenes[semana],$A54,tblOrdenes[estado],"Cerrada",tblOrdenes[es_habil],"sí") | G54: =IF(E54=0,"",F54/E54) | H54: =p_meta_adherencia
A55: ='PERFIL_HH'!$O$54 | B55: =COUNTIFS(tblOrdenes[semana],$A55,tblOrdenes[es_habil],"sí") | C55: =COUNTIFS(tblOrdenes[semana],$A55,tblOrdenes[estado],"Cerrada",tblOrdenes[es_habil],"sí") | D55: =IF(B55=0,"",C55/B55) | E55: =SUMIFS(tblOrdenes[horas_efectivas],tblOrdenes[semana],$A55,tblOrdenes[es_habil],"sí") | F55: =SUMIFS(tblOrdenes[horas_efectivas],tblOrdenes[semana],$A55,tblOrdenes[estado],"Cerrada",tblOrdenes[es_habil],"sí") | G55: =IF(E55=0,"",F55/E55) | H55: =p_meta_adherencia
A56: ='PERFIL_HH'!$O$55 | B56: =COUNTIFS(tblOrdenes[semana],$A56,tblOrdenes[es_habil],"sí") | C56: =COUNTIFS(tblOrdenes[semana],$A56,tblOrdenes[estado],"Cerrada",tblOrdenes[es_habil],"sí") | D56: =IF(B56=0,"",C56/B56) | E56: =SUMIFS(tblOrdenes[horas_efectivas],tblOrdenes[semana],$A56,tblOrdenes[es_habil],"sí") | F56: =SUMIFS(tblOrdenes[horas_efectivas],tblOrdenes[semana],$A56,tblOrdenes[estado],"Cerrada",tblOrdenes[es_habil],"sí") | G56: =IF(E56=0,"",F56/E56) | H56: =p_meta_adherencia
A57: ='PERFIL_HH'!$O$56 | B57: =COUNTIFS(tblOrdenes[semana],$A57,tblOrdenes[es_habil],"sí") | C57: =COUNTIFS(tblOrdenes[semana],$A57,tblOrdenes[estado],"Cerrada",tblOrdenes[es_habil],"sí") | D57: =IF(B57=0,"",C57/B57) | E57: =SUMIFS(tblOrdenes[horas_efectivas],tblOrdenes[semana],$A57,tblOrdenes[es_habil],"sí") | F57: =SUMIFS(tblOrdenes[horas_efectivas],tblOrdenes[semana],$A57,tblOrdenes[estado],"Cerrada",tblOrdenes[es_habil],"sí") | G57: =IF(E57=0,"",F57/E57) | H57: =p_meta_adherencia
A58: ='PERFIL_HH'!$O$57 | B58: =COUNTIFS(tblOrdenes[semana],$A58,tblOrdenes[es_habil],"sí") | C58: =COUNTIFS(tblOrdenes[semana],$A58,tblOrdenes[estado],"Cerrada",tblOrdenes[es_habil],"sí") | D58: =IF(B58=0,"",C58/B58) | E58: =SUMIFS(tblOrdenes[horas_efectivas],tblOrdenes[semana],$A58,tblOrdenes[es_habil],"sí") | F58: =SUMIFS(tblOrdenes[horas_efectivas],tblOrdenes[semana],$A58,tblOrdenes[estado],"Cerrada",tblOrdenes[es_habil],"sí") | G58: =IF(E58=0,"",F58/E58) | H58: =p_meta_adherencia
A59: ='PERFIL_HH'!$O$58 | B59: =COUNTIFS(tblOrdenes[semana],$A59,tblOrdenes[es_habil],"sí") | C59: =COUNTIFS(tblOrdenes[semana],$A59,tblOrdenes[estado],"Cerrada",tblOrdenes[es_habil],"sí") | D59: =IF(B59=0,"",C59/B59) | E59: =SUMIFS(tblOrdenes[horas_efectivas],tblOrdenes[semana],$A59,tblOrdenes[es_habil],"sí") | F59: =SUMIFS(tblOrdenes[horas_efectivas],tblOrdenes[semana],$A59,tblOrdenes[estado],"Cerrada",tblOrdenes[es_habil],"sí") | G59: =IF(E59=0,"",F59/E59) | H59: =p_meta_adherencia
A60: ='PERFIL_HH'!$O$59 | B60: =COUNTIFS(tblOrdenes[semana],$A60,tblOrdenes[es_habil],"sí") | C60: =COUNTIFS(tblOrdenes[semana],$A60,tblOrdenes[estado],"Cerrada",tblOrdenes[es_habil],"sí") | D60: =IF(B60=0,"",C60/B60) | E60: =SUMIFS(tblOrdenes[horas_efectivas],tblOrdenes[semana],$A60,tblOrdenes[es_habil],"sí") | F60: =SUMIFS(tblOrdenes[horas_efectivas],tblOrdenes[semana],$A60,tblOrdenes[estado],"Cerrada",tblOrdenes[es_habil],"sí") | G60: =IF(E60=0,"",F60/E60) | H60: =p_meta_adherencia
A61: ='PERFIL_HH'!$O$60 | B61: =COUNTIFS(tblOrdenes[semana],$A61,tblOrdenes[es_habil],"sí") | C61: =COUNTIFS(tblOrdenes[semana],$A61,tblOrdenes[estado],"Cerrada",tblOrdenes[es_habil],"sí") | D61: =IF(B61=0,"",C61/B61) | E61: =SUMIFS(tblOrdenes[horas_efectivas],tblOrdenes[semana],$A61,tblOrdenes[es_habil],"sí") | F61: =SUMIFS(tblOrdenes[horas_efectivas],tblOrdenes[semana],$A61,tblOrdenes[estado],"Cerrada",tblOrdenes[es_habil],"sí") | G61: =IF(E61=0,"",F61/E61) | H61: =p_meta_adherencia
A62: ='PERFIL_HH'!$O$61 | B62: =COUNTIFS(tblOrdenes[semana],$A62,tblOrdenes[es_habil],"sí") | C62: =COUNTIFS(tblOrdenes[semana],$A62,tblOrdenes[estado],"Cerrada",tblOrdenes[es_habil],"sí") | D62: =IF(B62=0,"",C62/B62) | E62: =SUMIFS(tblOrdenes[horas_efectivas],tblOrdenes[semana],$A62,tblOrdenes[es_habil],"sí") | F62: =SUMIFS(tblOrdenes[horas_efectivas],tblOrdenes[semana],$A62,tblOrdenes[estado],"Cerrada",tblOrdenes[es_habil],"sí") | G62: =IF(E62=0,"",F62/E62) | H62: =p_meta_adherencia
A63: ='PERFIL_HH'!$O$62 | B63: =COUNTIFS(tblOrdenes[semana],$A63,tblOrdenes[es_habil],"sí") | C63: =COUNTIFS(tblOrdenes[semana],$A63,tblOrdenes[estado],"Cerrada",tblOrdenes[es_habil],"sí") | D63: =IF(B63=0,"",C63/B63) | E63: =SUMIFS(tblOrdenes[horas_efectivas],tblOrdenes[semana],$A63,tblOrdenes[es_habil],"sí") | F63: =SUMIFS(tblOrdenes[horas_efectivas],tblOrdenes[semana],$A63,tblOrdenes[estado],"Cerrada",tblOrdenes[es_habil],"sí") | G63: =IF(E63=0,"",F63/E63) | H63: =p_meta_adherencia
A64: ='PERFIL_HH'!$O$63 | B64: =COUNTIFS(tblOrdenes[semana],$A64,tblOrdenes[es_habil],"sí") | C64: =COUNTIFS(tblOrdenes[semana],$A64,tblOrdenes[estado],"Cerrada",tblOrdenes[es_habil],"sí") | D64: =IF(B64=0,"",C64/B64) | E64: =SUMIFS(tblOrdenes[horas_efectivas],tblOrdenes[semana],$A64,tblOrdenes[es_habil],"sí") | F64: =SUMIFS(tblOrdenes[horas_efectivas],tblOrdenes[semana],$A64,tblOrdenes[estado],"Cerrada",tblOrdenes[es_habil],"sí") | G64: =IF(E64=0,"",F64/E64) | H64: =p_meta_adherencia
A66: POR ÁREA
A67: valor | B67: total_ot | C67: cerradas | D67: adherencia_conteo | E67: hh_total | F67: hh_cerradas | G67: adherencia_horas
A68: PRODUCCION | B68: =COUNTIFS(tblOrdenes[area],$A68,tblOrdenes[es_habil],"sí") | C68: =COUNTIFS(tblOrdenes[area],$A68,tblOrdenes[estado],"Cerrada",tblOrdenes[es_habil],"sí") | D68: =IF(B68=0,"",C68/B68) | E68: =SUMIFS(tblOrdenes[horas_efectivas],tblOrdenes[area],$A68,tblOrdenes[es_habil],"sí") | F68: =SUMIFS(tblOrdenes[horas_efectivas],tblOrdenes[area],$A68,tblOrdenes[estado],"Cerrada",tblOrdenes[es_habil],"sí") | G68: =IF(E68=0,"",F68/E68)
A69: EMPAQUE | B69: =COUNTIFS(tblOrdenes[area],$A69,tblOrdenes[es_habil],"sí") | C69: =COUNTIFS(tblOrdenes[area],$A69,tblOrdenes[estado],"Cerrada",tblOrdenes[es_habil],"sí") | D69: =IF(B69=0,"",C69/B69) | E69: =SUMIFS(tblOrdenes[horas_efectivas],tblOrdenes[area],$A69,tblOrdenes[es_habil],"sí") | F69: =SUMIFS(tblOrdenes[horas_efectivas],tblOrdenes[area],$A69,tblOrdenes[estado],"Cerrada",tblOrdenes[es_habil],"sí") | G69: =IF(E69=0,"",F69/E69)
A70: SERVICIOS | B70: =COUNTIFS(tblOrdenes[area],$A70,tblOrdenes[es_habil],"sí") | C70: =COUNTIFS(tblOrdenes[area],$A70,tblOrdenes[estado],"Cerrada",tblOrdenes[es_habil],"sí") | D70: =IF(B70=0,"",C70/B70) | E70: =SUMIFS(tblOrdenes[horas_efectivas],tblOrdenes[area],$A70,tblOrdenes[es_habil],"sí") | F70: =SUMIFS(tblOrdenes[horas_efectivas],tblOrdenes[area],$A70,tblOrdenes[estado],"Cerrada",tblOrdenes[es_habil],"sí") | G70: =IF(E70=0,"",F70/E70)
A72: POR SUB-ÁREA (agrupada bajo su área madre — col. I)
A73: valor | B73: total_ot | C73: cerradas | D73: adherencia_conteo | E73: hh_total | F73: hh_cerradas | G73: adherencia_horas | I73: área madre
A74: PRODUCCION | B74: =COUNTIFS(tblOrdenes[sub_area],$A74,tblOrdenes[es_habil],"sí") | C74: =COUNTIFS(tblOrdenes[sub_area],$A74,tblOrdenes[estado],"Cerrada",tblOrdenes[es_habil],"sí") | D74: =IF(B74=0,"",C74/B74) | E74: =SUMIFS(tblOrdenes[horas_efectivas],tblOrdenes[sub_area],$A74,tblOrdenes[es_habil],"sí") | F74: =SUMIFS(tblOrdenes[horas_efectivas],tblOrdenes[sub_area],$A74,tblOrdenes[estado],"Cerrada",tblOrdenes[es_habil],"sí") | G74: =IF(E74=0,"",F74/E74) | I74: PRODUCCION
A75: EMPAQUE | B75: =COUNTIFS(tblOrdenes[sub_area],$A75,tblOrdenes[es_habil],"sí") | C75: =COUNTIFS(tblOrdenes[sub_area],$A75,tblOrdenes[estado],"Cerrada",tblOrdenes[es_habil],"sí") | D75: =IF(B75=0,"",C75/B75) | E75: =SUMIFS(tblOrdenes[horas_efectivas],tblOrdenes[sub_area],$A75,tblOrdenes[es_habil],"sí") | F75: =SUMIFS(tblOrdenes[horas_efectivas],tblOrdenes[sub_area],$A75,tblOrdenes[estado],"Cerrada",tblOrdenes[es_habil],"sí") | G75: =IF(E75=0,"",F75/E75) | I75: EMPAQUE
A76: Vapor | B76: =COUNTIFS(tblOrdenes[sub_area],$A76,tblOrdenes[es_habil],"sí") | C76: =COUNTIFS(tblOrdenes[sub_area],$A76,tblOrdenes[estado],"Cerrada",tblOrdenes[es_habil],"sí") | D76: =IF(B76=0,"",C76/B76) | E76: =SUMIFS(tblOrdenes[horas_efectivas],tblOrdenes[sub_area],$A76,tblOrdenes[es_habil],"sí") | F76: =SUMIFS(tblOrdenes[horas_efectivas],tblOrdenes[sub_area],$A76,tblOrdenes[estado],"Cerrada",tblOrdenes[es_habil],"sí") | G76: =IF(E76=0,"",F76/E76) | I76: SERVICIOS
A77: Refrigeración | B77: =COUNTIFS(tblOrdenes[sub_area],$A77,tblOrdenes[es_habil],"sí") | C77: =COUNTIFS(tblOrdenes[sub_area],$A77,tblOrdenes[estado],"Cerrada",tblOrdenes[es_habil],"sí") | D77: =IF(B77=0,"",C77/B77) | E77: =SUMIFS(tblOrdenes[horas_efectivas],tblOrdenes[sub_area],$A77,tblOrdenes[es_habil],"sí") | F77: =SUMIFS(tblOrdenes[horas_efectivas],tblOrdenes[sub_area],$A77,tblOrdenes[estado],"Cerrada",tblOrdenes[es_habil],"sí") | G77: =IF(E77=0,"",F77/E77) | I77: SERVICIOS
A78: CO2 | B78: =COUNTIFS(tblOrdenes[sub_area],$A78,tblOrdenes[es_habil],"sí") | C78: =COUNTIFS(tblOrdenes[sub_area],$A78,tblOrdenes[estado],"Cerrada",tblOrdenes[es_habil],"sí") | D78: =IF(B78=0,"",C78/B78) | E78: =SUMIFS(tblOrdenes[horas_efectivas],tblOrdenes[sub_area],$A78,tblOrdenes[es_habil],"sí") | F78: =SUMIFS(tblOrdenes[horas_efectivas],tblOrdenes[sub_area],$A78,tblOrdenes[estado],"Cerrada",tblOrdenes[es_habil],"sí") | G78: =IF(E78=0,"",F78/E78) | I78: SERVICIOS
A79: Aire comprimido | B79: =COUNTIFS(tblOrdenes[sub_area],$A79,tblOrdenes[es_habil],"sí") | C79: =COUNTIFS(tblOrdenes[sub_area],$A79,tblOrdenes[estado],"Cerrada",tblOrdenes[es_habil],"sí") | D79: =IF(B79=0,"",C79/B79) | E79: =SUMIFS(tblOrdenes[horas_efectivas],tblOrdenes[sub_area],$A79,tblOrdenes[es_habil],"sí") | F79: =SUMIFS(tblOrdenes[horas_efectivas],tblOrdenes[sub_area],$A79,tblOrdenes[estado],"Cerrada",tblOrdenes[es_habil],"sí") | G79: =IF(E79=0,"",F79/E79) | I79: SERVICIOS
A81: POR ESPECIALIDAD
A82: valor | B82: total_ot | C82: cerradas | D82: adherencia_conteo | E82: hh_total | F82: hh_cerradas | G82: adherencia_horas
A83: MEC | B83: =COUNTIFS(tblOrdenes[especialidad],$A83,tblOrdenes[es_habil],"sí") | C83: =COUNTIFS(tblOrdenes[especialidad],$A83,tblOrdenes[estado],"Cerrada",tblOrdenes[es_habil],"sí") | D83: =IF(B83=0,"",C83/B83) | E83: =SUMIFS(tblOrdenes[horas_efectivas],tblOrdenes[especialidad],$A83,tblOrdenes[es_habil],"sí") | F83: =SUMIFS(tblOrdenes[horas_efectivas],tblOrdenes[especialidad],$A83,tblOrdenes[estado],"Cerrada",tblOrdenes[es_habil],"sí") | G83: =IF(E83=0,"",F83/E83)
A84: ELE | B84: =COUNTIFS(tblOrdenes[especialidad],$A84,tblOrdenes[es_habil],"sí") | C84: =COUNTIFS(tblOrdenes[especialidad],$A84,tblOrdenes[estado],"Cerrada",tblOrdenes[es_habil],"sí") | D84: =IF(B84=0,"",C84/B84) | E84: =SUMIFS(tblOrdenes[horas_efectivas],tblOrdenes[especialidad],$A84,tblOrdenes[es_habil],"sí") | F84: =SUMIFS(tblOrdenes[horas_efectivas],tblOrdenes[especialidad],$A84,tblOrdenes[estado],"Cerrada",tblOrdenes[es_habil],"sí") | G84: =IF(E84=0,"",F84/E84)
A85: AUT | B85: =COUNTIFS(tblOrdenes[especialidad],$A85,tblOrdenes[es_habil],"sí") | C85: =COUNTIFS(tblOrdenes[especialidad],$A85,tblOrdenes[estado],"Cerrada",tblOrdenes[es_habil],"sí") | D85: =IF(B85=0,"",C85/B85) | E85: =SUMIFS(tblOrdenes[horas_efectivas],tblOrdenes[especialidad],$A85,tblOrdenes[es_habil],"sí") | F85: =SUMIFS(tblOrdenes[horas_efectivas],tblOrdenes[especialidad],$A85,tblOrdenes[estado],"Cerrada",tblOrdenes[es_habil],"sí") | G85: =IF(E85=0,"",F85/E85)
A86: TERCERO | B86: =COUNTIFS(tblOrdenes[especialidad],$A86,tblOrdenes[es_habil],"sí") | C86: =COUNTIFS(tblOrdenes[especialidad],$A86,tblOrdenes[estado],"Cerrada",tblOrdenes[es_habil],"sí") | D86: =IF(B86=0,"",C86/B86) | E86: =SUMIFS(tblOrdenes[horas_efectivas],tblOrdenes[especialidad],$A86,tblOrdenes[es_habil],"sí") | F86: =SUMIFS(tblOrdenes[horas_efectivas],tblOrdenes[especialidad],$A86,tblOrdenes[estado],"Cerrada",tblOrdenes[es_habil],"sí") | G86: =IF(E86=0,"",F86/E86)
A88: POR COORDINADOR
A89: valor | B89: total_ot | C89: cerradas | D89: adherencia_conteo | E89: hh_total | F89: hh_cerradas | G89: adherencia_horas
A90: Coordinador A | B90: =COUNTIFS(tblOrdenes[coordinador],$A90,tblOrdenes[es_habil],"sí") | C90: =COUNTIFS(tblOrdenes[coordinador],$A90,tblOrdenes[estado],"Cerrada",tblOrdenes[es_habil],"sí") | D90: =IF(B90=0,"",C90/B90) | E90: =SUMIFS(tblOrdenes[horas_efectivas],tblOrdenes[coordinador],$A90,tblOrdenes[es_habil],"sí") | F90: =SUMIFS(tblOrdenes[horas_efectivas],tblOrdenes[coordinador],$A90,tblOrdenes[estado],"Cerrada",tblOrdenes[es_habil],"sí") | G90: =IF(E90=0,"",F90/E90)
A91: Coordinador B | B91: =COUNTIFS(tblOrdenes[coordinador],$A91,tblOrdenes[es_habil],"sí") | C91: =COUNTIFS(tblOrdenes[coordinador],$A91,tblOrdenes[estado],"Cerrada",tblOrdenes[es_habil],"sí") | D91: =IF(B91=0,"",C91/B91) | E91: =SUMIFS(tblOrdenes[horas_efectivas],tblOrdenes[coordinador],$A91,tblOrdenes[es_habil],"sí") | F91: =SUMIFS(tblOrdenes[horas_efectivas],tblOrdenes[coordinador],$A91,tblOrdenes[estado],"Cerrada",tblOrdenes[es_habil],"sí") | G91: =IF(E91=0,"",F91/E91)
A92: Coordinador C | B92: =COUNTIFS(tblOrdenes[coordinador],$A92,tblOrdenes[es_habil],"sí") | C92: =COUNTIFS(tblOrdenes[coordinador],$A92,tblOrdenes[estado],"Cerrada",tblOrdenes[es_habil],"sí") | D92: =IF(B92=0,"",C92/B92) | E92: =SUMIFS(tblOrdenes[horas_efectivas],tblOrdenes[coordinador],$A92,tblOrdenes[es_habil],"sí") | F92: =SUMIFS(tblOrdenes[horas_efectivas],tblOrdenes[coordinador],$A92,tblOrdenes[estado],"Cerrada",tblOrdenes[es_habil],"sí") | G92: =IF(E92=0,"",F92/E92)
A94: POR CLASIFICACIÓN
A95: valor | B95: total_ot | C95: cerradas | D95: adherencia_conteo | E95: hh_total | F95: hh_cerradas | G95: adherencia_horas
A96: preventiva | B96: =COUNTIFS(tblOrdenes[clasificacion],$A96,tblOrdenes[es_habil],"sí") | C96: =COUNTIFS(tblOrdenes[clasificacion],$A96,tblOrdenes[estado],"Cerrada",tblOrdenes[es_habil],"sí") | D96: =IF(B96=0,"",C96/B96) | E96: =SUMIFS(tblOrdenes[horas_efectivas],tblOrdenes[clasificacion],$A96,tblOrdenes[es_habil],"sí") | F96: =SUMIFS(tblOrdenes[horas_efectivas],tblOrdenes[clasificacion],$A96,tblOrdenes[estado],"Cerrada",tblOrdenes[es_habil],"sí") | G96: =IF(E96=0,"",F96/E96)
A97: correctiva | B97: =COUNTIFS(tblOrdenes[clasificacion],$A97,tblOrdenes[es_habil],"sí") | C97: =COUNTIFS(tblOrdenes[clasificacion],$A97,tblOrdenes[estado],"Cerrada",tblOrdenes[es_habil],"sí") | D97: =IF(B97=0,"",C97/B97) | E97: =SUMIFS(tblOrdenes[horas_efectivas],tblOrdenes[clasificacion],$A97,tblOrdenes[es_habil],"sí") | F97: =SUMIFS(tblOrdenes[horas_efectivas],tblOrdenes[clasificacion],$A97,tblOrdenes[estado],"Cerrada",tblOrdenes[es_habil],"sí") | G97: =IF(E97=0,"",F97/E97)
A98: sin_clasificar | B98: =COUNTIFS(tblOrdenes[clasificacion],$A98,tblOrdenes[es_habil],"sí") | C98: =COUNTIFS(tblOrdenes[clasificacion],$A98,tblOrdenes[estado],"Cerrada",tblOrdenes[es_habil],"sí") | D98: =IF(B98=0,"",C98/B98) | E98: =SUMIFS(tblOrdenes[horas_efectivas],tblOrdenes[clasificacion],$A98,tblOrdenes[es_habil],"sí") | F98: =SUMIFS(tblOrdenes[horas_efectivas],tblOrdenes[clasificacion],$A98,tblOrdenes[estado],"Cerrada",tblOrdenes[es_habil],"sí") | G98: =IF(E98=0,"",F98/E98)
A100: POR CLASE DE MANTENIMIENTO (mix; la clase la hereda la orden de CAT_TIPOS_OT)
A101: valor | B101: total_ot | C101: cerradas | D101: adherencia_conteo | E101: hh_total | F101: hh_cerradas | G101: adherencia_horas
A102: predictivo | B102: =COUNTIFS(tblOrdenes[clase_mantenimiento],$A102,tblOrdenes[es_habil],"sí") | C102: =COUNTIFS(tblOrdenes[clase_mantenimiento],$A102,tblOrdenes[estado],"Cerrada",tblOrdenes[es_habil],"sí") | D102: =IF(B102=0,"",C102/B102) | E102: =SUMIFS(tblOrdenes[horas_efectivas],tblOrdenes[clase_mantenimiento],$A102,tblOrdenes[es_habil],"sí") | F102: =SUMIFS(tblOrdenes[horas_efectivas],tblOrdenes[clase_mantenimiento],$A102,tblOrdenes[estado],"Cerrada",tblOrdenes[es_habil],"sí") | G102: =IF(E102=0,"",F102/E102)
A103: preventivo | B103: =COUNTIFS(tblOrdenes[clase_mantenimiento],$A103,tblOrdenes[es_habil],"sí") | C103: =COUNTIFS(tblOrdenes[clase_mantenimiento],$A103,tblOrdenes[estado],"Cerrada",tblOrdenes[es_habil],"sí") | D103: =IF(B103=0,"",C103/B103) | E103: =SUMIFS(tblOrdenes[horas_efectivas],tblOrdenes[clase_mantenimiento],$A103,tblOrdenes[es_habil],"sí") | F103: =SUMIFS(tblOrdenes[horas_efectivas],tblOrdenes[clase_mantenimiento],$A103,tblOrdenes[estado],"Cerrada",tblOrdenes[es_habil],"sí") | G103: =IF(E103=0,"",F103/E103)
A104: correctivo_programado | B104: =COUNTIFS(tblOrdenes[clase_mantenimiento],$A104,tblOrdenes[es_habil],"sí") | C104: =COUNTIFS(tblOrdenes[clase_mantenimiento],$A104,tblOrdenes[estado],"Cerrada",tblOrdenes[es_habil],"sí") | D104: =IF(B104=0,"",C104/B104) | E104: =SUMIFS(tblOrdenes[horas_efectivas],tblOrdenes[clase_mantenimiento],$A104,tblOrdenes[es_habil],"sí") | F104: =SUMIFS(tblOrdenes[horas_efectivas],tblOrdenes[clase_mantenimiento],$A104,tblOrdenes[estado],"Cerrada",tblOrdenes[es_habil],"sí") | G104: =IF(E104=0,"",F104/E104)
A105: emergencia | B105: =COUNTIFS(tblOrdenes[clase_mantenimiento],$A105,tblOrdenes[es_habil],"sí") | C105: =COUNTIFS(tblOrdenes[clase_mantenimiento],$A105,tblOrdenes[estado],"Cerrada",tblOrdenes[es_habil],"sí") | D105: =IF(B105=0,"",C105/B105) | E105: =SUMIFS(tblOrdenes[horas_efectivas],tblOrdenes[clase_mantenimiento],$A105,tblOrdenes[es_habil],"sí") | F105: =SUMIFS(tblOrdenes[horas_efectivas],tblOrdenes[clase_mantenimiento],$A105,tblOrdenes[estado],"Cerrada",tblOrdenes[es_habil],"sí") | G105: =IF(E105=0,"",F105/E105)
A106: SIN CLASIFICAR | B106: =COUNTIFS(tblOrdenes[clase_mantenimiento],$A106,tblOrdenes[es_habil],"sí") | C106: =COUNTIFS(tblOrdenes[clase_mantenimiento],$A106,tblOrdenes[estado],"Cerrada",tblOrdenes[es_habil],"sí") | D106: =IF(B106=0,"",C106/B106) | E106: =SUMIFS(tblOrdenes[horas_efectivas],tblOrdenes[clase_mantenimiento],$A106,tblOrdenes[es_habil],"sí") | F106: =SUMIFS(tblOrdenes[horas_efectivas],tblOrdenes[clase_mantenimiento],$A106,tblOrdenes[estado],"Cerrada",tblOrdenes[es_habil],"sí") | G106: =IF(E106=0,"",F106/E106)
...

Sheet PERFIL_HH
A1: PERFIL DE HH (REGLA-6) — especialidad × semana. La serie de semanas se deriva de los datos (capacidad 60); las semanas sin órdenes están ocultas.
A2: =HYPERLINK("#DASHBOARD!A1","◂ VOLVER AL TABLERO")
A3: especialidad | B3: semana | C3: hh_disponible | D3: hh_productiva | E3: hh_preventiva | F3: hh_correctiva | G3: hh_planificada | H3: holgura | I3: pct_carga | N3: lunes_semana | O3: semana (serie auto)
A4: MEC | B4: =$O$4 | C4: =SUMIFS(tblAsignaciones[horas_disponibles],tblAsignaciones[especialidad],$A4,tblAsignaciones[semana],$B4) | D4: =C4*p_factor_productividad | E4: =SUMIFS(tblOrdenes[horas_efectivas],tblOrdenes[especialidad],$A4,tblOrdenes[semana],$B4,tblOrdenes[clasificacion],"preventiva") | F4: =SUMIFS(tblOrdenes[horas_efectivas],tblOrdenes[especialidad],$A4,tblOrdenes[semana],$B4,tblOrdenes[clasificacion],"correctiva") | G4: =E4+F4 | H4: =D4-G4 | I4: =IF(D4=0,"",G4/D4) | N4: =IF(COUNT(tblOrdenes[fecha_inicio])=0,"",MIN(tblOrdenes[fecha_inicio])-WEEKDAY(MIN(tblOrdenes[fecha_inicio]),2)+1) | O4: =IF(N4="","",YEAR(N4+4-WEEKDAY(N4,2))&"-S"&TEXT(_xlfn.ISOWEEKNUM(N4),"00"))
A5: ELE | B5: =$O$4 | C5: =SUMIFS(tblAsignaciones[horas_disponibles],tblAsignaciones[especialidad],$A5,tblAsignaciones[semana],$B5) | D5: =C5*p_factor_productividad | E5: =SUMIFS(tblOrdenes[horas_efectivas],tblOrdenes[especialidad],$A5,tblOrdenes[semana],$B5,tblOrdenes[clasificacion],"preventiva") | F5: =SUMIFS(tblOrdenes[horas_efectivas],tblOrdenes[especialidad],$A5,tblOrdenes[semana],$B5,tblOrdenes[clasificacion],"correctiva") | G5: =E5+F5 | H5: =D5-G5 | I5: =IF(D5=0,"",G5/D5) | N5: =IF(N4="","",IF(N4+7>MAX(tblOrdenes[fecha_inicio]),"",N4+7)) | O5: =IF(N5="","",YEAR(N5+4-WEEKDAY(N5,2))&"-S"&TEXT(_xlfn.ISOWEEKNUM(N5),"00"))
A6: AUT | B6: =$O$4 | C6: =SUMIFS(tblAsignaciones[horas_disponibles],tblAsignaciones[especialidad],$A6,tblAsignaciones[semana],$B6) | D6: =C6*p_factor_productividad | E6: =SUMIFS(tblOrdenes[horas_efectivas],tblOrdenes[especialidad],$A6,tblOrdenes[semana],$B6,tblOrdenes[clasificacion],"preventiva") | F6: =SUMIFS(tblOrdenes[horas_efectivas],tblOrdenes[especialidad],$A6,tblOrdenes[semana],$B6,tblOrdenes[clasificacion],"correctiva") | G6: =E6+F6 | H6: =D6-G6 | I6: =IF(D6=0,"",G6/D6) | N6: =IF(N5="","",IF(N5+7>MAX(tblOrdenes[fecha_inicio]),"",N5+7)) | O6: =IF(N6="","",YEAR(N6+4-WEEKDAY(N6,2))&"-S"&TEXT(_xlfn.ISOWEEKNUM(N6),"00"))
A7: TERCERO | B7: =$O$4 | C7: =SUMIFS(tblAsignaciones[horas_disponibles],tblAsignaciones[especialidad],$A7,tblAsignaciones[semana],$B7) | D7: =C7*p_factor_productividad | E7: =SUMIFS(tblOrdenes[horas_efectivas],tblOrdenes[especialidad],$A7,tblOrdenes[semana],$B7,tblOrdenes[clasificacion],"preventiva") | F7: =SUMIFS(tblOrdenes[horas_efectivas],tblOrdenes[especialidad],$A7,tblOrdenes[semana],$B7,tblOrdenes[clasificacion],"correctiva") | G7: =E7+F7 | H7: =D7-G7 | I7: =IF(D7=0,"",G7/D7) | N7: =IF(N6="","",IF(N6+7>MAX(tblOrdenes[fecha_inicio]),"",N6+7)) | O7: =IF(N7="","",YEAR(N7+4-WEEKDAY(N7,2))&"-S"&TEXT(_xlfn.ISOWEEKNUM(N7),"00"))
A8: MEC | B8: =$O$5 | C8: =SUMIFS(tblAsignaciones[horas_disponibles],tblAsignaciones[especialidad],$A8,tblAsignaciones[semana],$B8) | D8: =C8*p_factor_productividad | E8: =SUMIFS(tblOrdenes[horas_efectivas],tblOrdenes[especialidad],$A8,tblOrdenes[semana],$B8,tblOrdenes[clasificacion],"preventiva") | F8: =SUMIFS(tblOrdenes[horas_efectivas],tblOrdenes[especialidad],$A8,tblOrdenes[semana],$B8,tblOrdenes[clasificacion],"correctiva") | G8: =E8+F8 | H8: =D8-G8 | I8: =IF(D8=0,"",G8/D8) | N8: =IF(N7="","",IF(N7+7>MAX(tblOrdenes[fecha_inicio]),"",N7+7)) | O8: =IF(N8="","",YEAR(N8+4-WEEKDAY(N8,2))&"-S"&TEXT(_xlfn.ISOWEEKNUM(N8),"00"))
A9: ELE | B9: =$O$5 | C9: =SUMIFS(tblAsignaciones[horas_disponibles],tblAsignaciones[especialidad],$A9,tblAsignaciones[semana],$B9) | D9: =C9*p_factor_productividad | E9: =SUMIFS(tblOrdenes[horas_efectivas],tblOrdenes[especialidad],$A9,tblOrdenes[semana],$B9,tblOrdenes[clasificacion],"preventiva") | F9: =SUMIFS(tblOrdenes[horas_efectivas],tblOrdenes[especialidad],$A9,tblOrdenes[semana],$B9,tblOrdenes[clasificacion],"correctiva") | G9: =E9+F9 | H9: =D9-G9 | I9: =IF(D9=0,"",G9/D9) | N9: =IF(N8="","",IF(N8+7>MAX(tblOrdenes[fecha_inicio]),"",N8+7)) | O9: =IF(N9="","",YEAR(N9+4-WEEKDAY(N9,2))&"-S"&TEXT(_xlfn.ISOWEEKNUM(N9),"00"))
A10: AUT | B10: =$O$5 | C10: =SUMIFS(tblAsignaciones[horas_disponibles],tblAsignaciones[especialidad],$A10,tblAsignaciones[semana],$B10) | D10: =C10*p_factor_productividad | E10: =SUMIFS(tblOrdenes[horas_efectivas],tblOrdenes[especialidad],$A10,tblOrdenes[semana],$B10,tblOrdenes[clasificacion],"preventiva") | F10: =SUMIFS(tblOrdenes[horas_efectivas],tblOrdenes[especialidad],$A10,tblOrdenes[semana],$B10,tblOrdenes[clasificacion],"correctiva") | G10: =E10+F10 | H10: =D10-G10 | I10: =IF(D10=0,"",G10/D10) | N10: =IF(N9="","",IF(N9+7>MAX(tblOrdenes[fecha_inicio]),"",N9+7)) | O10: =IF(N10="","",YEAR(N10+4-WEEKDAY(N10,2))&"-S"&TEXT(_xlfn.ISOWEEKNUM(N10),"00"))
A11: TERCERO | B11: =$O$5 | C11: =SUMIFS(tblAsignaciones[horas_disponibles],tblAsignaciones[especialidad],$A11,tblAsignaciones[semana],$B11) | D11: =C11*p_factor_productividad | E11: =SUMIFS(tblOrdenes[horas_efectivas],tblOrdenes[especialidad],$A11,tblOrdenes[semana],$B11,tblOrdenes[clasificacion],"preventiva") | F11: =SUMIFS(tblOrdenes[horas_efectivas],tblOrdenes[especialidad],$A11,tblOrdenes[semana],$B11,tblOrdenes[clasificacion],"correctiva") | G11: =E11+F11 | H11: =D11-G11 | I11: =IF(D11=0,"",G11/D11) | N11: =IF(N10="","",IF(N10+7>MAX(tblOrdenes[fecha_inicio]),"",N10+7)) | O11: =IF(N11="","",YEAR(N11+4-WEEKDAY(N11,2))&"-S"&TEXT(_xlfn.ISOWEEKNUM(N11),"00"))
A12: MEC | B12: =$O$6 | C12: =SUMIFS(tblAsignaciones[horas_disponibles],tblAsignaciones[especialidad],$A12,tblAsignaciones[semana],$B12) | D12: =C12*p_factor_productividad | E12: =SUMIFS(tblOrdenes[horas_efectivas],tblOrdenes[especialidad],$A12,tblOrdenes[semana],$B12,tblOrdenes[clasificacion],"preventiva") | F12: =SUMIFS(tblOrdenes[horas_efectivas],tblOrdenes[especialidad],$A12,tblOrdenes[semana],$B12,tblOrdenes[clasificacion],"correctiva") | G12: =E12+F12 | H12: =D12-G12 | I12: =IF(D12=0,"",G12/D12) | N12: =IF(N11="","",IF(N11+7>MAX(tblOrdenes[fecha_inicio]),"",N11+7)) | O12: =IF(N12="","",YEAR(N12+4-WEEKDAY(N12,2))&"-S"&TEXT(_xlfn.ISOWEEKNUM(N12),"00"))
A13: ELE | B13: =$O$6 | C13: =SUMIFS(tblAsignaciones[horas_disponibles],tblAsignaciones[especialidad],$A13,tblAsignaciones[semana],$B13) | D13: =C13*p_factor_productividad | E13: =SUMIFS(tblOrdenes[horas_efectivas],tblOrdenes[especialidad],$A13,tblOrdenes[semana],$B13,tblOrdenes[clasificacion],"preventiva") | F13: =SUMIFS(tblOrdenes[horas_efectivas],tblOrdenes[especialidad],$A13,tblOrdenes[semana],$B13,tblOrdenes[clasificacion],"correctiva") | G13: =E13+F13 | H13: =D13-G13 | I13: =IF(D13=0,"",G13/D13) | N13: =IF(N12="","",IF(N12+7>MAX(tblOrdenes[fecha_inicio]),"",N12+7)) | O13: =IF(N13="","",YEAR(N13+4-WEEKDAY(N13,2))&"-S"&TEXT(_xlfn.ISOWEEKNUM(N13),"00"))
A14: AUT | B14: =$O$6 | C14: =SUMIFS(tblAsignaciones[horas_disponibles],tblAsignaciones[especialidad],$A14,tblAsignaciones[semana],$B14) | D14: =C14*p_factor_productividad | E14: =SUMIFS(tblOrdenes[horas_efectivas],tblOrdenes[especialidad],$A14,tblOrdenes[semana],$B14,tblOrdenes[clasificacion],"preventiva") | F14: =SUMIFS(tblOrdenes[horas_efectivas],tblOrdenes[especialidad],$A14,tblOrdenes[semana],$B14,tblOrdenes[clasificacion],"correctiva") | G14: =E14+F14 | H14: =D14-G14 | I14: =IF(D14=0,"",G14/D14) | N14: =IF(N13="","",IF(N13+7>MAX(tblOrdenes[fecha_inicio]),"",N13+7)) | O14: =IF(N14="","",YEAR(N14+4-WEEKDAY(N14,2))&"-S"&TEXT(_xlfn.ISOWEEKNUM(N14),"00"))
A15: TERCERO | B15: =$O$6 | C15: =SUMIFS(tblAsignaciones[horas_disponibles],tblAsignaciones[especialidad],$A15,tblAsignaciones[semana],$B15) | D15: =C15*p_factor_productividad | E15: =SUMIFS(tblOrdenes[horas_efectivas],tblOrdenes[especialidad],$A15,tblOrdenes[semana],$B15,tblOrdenes[clasificacion],"preventiva") | F15: =SUMIFS(tblOrdenes[horas_efectivas],tblOrdenes[especialidad],$A15,tblOrdenes[semana],$B15,tblOrdenes[clasificacion],"correctiva") | G15: =E15+F15 | H15: =D15-G15 | I15: =IF(D15=0,"",G15/D15) | N15: =IF(N14="","",IF(N14+7>MAX(tblOrdenes[fecha_inicio]),"",N14+7)) | O15: =IF(N15="","",YEAR(N15+4-WEEKDAY(N15,2))&"-S"&TEXT(_xlfn.ISOWEEKNUM(N15),"00"))
A16: MEC | B16: =$O$7 | C16: =SUMIFS(tblAsignaciones[horas_disponibles],tblAsignaciones[especialidad],$A16,tblAsignaciones[semana],$B16) | D16: =C16*p_factor_productividad | E16: =SUMIFS(tblOrdenes[horas_efectivas],tblOrdenes[especialidad],$A16,tblOrdenes[semana],$B16,tblOrdenes[clasificacion],"preventiva") | F16: =SUMIFS(tblOrdenes[horas_efectivas],tblOrdenes[especialidad],$A16,tblOrdenes[semana],$B16,tblOrdenes[clasificacion],"correctiva") | G16: =E16+F16 | H16: =D16-G16 | I16: =IF(D16=0,"",G16/D16) | N16: =IF(N15="","",IF(N15+7>MAX(tblOrdenes[fecha_inicio]),"",N15+7)) | O16: =IF(N16="","",YEAR(N16+4-WEEKDAY(N16,2))&"-S"&TEXT(_xlfn.ISOWEEKNUM(N16),"00"))
A17: ELE | B17: =$O$7 | C17: =SUMIFS(tblAsignaciones[horas_disponibles],tblAsignaciones[especialidad],$A17,tblAsignaciones[semana],$B17) | D17: =C17*p_factor_productividad | E17: =SUMIFS(tblOrdenes[horas_efectivas],tblOrdenes[especialidad],$A17,tblOrdenes[semana],$B17,tblOrdenes[clasificacion],"preventiva") | F17: =SUMIFS(tblOrdenes[horas_efectivas],tblOrdenes[especialidad],$A17,tblOrdenes[semana],$B17,tblOrdenes[clasificacion],"correctiva") | G17: =E17+F17 | H17: =D17-G17 | I17: =IF(D17=0,"",G17/D17) | N17: =IF(N16="","",IF(N16+7>MAX(tblOrdenes[fecha_inicio]),"",N16+7)) | O17: =IF(N17="","",YEAR(N17+4-WEEKDAY(N17,2))&"-S"&TEXT(_xlfn.ISOWEEKNUM(N17),"00"))
A18: AUT | B18: =$O$7 | C18: =SUMIFS(tblAsignaciones[horas_disponibles],tblAsignaciones[especialidad],$A18,tblAsignaciones[semana],$B18) | D18: =C18*p_factor_productividad | E18: =SUMIFS(tblOrdenes[horas_efectivas],tblOrdenes[especialidad],$A18,tblOrdenes[semana],$B18,tblOrdenes[clasificacion],"preventiva") | F18: =SUMIFS(tblOrdenes[horas_efectivas],tblOrdenes[especialidad],$A18,tblOrdenes[semana],$B18,tblOrdenes[clasificacion],"correctiva") | G18: =E18+F18 | H18: =D18-G18 | I18: =IF(D18=0,"",G18/D18) | N18: =IF(N17="","",IF(N17+7>MAX(tblOrdenes[fecha_inicio]),"",N17+7)) | O18: =IF(N18="","",YEAR(N18+4-WEEKDAY(N18,2))&"-S"&TEXT(_xlfn.ISOWEEKNUM(N18),"00"))
A19: TERCERO | B19: =$O$7 | C19: =SUMIFS(tblAsignaciones[horas_disponibles],tblAsignaciones[especialidad],$A19,tblAsignaciones[semana],$B19) | D19: =C19*p_factor_productividad | E19: =SUMIFS(tblOrdenes[horas_efectivas],tblOrdenes[especialidad],$A19,tblOrdenes[semana],$B19,tblOrdenes[clasificacion],"preventiva") | F19: =SUMIFS(tblOrdenes[horas_efectivas],tblOrdenes[especialidad],$A19,tblOrdenes[semana],$B19,tblOrdenes[clasificacion],"correctiva") | G19: =E19+F19 | H19: =D19-G19 | I19: =IF(D19=0,"",G19/D19) | N19: =IF(N18="","",IF(N18+7>MAX(tblOrdenes[fecha_inicio]),"",N18+7)) | O19: =IF(N19="","",YEAR(N19+4-WEEKDAY(N19,2))&"-S"&TEXT(_xlfn.ISOWEEKNUM(N19),"00"))
A20: MEC | B20: =$O$8 | C20: =SUMIFS(tblAsignaciones[horas_disponibles],tblAsignaciones[especialidad],$A20,tblAsignaciones[semana],$B20) | D20: =C20*p_factor_productividad | E20: =SUMIFS(tblOrdenes[horas_efectivas],tblOrdenes[especialidad],$A20,tblOrdenes[semana],$B20,tblOrdenes[clasificacion],"preventiva") | F20: =SUMIFS(tblOrdenes[horas_efectivas],tblOrdenes[especialidad],$A20,tblOrdenes[semana],$B20,tblOrdenes[clasificacion],"correctiva") | G20: =E20+F20 | H20: =D20-G20 | I20: =IF(D20=0,"",G20/D20) | N20: =IF(N19="","",IF(N19+7>MAX(tblOrdenes[fecha_inicio]),"",N19+7)) | O20: =IF(N20="","",YEAR(N20+4-WEEKDAY(N20,2))&"-S"&TEXT(_xlfn.ISOWEEKNUM(N20),"00"))
A21: ELE | B21: =$O$8 | C21: =SUMIFS(tblAsignaciones[horas_disponibles],tblAsignaciones[especialidad],$A21,tblAsignaciones[semana],$B21) | D21: =C21*p_factor_productividad | E21: =SUMIFS(tblOrdenes[horas_efectivas],tblOrdenes[especialidad],$A21,tblOrdenes[semana],$B21,tblOrdenes[clasificacion],"preventiva") | F21: =SUMIFS(tblOrdenes[horas_efectivas],tblOrdenes[especialidad],$A21,tblOrdenes[semana],$B21,tblOrdenes[clasificacion],"correctiva") | G21: =E21+F21 | H21: =D21-G21 | I21: =IF(D21=0,"",G21/D21) | N21: =IF(N20="","",IF(N20+7>MAX(tblOrdenes[fecha_inicio]),"",N20+7)) | O21: =IF(N21="","",YEAR(N21+4-WEEKDAY(N21,2))&"-S"&TEXT(_xlfn.ISOWEEKNUM(N21),"00"))
A22: AUT | B22: =$O$8 | C22: =SUMIFS(tblAsignaciones[horas_disponibles],tblAsignaciones[especialidad],$A22,tblAsignaciones[semana],$B22) | D22: =C22*p_factor_productividad | E22: =SUMIFS(tblOrdenes[horas_efectivas],tblOrdenes[especialidad],$A22,tblOrdenes[semana],$B22,tblOrdenes[clasificacion],"preventiva") | F22: =SUMIFS(tblOrdenes[horas_efectivas],tblOrdenes[especialidad],$A22,tblOrdenes[semana],$B22,tblOrdenes[clasificacion],"correctiva") | G22: =E22+F22 | H22: =D22-G22 | I22: =IF(D22=0,"",G22/D22) | N22: =IF(N21="","",IF(N21+7>MAX(tblOrdenes[fecha_inicio]),"",N21+7)) | O22: =IF(N22="","",YEAR(N22+4-WEEKDAY(N22,2))&"-S"&TEXT(_xlfn.ISOWEEKNUM(N22),"00"))
A23: TERCERO | B23: =$O$8 | C23: =SUMIFS(tblAsignaciones[horas_disponibles],tblAsignaciones[especialidad],$A23,tblAsignaciones[semana],$B23) | D23: =C23*p_factor_productividad | E23: =SUMIFS(tblOrdenes[horas_efectivas],tblOrdenes[especialidad],$A23,tblOrdenes[semana],$B23,tblOrdenes[clasificacion],"preventiva") | F23: =SUMIFS(tblOrdenes[horas_efectivas],tblOrdenes[especialidad],$A23,tblOrdenes[semana],$B23,tblOrdenes[clasificacion],"correctiva") | G23: =E23+F23 | H23: =D23-G23 | I23: =IF(D23=0,"",G23/D23) | N23: =IF(N22="","",IF(N22+7>MAX(tblOrdenes[fecha_inicio]),"",N22+7)) | O23: =IF(N23="","",YEAR(N23+4-WEEKDAY(N23,2))&"-S"&TEXT(_xlfn.ISOWEEKNUM(N23),"00"))
A24: MEC | B24: =$O$9 | C24: =SUMIFS(tblAsignaciones[horas_disponibles],tblAsignaciones[especialidad],$A24,tblAsignaciones[semana],$B24) | D24: =C24*p_factor_productividad | E24: =SUMIFS(tblOrdenes[horas_efectivas],tblOrdenes[especialidad],$A24,tblOrdenes[semana],$B24,tblOrdenes[clasificacion],"preventiva") | F24: =SUMIFS(tblOrdenes[horas_efectivas],tblOrdenes[especialidad],$A24,tblOrdenes[semana],$B24,tblOrdenes[clasificacion],"correctiva") | G24: =E24+F24 | H24: =D24-G24 | I24: =IF(D24=0,"",G24/D24) | N24: =IF(N23="","",IF(N23+7>MAX(tblOrdenes[fecha_inicio]),"",N23+7)) | O24: =IF(N24="","",YEAR(N24+4-WEEKDAY(N24,2))&"-S"&TEXT(_xlfn.ISOWEEKNUM(N24),"00"))
A25: ELE | B25: =$O$9 | C25: =SUMIFS(tblAsignaciones[horas_disponibles],tblAsignaciones[especialidad],$A25,tblAsignaciones[semana],$B25) | D25: =C25*p_factor_productividad | E25: =SUMIFS(tblOrdenes[horas_efectivas],tblOrdenes[especialidad],$A25,tblOrdenes[semana],$B25,tblOrdenes[clasificacion],"preventiva") | F25: =SUMIFS(tblOrdenes[horas_efectivas],tblOrdenes[especialidad],$A25,tblOrdenes[semana],$B25,tblOrdenes[clasificacion],"correctiva") | G25: =E25+F25 | H25: =D25-G25 | I25: =IF(D25=0,"",G25/D25) | N25: =IF(N24="","",IF(N24+7>MAX(tblOrdenes[fecha_inicio]),"",N24+7)) | O25: =IF(N25="","",YEAR(N25+4-WEEKDAY(N25,2))&"-S"&TEXT(_xlfn.ISOWEEKNUM(N25),"00"))
A26: AUT | B26: =$O$9 | C26: =SUMIFS(tblAsignaciones[horas_disponibles],tblAsignaciones[especialidad],$A26,tblAsignaciones[semana],$B26) | D26: =C26*p_factor_productividad | E26: =SUMIFS(tblOrdenes[horas_efectivas],tblOrdenes[especialidad],$A26,tblOrdenes[semana],$B26,tblOrdenes[clasificacion],"preventiva") | F26: =SUMIFS(tblOrdenes[horas_efectivas],tblOrdenes[especialidad],$A26,tblOrdenes[semana],$B26,tblOrdenes[clasificacion],"correctiva") | G26: =E26+F26 | H26: =D26-G26 | I26: =IF(D26=0,"",G26/D26) | N26: =IF(N25="","",IF(N25+7>MAX(tblOrdenes[fecha_inicio]),"",N25+7)) | O26: =IF(N26="","",YEAR(N26+4-WEEKDAY(N26,2))&"-S"&TEXT(_xlfn.ISOWEEKNUM(N26),"00"))
A27: TERCERO | B27: =$O$9 | C27: =SUMIFS(tblAsignaciones[horas_disponibles],tblAsignaciones[especialidad],$A27,tblAsignaciones[semana],$B27) | D27: =C27*p_factor_productividad | E27: =SUMIFS(tblOrdenes[horas_efectivas],tblOrdenes[especialidad],$A27,tblOrdenes[semana],$B27,tblOrdenes[clasificacion],"preventiva") | F27: =SUMIFS(tblOrdenes[horas_efectivas],tblOrdenes[especialidad],$A27,tblOrdenes[semana],$B27,tblOrdenes[clasificacion],"correctiva") | G27: =E27+F27 | H27: =D27-G27 | I27: =IF(D27=0,"",G27/D27) | N27: =IF(N26="","",IF(N26+7>MAX(tblOrdenes[fecha_inicio]),"",N26+7)) | O27: =IF(N27="","",YEAR(N27+4-WEEKDAY(N27,2))&"-S"&TEXT(_xlfn.ISOWEEKNUM(N27),"00"))
A28: MEC | B28: =$O$10 | C28: =SUMIFS(tblAsignaciones[horas_disponibles],tblAsignaciones[especialidad],$A28,tblAsignaciones[semana],$B28) | D28: =C28*p_factor_productividad | E28: =SUMIFS(tblOrdenes[horas_efectivas],tblOrdenes[especialidad],$A28,tblOrdenes[semana],$B28,tblOrdenes[clasificacion],"preventiva") | F28: =SUMIFS(tblOrdenes[horas_efectivas],tblOrdenes[especialidad],$A28,tblOrdenes[semana],$B28,tblOrdenes[clasificacion],"correctiva") | G28: =E28+F28 | H28: =D28-G28 | I28: =IF(D28=0,"",G28/D28) | N28: =IF(N27="","",IF(N27+7>MAX(tblOrdenes[fecha_inicio]),"",N27+7)) | O28: =IF(N28="","",YEAR(N28+4-WEEKDAY(N28,2))&"-S"&TEXT(_xlfn.ISOWEEKNUM(N28),"00"))
A29: ELE | B29: =$O$10 | C29: =SUMIFS(tblAsignaciones[horas_disponibles],tblAsignaciones[especialidad],$A29,tblAsignaciones[semana],$B29) | D29: =C29*p_factor_productividad | E29: =SUMIFS(tblOrdenes[horas_efectivas],tblOrdenes[especialidad],$A29,tblOrdenes[semana],$B29,tblOrdenes[clasificacion],"preventiva") | F29: =SUMIFS(tblOrdenes[horas_efectivas],tblOrdenes[especialidad],$A29,tblOrdenes[semana],$B29,tblOrdenes[clasificacion],"correctiva") | G29: =E29+F29 | H29: =D29-G29 | I29: =IF(D29=0,"",G29/D29) | N29: =IF(N28="","",IF(N28+7>MAX(tblOrdenes[fecha_inicio]),"",N28+7)) | O29: =IF(N29="","",YEAR(N29+4-WEEKDAY(N29,2))&"-S"&TEXT(_xlfn.ISOWEEKNUM(N29),"00"))
A30: AUT | B30: =$O$10 | C30: =SUMIFS(tblAsignaciones[horas_disponibles],tblAsignaciones[especialidad],$A30,tblAsignaciones[semana],$B30) | D30: =C30*p_factor_productividad | E30: =SUMIFS(tblOrdenes[horas_efectivas],tblOrdenes[especialidad],$A30,tblOrdenes[semana],$B30,tblOrdenes[clasificacion],"preventiva") | F30: =SUMIFS(tblOrdenes[horas_efectivas],tblOrdenes[especialidad],$A30,tblOrdenes[semana],$B30,tblOrdenes[clasificacion],"correctiva") | G30: =E30+F30 | H30: =D30-G30 | I30: =IF(D30=0,"",G30/D30) | N30: =IF(N29="","",IF(N29+7>MAX(tblOrdenes[fecha_inicio]),"",N29+7)) | O30: =IF(N30="","",YEAR(N30+4-WEEKDAY(N30,2))&"-S"&TEXT(_xlfn.ISOWEEKNUM(N30),"00"))
A31: TERCERO | B31: =$O$10 | C31: =SUMIFS(tblAsignaciones[horas_disponibles],tblAsignaciones[especialidad],$A31,tblAsignaciones[semana],$B31) | D31: =C31*p_factor_productividad | E31: =SUMIFS(tblOrdenes[horas_efectivas],tblOrdenes[especialidad],$A31,tblOrdenes[semana],$B31,tblOrdenes[clasificacion],"preventiva") | F31: =SUMIFS(tblOrdenes[horas_efectivas],tblOrdenes[especialidad],$A31,tblOrdenes[semana],$B31,tblOrdenes[clasificacion],"correctiva") | G31: =E31+F31 | H31: =D31-G31 | I31: =IF(D31=0,"",G31/D31) | N31: =IF(N30="","",IF(N30+7>MAX(tblOrdenes[fecha_inicio]),"",N30+7)) | O31: =IF(N31="","",YEAR(N31+4-WEEKDAY(N31,2))&"-S"&TEXT(_xlfn.ISOWEEKNUM(N31),"00"))
A32: MEC | B32: =$O$11 | C32: =SUMIFS(tblAsignaciones[horas_disponibles],tblAsignaciones[especialidad],$A32,tblAsignaciones[semana],$B32) | D32: =C32*p_factor_productividad | E32: =SUMIFS(tblOrdenes[horas_efectivas],tblOrdenes[especialidad],$A32,tblOrdenes[semana],$B32,tblOrdenes[clasificacion],"preventiva") | F32: =SUMIFS(tblOrdenes[horas_efectivas],tblOrdenes[especialidad],$A32,tblOrdenes[semana],$B32,tblOrdenes[clasificacion],"correctiva") | G32: =E32+F32 | H32: =D32-G32 | I32: =IF(D32=0,"",G32/D32) | N32: =IF(N31="","",IF(N31+7>MAX(tblOrdenes[fecha_inicio]),"",N31+7)) | O32: =IF(N32="","",YEAR(N32+4-WEEKDAY(N32,2))&"-S"&TEXT(_xlfn.ISOWEEKNUM(N32),"00"))
A33: ELE | B33: =$O$11 | C33: =SUMIFS(tblAsignaciones[horas_disponibles],tblAsignaciones[especialidad],$A33,tblAsignaciones[semana],$B33) | D33: =C33*p_factor_productividad | E33: =SUMIFS(tblOrdenes[horas_efectivas],tblOrdenes[especialidad],$A33,tblOrdenes[semana],$B33,tblOrdenes[clasificacion],"preventiva") | F33: =SUMIFS(tblOrdenes[horas_efectivas],tblOrdenes[especialidad],$A33,tblOrdenes[semana],$B33,tblOrdenes[clasificacion],"correctiva") | G33: =E33+F33 | H33: =D33-G33 | I33: =IF(D33=0,"",G33/D33) | N33: =IF(N32="","",IF(N32+7>MAX(tblOrdenes[fecha_inicio]),"",N32+7)) | O33: =IF(N33="","",YEAR(N33+4-WEEKDAY(N33,2))&"-S"&TEXT(_xlfn.ISOWEEKNUM(N33),"00"))
A34: AUT | B34: =$O$11 | C34: =SUMIFS(tblAsignaciones[horas_disponibles],tblAsignaciones[especialidad],$A34,tblAsignaciones[semana],$B34) | D34: =C34*p_factor_productividad | E34: =SUMIFS(tblOrdenes[horas_efectivas],tblOrdenes[especialidad],$A34,tblOrdenes[semana],$B34,tblOrdenes[clasificacion],"preventiva") | F34: =SUMIFS(tblOrdenes[horas_efectivas],tblOrdenes[especialidad],$A34,tblOrdenes[semana],$B34,tblOrdenes[clasificacion],"correctiva") | G34: =E34+F34 | H34: =D34-G34 | I34: =IF(D34=0,"",G34/D34) | N34: =IF(N33="","",IF(N33+7>MAX(tblOrdenes[fecha_inicio]),"",N33+7)) | O34: =IF(N34="","",YEAR(N34+4-WEEKDAY(N34,2))&"-S"&TEXT(_xlfn.ISOWEEKNUM(N34),"00"))
A35: TERCERO | B35: =$O$11 | C35: =SUMIFS(tblAsignaciones[horas_disponibles],tblAsignaciones[especialidad],$A35,tblAsignaciones[semana],$B35) | D35: =C35*p_factor_productividad | E35: =SUMIFS(tblOrdenes[horas_efectivas],tblOrdenes[especialidad],$A35,tblOrdenes[semana],$B35,tblOrdenes[clasificacion],"preventiva") | F35: =SUMIFS(tblOrdenes[horas_efectivas],tblOrdenes[especialidad],$A35,tblOrdenes[semana],$B35,tblOrdenes[clasificacion],"correctiva") | G35: =E35+F35 | H35: =D35-G35 | I35: =IF(D35=0,"",G35/D35) | N35: =IF(N34="","",IF(N34+7>MAX(tblOrdenes[fecha_inicio]),"",N34+7)) | O35: =IF(N35="","",YEAR(N35+4-WEEKDAY(N35,2))&"-S"&TEXT(_xlfn.ISOWEEKNUM(N35),"00"))
A36: MEC | B36: =$O$12 | C36: =SUMIFS(tblAsignaciones[horas_disponibles],tblAsignaciones[especialidad],$A36,tblAsignaciones[semana],$B36) | D36: =C36*p_factor_productividad | E36: =SUMIFS(tblOrdenes[horas_efectivas],tblOrdenes[especialidad],$A36,tblOrdenes[semana],$B36,tblOrdenes[clasificacion],"preventiva") | F36: =SUMIFS(tblOrdenes[horas_efectivas],tblOrdenes[especialidad],$A36,tblOrdenes[semana],$B36,tblOrdenes[clasificacion],"correctiva") | G36: =E36+F36 | H36: =D36-G36 | I36: =IF(D36=0,"",G36/D36) | N36: =IF(N35="","",IF(N35+7>MAX(tblOrdenes[fecha_inicio]),"",N35+7)) | O36: =IF(N36="","",YEAR(N36+4-WEEKDAY(N36,2))&"-S"&TEXT(_xlfn.ISOWEEKNUM(N36),"00"))
A37: ELE | B37: =$O$12 | C37: =SUMIFS(tblAsignaciones[horas_disponibles],tblAsignaciones[especialidad],$A37,tblAsignaciones[semana],$B37) | D37: =C37*p_factor_productividad | E37: =SUMIFS(tblOrdenes[horas_efectivas],tblOrdenes[especialidad],$A37,tblOrdenes[semana],$B37,tblOrdenes[clasificacion],"preventiva") | F37: =SUMIFS(tblOrdenes[horas_efectivas],tblOrdenes[especialidad],$A37,tblOrdenes[semana],$B37,tblOrdenes[clasificacion],"correctiva") | G37: =E37+F37 | H37: =D37-G37 | I37: =IF(D37=0,"",G37/D37) | N37: =IF(N36="","",IF(N36+7>MAX(tblOrdenes[fecha_inicio]),"",N36+7)) | O37: =IF(N37="","",YEAR(N37+4-WEEKDAY(N37,2))&"-S"&TEXT(_xlfn.ISOWEEKNUM(N37),"00"))
A38: AUT | B38: =$O$12 | C38: =SUMIFS(tblAsignaciones[horas_disponibles],tblAsignaciones[especialidad],$A38,tblAsignaciones[semana],$B38) | D38: =C38*p_factor_productividad | E38: =SUMIFS(tblOrdenes[horas_efectivas],tblOrdenes[especialidad],$A38,tblOrdenes[semana],$B38,tblOrdenes[clasificacion],"preventiva") | F38: =SUMIFS(tblOrdenes[horas_efectivas],tblOrdenes[especialidad],$A38,tblOrdenes[semana],$B38,tblOrdenes[clasificacion],"correctiva") | G38: =E38+F38 | H38: =D38-G38 | I38: =IF(D38=0,"",G38/D38) | N38: =IF(N37="","",IF(N37+7>MAX(tblOrdenes[fecha_inicio]),"",N37+7)) | O38: =IF(N38="","",YEAR(N38+4-WEEKDAY(N38,2))&"-S"&TEXT(_xlfn.ISOWEEKNUM(N38),"00"))
A39: TERCERO | B39: =$O$12 | C39: =SUMIFS(tblAsignaciones[horas_disponibles],tblAsignaciones[especialidad],$A39,tblAsignaciones[semana],$B39) | D39: =C39*p_factor_productividad | E39: =SUMIFS(tblOrdenes[horas_efectivas],tblOrdenes[especialidad],$A39,tblOrdenes[semana],$B39,tblOrdenes[clasificacion],"preventiva") | F39: =SUMIFS(tblOrdenes[horas_efectivas],tblOrdenes[especialidad],$A39,tblOrdenes[semana],$B39,tblOrdenes[clasificacion],"correctiva") | G39: =E39+F39 | H39: =D39-G39 | I39: =IF(D39=0,"",G39/D39) | N39: =IF(N38="","",IF(N38+7>MAX(tblOrdenes[fecha_inicio]),"",N38+7)) | O39: =IF(N39="","",YEAR(N39+4-WEEKDAY(N39,2))&"-S"&TEXT(_xlfn.ISOWEEKNUM(N39),"00"))
A40: MEC | B40: =$O$13 | C40: =SUMIFS(tblAsignaciones[horas_disponibles],tblAsignaciones[especialidad],$A40,tblAsignaciones[semana],$B40) | D40: =C40*p_factor_productividad | E40: =SUMIFS(tblOrdenes[horas_efectivas],tblOrdenes[especialidad],$A40,tblOrdenes[semana],$B40,tblOrdenes[clasificacion],"preventiva") | F40: =SUMIFS(tblOrdenes[horas_efectivas],tblOrdenes[especialidad],$A40,tblOrdenes[semana],$B40,tblOrdenes[clasificacion],"correctiva") | G40: =E40+F40 | H40: =D40-G40 | I40: =IF(D40=0,"",G40/D40) | N40: =IF(N39="","",IF(N39+7>MAX(tblOrdenes[fecha_inicio]),"",N39+7)) | O40: =IF(N40="","",YEAR(N40+4-WEEKDAY(N40,2))&"-S"&TEXT(_xlfn.ISOWEEKNUM(N40),"00"))
A41: ELE | B41: =$O$13 | C41: =SUMIFS(tblAsignaciones[horas_disponibles],tblAsignaciones[especialidad],$A41,tblAsignaciones[semana],$B41) | D41: =C41*p_factor_productividad | E41: =SUMIFS(tblOrdenes[horas_efectivas],tblOrdenes[especialidad],$A41,tblOrdenes[semana],$B41,tblOrdenes[clasificacion],"preventiva") | F41: =SUMIFS(tblOrdenes[horas_efectivas],tblOrdenes[especialidad],$A41,tblOrdenes[semana],$B41,tblOrdenes[clasificacion],"correctiva") | G41: =E41+F41 | H41: =D41-G41 | I41: =IF(D41=0,"",G41/D41) | N41: =IF(N40="","",IF(N40+7>MAX(tblOrdenes[fecha_inicio]),"",N40+7)) | O41: =IF(N41="","",YEAR(N41+4-WEEKDAY(N41,2))&"-S"&TEXT(_xlfn.ISOWEEKNUM(N41),"00"))
A42: AUT | B42: =$O$13 | C42: =SUMIFS(tblAsignaciones[horas_disponibles],tblAsignaciones[especialidad],$A42,tblAsignaciones[semana],$B42) | D42: =C42*p_factor_productividad | E42: =SUMIFS(tblOrdenes[horas_efectivas],tblOrdenes[especialidad],$A42,tblOrdenes[semana],$B42,tblOrdenes[clasificacion],"preventiva") | F42: =SUMIFS(tblOrdenes[horas_efectivas],tblOrdenes[especialidad],$A42,tblOrdenes[semana],$B42,tblOrdenes[clasificacion],"correctiva") | G42: =E42+F42 | H42: =D42-G42 | I42: =IF(D42=0,"",G42/D42) | N42: =IF(N41="","",IF(N41+7>MAX(tblOrdenes[fecha_inicio]),"",N41+7)) | O42: =IF(N42="","",YEAR(N42+4-WEEKDAY(N42,2))&"-S"&TEXT(_xlfn.ISOWEEKNUM(N42),"00"))
A43: TERCERO | B43: =$O$13 | C43: =SUMIFS(tblAsignaciones[horas_disponibles],tblAsignaciones[especialidad],$A43,tblAsignaciones[semana],$B43) | D43: =C43*p_factor_productividad | E43: =SUMIFS(tblOrdenes[horas_efectivas],tblOrdenes[especialidad],$A43,tblOrdenes[semana],$B43,tblOrdenes[clasificacion],"preventiva") | F43: =SUMIFS(tblOrdenes[horas_efectivas],tblOrdenes[especialidad],$A43,tblOrdenes[semana],$B43,tblOrdenes[clasificacion],"correctiva") | G43: =E43+F43 | H43: =D43-G43 | I43: =IF(D43=0,"",G43/D43) | N43: =IF(N42="","",IF(N42+7>MAX(tblOrdenes[fecha_inicio]),"",N42+7)) | O43: =IF(N43="","",YEAR(N43+4-WEEKDAY(N43,2))&"-S"&TEXT(_xlfn.ISOWEEKNUM(N43),"00"))
A44: MEC | B44: =$O$14 | C44: =SUMIFS(tblAsignaciones[horas_disponibles],tblAsignaciones[especialidad],$A44,tblAsignaciones[semana],$B44) | D44: =C44*p_factor_productividad | E44: =SUMIFS(tblOrdenes[horas_efectivas],tblOrdenes[especialidad],$A44,tblOrdenes[semana],$B44,tblOrdenes[clasificacion],"preventiva") | F44: =SUMIFS(tblOrdenes[horas_efectivas],tblOrdenes[especialidad],$A44,tblOrdenes[semana],$B44,tblOrdenes[clasificacion],"correctiva") | G44: =E44+F44 | H44: =D44-G44 | I44: =IF(D44=0,"",G44/D44) | N44: =IF(N43="","",IF(N43+7>MAX(tblOrdenes[fecha_inicio]),"",N43+7)) | O44: =IF(N44="","",YEAR(N44+4-WEEKDAY(N44,2))&"-S"&TEXT(_xlfn.ISOWEEKNUM(N44),"00"))
A45: ELE | B45: =$O$14 | C45: =SUMIFS(tblAsignaciones[horas_disponibles],tblAsignaciones[especialidad],$A45,tblAsignaciones[semana],$B45) | D45: =C45*p_factor_productividad | E45: =SUMIFS(tblOrdenes[horas_efectivas],tblOrdenes[especialidad],$A45,tblOrdenes[semana],$B45,tblOrdenes[clasificacion],"preventiva") | F45: =SUMIFS(tblOrdenes[horas_efectivas],tblOrdenes[especialidad],$A45,tblOrdenes[semana],$B45,tblOrdenes[clasificacion],"correctiva") | G45: =E45+F45 | H45: =D45-G45 | I45: =IF(D45=0,"",G45/D45) | N45: =IF(N44="","",IF(N44+7>MAX(tblOrdenes[fecha_inicio]),"",N44+7)) | O45: =IF(N45="","",YEAR(N45+4-WEEKDAY(N45,2))&"-S"&TEXT(_xlfn.ISOWEEKNUM(N45),"00"))
A46: AUT | B46: =$O$14 | C46: =SUMIFS(tblAsignaciones[horas_disponibles],tblAsignaciones[especialidad],$A46,tblAsignaciones[semana],$B46) | D46: =C46*p_factor_productividad | E46: =SUMIFS(tblOrdenes[horas_efectivas],tblOrdenes[especialidad],$A46,tblOrdenes[semana],$B46,tblOrdenes[clasificacion],"preventiva") | F46: =SUMIFS(tblOrdenes[horas_efectivas],tblOrdenes[especialidad],$A46,tblOrdenes[semana],$B46,tblOrdenes[clasificacion],"correctiva") | G46: =E46+F46 | H46: =D46-G46 | I46: =IF(D46=0,"",G46/D46) | N46: =IF(N45="","",IF(N45+7>MAX(tblOrdenes[fecha_inicio]),"",N45+7)) | O46: =IF(N46="","",YEAR(N46+4-WEEKDAY(N46,2))&"-S"&TEXT(_xlfn.ISOWEEKNUM(N46),"00"))
A47: TERCERO | B47: =$O$14 | C47: =SUMIFS(tblAsignaciones[horas_disponibles],tblAsignaciones[especialidad],$A47,tblAsignaciones[semana],$B47) | D47: =C47*p_factor_productividad | E47: =SUMIFS(tblOrdenes[horas_efectivas],tblOrdenes[especialidad],$A47,tblOrdenes[semana],$B47,tblOrdenes[clasificacion],"preventiva") | F47: =SUMIFS(tblOrdenes[horas_efectivas],tblOrdenes[especialidad],$A47,tblOrdenes[semana],$B47,tblOrdenes[clasificacion],"correctiva") | G47: =E47+F47 | H47: =D47-G47 | I47: =IF(D47=0,"",G47/D47) | N47: =IF(N46="","",IF(N46+7>MAX(tblOrdenes[fecha_inicio]),"",N46+7)) | O47: =IF(N47="","",YEAR(N47+4-WEEKDAY(N47,2))&"-S"&TEXT(_xlfn.ISOWEEKNUM(N47),"00"))
A48: MEC | B48: =$O$15 | C48: =SUMIFS(tblAsignaciones[horas_disponibles],tblAsignaciones[especialidad],$A48,tblAsignaciones[semana],$B48) | D48: =C48*p_factor_productividad | E48: =SUMIFS(tblOrdenes[horas_efectivas],tblOrdenes[especialidad],$A48,tblOrdenes[semana],$B48,tblOrdenes[clasificacion],"preventiva") | F48: =SUMIFS(tblOrdenes[horas_efectivas],tblOrdenes[especialidad],$A48,tblOrdenes[semana],$B48,tblOrdenes[clasificacion],"correctiva") | G48: =E48+F48 | H48: =D48-G48 | I48: =IF(D48=0,"",G48/D48) | N48: =IF(N47="","",IF(N47+7>MAX(tblOrdenes[fecha_inicio]),"",N47+7)) | O48: =IF(N48="","",YEAR(N48+4-WEEKDAY(N48,2))&"-S"&TEXT(_xlfn.ISOWEEKNUM(N48),"00"))
A49: ELE | B49: =$O$15 | C49: =SUMIFS(tblAsignaciones[horas_disponibles],tblAsignaciones[especialidad],$A49,tblAsignaciones[semana],$B49) | D49: =C49*p_factor_productividad | E49: =SUMIFS(tblOrdenes[horas_efectivas],tblOrdenes[especialidad],$A49,tblOrdenes[semana],$B49,tblOrdenes[clasificacion],"preventiva") | F49: =SUMIFS(tblOrdenes[horas_efectivas],tblOrdenes[especialidad],$A49,tblOrdenes[semana],$B49,tblOrdenes[clasificacion],"correctiva") | G49: =E49+F49 | H49: =D49-G49 | I49: =IF(D49=0,"",G49/D49) | N49: =IF(N48="","",IF(N48+7>MAX(tblOrdenes[fecha_inicio]),"",N48+7)) | O49: =IF(N49="","",YEAR(N49+4-WEEKDAY(N49,2))&"-S"&TEXT(_xlfn.ISOWEEKNUM(N49),"00"))
A50: AUT | B50: =$O$15 | C50: =SUMIFS(tblAsignaciones[horas_disponibles],tblAsignaciones[especialidad],$A50,tblAsignaciones[semana],$B50) | D50: =C50*p_factor_productividad | E50: =SUMIFS(tblOrdenes[horas_efectivas],tblOrdenes[especialidad],$A50,tblOrdenes[semana],$B50,tblOrdenes[clasificacion],"preventiva") | F50: =SUMIFS(tblOrdenes[horas_efectivas],tblOrdenes[especialidad],$A50,tblOrdenes[semana],$B50,tblOrdenes[clasificacion],"correctiva") | G50: =E50+F50 | H50: =D50-G50 | I50: =IF(D50=0,"",G50/D50) | N50: =IF(N49="","",IF(N49+7>MAX(tblOrdenes[fecha_inicio]),"",N49+7)) | O50: =IF(N50="","",YEAR(N50+4-WEEKDAY(N50,2))&"-S"&TEXT(_xlfn.ISOWEEKNUM(N50),"00"))
A51: TERCERO | B51: =$O$15 | C51: =SUMIFS(tblAsignaciones[horas_disponibles],tblAsignaciones[especialidad],$A51,tblAsignaciones[semana],$B51) | D51: =C51*p_factor_productividad | E51: =SUMIFS(tblOrdenes[horas_efectivas],tblOrdenes[especialidad],$A51,tblOrdenes[semana],$B51,tblOrdenes[clasificacion],"preventiva") | F51: =SUMIFS(tblOrdenes[horas_efectivas],tblOrdenes[especialidad],$A51,tblOrdenes[semana],$B51,tblOrdenes[clasificacion],"correctiva") | G51: =E51+F51 | H51: =D51-G51 | I51: =IF(D51=0,"",G51/D51) | N51: =IF(N50="","",IF(N50+7>MAX(tblOrdenes[fecha_inicio]),"",N50+7)) | O51: =IF(N51="","",YEAR(N51+4-WEEKDAY(N51,2))&"-S"&TEXT(_xlfn.ISOWEEKNUM(N51),"00"))
A52: MEC | B52: =$O$16 | C52: =SUMIFS(tblAsignaciones[horas_disponibles],tblAsignaciones[especialidad],$A52,tblAsignaciones[semana],$B52) | D52: =C52*p_factor_productividad | E52: =SUMIFS(tblOrdenes[horas_efectivas],tblOrdenes[especialidad],$A52,tblOrdenes[semana],$B52,tblOrdenes[clasificacion],"preventiva") | F52: =SUMIFS(tblOrdenes[horas_efectivas],tblOrdenes[especialidad],$A52,tblOrdenes[semana],$B52,tblOrdenes[clasificacion],"correctiva") | G52: =E52+F52 | H52: =D52-G52 | I52: =IF(D52=0,"",G52/D52) | N52: =IF(N51="","",IF(N51+7>MAX(tblOrdenes[fecha_inicio]),"",N51+7)) | O52: =IF(N52="","",YEAR(N52+4-WEEKDAY(N52,2))&"-S"&TEXT(_xlfn.ISOWEEKNUM(N52),"00"))
A53: ELE | B53: =$O$16 | C53: =SUMIFS(tblAsignaciones[horas_disponibles],tblAsignaciones[especialidad],$A53,tblAsignaciones[semana],$B53) | D53: =C53*p_factor_productividad | E53: =SUMIFS(tblOrdenes[horas_efectivas],tblOrdenes[especialidad],$A53,tblOrdenes[semana],$B53,tblOrdenes[clasificacion],"preventiva") | F53: =SUMIFS(tblOrdenes[horas_efectivas],tblOrdenes[especialidad],$A53,tblOrdenes[semana],$B53,tblOrdenes[clasificacion],"correctiva") | G53: =E53+F53 | H53: =D53-G53 | I53: =IF(D53=0,"",G53/D53) | N53: =IF(N52="","",IF(N52+7>MAX(tblOrdenes[fecha_inicio]),"",N52+7)) | O53: =IF(N53="","",YEAR(N53+4-WEEKDAY(N53,2))&"-S"&TEXT(_xlfn.ISOWEEKNUM(N53),"00"))
A54: AUT | B54: =$O$16 | C54: =SUMIFS(tblAsignaciones[horas_disponibles],tblAsignaciones[especialidad],$A54,tblAsignaciones[semana],$B54) | D54: =C54*p_factor_productividad | E54: =SUMIFS(tblOrdenes[horas_efectivas],tblOrdenes[especialidad],$A54,tblOrdenes[semana],$B54,tblOrdenes[clasificacion],"preventiva") | F54: =SUMIFS(tblOrdenes[horas_efectivas],tblOrdenes[especialidad],$A54,tblOrdenes[semana],$B54,tblOrdenes[clasificacion],"correctiva") | G54: =E54+F54 | H54: =D54-G54 | I54: =IF(D54=0,"",G54/D54) | N54: =IF(N53="","",IF(N53+7>MAX(tblOrdenes[fecha_inicio]),"",N53+7)) | O54: =IF(N54="","",YEAR(N54+4-WEEKDAY(N54,2))&"-S"&TEXT(_xlfn.ISOWEEKNUM(N54),"00"))
A55: TERCERO | B55: =$O$16 | C55: =SUMIFS(tblAsignaciones[horas_disponibles],tblAsignaciones[especialidad],$A55,tblAsignaciones[semana],$B55) | D55: =C55*p_factor_productividad | E55: =SUMIFS(tblOrdenes[horas_efectivas],tblOrdenes[especialidad],$A55,tblOrdenes[semana],$B55,tblOrdenes[clasificacion],"preventiva") | F55: =SUMIFS(tblOrdenes[horas_efectivas],tblOrdenes[especialidad],$A55,tblOrdenes[semana],$B55,tblOrdenes[clasificacion],"correctiva") | G55: =E55+F55 | H55: =D55-G55 | I55: =IF(D55=0,"",G55/D55) | N55: =IF(N54="","",IF(N54+7>MAX(tblOrdenes[fecha_inicio]),"",N54+7)) | O55: =IF(N55="","",YEAR(N55+4-WEEKDAY(N55,2))&"-S"&TEXT(_xlfn.ISOWEEKNUM(N55),"00"))
A56: MEC | B56: =$O$17 | C56: =SUMIFS(tblAsignaciones[horas_disponibles],tblAsignaciones[especialidad],$A56,tblAsignaciones[semana],$B56) | D56: =C56*p_factor_productividad | E56: =SUMIFS(tblOrdenes[horas_efectivas],tblOrdenes[especialidad],$A56,tblOrdenes[semana],$B56,tblOrdenes[clasificacion],"preventiva") | F56: =SUMIFS(tblOrdenes[horas_efectivas],tblOrdenes[especialidad],$A56,tblOrdenes[semana],$B56,tblOrdenes[clasificacion],"correctiva") | G56: =E56+F56 | H56: =D56-G56 | I56: =IF(D56=0,"",G56/D56) | N56: =IF(N55="","",IF(N55+7>MAX(tblOrdenes[fecha_inicio]),"",N55+7)) | O56: =IF(N56="","",YEAR(N56+4-WEEKDAY(N56,2))&"-S"&TEXT(_xlfn.ISOWEEKNUM(N56),"00"))
A57: ELE | B57: =$O$17 | C57: =SUMIFS(tblAsignaciones[horas_disponibles],tblAsignaciones[especialidad],$A57,tblAsignaciones[semana],$B57) | D57: =C57*p_factor_productividad | E57: =SUMIFS(tblOrdenes[horas_efectivas],tblOrdenes[especialidad],$A57,tblOrdenes[semana],$B57,tblOrdenes[clasificacion],"preventiva") | F57: =SUMIFS(tblOrdenes[horas_efectivas],tblOrdenes[especialidad],$A57,tblOrdenes[semana],$B57,tblOrdenes[clasificacion],"correctiva") | G57: =E57+F57 | H57: =D57-G57 | I57: =IF(D57=0,"",G57/D57) | N57: =IF(N56="","",IF(N56+7>MAX(tblOrdenes[fecha_inicio]),"",N56+7)) | O57: =IF(N57="","",YEAR(N57+4-WEEKDAY(N57,2))&"-S"&TEXT(_xlfn.ISOWEEKNUM(N57),"00"))
A58: AUT | B58: =$O$17 | C58: =SUMIFS(tblAsignaciones[horas_disponibles],tblAsignaciones[especialidad],$A58,tblAsignaciones[semana],$B58) | D58: =C58*p_factor_productividad | E58: =SUMIFS(tblOrdenes[horas_efectivas],tblOrdenes[especialidad],$A58,tblOrdenes[semana],$B58,tblOrdenes[clasificacion],"preventiva") | F58: =SUMIFS(tblOrdenes[horas_efectivas],tblOrdenes[especialidad],$A58,tblOrdenes[semana],$B58,tblOrdenes[clasificacion],"correctiva") | G58: =E58+F58 | H58: =D58-G58 | I58: =IF(D58=0,"",G58/D58) | N58: =IF(N57="","",IF(N57+7>MAX(tblOrdenes[fecha_inicio]),"",N57+7)) | O58: =IF(N58="","",YEAR(N58+4-WEEKDAY(N58,2))&"-S"&TEXT(_xlfn.ISOWEEKNUM(N58),"00"))
A59: TERCERO | B59: =$O$17 | C59: =SUMIFS(tblAsignaciones[horas_disponibles],tblAsignaciones[especialidad],$A59,tblAsignaciones[semana],$B59) | D59: =C59*p_factor_productividad | E59: =SUMIFS(tblOrdenes[horas_efectivas],tblOrdenes[especialidad],$A59,tblOrdenes[semana],$B59,tblOrdenes[clasificacion],"preventiva") | F59: =SUMIFS(tblOrdenes[horas_efectivas],tblOrdenes[especialidad],$A59,tblOrdenes[semana],$B59,tblOrdenes[clasificacion],"correctiva") | G59: =E59+F59 | H59: =D59-G59 | I59: =IF(D59=0,"",G59/D59) | N59: =IF(N58="","",IF(N58+7>MAX(tblOrdenes[fecha_inicio]),"",N58+7)) | O59: =IF(N59="","",YEAR(N59+4-WEEKDAY(N59,2))&"-S"&TEXT(_xlfn.ISOWEEKNUM(N59),"00"))
A60: MEC | B60: =$O$18 | C60: =SUMIFS(tblAsignaciones[horas_disponibles],tblAsignaciones[especialidad],$A60,tblAsignaciones[semana],$B60) | D60: =C60*p_factor_productividad | E60: =SUMIFS(tblOrdenes[horas_efectivas],tblOrdenes[especialidad],$A60,tblOrdenes[semana],$B60,tblOrdenes[clasificacion],"preventiva") | F60: =SUMIFS(tblOrdenes[horas_efectivas],tblOrdenes[especialidad],$A60,tblOrdenes[semana],$B60,tblOrdenes[clasificacion],"correctiva") | G60: =E60+F60 | H60: =D60-G60 | I60: =IF(D60=0,"",G60/D60) | N60: =IF(N59="","",IF(N59+7>MAX(tblOrdenes[fecha_inicio]),"",N59+7)) | O60: =IF(N60="","",YEAR(N60+4-WEEKDAY(N60,2))&"-S"&TEXT(_xlfn.ISOWEEKNUM(N60),"00"))
A61: ELE | B61: =$O$18 | C61: =SUMIFS(tblAsignaciones[horas_disponibles],tblAsignaciones[especialidad],$A61,tblAsignaciones[semana],$B61) | D61: =C61*p_factor_productividad | E61: =SUMIFS(tblOrdenes[horas_efectivas],tblOrdenes[especialidad],$A61,tblOrdenes[semana],$B61,tblOrdenes[clasificacion],"preventiva") | F61: =SUMIFS(tblOrdenes[horas_efectivas],tblOrdenes[especialidad],$A61,tblOrdenes[semana],$B61,tblOrdenes[clasificacion],"correctiva") | G61: =E61+F61 | H61: =D61-G61 | I61: =IF(D61=0,"",G61/D61) | N61: =IF(N60="","",IF(N60+7>MAX(tblOrdenes[fecha_inicio]),"",N60+7)) | O61: =IF(N61="","",YEAR(N61+4-WEEKDAY(N61,2))&"-S"&TEXT(_xlfn.ISOWEEKNUM(N61),"00"))
A62: AUT | B62: =$O$18 | C62: =SUMIFS(tblAsignaciones[horas_disponibles],tblAsignaciones[especialidad],$A62,tblAsignaciones[semana],$B62) | D62: =C62*p_factor_productividad | E62: =SUMIFS(tblOrdenes[horas_efectivas],tblOrdenes[especialidad],$A62,tblOrdenes[semana],$B62,tblOrdenes[clasificacion],"preventiva") | F62: =SUMIFS(tblOrdenes[horas_efectivas],tblOrdenes[especialidad],$A62,tblOrdenes[semana],$B62,tblOrdenes[clasificacion],"correctiva") | G62: =E62+F62 | H62: =D62-G62 | I62: =IF(D62=0,"",G62/D62) | N62: =IF(N61="","",IF(N61+7>MAX(tblOrdenes[fecha_inicio]),"",N61+7)) | O62: =IF(N62="","",YEAR(N62+4-WEEKDAY(N62,2))&"-S"&TEXT(_xlfn.ISOWEEKNUM(N62),"00"))
A63: TERCERO | B63: =$O$18 | C63: =SUMIFS(tblAsignaciones[horas_disponibles],tblAsignaciones[especialidad],$A63,tblAsignaciones[semana],$B63) | D63: =C63*p_factor_productividad | E63: =SUMIFS(tblOrdenes[horas_efectivas],tblOrdenes[especialidad],$A63,tblOrdenes[semana],$B63,tblOrdenes[clasificacion],"preventiva") | F63: =SUMIFS(tblOrdenes[horas_efectivas],tblOrdenes[especialidad],$A63,tblOrdenes[semana],$B63,tblOrdenes[clasificacion],"correctiva") | G63: =E63+F63 | H63: =D63-G63 | I63: =IF(D63=0,"",G63/D63) | N63: =IF(N62="","",IF(N62+7>MAX(tblOrdenes[fecha_inicio]),"",N62+7)) | O63: =IF(N63="","",YEAR(N63+4-WEEKDAY(N63,2))&"-S"&TEXT(_xlfn.ISOWEEKNUM(N63),"00"))
A64: MEC | B64: =$O$19 | C64: =SUMIFS(tblAsignaciones[horas_disponibles],tblAsignaciones[especialidad],$A64,tblAsignaciones[semana],$B64) | D64: =C64*p_factor_productividad | E64: =SUMIFS(tblOrdenes[horas_efectivas],tblOrdenes[especialidad],$A64,tblOrdenes[semana],$B64,tblOrdenes[clasificacion],"preventiva") | F64: =SUMIFS(tblOrdenes[horas_efectivas],tblOrdenes[especialidad],$A64,tblOrdenes[semana],$B64,tblOrdenes[clasificacion],"correctiva") | G64: =E64+F64 | H64: =D64-G64 | I64: =IF(D64=0,"",G64/D64)
A65: ELE | B65: =$O$19 | C65: =SUMIFS(tblAsignaciones[horas_disponibles],tblAsignaciones[especialidad],$A65,tblAsignaciones[semana],$B65) | D65: =C65*p_factor_productividad | E65: =SUMIFS(tblOrdenes[horas_efectivas],tblOrdenes[especialidad],$A65,tblOrdenes[semana],$B65,tblOrdenes[clasificacion],"preventiva") | F65: =SUMIFS(tblOrdenes[horas_efectivas],tblOrdenes[especialidad],$A65,tblOrdenes[semana],$B65,tblOrdenes[clasificacion],"correctiva") | G65: =E65+F65 | H65: =D65-G65 | I65: =IF(D65=0,"",G65/D65)
A66: AUT | B66: =$O$19 | C66: =SUMIFS(tblAsignaciones[horas_disponibles],tblAsignaciones[especialidad],$A66,tblAsignaciones[semana],$B66) | D66: =C66*p_factor_productividad | E66: =SUMIFS(tblOrdenes[horas_efectivas],tblOrdenes[especialidad],$A66,tblOrdenes[semana],$B66,tblOrdenes[clasificacion],"preventiva") | F66: =SUMIFS(tblOrdenes[horas_efectivas],tblOrdenes[especialidad],$A66,tblOrdenes[semana],$B66,tblOrdenes[clasificacion],"correctiva") | G66: =E66+F66 | H66: =D66-G66 | I66: =IF(D66=0,"",G66/D66)
A67: TERCERO | B67: =$O$19 | C67: =SUMIFS(tblAsignaciones[horas_disponibles],tblAsignaciones[especialidad],$A67,tblAsignaciones[semana],$B67) | D67: =C67*p_factor_productividad | E67: =SUMIFS(tblOrdenes[horas_efectivas],tblOrdenes[especialidad],$A67,tblOrdenes[semana],$B67,tblOrdenes[clasificacion],"preventiva") | F67: =SUMIFS(tblOrdenes[horas_efectivas],tblOrdenes[especialidad],$A67,tblOrdenes[semana],$B67,tblOrdenes[clasificacion],"correctiva") | G67: =E67+F67 | H67: =D67-G67 | I67: =IF(D67=0,"",G67/D67)
A68: MEC | B68: =$O$20 | C68: =SUMIFS(tblAsignaciones[horas_disponibles],tblAsignaciones[especialidad],$A68,tblAsignaciones[semana],$B68) | D68: =C68*p_factor_productividad | E68: =SUMIFS(tblOrdenes[horas_efectivas],tblOrdenes[especialidad],$A68,tblOrdenes[semana],$B68,tblOrdenes[clasificacion],"preventiva") | F68: =SUMIFS(tblOrdenes[horas_efectivas],tblOrdenes[especialidad],$A68,tblOrdenes[semana],$B68,tblOrdenes[clasificacion],"correctiva") | G68: =E68+F68 | H68: =D68-G68 | I68: =IF(D68=0,"",G68/D68)
A69: ELE | B69: =$O$20 | C69: =SUMIFS(tblAsignaciones[horas_disponibles],tblAsignaciones[especialidad],$A69,tblAsignaciones[semana],$B69) | D69: =C69*p_factor_productividad | E69: =SUMIFS(tblOrdenes[horas_efectivas],tblOrdenes[especialidad],$A69,tblOrdenes[semana],$B69,tblOrdenes[clasificacion],"preventiva") | F69: =SUMIFS(tblOrdenes[horas_efectivas],tblOrdenes[especialidad],$A69,tblOrdenes[semana],$B69,tblOrdenes[clasificacion],"correctiva") | G69: =E69+F69 | H69: =D69-G69 | I69: =IF(D69=0,"",G69/D69)
A70: AUT | B70: =$O$20 | C70: =SUMIFS(tblAsignaciones[horas_disponibles],tblAsignaciones[especialidad],$A70,tblAsignaciones[semana],$B70) | D70: =C70*p_factor_productividad | E70: =SUMIFS(tblOrdenes[horas_efectivas],tblOrdenes[especialidad],$A70,tblOrdenes[semana],$B70,tblOrdenes[clasificacion],"preventiva") | F70: =SUMIFS(tblOrdenes[horas_efectivas],tblOrdenes[especialidad],$A70,tblOrdenes[semana],$B70,tblOrdenes[clasificacion],"correctiva") | G70: =E70+F70 | H70: =D70-G70 | I70: =IF(D70=0,"",G70/D70)
A71: TERCERO | B71: =$O$20 | C71: =SUMIFS(tblAsignaciones[horas_disponibles],tblAsignaciones[especialidad],$A71,tblAsignaciones[semana],$B71) | D71: =C71*p_factor_productividad | E71: =SUMIFS(tblOrdenes[horas_efectivas],tblOrdenes[especialidad],$A71,tblOrdenes[semana],$B71,tblOrdenes[clasificacion],"preventiva") | F71: =SUMIFS(tblOrdenes[horas_efectivas],tblOrdenes[especialidad],$A71,tblOrdenes[semana],$B71,tblOrdenes[clasificacion],"correctiva") | G71: =E71+F71 | H71: =D71-G71 | I71: =IF(D71=0,"",G71/D71)
A72: MEC | B72: =$O$21 | C72: =SUMIFS(tblAsignaciones[horas_disponibles],tblAsignaciones[especialidad],$A72,tblAsignaciones[semana],$B72) | D72: =C72*p_factor_productividad | E72: =SUMIFS(tblOrdenes[horas_efectivas],tblOrdenes[especialidad],$A72,tblOrdenes[semana],$B72,tblOrdenes[clasificacion],"preventiva") | F72: =SUMIFS(tblOrdenes[horas_efectivas],tblOrdenes[especialidad],$A72,tblOrdenes[semana],$B72,tblOrdenes[clasificacion],"correctiva") | G72: =E72+F72 | H72: =D72-G72 | I72: =IF(D72=0,"",G72/D72)
A73: ELE | B73: =$O$21 | C73: =SUMIFS(tblAsignaciones[horas_disponibles],tblAsignaciones[especialidad],$A73,tblAsignaciones[semana],$B73) | D73: =C73*p_factor_productividad | E73: =SUMIFS(tblOrdenes[horas_efectivas],tblOrdenes[especialidad],$A73,tblOrdenes[semana],$B73,tblOrdenes[clasificacion],"preventiva") | F73: =SUMIFS(tblOrdenes[horas_efectivas],tblOrdenes[especialidad],$A73,tblOrdenes[semana],$B73,tblOrdenes[clasificacion],"correctiva") | G73: =E73+F73 | H73: =D73-G73 | I73: =IF(D73=0,"",G73/D73)
A74: AUT | B74: =$O$21 | C74: =SUMIFS(tblAsignaciones[horas_disponibles],tblAsignaciones[especialidad],$A74,tblAsignaciones[semana],$B74) | D74: =C74*p_factor_productividad | E74: =SUMIFS(tblOrdenes[horas_efectivas],tblOrdenes[especialidad],$A74,tblOrdenes[semana],$B74,tblOrdenes[clasificacion],"preventiva") | F74: =SUMIFS(tblOrdenes[horas_efectivas],tblOrdenes[especialidad],$A74,tblOrdenes[semana],$B74,tblOrdenes[clasificacion],"correctiva") | G74: =E74+F74 | H74: =D74-G74 | I74: =IF(D74=0,"",G74/D74)
A75: TERCERO | B75: =$O$21 | C75: =SUMIFS(tblAsignaciones[horas_disponibles],tblAsignaciones[especialidad],$A75,tblAsignaciones[semana],$B75) | D75: =C75*p_factor_productividad | E75: =SUMIFS(tblOrdenes[horas_efectivas],tblOrdenes[especialidad],$A75,tblOrdenes[semana],$B75,tblOrdenes[clasificacion],"preventiva") | F75: =SUMIFS(tblOrdenes[horas_efectivas],tblOrdenes[especialidad],$A75,tblOrdenes[semana],$B75,tblOrdenes[clasificacion],"correctiva") | G75: =E75+F75 | H75: =D75-G75 | I75: =IF(D75=0,"",G75/D75)
A76: MEC | B76: =$O$22 | C76: =SUMIFS(tblAsignaciones[horas_disponibles],tblAsignaciones[especialidad],$A76,tblAsignaciones[semana],$B76) | D76: =C76*p_factor_productividad | E76: =SUMIFS(tblOrdenes[horas_efectivas],tblOrdenes[especialidad],$A76,tblOrdenes[semana],$B76,tblOrdenes[clasificacion],"preventiva") | F76: =SUMIFS(tblOrdenes[horas_efectivas],tblOrdenes[especialidad],$A76,tblOrdenes[semana],$B76,tblOrdenes[clasificacion],"correctiva") | G76: =E76+F76 | H76: =D76-G76 | I76: =IF(D76=0,"",G76/D76)
A77: ELE | B77: =$O$22 | C77: =SUMIFS(tblAsignaciones[horas_disponibles],tblAsignaciones[especialidad],$A77,tblAsignaciones[semana],$B77) | D77: =C77*p_factor_productividad | E77: =SUMIFS(tblOrdenes[horas_efectivas],tblOrdenes[especialidad],$A77,tblOrdenes[semana],$B77,tblOrdenes[clasificacion],"preventiva") | F77: =SUMIFS(tblOrdenes[horas_efectivas],tblOrdenes[especialidad],$A77,tblOrdenes[semana],$B77,tblOrdenes[clasificacion],"correctiva") | G77: =E77+F77 | H77: =D77-G77 | I77: =IF(D77=0,"",G77/D77)
A78: AUT | B78: =$O$22 | C78: =SUMIFS(tblAsignaciones[horas_disponibles],tblAsignaciones[especialidad],$A78,tblAsignaciones[semana],$B78) | D78: =C78*p_factor_productividad | E78: =SUMIFS(tblOrdenes[horas_efectivas],tblOrdenes[especialidad],$A78,tblOrdenes[semana],$B78,tblOrdenes[clasificacion],"preventiva") | F78: =SUMIFS(tblOrdenes[horas_efectivas],tblOrdenes[especialidad],$A78,tblOrdenes[semana],$B78,tblOrdenes[clasificacion],"correctiva") | G78: =E78+F78 | H78: =D78-G78 | I78: =IF(D78=0,"",G78/D78)
A79: TERCERO | B79: =$O$22 | C79: =SUMIFS(tblAsignaciones[horas_disponibles],tblAsignaciones[especialidad],$A79,tblAsignaciones[semana],$B79) | D79: =C79*p_factor_productividad | E79: =SUMIFS(tblOrdenes[horas_efectivas],tblOrdenes[especialidad],$A79,tblOrdenes[semana],$B79,tblOrdenes[clasificacion],"preventiva") | F79: =SUMIFS(tblOrdenes[horas_efectivas],tblOrdenes[especialidad],$A79,tblOrdenes[semana],$B79,tblOrdenes[clasificacion],"correctiva") | G79: =E79+F79 | H79: =D79-G79 | I79: =IF(D79=0,"",G79/D79)
A80: MEC | B80: =$O$23 | C80: =SUMIFS(tblAsignaciones[horas_disponibles],tblAsignaciones[especialidad],$A80,tblAsignaciones[semana],$B80) | D80: =C80*p_factor_productividad | E80: =SUMIFS(tblOrdenes[horas_efectivas],tblOrdenes[especialidad],$A80,tblOrdenes[semana],$B80,tblOrdenes[clasificacion],"preventiva") | F80: =SUMIFS(tblOrdenes[horas_efectivas],tblOrdenes[especialidad],$A80,tblOrdenes[semana],$B80,tblOrdenes[clasificacion],"correctiva") | G80: =E80+F80 | H80: =D80-G80 | I80: =IF(D80=0,"",G80/D80)
A81: ELE | B81: =$O$23 | C81: =SUMIFS(tblAsignaciones[horas_disponibles],tblAsignaciones[especialidad],$A81,tblAsignaciones[semana],$B81) | D81: =C81*p_factor_productividad | E81: =SUMIFS(tblOrdenes[horas_efectivas],tblOrdenes[especialidad],$A81,tblOrdenes[semana],$B81,tblOrdenes[clasificacion],"preventiva") | F81: =SUMIFS(tblOrdenes[horas_efectivas],tblOrdenes[especialidad],$A81,tblOrdenes[semana],$B81,tblOrdenes[clasificacion],"correctiva") | G81: =E81+F81 | H81: =D81-G81 | I81: =IF(D81=0,"",G81/D81)
A82: AUT | B82: =$O$23 | C82: =SUMIFS(tblAsignaciones[horas_disponibles],tblAsignaciones[especialidad],$A82,tblAsignaciones[semana],$B82) | D82: =C82*p_factor_productividad | E82: =SUMIFS(tblOrdenes[horas_efectivas],tblOrdenes[especialidad],$A82,tblOrdenes[semana],$B82,tblOrdenes[clasificacion],"preventiva") | F82: =SUMIFS(tblOrdenes[horas_efectivas],tblOrdenes[especialidad],$A82,tblOrdenes[semana],$B82,tblOrdenes[clasificacion],"correctiva") | G82: =E82+F82 | H82: =D82-G82 | I82: =IF(D82=0,"",G82/D82)
A83: TERCERO | B83: =$O$23 | C83: =SUMIFS(tblAsignaciones[horas_disponibles],tblAsignaciones[especialidad],$A83,tblAsignaciones[semana],$B83) | D83: =C83*p_factor_productividad | E83: =SUMIFS(tblOrdenes[horas_efectivas],tblOrdenes[especialidad],$A83,tblOrdenes[semana],$B83,tblOrdenes[clasificacion],"preventiva") | F83: =SUMIFS(tblOrdenes[horas_efectivas],tblOrdenes[especialidad],$A83,tblOrdenes[semana],$B83,tblOrdenes[clasificacion],"correctiva") | G83: =E83+F83 | H83: =D83-G83 | I83: =IF(D83=0,"",G83/D83)
A84: MEC | B84: =$O$24 | C84: =SUMIFS(tblAsignaciones[horas_disponibles],tblAsignaciones[especialidad],$A84,tblAsignaciones[semana],$B84) | D84: =C84*p_factor_productividad | E84: =SUMIFS(tblOrdenes[horas_efectivas],tblOrdenes[especialidad],$A84,tblOrdenes[semana],$B84,tblOrdenes[clasificacion],"preventiva") | F84: =SUMIFS(tblOrdenes[horas_efectivas],tblOrdenes[especialidad],$A84,tblOrdenes[semana],$B84,tblOrdenes[clasificacion],"correctiva") | G84: =E84+F84 | H84: =D84-G84 | I84: =IF(D84=0,"",G84/D84)
A85: ELE | B85: =$O$24 | C85: =SUMIFS(tblAsignaciones[horas_disponibles],tblAsignaciones[especialidad],$A85,tblAsignaciones[semana],$B85) | D85: =C85*p_factor_productividad | E85: =SUMIFS(tblOrdenes[horas_efectivas],tblOrdenes[especialidad],$A85,tblOrdenes[semana],$B85,tblOrdenes[clasificacion],"preventiva") | F85: =SUMIFS(tblOrdenes[horas_efectivas],tblOrdenes[especialidad],$A85,tblOrdenes[semana],$B85,tblOrdenes[clasificacion],"correctiva") | G85: =E85+F85 | H85: =D85-G85 | I85: =IF(D85=0,"",G85/D85)
A86: AUT | B86: =$O$24 | C86: =SUMIFS(tblAsignaciones[horas_disponibles],tblAsignaciones[especialidad],$A86,tblAsignaciones[semana],$B86) | D86: =C86*p_factor_productividad | E86: =SUMIFS(tblOrdenes[horas_efectivas],tblOrdenes[especialidad],$A86,tblOrdenes[semana],$B86,tblOrdenes[clasificacion],"preventiva") | F86: =SUMIFS(tblOrdenes[horas_efectivas],tblOrdenes[especialidad],$A86,tblOrdenes[semana],$B86,tblOrdenes[clasificacion],"correctiva") | G86: =E86+F86 | H86: =D86-G86 | I86: =IF(D86=0,"",G86/D86)
A87: TERCERO | B87: =$O$24 | C87: =SUMIFS(tblAsignaciones[horas_disponibles],tblAsignaciones[especialidad],$A87,tblAsignaciones[semana],$B87) | D87: =C87*p_factor_productividad | E87: =SUMIFS(tblOrdenes[horas_efectivas],tblOrdenes[especialidad],$A87,tblOrdenes[semana],$B87,tblOrdenes[clasificacion],"preventiva") | F87: =SUMIFS(tblOrdenes[horas_efectivas],tblOrdenes[especialidad],$A87,tblOrdenes[semana],$B87,tblOrdenes[clasificacion],"correctiva") | G87: =E87+F87 | H87: =D87-G87 | I87: =IF(D87=0,"",G87/D87)
A88: MEC | B88: =$O$25 | C88: =SUMIFS(tblAsignaciones[horas_disponibles],tblAsignaciones[especialidad],$A88,tblAsignaciones[semana],$B88) | D88: =C88*p_factor_productividad | E88: =SUMIFS(tblOrdenes[horas_efectivas],tblOrdenes[especialidad],$A88,tblOrdenes[semana],$B88,tblOrdenes[clasificacion],"preventiva") | F88: =SUMIFS(tblOrdenes[horas_efectivas],tblOrdenes[especialidad],$A88,tblOrdenes[semana],$B88,tblOrdenes[clasificacion],"correctiva") | G88: =E88+F88 | H88: =D88-G88 | I88: =IF(D88=0,"",G88/D88)
A89: ELE | B89: =$O$25 | C89: =SUMIFS(tblAsignaciones[horas_disponibles],tblAsignaciones[especialidad],$A89,tblAsignaciones[semana],$B89) | D89: =C89*p_factor_productividad | E89: =SUMIFS(tblOrdenes[horas_efectivas],tblOrdenes[especialidad],$A89,tblOrdenes[semana],$B89,tblOrdenes[clasificacion],"preventiva") | F89: =SUMIFS(tblOrdenes[horas_efectivas],tblOrdenes[especialidad],$A89,tblOrdenes[semana],$B89,tblOrdenes[clasificacion],"correctiva") | G89: =E89+F89 | H89: =D89-G89 | I89: =IF(D89=0,"",G89/D89)
A90: AUT | B90: =$O$25 | C90: =SUMIFS(tblAsignaciones[horas_disponibles],tblAsignaciones[especialidad],$A90,tblAsignaciones[semana],$B90) | D90: =C90*p_factor_productividad | E90: =SUMIFS(tblOrdenes[horas_efectivas],tblOrdenes[especialidad],$A90,tblOrdenes[semana],$B90,tblOrdenes[clasificacion],"preventiva") | F90: =SUMIFS(tblOrdenes[horas_efectivas],tblOrdenes[especialidad],$A90,tblOrdenes[semana],$B90,tblOrdenes[clasificacion],"correctiva") | G90: =E90+F90 | H90: =D90-G90 | I90: =IF(D90=0,"",G90/D90)
A91: TERCERO | B91: =$O$25 | C91: =SUMIFS(tblAsignaciones[horas_disponibles],tblAsignaciones[especialidad],$A91,tblAsignaciones[semana],$B91) | D91: =C91*p_factor_productividad | E91: =SUMIFS(tblOrdenes[horas_efectivas],tblOrdenes[especialidad],$A91,tblOrdenes[semana],$B91,tblOrdenes[clasificacion],"preventiva") | F91: =SUMIFS(tblOrdenes[horas_efectivas],tblOrdenes[especialidad],$A91,tblOrdenes[semana],$B91,tblOrdenes[clasificacion],"correctiva") | G91: =E91+F91 | H91: =D91-G91 | I91: =IF(D91=0,"",G91/D91)
A92: MEC | B92: =$O$26 | C92: =SUMIFS(tblAsignaciones[horas_disponibles],tblAsignaciones[especialidad],$A92,tblAsignaciones[semana],$B92) | D92: =C92*p_factor_productividad | E92: =SUMIFS(tblOrdenes[horas_efectivas],tblOrdenes[especialidad],$A92,tblOrdenes[semana],$B92,tblOrdenes[clasificacion],"preventiva") | F92: =SUMIFS(tblOrdenes[horas_efectivas],tblOrdenes[especialidad],$A92,tblOrdenes[semana],$B92,tblOrdenes[clasificacion],"correctiva") | G92: =E92+F92 | H92: =D92-G92 | I92: =IF(D92=0,"",G92/D92)
A93: ELE | B93: =$O$26 | C93: =SUMIFS(tblAsignaciones[horas_disponibles],tblAsignaciones[especialidad],$A93,tblAsignaciones[semana],$B93) | D93: =C93*p_factor_productividad | E93: =SUMIFS(tblOrdenes[horas_efectivas],tblOrdenes[especialidad],$A93,tblOrdenes[semana],$B93,tblOrdenes[clasificacion],"preventiva") | F93: =SUMIFS(tblOrdenes[horas_efectivas],tblOrdenes[especialidad],$A93,tblOrdenes[semana],$B93,tblOrdenes[clasificacion],"correctiva") | G93: =E93+F93 | H93: =D93-G93 | I93: =IF(D93=0,"",G93/D93)
A94: AUT | B94: =$O$26 | C94: =SUMIFS(tblAsignaciones[horas_disponibles],tblAsignaciones[especialidad],$A94,tblAsignaciones[semana],$B94) | D94: =C94*p_factor_productividad | E94: =SUMIFS(tblOrdenes[horas_efectivas],tblOrdenes[especialidad],$A94,tblOrdenes[semana],$B94,tblOrdenes[clasificacion],"preventiva") | F94: =SUMIFS(tblOrdenes[horas_efectivas],tblOrdenes[especialidad],$A94,tblOrdenes[semana],$B94,tblOrdenes[clasificacion],"correctiva") | G94: =E94+F94 | H94: =D94-G94 | I94: =IF(D94=0,"",G94/D94)
A95: TERCERO | B95: =$O$26 | C95: =SUMIFS(tblAsignaciones[horas_disponibles],tblAsignaciones[especialidad],$A95,tblAsignaciones[semana],$B95) | D95: =C95*p_factor_productividad | E95: =SUMIFS(tblOrdenes[horas_efectivas],tblOrdenes[especialidad],$A95,tblOrdenes[semana],$B95,tblOrdenes[clasificacion],"preventiva") | F95: =SUMIFS(tblOrdenes[horas_efectivas],tblOrdenes[especialidad],$A95,tblOrdenes[semana],$B95,tblOrdenes[clasificacion],"correctiva") | G95: =E95+F95 | H95: =D95-G95 | I95: =IF(D95=0,"",G95/D95)
A96: MEC | B96: =$O$27 | C96: =SUMIFS(tblAsignaciones[horas_disponibles],tblAsignaciones[especialidad],$A96,tblAsignaciones[semana],$B96) | D96: =C96*p_factor_productividad | E96: =SUMIFS(tblOrdenes[horas_efectivas],tblOrdenes[especialidad],$A96,tblOrdenes[semana],$B96,tblOrdenes[clasificacion],"preventiva") | F96: =SUMIFS(tblOrdenes[horas_efectivas],tblOrdenes[especialidad],$A96,tblOrdenes[semana],$B96,tblOrdenes[clasificacion],"correctiva") | G96: =E96+F96 | H96: =D96-G96 | I96: =IF(D96=0,"",G96/D96)
A97: ELE | B97: =$O$27 | C97: =SUMIFS(tblAsignaciones[horas_disponibles],tblAsignaciones[especialidad],$A97,tblAsignaciones[semana],$B97) | D97: =C97*p_factor_productividad | E97: =SUMIFS(tblOrdenes[horas_efectivas],tblOrdenes[especialidad],$A97,tblOrdenes[semana],$B97,tblOrdenes[clasificacion],"preventiva") | F97: =SUMIFS(tblOrdenes[horas_efectivas],tblOrdenes[especialidad],$A97,tblOrdenes[semana],$B97,tblOrdenes[clasificacion],"correctiva") | G97: =E97+F97 | H97: =D97-G97 | I97: =IF(D97=0,"",G97/D97)
A98: AUT | B98: =$O$27 | C98: =SUMIFS(tblAsignaciones[horas_disponibles],tblAsignaciones[especialidad],$A98,tblAsignaciones[semana],$B98) | D98: =C98*p_factor_productividad | E98: =SUMIFS(tblOrdenes[horas_efectivas],tblOrdenes[especialidad],$A98,tblOrdenes[semana],$B98,tblOrdenes[clasificacion],"preventiva") | F98: =SUMIFS(tblOrdenes[horas_efectivas],tblOrdenes[especialidad],$A98,tblOrdenes[semana],$B98,tblOrdenes[clasificacion],"correctiva") | G98: =E98+F98 | H98: =D98-G98 | I98: =IF(D98=0,"",G98/D98)
A99: TERCERO | B99: =$O$27 | C99: =SUMIFS(tblAsignaciones[horas_disponibles],tblAsignaciones[especialidad],$A99,tblAsignaciones[semana],$B99) | D99: =C99*p_factor_productividad | E99: =SUMIFS(tblOrdenes[horas_efectivas],tblOrdenes[especialidad],$A99,tblOrdenes[semana],$B99,tblOrdenes[clasificacion],"preventiva") | F99: =SUMIFS(tblOrdenes[horas_efectivas],tblOrdenes[especialidad],$A99,tblOrdenes[semana],$B99,tblOrdenes[clasificacion],"correctiva") | G99: =E99+F99 | H99: =D99-G99 | I99: =IF(D99=0,"",G99/D99)
A100: MEC | B100: =$O$28 | C100: =SUMIFS(tblAsignaciones[horas_disponibles],tblAsignaciones[especialidad],$A100,tblAsignaciones[semana],$B100) | D100: =C100*p_factor_productividad | E100: =SUMIFS(tblOrdenes[horas_efectivas],tblOrdenes[especialidad],$A100,tblOrdenes[semana],$B100,tblOrdenes[clasificacion],"preventiva") | F100: =SUMIFS(tblOrdenes[horas_efectivas],tblOrdenes[especialidad],$A100,tblOrdenes[semana],$B100,tblOrdenes[clasificacion],"correctiva") | G100: =E100+F100 | H100: =D100-G100 | I100: =IF(D100=0,"",G100/D100)
...

Sheet BACKLOG
A1: BACKLOG (REGLA-3) — envejecimiento de órdenes pendientes
A2: =HYPERLINK("#DASHBOARD!A1","◂ VOLVER AL TABLERO")
A3: tramo (días) | B3: ordenes | C3: hh_estimadas
A4: 0-30 | B4: =COUNTIFS(tblOrdenes[estado],"Pendiente",tblOrdenes[backlog_dias],">=0",tblOrdenes[backlog_dias],"<=30") | C4: =SUMIFS(tblOrdenes[horas_efectivas],tblOrdenes[estado],"Pendiente",tblOrdenes[backlog_dias],">=0",tblOrdenes[backlog_dias],"<=30")
A5: 31-60 | B5: =COUNTIFS(tblOrdenes[estado],"Pendiente",tblOrdenes[backlog_dias],">=31",tblOrdenes[backlog_dias],"<=60") | C5: =SUMIFS(tblOrdenes[horas_efectivas],tblOrdenes[estado],"Pendiente",tblOrdenes[backlog_dias],">=31",tblOrdenes[backlog_dias],"<=60")
A6: 61-90 | B6: =COUNTIFS(tblOrdenes[estado],"Pendiente",tblOrdenes[backlog_dias],">=61",tblOrdenes[backlog_dias],"<=90") | C6: =SUMIFS(tblOrdenes[horas_efectivas],tblOrdenes[estado],"Pendiente",tblOrdenes[backlog_dias],">=61",tblOrdenes[backlog_dias],"<=90")
A7: >90 | B7: =COUNTIFS(tblOrdenes[estado],"Pendiente",tblOrdenes[backlog_dias],">90") | C7: =SUMIFS(tblOrdenes[horas_efectivas],tblOrdenes[estado],"Pendiente",tblOrdenes[backlog_dias],">90")
A10: POR ESPECIALIDAD
A11: especialidad | B11: 0-30 | C11: 31-60 | D11: 61-90 | E11: >90
A12: MEC | B12: =COUNTIFS(tblOrdenes[estado],"Pendiente",tblOrdenes[backlog_dias],">=0",tblOrdenes[backlog_dias],"<=30",tblOrdenes[especialidad],$A12) | C12: =COUNTIFS(tblOrdenes[estado],"Pendiente",tblOrdenes[backlog_dias],">=31",tblOrdenes[backlog_dias],"<=60",tblOrdenes[especialidad],$A12) | D12: =COUNTIFS(tblOrdenes[estado],"Pendiente",tblOrdenes[backlog_dias],">=61",tblOrdenes[backlog_dias],"<=90",tblOrdenes[especialidad],$A12) | E12: =COUNTIFS(tblOrdenes[estado],"Pendiente",tblOrdenes[backlog_dias],">90",tblOrdenes[especialidad],$A12)
A13: ELE | B13: =COUNTIFS(tblOrdenes[estado],"Pendiente",tblOrdenes[backlog_dias],">=0",tblOrdenes[backlog_dias],"<=30",tblOrdenes[especialidad],$A13) | C13: =COUNTIFS(tblOrdenes[estado],"Pendiente",tblOrdenes[backlog_dias],">=31",tblOrdenes[backlog_dias],"<=60",tblOrdenes[especialidad],$A13) | D13: =COUNTIFS(tblOrdenes[estado],"Pendiente",tblOrdenes[backlog_dias],">=61",tblOrdenes[backlog_dias],"<=90",tblOrdenes[especialidad],$A13) | E13: =COUNTIFS(tblOrdenes[estado],"Pendiente",tblOrdenes[backlog_dias],">90",tblOrdenes[especialidad],$A13)
A14: AUT | B14: =COUNTIFS(tblOrdenes[estado],"Pendiente",tblOrdenes[backlog_dias],">=0",tblOrdenes[backlog_dias],"<=30",tblOrdenes[especialidad],$A14) | C14: =COUNTIFS(tblOrdenes[estado],"Pendiente",tblOrdenes[backlog_dias],">=31",tblOrdenes[backlog_dias],"<=60",tblOrdenes[especialidad],$A14) | D14: =COUNTIFS(tblOrdenes[estado],"Pendiente",tblOrdenes[backlog_dias],">=61",tblOrdenes[backlog_dias],"<=90",tblOrdenes[especialidad],$A14) | E14: =COUNTIFS(tblOrdenes[estado],"Pendiente",tblOrdenes[backlog_dias],">90",tblOrdenes[especialidad],$A14)
A15: TERCERO | B15: =COUNTIFS(tblOrdenes[estado],"Pendiente",tblOrdenes[backlog_dias],">=0",tblOrdenes[backlog_dias],"<=30",tblOrdenes[especialidad],$A15) | C15: =COUNTIFS(tblOrdenes[estado],"Pendiente",tblOrdenes[backlog_dias],">=31",tblOrdenes[backlog_dias],"<=60",tblOrdenes[especialidad],$A15) | D15: =COUNTIFS(tblOrdenes[estado],"Pendiente",tblOrdenes[backlog_dias],">=61",tblOrdenes[backlog_dias],"<=90",tblOrdenes[especialidad],$A15) | E15: =COUNTIFS(tblOrdenes[estado],"Pendiente",tblOrdenes[backlog_dias],">90",tblOrdenes[especialidad],$A15)
A17: POR ÁREA
A18: area | B18: 0-30 | C18: 31-60 | D18: 61-90 | E18: >90
A19: PRODUCCION | B19: =COUNTIFS(tblOrdenes[estado],"Pendiente",tblOrdenes[backlog_dias],">=0",tblOrdenes[backlog_dias],"<=30",tblOrdenes[area],$A19) | C19: =COUNTIFS(tblOrdenes[estado],"Pendiente",tblOrdenes[backlog_dias],">=31",tblOrdenes[backlog_dias],"<=60",tblOrdenes[area],$A19) | D19: =COUNTIFS(tblOrdenes[estado],"Pendiente",tblOrdenes[backlog_dias],">=61",tblOrdenes[backlog_dias],"<=90",tblOrdenes[area],$A19) | E19: =COUNTIFS(tblOrdenes[estado],"Pendiente",tblOrdenes[backlog_dias],">90",tblOrdenes[area],$A19)
A20: EMPAQUE | B20: =COUNTIFS(tblOrdenes[estado],"Pendiente",tblOrdenes[backlog_dias],">=0",tblOrdenes[backlog_dias],"<=30",tblOrdenes[area],$A20) | C20: =COUNTIFS(tblOrdenes[estado],"Pendiente",tblOrdenes[backlog_dias],">=31",tblOrdenes[backlog_dias],"<=60",tblOrdenes[area],$A20) | D20: =COUNTIFS(tblOrdenes[estado],"Pendiente",tblOrdenes[backlog_dias],">=61",tblOrdenes[backlog_dias],"<=90",tblOrdenes[area],$A20) | E20: =COUNTIFS(tblOrdenes[estado],"Pendiente",tblOrdenes[backlog_dias],">90",tblOrdenes[area],$A20)
A21: SERVICIOS | B21: =COUNTIFS(tblOrdenes[estado],"Pendiente",tblOrdenes[backlog_dias],">=0",tblOrdenes[backlog_dias],"<=30",tblOrdenes[area],$A21) | C21: =COUNTIFS(tblOrdenes[estado],"Pendiente",tblOrdenes[backlog_dias],">=31",tblOrdenes[backlog_dias],"<=60",tblOrdenes[area],$A21) | D21: =COUNTIFS(tblOrdenes[estado],"Pendiente",tblOrdenes[backlog_dias],">=61",tblOrdenes[backlog_dias],"<=90",tblOrdenes[area],$A21) | E21: =COUNTIFS(tblOrdenes[estado],"Pendiente",tblOrdenes[backlog_dias],">90",tblOrdenes[area],$A21)
A23: POR SUB-ÁREA (herencia: área sin subdividir con su propio nombre)
A24: sub_area | B24: 0-30 | C24: 31-60 | D24: 61-90 | E24: >90
A25: PRODUCCION | B25: =COUNTIFS(tblOrdenes[estado],"Pendiente",tblOrdenes[backlog_dias],">=0",tblOrdenes[backlog_dias],"<=30",tblOrdenes[sub_area],$A25) | C25: =COUNTIFS(tblOrdenes[estado],"Pendiente",tblOrdenes[backlog_dias],">=31",tblOrdenes[backlog_dias],"<=60",tblOrdenes[sub_area],$A25) | D25: =COUNTIFS(tblOrdenes[estado],"Pendiente",tblOrdenes[backlog_dias],">=61",tblOrdenes[backlog_dias],"<=90",tblOrdenes[sub_area],$A25) | E25: =COUNTIFS(tblOrdenes[estado],"Pendiente",tblOrdenes[backlog_dias],">90",tblOrdenes[sub_area],$A25)
A26: EMPAQUE | B26: =COUNTIFS(tblOrdenes[estado],"Pendiente",tblOrdenes[backlog_dias],">=0",tblOrdenes[backlog_dias],"<=30",tblOrdenes[sub_area],$A26) | C26: =COUNTIFS(tblOrdenes[estado],"Pendiente",tblOrdenes[backlog_dias],">=31",tblOrdenes[backlog_dias],"<=60",tblOrdenes[sub_area],$A26) | D26: =COUNTIFS(tblOrdenes[estado],"Pendiente",tblOrdenes[backlog_dias],">=61",tblOrdenes[backlog_dias],"<=90",tblOrdenes[sub_area],$A26) | E26: =COUNTIFS(tblOrdenes[estado],"Pendiente",tblOrdenes[backlog_dias],">90",tblOrdenes[sub_area],$A26)
A27: Vapor | B27: =COUNTIFS(tblOrdenes[estado],"Pendiente",tblOrdenes[backlog_dias],">=0",tblOrdenes[backlog_dias],"<=30",tblOrdenes[sub_area],$A27) | C27: =COUNTIFS(tblOrdenes[estado],"Pendiente",tblOrdenes[backlog_dias],">=31",tblOrdenes[backlog_dias],"<=60",tblOrdenes[sub_area],$A27) | D27: =COUNTIFS(tblOrdenes[estado],"Pendiente",tblOrdenes[backlog_dias],">=61",tblOrdenes[backlog_dias],"<=90",tblOrdenes[sub_area],$A27) | E27: =COUNTIFS(tblOrdenes[estado],"Pendiente",tblOrdenes[backlog_dias],">90",tblOrdenes[sub_area],$A27)
A28: Refrigeración | B28: =COUNTIFS(tblOrdenes[estado],"Pendiente",tblOrdenes[backlog_dias],">=0",tblOrdenes[backlog_dias],"<=30",tblOrdenes[sub_area],$A28) | C28: =COUNTIFS(tblOrdenes[estado],"Pendiente",tblOrdenes[backlog_dias],">=31",tblOrdenes[backlog_dias],"<=60",tblOrdenes[sub_area],$A28) | D28: =COUNTIFS(tblOrdenes[estado],"Pendiente",tblOrdenes[backlog_dias],">=61",tblOrdenes[backlog_dias],"<=90",tblOrdenes[sub_area],$A28) | E28: =COUNTIFS(tblOrdenes[estado],"Pendiente",tblOrdenes[backlog_dias],">90",tblOrdenes[sub_area],$A28)
A29: CO2 | B29: =COUNTIFS(tblOrdenes[estado],"Pendiente",tblOrdenes[backlog_dias],">=0",tblOrdenes[backlog_dias],"<=30",tblOrdenes[sub_area],$A29) | C29: =COUNTIFS(tblOrdenes[estado],"Pendiente",tblOrdenes[backlog_dias],">=31",tblOrdenes[backlog_dias],"<=60",tblOrdenes[sub_area],$A29) | D29: =COUNTIFS(tblOrdenes[estado],"Pendiente",tblOrdenes[backlog_dias],">=61",tblOrdenes[backlog_dias],"<=90",tblOrdenes[sub_area],$A29) | E29: =COUNTIFS(tblOrdenes[estado],"Pendiente",tblOrdenes[backlog_dias],">90",tblOrdenes[sub_area],$A29)
A30: Aire comprimido | B30: =COUNTIFS(tblOrdenes[estado],"Pendiente",tblOrdenes[backlog_dias],">=0",tblOrdenes[backlog_dias],"<=30",tblOrdenes[sub_area],$A30) | C30: =COUNTIFS(tblOrdenes[estado],"Pendiente",tblOrdenes[backlog_dias],">=31",tblOrdenes[backlog_dias],"<=60",tblOrdenes[sub_area],$A30) | D30: =COUNTIFS(tblOrdenes[estado],"Pendiente",tblOrdenes[backlog_dias],">=61",tblOrdenes[backlog_dias],"<=90",tblOrdenes[sub_area],$A30) | E30: =COUNTIFS(tblOrdenes[estado],"Pendiente",tblOrdenes[backlog_dias],">90",tblOrdenes[sub_area],$A30)
A32: AL CORTE DEL TABLERO (fuente del DASHBOARD; no editar) — el backlog es ACUMULADO: cuenta todo lo pendiente con fecha hasta el corte del mes, no solo lo del mes.
A33: mes | B33: corte | C33: ordenes_pendientes | D33: hh_pendientes | E33: capacidad_productiva_semanal | F33: semanas_de_backlog
A34: 2025-10 | B34: =IF($A34="","",IF($A34=YEAR(p_fecha_datos)&"-"&TEXT(MONTH(p_fecha_datos),"00"),p_fecha_datos-1,DATE(VALUE(LEFT($A34,4)),VALUE(RIGHT($A34,2))+1,0))) | C34: =COUNTIFS(tblOrdenes[estado],"Pendiente",tblOrdenes[fecha_inicio],"<="&$B34) | D34: =SUMIFS(tblOrdenes[horas_efectivas],tblOrdenes[estado],"Pendiente",tblOrdenes[fecha_inicio],"<="&$B34) | E34: =p_base_semanal_horas*p_factor_productividad*COUNTIFS(tblTecnicos[activo],"sí") | F34: =IF($E34=0,"",$D34/$E34)
A35: 2025-11 | B35: =IF($A35="","",IF($A35=YEAR(p_fecha_datos)&"-"&TEXT(MONTH(p_fecha_datos),"00"),p_fecha_datos-1,DATE(VALUE(LEFT($A35,4)),VALUE(RIGHT($A35,2))+1,0))) | C35: =COUNTIFS(tblOrdenes[estado],"Pendiente",tblOrdenes[fecha_inicio],"<="&$B35) | D35: =SUMIFS(tblOrdenes[horas_efectivas],tblOrdenes[estado],"Pendiente",tblOrdenes[fecha_inicio],"<="&$B35) | E35: =p_base_semanal_horas*p_factor_productividad*COUNTIFS(tblTecnicos[activo],"sí") | F35: =IF($E35=0,"",$D35/$E35)
A36: 2025-12 | B36: =IF($A36="","",IF($A36=YEAR(p_fecha_datos)&"-"&TEXT(MONTH(p_fecha_datos),"00"),p_fecha_datos-1,DATE(VALUE(LEFT($A36,4)),VALUE(RIGHT($A36,2))+1,0))) | C36: =COUNTIFS(tblOrdenes[estado],"Pendiente",tblOrdenes[fecha_inicio],"<="&$B36) | D36: =SUMIFS(tblOrdenes[horas_efectivas],tblOrdenes[estado],"Pendiente",tblOrdenes[fecha_inicio],"<="&$B36) | E36: =p_base_semanal_horas*p_factor_productividad*COUNTIFS(tblTecnicos[activo],"sí") | F36: =IF($E36=0,"",$D36/$E36)
A37: 2026-01 | B37: =IF($A37="","",IF($A37=YEAR(p_fecha_datos)&"-"&TEXT(MONTH(p_fecha_datos),"00"),p_fecha_datos-1,DATE(VALUE(LEFT($A37,4)),VALUE(RIGHT($A37,2))+1,0))) | C37: =COUNTIFS(tblOrdenes[estado],"Pendiente",tblOrdenes[fecha_inicio],"<="&$B37) | D37: =SUMIFS(tblOrdenes[horas_efectivas],tblOrdenes[estado],"Pendiente",tblOrdenes[fecha_inicio],"<="&$B37) | E37: =p_base_semanal_horas*p_factor_productividad*COUNTIFS(tblTecnicos[activo],"sí") | F37: =IF($E37=0,"",$D37/$E37)
A38: 2026-02 | B38: =IF($A38="","",IF($A38=YEAR(p_fecha_datos)&"-"&TEXT(MONTH(p_fecha_datos),"00"),p_fecha_datos-1,DATE(VALUE(LEFT($A38,4)),VALUE(RIGHT($A38,2))+1,0))) | C38: =COUNTIFS(tblOrdenes[estado],"Pendiente",tblOrdenes[fecha_inicio],"<="&$B38) | D38: =SUMIFS(tblOrdenes[horas_efectivas],tblOrdenes[estado],"Pendiente",tblOrdenes[fecha_inicio],"<="&$B38) | E38: =p_base_semanal_horas*p_factor_productividad*COUNTIFS(tblTecnicos[activo],"sí") | F38: =IF($E38=0,"",$D38/$E38)
A39: 2026-03 | B39: =IF($A39="","",IF($A39=YEAR(p_fecha_datos)&"-"&TEXT(MONTH(p_fecha_datos),"00"),p_fecha_datos-1,DATE(VALUE(LEFT($A39,4)),VALUE(RIGHT($A39,2))+1,0))) | C39: =COUNTIFS(tblOrdenes[estado],"Pendiente",tblOrdenes[fecha_inicio],"<="&$B39) | D39: =SUMIFS(tblOrdenes[horas_efectivas],tblOrdenes[estado],"Pendiente",tblOrdenes[fecha_inicio],"<="&$B39) | E39: =p_base_semanal_horas*p_factor_productividad*COUNTIFS(tblTecnicos[activo],"sí") | F39: =IF($E39=0,"",$D39/$E39)
A40: 2026-04 | B40: =IF($A40="","",IF($A40=YEAR(p_fecha_datos)&"-"&TEXT(MONTH(p_fecha_datos),"00"),p_fecha_datos-1,DATE(VALUE(LEFT($A40,4)),VALUE(RIGHT($A40,2))+1,0))) | C40: =COUNTIFS(tblOrdenes[estado],"Pendiente",tblOrdenes[fecha_inicio],"<="&$B40) | D40: =SUMIFS(tblOrdenes[horas_efectivas],tblOrdenes[estado],"Pendiente",tblOrdenes[fecha_inicio],"<="&$B40) | E40: =p_base_semanal_horas*p_factor_productividad*COUNTIFS(tblTecnicos[activo],"sí") | F40: =IF($E40=0,"",$D40/$E40)
A41: 2026-05 | B41: =IF($A41="","",IF($A41=YEAR(p_fecha_datos)&"-"&TEXT(MONTH(p_fecha_datos),"00"),p_fecha_datos-1,DATE(VALUE(LEFT($A41,4)),VALUE(RIGHT($A41,2))+1,0))) | C41: =COUNTIFS(tblOrdenes[estado],"Pendiente",tblOrdenes[fecha_inicio],"<="&$B41) | D41: =SUMIFS(tblOrdenes[horas_efectivas],tblOrdenes[estado],"Pendiente",tblOrdenes[fecha_inicio],"<="&$B41) | E41: =p_base_semanal_horas*p_factor_productividad*COUNTIFS(tblTecnicos[activo],"sí") | F41: =IF($E41=0,"",$D41/$E41)
A42: 2026-06 | B42: =IF($A42="","",IF($A42=YEAR(p_fecha_datos)&"-"&TEXT(MONTH(p_fecha_datos),"00"),p_fecha_datos-1,DATE(VALUE(LEFT($A42,4)),VALUE(RIGHT($A42,2))+1,0))) | C42: =COUNTIFS(tblOrdenes[estado],"Pendiente",tblOrdenes[fecha_inicio],"<="&$B42) | D42: =SUMIFS(tblOrdenes[horas_efectivas],tblOrdenes[estado],"Pendiente",tblOrdenes[fecha_inicio],"<="&$B42) | E42: =p_base_semanal_horas*p_factor_productividad*COUNTIFS(tblTecnicos[activo],"sí") | F42: =IF($E42=0,"",$D42/$E42)
A43: 2026-07 | B43: =IF($A43="","",IF($A43=YEAR(p_fecha_datos)&"-"&TEXT(MONTH(p_fecha_datos),"00"),p_fecha_datos-1,DATE(VALUE(LEFT($A43,4)),VALUE(RIGHT($A43,2))+1,0))) | C43: =COUNTIFS(tblOrdenes[estado],"Pendiente",tblOrdenes[fecha_inicio],"<="&$B43) | D43: =SUMIFS(tblOrdenes[horas_efectivas],tblOrdenes[estado],"Pendiente",tblOrdenes[fecha_inicio],"<="&$B43) | E43: =p_base_semanal_horas*p_factor_productividad*COUNTIFS(tblTecnicos[activo],"sí") | F43: =IF($E43=0,"",$D43/$E43)
A44: 2026-08 | B44: =IF($A44="","",IF($A44=YEAR(p_fecha_datos)&"-"&TEXT(MONTH(p_fecha_datos),"00"),p_fecha_datos-1,DATE(VALUE(LEFT($A44,4)),VALUE(RIGHT($A44,2))+1,0))) | C44: =COUNTIFS(tblOrdenes[estado],"Pendiente",tblOrdenes[fecha_inicio],"<="&$B44) | D44: =SUMIFS(tblOrdenes[horas_efectivas],tblOrdenes[estado],"Pendiente",tblOrdenes[fecha_inicio],"<="&$B44) | E44: =p_base_semanal_horas*p_factor_productividad*COUNTIFS(tblTecnicos[activo],"sí") | F44: =IF($E44=0,"",$D44/$E44)
A45: 2026-09 | B45: =IF($A45="","",IF($A45=YEAR(p_fecha_datos)&"-"&TEXT(MONTH(p_fecha_datos),"00"),p_fecha_datos-1,DATE(VALUE(LEFT($A45,4)),VALUE(RIGHT($A45,2))+1,0))) | C45: =COUNTIFS(tblOrdenes[estado],"Pendiente",tblOrdenes[fecha_inicio],"<="&$B45) | D45: =SUMIFS(tblOrdenes[horas_efectivas],tblOrdenes[estado],"Pendiente",tblOrdenes[fecha_inicio],"<="&$B45) | E45: =p_base_semanal_horas*p_factor_productividad*COUNTIFS(tblTecnicos[activo],"sí") | F45: =IF($E45=0,"",$D45/$E45)
... A51: 2027-03 | B51: =IF($A51="","",IF($A51=YEAR(p_fecha_datos)&"-"&TEXT(MONTH(p_fecha_datos),"00"),p_fecha_datos-1,DATE(VALUE(LEFT($A51,4)),VALUE(RIGHT($A51,2))+1,0))) | C51: =COUNTIFS(tblOrdenes[estado],"Pendiente",tblOrdenes[fecha_inicio],"<="&$B51) | D51: =SUMIFS(tblOrdenes[horas_efectivas],tblOrdenes[estado],"Pendiente",tblOrdenes[fecha_inicio],"<="&$B51) | E51: =p_base_semanal_horas*p_factor_productividad*COUNTIFS(tblTecnicos[activo],"sí") | F51: =IF($E51=0,"",$D51/$E51)

Sheet COSTOS
A1: ="COSTOS ("&p_moneda&") — REGLA-8: real (servicio + materiales) contra plan"
A2: =HYPERLINK("#DASHBOARD!A1","◂ VOLVER AL TABLERO")
A3: PLAN por área (costo_plan)
A4: anio | B4: 2026 | C4: 2026
A5: mes | B5: 7 | C5: 8 | D5: TOTAL
A6: PRODUCCION | B6: =SUMIFS(tblOrdenes[costo_plan],tblOrdenes[area],$A6,tblOrdenes[anio],B$4,tblOrdenes[mes],B$5) | C6: =SUMIFS(tblOrdenes[costo_plan],tblOrdenes[area],$A6,tblOrdenes[anio],C$4,tblOrdenes[mes],C$5) | D6: =SUM(B6:C6)
A7: EMPAQUE | B7: =SUMIFS(tblOrdenes[costo_plan],tblOrdenes[area],$A7,tblOrdenes[anio],B$4,tblOrdenes[mes],B$5) | C7: =SUMIFS(tblOrdenes[costo_plan],tblOrdenes[area],$A7,tblOrdenes[anio],C$4,tblOrdenes[mes],C$5) | D7: =SUM(B7:C7)
A8: SERVICIOS | B8: =SUMIFS(tblOrdenes[costo_plan],tblOrdenes[area],$A8,tblOrdenes[anio],B$4,tblOrdenes[mes],B$5) | C8: =SUMIFS(tblOrdenes[costo_plan],tblOrdenes[area],$A8,tblOrdenes[anio],C$4,tblOrdenes[mes],C$5) | D8: =SUM(B8:C8)
A9: TOTAL | B9: =SUM(B6:B8) | C9: =SUM(C6:C8) | D9: =SUM(D6:D8)
A11: REAL por área (costo_total = servicio + materiales)
A12: anio | B12: 2026 | C12: 2026
A13: mes | B13: 7 | C13: 8 | D13: TOTAL
A14: PRODUCCION | B14: =SUMIFS(tblOrdenes[costo_total],tblOrdenes[area],$A14,tblOrdenes[anio],B$12,tblOrdenes[mes],B$13) | C14: =SUMIFS(tblOrdenes[costo_total],tblOrdenes[area],$A14,tblOrdenes[anio],C$12,tblOrdenes[mes],C$13) | D14: =SUM(B14:C14)
A15: EMPAQUE | B15: =SUMIFS(tblOrdenes[costo_total],tblOrdenes[area],$A15,tblOrdenes[anio],B$12,tblOrdenes[mes],B$13) | C15: =SUMIFS(tblOrdenes[costo_total],tblOrdenes[area],$A15,tblOrdenes[anio],C$12,tblOrdenes[mes],C$13) | D15: =SUM(B15:C15)
A16: SERVICIOS | B16: =SUMIFS(tblOrdenes[costo_total],tblOrdenes[area],$A16,tblOrdenes[anio],B$12,tblOrdenes[mes],B$13) | C16: =SUMIFS(tblOrdenes[costo_total],tblOrdenes[area],$A16,tblOrdenes[anio],C$12,tblOrdenes[mes],C$13) | D16: =SUM(B16:C16)
A17: TOTAL | B17: =SUM(B14:B16) | C17: =SUM(C14:C16) | D17: =SUM(D14:D16)
A19: DESVÍO por área (real − plan)
A20: PRODUCCION | B20: =B14-B6 | C20: =C14-C6 | D20: =D14-D6
A21: EMPAQUE | B21: =B15-B7 | C21: =C15-C7 | D21: =D15-D7
A22: SERVICIOS | B22: =B16-B8 | C22: =C16-C8 | D22: =D16-D8
A23: TOTAL | B23: =B17-B9 | C23: =C17-C9 | D23: =D17-D9
A25: REAL por sub-área (herencia: un área sin subdividir aparece con su propio nombre; el TOTAL coincide con el de por área)
A26: anio | B26: 2026 | C26: 2026
A27: mes | B27: 7 | C27: 8 | D27: TOTAL
A28: PRODUCCION | B28: =SUMIFS(tblOrdenes[costo_total],tblOrdenes[sub_area],$A28,tblOrdenes[anio],B$26,tblOrdenes[mes],B$27) | C28: =SUMIFS(tblOrdenes[costo_total],tblOrdenes[sub_area],$A28,tblOrdenes[anio],C$26,tblOrdenes[mes],C$27) | D28: =SUM(B28:C28)
A29: EMPAQUE | B29: =SUMIFS(tblOrdenes[costo_total],tblOrdenes[sub_area],$A29,tblOrdenes[anio],B$26,tblOrdenes[mes],B$27) | C29: =SUMIFS(tblOrdenes[costo_total],tblOrdenes[sub_area],$A29,tblOrdenes[anio],C$26,tblOrdenes[mes],C$27) | D29: =SUM(B29:C29)
A30: Vapor | B30: =SUMIFS(tblOrdenes[costo_total],tblOrdenes[sub_area],$A30,tblOrdenes[anio],B$26,tblOrdenes[mes],B$27) | C30: =SUMIFS(tblOrdenes[costo_total],tblOrdenes[sub_area],$A30,tblOrdenes[anio],C$26,tblOrdenes[mes],C$27) | D30: =SUM(B30:C30)
A31: Refrigeración | B31: =SUMIFS(tblOrdenes[costo_total],tblOrdenes[sub_area],$A31,tblOrdenes[anio],B$26,tblOrdenes[mes],B$27) | C31: =SUMIFS(tblOrdenes[costo_total],tblOrdenes[sub_area],$A31,tblOrdenes[anio],C$26,tblOrdenes[mes],C$27) | D31: =SUM(B31:C31)
A32: CO2 | B32: =SUMIFS(tblOrdenes[costo_total],tblOrdenes[sub_area],$A32,tblOrdenes[anio],B$26,tblOrdenes[mes],B$27) | C32: =SUMIFS(tblOrdenes[costo_total],tblOrdenes[sub_area],$A32,tblOrdenes[anio],C$26,tblOrdenes[mes],C$27) | D32: =SUM(B32:C32)
A33: Aire comprimido | B33: =SUMIFS(tblOrdenes[costo_total],tblOrdenes[sub_area],$A33,tblOrdenes[anio],B$26,tblOrdenes[mes],B$27) | C33: =SUMIFS(tblOrdenes[costo_total],tblOrdenes[sub_area],$A33,tblOrdenes[anio],C$26,tblOrdenes[mes],C$27) | D33: =SUM(B33:C33)
A34: TOTAL | B34: =SUM(B28:B33) | C34: =SUM(C28:C33) | D34: =SUM(D28:D33)
A36: REAL por línea
A37: anio | B37: 2026 | C37: 2026
A38: mes | B38: 7 | C38: 8 | D38: TOTAL
A39: L1 | B39: =SUMIFS(tblOrdenes[costo_total],tblOrdenes[linea],$A39,tblOrdenes[anio],B$37,tblOrdenes[mes],B$38) | C39: =SUMIFS(tblOrdenes[costo_total],tblOrdenes[linea],$A39,tblOrdenes[anio],C$37,tblOrdenes[mes],C$38) | D39: =SUM(B39:C39)
A40: L2 | B40: =SUMIFS(tblOrdenes[costo_total],tblOrdenes[linea],$A40,tblOrdenes[anio],B$37,tblOrdenes[mes],B$38) | C40: =SUMIFS(tblOrdenes[costo_total],tblOrdenes[linea],$A40,tblOrdenes[anio],C$37,tblOrdenes[mes],C$38) | D40: =SUM(B40:C40)
A41: L3 | B41: =SUMIFS(tblOrdenes[costo_total],tblOrdenes[linea],$A41,tblOrdenes[anio],B$37,tblOrdenes[mes],B$38) | C41: =SUMIFS(tblOrdenes[costo_total],tblOrdenes[linea],$A41,tblOrdenes[anio],C$37,tblOrdenes[mes],C$38) | D41: =SUM(B41:C41)
A42: L4 | B42: =SUMIFS(tblOrdenes[costo_total],tblOrdenes[linea],$A42,tblOrdenes[anio],B$37,tblOrdenes[mes],B$38) | C42: =SUMIFS(tblOrdenes[costo_total],tblOrdenes[linea],$A42,tblOrdenes[anio],C$37,tblOrdenes[mes],C$38) | D42: =SUM(B42:C42)
A43: SG | B43: =SUMIFS(tblOrdenes[costo_total],tblOrdenes[linea],$A43,tblOrdenes[anio],B$37,tblOrdenes[mes],B$38) | C43: =SUMIFS(tblOrdenes[costo_total],tblOrdenes[linea],$A43,tblOrdenes[anio],C$37,tblOrdenes[mes],C$38) | D43: =SUM(B43:C43)
A44: SG | B44: =SUMIFS(tblOrdenes[costo_total],tblOrdenes[linea],$A44,tblOrdenes[anio],B$37,tblOrdenes[mes],B$38) | C44: =SUMIFS(tblOrdenes[costo_total],tblOrdenes[linea],$A44,tblOrdenes[anio],C$37,tblOrdenes[mes],C$38) | D44: =SUM(B44:C44)
A45: TC | B45: =SUMIFS(tblOrdenes[costo_total],tblOrdenes[linea],$A45,tblOrdenes[anio],B$37,tblOrdenes[mes],B$38) | C45: =SUMIFS(tblOrdenes[costo_total],tblOrdenes[linea],$A45,tblOrdenes[anio],C$37,tblOrdenes[mes],C$38) | D45: =SUM(B45:C45)
A46: TC | B46: =SUMIFS(tblOrdenes[costo_total],tblOrdenes[linea],$A46,tblOrdenes[anio],B$37,tblOrdenes[mes],B$38) | C46: =SUMIFS(tblOrdenes[costo_total],tblOrdenes[linea],$A46,tblOrdenes[anio],C$37,tblOrdenes[mes],C$38) | D46: =SUM(B46:C46)
A47: CO | B47: =SUMIFS(tblOrdenes[costo_total],tblOrdenes[linea],$A47,tblOrdenes[anio],B$37,tblOrdenes[mes],B$38) | C47: =SUMIFS(tblOrdenes[costo_total],tblOrdenes[linea],$A47,tblOrdenes[anio],C$37,tblOrdenes[mes],C$38) | D47: =SUM(B47:C47)
A48: AC | B48: =SUMIFS(tblOrdenes[costo_total],tblOrdenes[linea],$A48,tblOrdenes[anio],B$37,tblOrdenes[mes],B$38) | C48: =SUMIFS(tblOrdenes[costo_total],tblOrdenes[linea],$A48,tblOrdenes[anio],C$37,tblOrdenes[mes],C$38) | D48: =SUM(B48:C48)
A49: TOTAL | B49: =SUM(B39:B48) | C49: =SUM(C39:C48) | D49: =SUM(D39:D48)

Sheet PRESUPUESTO
A1: ="PRESUPUESTO OPEX "&p_anio_presupuesto&" — plan mensual vs gasto real ("&p_moneda&")"
A2: Alcance OPEX: materiales, servicios y terceros. La mano de obra propia NO es costo y no entra ni en el plan ni en el real. Nada de CAPEX ni de costo de ciclo de vida.
A3: La categoría de cada orden se hereda del CATÁLOGO de actividades (CAT_ACTIVIDADES: categoria_presupuesto + clasificacion). Onboardear otra empresa = editar el catálogo.
A4: El gasto real sale del mismo campo que COSTOS (costo_total, REGLA-8). Lo que no tenga categoría en catálogo cae en la fila SIN CLASIFICAR: el gasto nunca desaparece.
A5: =HYPERLINK("#DASHBOARD!A1","◂ VOLVER AL TABLERO")
A6: BLOQUE DE ENTRADA — plan manual del año (azul = editable)
A7: categoria | B7: clasificacion | C7: ene | D7: feb | E7: mar | F7: abr | G7: may | H7: jun | I7: jul | J7: ago | K7: sep | L7: oct | M7: nov | N7: dic | O7: presupuesto_anual | P7: suma_12_meses | Q7: cuadre
A8: Repuestos mandatorios | B8: fijo | C8: 0 | D8: 0 | E8: 0 | F8: 0 | G8: 0 | H8: 0 | I8: 290 | J8: 90 | K8: 0 | L8: 0 | M8: 0 | N8: 0 | O8: 380 | P8: =SUM($C8:$N8) | Q8: =IF(ROUND($P8-$O8,2)=0,"cuadra","DESCUADRE: "&TEXT($P8-$O8,"+#,##0;-#,##0")&" vs anual")
A9: Servicios contratados | B9: fijo | C9: 0 | D9: 0 | E9: 0 | F9: 0 | G9: 0 | H9: 0 | I9: 400 | J9: 180 | K9: 0 | L9: 0 | M9: 0 | N9: 0 | O9: 580 | P9: =SUM($C9:$N9) | Q9: =IF(ROUND($P9-$O9,2)=0,"cuadra","DESCUADRE: "&TEXT($P9-$O9,"+#,##0;-#,##0")&" vs anual")
A10: Overhauls programados | B10: fijo | C10: 400 | D10: 400 | E10: 400 | F10: 400 | G10: 400 | H10: 400 | I10: 400 | J10: 400 | K10: 400 | L10: 400 | M10: 400 | N10: 400 | O10: 4800 | P10: =SUM($C10:$N10) | Q10: =IF(ROUND($P10-$O10,2)=0,"cuadra","DESCUADRE: "&TEXT($P10-$O10,"+#,##0;-#,##0")&" vs anual")
A11: Correctivos - materiales | B11: variable | C11: 0 | D11: 0 | E11: 0 | F11: 0 | G11: 0 | H11: 0 | I11: 370 | J11: 0 | K11: 0 | L11: 0 | M11: 0 | N11: 0 | O11: 370 | P11: =SUM($C11:$N11) | Q11: =IF(ROUND($P11-$O11,2)=0,"cuadra","DESCUADRE: "&TEXT($P11-$O11,"+#,##0;-#,##0")&" vs anual")
A12: Servicios requeridos | B12: variable | C12: 400 | D12: 400 | E12: 400 | F12: 400 | G12: 400 | H12: 400 | I12: 400 | J12: 400 | K12: 400 | L12: 400 | M12: 400 | N12: 400 | O12: 4800 | P12: =SUM($C12:$N12) | Q12: =IF(ROUND($P12-$O12,2)=0,"cuadra","DESCUADRE: "&TEXT($P12-$O12,"+#,##0;-#,##0")&" vs anual")
A13: Refacciones nuevas | B13: variable | C13: 400 | D13: 400 | E13: 400 | F13: 400 | G13: 400 | H13: 400 | I13: 400 | J13: 400 | K13: 400 | L13: 400 | M13: 400 | N13: 400 | O13: 4800 | P13: =SUM($C13:$N13) | Q13: =IF(ROUND($P13-$O13,2)=0,"cuadra","DESCUADRE: "&TEXT($P13-$O13,"+#,##0;-#,##0")&" vs anual")
A14: TOTAL | C14: =SUM(C8:C13) | D14: =SUM(D8:D13) | E14: =SUM(E8:E13) | F14: =SUM(F8:F13) | G14: =SUM(G8:G13) | H14: =SUM(H8:H13) | I14: =SUM(I8:I13) | J14: =SUM(J8:J13) | ... P14: =SUM(P8:P13)
A16: BLOQUE DE COMPARACIÓN — presupuesto vs real por categoría y mes
A17: mes de corte del YTD: | B17: =IF(YEAR(TODAY())>p_anio_presupuesto,12,IF(YEAR(TODAY())<p_anio_presupuesto,0,MONTH(TODAY())))
A19: PRESUPUESTO (del bloque de entrada)
A20: categoria | B20: clasificacion | C20: ene | D20: feb | E20: mar | F20: abr | G20: may | H20: jun | I20: jul | J20: ago | K20: sep | L20: oct | M20: nov | N20: dic | O20: YTD
A21: Repuestos mandatorios | B21: fijo | C21: =C8 | D21: =D8 | E21: =E8 | F21: =F8 | G21: =G8 | H21: =H8 | I21: =I8 | J21: =J8 | ... N21: =N8 | O21: =SUMPRODUCT(({1,2,3,4,5,6,7,8,9,10,11,12}<=$B$17)*($C21:$N21))
A22: Servicios contratados | B22: fijo | C22: =C9 | D22: =D9 | E22: =E9 | F22: =F9 | G22: =G9 | H22: =H9 | I22: =I9 | J22: =J9 | ... N22: =N9 | O22: =SUMPRODUCT(({1,2,3,4,5,6,7,8,9,10,11,12}<=$B$17)*($C22:$N22))
A23: Overhauls programados | B23: fijo | C23: =C10 | D23: =D10 | E23: =E10 | F23: =F10 | G23: =G10 | H23: =H10 | I23: =I10 | J23: =J10 | ... N23: =N10 | O23: =SUMPRODUCT(({1,2,3,4,5,6,7,8,9,10,11,12}<=$B$17)*($C23:$N23))
A24: Correctivos - materiales | B24: variable | C24: =C11 | D24: =D11 | E24: =E11 | F24: =F11 | G24: =G11 | H24: =H11 | I24: =I11 | J24: =J11 | ... N24: =N11 | O24: =SUMPRODUCT(({1,2,3,4,5,6,7,8,9,10,11,12}<=$B$17)*($C24:$N24))
A25: Servicios requeridos | B25: variable | C25: =C12 | D25: =D12 | E25: =E12 | F25: =F12 | G25: =G12 | H25: =H12 | I25: =I12 | J25: =J12 | ... N25: =N12 | O25: =SUMPRODUCT(({1,2,3,4,5,6,7,8,9,10,11,12}<=$B$17)*($C25:$N25))
A26: Refacciones nuevas | B26: variable | C26: =C13 | D26: =D13 | E26: =E13 | F26: =F13 | G26: =G13 | H26: =H13 | I26: =I13 | J26: =J13 | ... N26: =N13 | O26: =SUMPRODUCT(({1,2,3,4,5,6,7,8,9,10,11,12}<=$B$17)*($C26:$N26))
A27: SIN CLASIFICAR | C27: 0 | D27: 0 | E27: 0 | F27: 0 | G27: 0 | H27: 0 | I27: 0 | J27: 0 | K27: 0 | L27: 0 | M27: 0 | N27: 0 | O27: =SUMPRODUCT(({1,2,3,4,5,6,7,8,9,10,11,12}<=$B$17)*($C27:$N27))
A28: Subtotal FIJO | C28: =C21+C22+C23 | D28: =D21+D22+D23 | E28: =E21+E22+E23 | F28: =F21+F22+F23 | G28: =G21+G22+G23 | H28: =H21+H22+H23 | I28: =I21+I22+I23 | J28: =J21+J22+J23 | ... N28: =N21+N22+N23 | O28: =SUMPRODUCT(({1,2,3,4,5,6,7,8,9,10,11,12}<=$B$17)*($C28:$N28))
A29: Subtotal VARIABLE | C29: =C24+C25+C26 | D29: =D24+D25+D26 | E29: =E24+E25+E26 | F29: =F24+F25+F26 | G29: =G24+G25+G26 | H29: =H24+H25+H26 | I29: =I24+I25+I26 | J29: =J24+J25+J26 | ... N29: =N24+N25+N26 | O29: =SUMPRODUCT(({1,2,3,4,5,6,7,8,9,10,11,12}<=$B$17)*($C29:$N29))
A30: TOTAL GENERAL | C30: =C21+C22+C23+C24+C25+C26+C27 | D30: =D21+D22+D23+D24+D25+D26+D27 | E30: =E21+E22+E23+E24+E25+E26+E27 | F30: =F21+F22+F23+F24+F25+F26+F27 | G30: =G21+G22+G23+G24+G25+G26+G27 | H30: =H21+H22+H23+H24+H25+H26+H27 | I30: =I21+I22+I23+I24+I25+I26+I27 | J30: =J21+J22+J23+J24+J25+J26+J27 | ... N30: =N21+N22+N23+N24+N25+N26+N27 | O30: =SUMPRODUCT(({1,2,3,4,5,6,7,8,9,10,11,12}<=$B$17)*($C30:$N30))
A32: REAL (gasto del mes; mismo campo y misma convención de mes que COSTOS)
A33: categoria | B33: clasificacion | C33: ene | D33: feb | E33: mar | F33: abr | G33: may | H33: jun | I33: jul | J33: ago | K33: sep | L33: oct | M33: nov | N33: dic | O33: YTD
A34: Repuestos mandatorios | B34: fijo | C34: =SUMIFS(tblOrdenes[costo_total],tblOrdenes[anio],p_anio_presupuesto,tblOrdenes[mes],1,tblOrdenes[categoria_presupuesto],$A34) | D34: =SUMIFS(tblOrdenes[costo_total],tblOrdenes[anio],p_anio_presupuesto,tblOrdenes[mes],2,tblOrdenes[categoria_presupuesto],$A34) | E34: =SUMIFS(tblOrdenes[costo_total],tblOrdenes[anio],p_anio_presupuesto,tblOrdenes[mes],3,tblOrdenes[categoria_presupuesto],$A34) | F34: =SUMIFS(tblOrdenes[costo_total],tblOrdenes[anio],p_anio_presupuesto,tblOrdenes[mes],4,tblOrdenes[categoria_presupuesto],$A34) | G34: =SUMIFS(tblOrdenes[costo_total],tblOrdenes[anio],p_anio_presupuesto,tblOrdenes[mes],5,tblOrdenes[categoria_presupuesto],$A34) | H34: =SUMIFS(tblOrdenes[costo_total],tblOrdenes[anio],p_anio_presupuesto,tblOrdenes[mes],6,tblOrdenes[categoria_presupuesto],$A34) | I34: =SUMIFS(tblOrdenes[costo_total],tblOrdenes[anio],p_anio_presupuesto,tblOrdenes[mes],7,tblOrdenes[categoria_presupuesto],$A34) | J34: =SUMIFS(tblOrdenes[costo_total],tblOrdenes[anio],p_anio_presupuesto,tblOrdenes[mes],8,tblOrdenes[categoria_presupuesto],$A34) | K34: =SUMIFS(tblOrdenes[costo_total],tblOrdenes[anio],p_anio_presupuesto,tblOrdenes[mes],9,tblOrdenes[categoria_presupuesto],$A34) | L34: =SUMIFS(tblOrdenes[costo_total],tblOrdenes[anio],p_anio_presupuesto,tblOrdenes[mes],10,tblOrdenes[categoria_presupuesto],$A34) | M34: =SUMIFS(tblOrdenes[costo_total],tblOrdenes[anio],p_anio_presupuesto,tblOrdenes[mes],11,tblOrdenes[categoria_presupuesto],$A34) | N34: =SUMIFS(tblOrdenes[costo_total],tblOrdenes[anio],p_anio_presupuesto,tblOrdenes[mes],12,tblOrdenes[categoria_presupuesto],$A34) | O34: =SUMPRODUCT(({1,2,3,4,5,6,7,8,9,10,11,12}<=$B$17)*($C34:$N34))
A35: Servicios contratados | B35: fijo | C35: =SUMIFS(tblOrdenes[costo_total],tblOrdenes[anio],p_anio_presupuesto,tblOrdenes[mes],1,tblOrdenes[categoria_presupuesto],$A35) | D35: =SUMIFS(tblOrdenes[costo_total],tblOrdenes[anio],p_anio_presupuesto,tblOrdenes[mes],2,tblOrdenes[categoria_presupuesto],$A35) | E35: =SUMIFS(tblOrdenes[costo_total],tblOrdenes[anio],p_anio_presupuesto,tblOrdenes[mes],3,tblOrdenes[categoria_presupuesto],$A35) | F35: =SUMIFS(tblOrdenes[costo_total],tblOrdenes[anio],p_anio_presupuesto,tblOrdenes[mes],4,tblOrdenes[categoria_presupuesto],$A35) | G35: =SUMIFS(tblOrdenes[costo_total],tblOrdenes[anio],p_anio_presupuesto,tblOrdenes[mes],5,tblOrdenes[categoria_presupuesto],$A35) | H35: =SUMIFS(tblOrdenes[costo_total],tblOrdenes[anio],p_anio_presupuesto,tblOrdenes[mes],6,tblOrdenes[categoria_presupuesto],$A35) | I35: =SUMIFS(tblOrdenes[costo_total],tblOrdenes[anio],p_anio_presupuesto,tblOrdenes[mes],7,tblOrdenes[categoria_presupuesto],$A35) | J35: =SUMIFS(tblOrdenes[costo_total],tblOrdenes[anio],p_anio_presupuesto,tblOrdenes[mes],8,tblOrdenes[categoria_presupuesto],$A35) | K35: =SUMIFS(tblOrdenes[costo_total],tblOrdenes[anio],p_anio_presupuesto,tblOrdenes[mes],9,tblOrdenes[categoria_presupuesto],$A35) | L35: =SUMIFS(tblOrdenes[costo_total],tblOrdenes[anio],p_anio_presupuesto,tblOrdenes[mes],10,tblOrdenes[categoria_presupuesto],$A35) | M35: =SUMIFS(tblOrdenes[costo_total],tblOrdenes[anio],p_anio_presupuesto,tblOrdenes[mes],11,tblOrdenes[categoria_presupuesto],$A35) | N35: =SUMIFS(tblOrdenes[costo_total],tblOrdenes[anio],p_anio_presupuesto,tblOrdenes[mes],12,tblOrdenes[categoria_presupuesto],$A35) | O35: =SUMPRODUCT(({1,2,3,4,5,6,7,8,9,10,11,12}<=$B$17)*($C35:$N35))
A36: Overhauls programados | B36: fijo | C36: =SUMIFS(tblOrdenes[costo_total],tblOrdenes[anio],p_anio_presupuesto,tblOrdenes[mes],1,tblOrdenes[categoria_presupuesto],$A36) | D36: =SUMIFS(tblOrdenes[costo_total],tblOrdenes[anio],p_anio_presupuesto,tblOrdenes[mes],2,tblOrdenes[categoria_presupuesto],$A36) | E36: =SUMIFS(tblOrdenes[costo_total],tblOrdenes[anio],p_anio_presupuesto,tblOrdenes[mes],3,tblOrdenes[categoria_presupuesto],$A36) | F36: =SUMIFS(tblOrdenes[costo_total],tblOrdenes[anio],p_anio_presupuesto,tblOrdenes[mes],4,tblOrdenes[categoria_presupuesto],$A36) | G36: =SUMIFS(tblOrdenes[costo_total],tblOrdenes[anio],p_anio_presupuesto,tblOrdenes[mes],5,tblOrdenes[categoria_presupuesto],$A36) | H36: =SUMIFS(tblOrdenes[costo_total],tblOrdenes[anio],p_anio_presupuesto,tblOrdenes[mes],6,tblOrdenes[categoria_presupuesto],$A36) | I36: =SUMIFS(tblOrdenes[costo_total],tblOrdenes[anio],p_anio_presupuesto,tblOrdenes[mes],7,tblOrdenes[categoria_presupuesto],$A36) | J36: =SUMIFS(tblOrdenes[costo_total],tblOrdenes[anio],p_anio_presupuesto,tblOrdenes[mes],8,tblOrdenes[categoria_presupuesto],$A36) | K36: =SUMIFS(tblOrdenes[costo_total],tblOrdenes[anio],p_anio_presupuesto,tblOrdenes[mes],9,tblOrdenes[categoria_presupuesto],$A36) | L36: =SUMIFS(tblOrdenes[costo_total],tblOrdenes[anio],p_anio_presupuesto,tblOrdenes[mes],10,tblOrdenes[categoria_presupuesto],$A36) | M36: =SUMIFS(tblOrdenes[costo_total],tblOrdenes[anio],p_anio_presupuesto,tblOrdenes[mes],11,tblOrdenes[categoria_presupuesto],$A36) | N36: =SUMIFS(tblOrdenes[costo_total],tblOrdenes[anio],p_anio_presupuesto,tblOrdenes[mes],12,tblOrdenes[categoria_presupuesto],$A36) | O36: =SUMPRODUCT(({1,2,3,4,5,6,7,8,9,10,11,12}<=$B$17)*($C36:$N36))
