Workbook
Name p_moneda: PARAMETROS!$B$6
Name p_horas_jornada: PARAMETROS!$B$7
Name p_factor_productividad: PARAMETROS!$B$8
Name p_dias_backlog_max: PARAMETROS!$B$11
Name p_dias_backlog_min: PARAMETROS!$B$12
Name p_meta_adherencia: PARAMETROS!$B$13
Name p_meta_ratio_prev_corr: PARAMETROS!$B$14
Name p_ruta_base_checklists: PARAMETROS!$B$16
Name lista_turnos: PARAMETROS!$E$5:$E$10
Name lista_no_disponible: PARAMETROS!$G$5:$G$6
Name lista_dias: PARAMETROS!$I$5:$I$11
Name lista_tecnicos: TECNICOS!$B$4:$B$15

Sheet INICIO
A1: MantPlan — Planificador semanal de mantenimiento
A2: Versión 2.0.0 · generado 2026-07-20 · datos 100 % sintéticos de ejemplo
A4: PRINCIPIO RECTOR — separación entre lógica y datos:
A5: · MOTOR: las 10 reglas de negocio viven en las fórmulas de este libro y nunca cambian.
A6: · CATÁLOGOS: centros de costo, puestos, actividades, tipos de OT y estados se cargan por empresa.
A7: · PARÁMETROS: jornada, productividad, ventanas de backlog y metas se ajustan en PARAMETROS.
A8: · No hay macros, ni enlaces externos, ni códigos de empresa dentro de ninguna fórmula.
A10: FLUJO DE USO EN 5 PASOS:
A11: 1. Ajuste PARAMETROS y cargue los catálogos de su empresa (hojas CAT_*).
A12: 2. Pegue la exportación de órdenes (12 columnas, en este orden) directamente en ORDENES!A4:
A13: un solo bloque contiguo A:L. Hay 1.200 filas provisionadas con las fórmulas ya escritas.
A14: 3. Pegue la segunda exportación (estados y costos) en 2_IMPORTAR_EJECUCION.
... A24: · PLAN_SEMANAL: el gráfico de carga por técnico responde a los mismos selectores que la grilla.

Sheet PARAMETROS
A1: PARÁMETROS DEL MOTOR (Tabla 10)
A3: parametro | B3: valor | C3: descripcion | E3: listas auxiliares
A4: nombre_empresa | B4: Empresa Ejemplo S.A. | C4: Editable. Solo informativo, no participa en cálculos. | E4: turnos y códigos de ausencia: | G4: no disponible: | I4: días (1 = lunes):
A5: nombre_planta | B5: Planta Ejemplo | C5: Editable. Solo informativo. | E5: B1 | G5: VAC | I5: lunes
A6: moneda | B6: USD | C6: Moneda de los costos. | E6: T1 | G6: X | I6: martes
A7: horas_jornada | B7: 7 | C7: Horas de trabajo por técnico y día (REGLA-5). | E7: T2 | I7: miércoles
A8: factor_productividad | B8: 0.87 | C8: Fracción productiva de la jornada (REGLA-6). | E8: T3 | I8: jueves
A9: turnos | B9: B1,T1,T2,T3 | C9: Códigos de turno válidos (lista auxiliar a la derecha). | E9: VAC | I9: viernes
A10: codigos_no_disponible | B10: VAC,X | C10: Códigos que anulan la disponibilidad (REGLA-5). | E10: X | I10: sábado
A11: dias_backlog_max | B11: 30 | C11: Días hacia atrás que siguen siendo plan (REGLAS 3 y 4). | I11: domingo
A12: dias_backlog_min | B12: -92 | C12: Días hacia adelante (negativo) que entran al plan (REGLA-4).
A13: meta_adherencia | B13: 0.95 | C13: Meta de adherencia semanal (REGLA-7).
A14: meta_ratio_prev_corr | B14: 0.8 | C14: Meta: fracción preventiva mínima de las HH (REGLA-9).
A15: primer_dia_semana | B15: lunes | C15: Inicio de semana. La semana ISO (REGLA-2) empieza en lunes.
A16: ruta_base_checklists | B16: C:\MANTPLAN\checklists\ | C16: Base para los hipervínculos de la columna link_checklist.

Sheet 1_IMPORTAR_ORDENES
A1: ZONA DE PEGADO — exportación de órdenes del ERP
A3: Ordene la exportación de su ERP con estas 12 cabeceras exactas (misma disposición que ORDENES!A:L)
A4: y péguela EN UN SOLO PASO en ORDENES!A4 (o desde la primera fila libre). Nada más que hacer:
A5: las columnas calculadas ya están escritas en las 1.200 filas provisionadas de la tabla.
A6: operacion es opcional: si su ERP no maneja operaciones, déjela vacía y el sistema asume "0010".
A7: horas_ajustadas (columna M de ORDENES) es del planificador y NO se pega: sobrevive a la re-importación.
A8: orden | B8: operacion | C8: descripcion_general | D8: descripcion_operacion | E8: equipo | F8: centro_costo | G8: puesto_trabajo | H8: cod_actividad | I8: tipo_ot | J8: fecha_inicio | K8: horas_estimadas | L8: costo_plan
A9: OT-000001 | B9: 0010 | C9: Lubricación programada — EQ-102 | D9: Lubricación programada en EQ-102 | E9: EQ-102 | F9: CC-110 | G9: PU-MEC | H9: ACT-02 | I9: TIPO-P2 | J9: 46216 | K9: 10 | L9: 250
A10: OT-000002 | B10: 0010 | C10: Análisis predictivo — EQ-108 | D10: Análisis predictivo en EQ-108 | E10: EQ-108 | F10: CC-210 | G10: PU-MEC | H10: ACT-04 | I10: TIPO-P1 | J10: 46217 | K10: 8 | L10: 200

Sheet 2_IMPORTAR_EJECUCION
A1: ZONA DE PEGADO — segunda exportación: estados y costos (tblEjecucion)
A3: Pegue aquí los estados y costos reales del ERP, con estas cabeceras exactas, desde la primera fila vacía.
A4: id_operacion se calcula solo. El catálogo CAT_ESTADOS_ERP traduce estado_sistema a Cerrada/Pendiente.
A5: Las órdenes sin par en esta tabla quedan como "Pendiente" (REGLA-10).
A8: orden | B8: operacion | C8: estado_sistema | D8: prioridad | E8: estado_instalacion | F8: precio | G8: costo_real | H8: costo_plan_total | I8: estado_usuario | J8: id_operacion
A9: OT-000001 | B9: 0010 | C9: LIB | D9: 1-ALTA | E9: OPERATIVO | F9: 100 | G9: 0 | H9: 250 | I9: LIBERADA | J9: =IF(tblEjecucion[[#This Row],[orden]]="","",tblEjecucion[[#This Row],[orden]]&IF(tblEjecucion[[#This Row],[operacion]]="","0010",tblEjecucion[[#This Row],[operacion]]))
A10: OT-000002 | B10: 0010 | C10: CERR | D10: 2-MEDIA | E10: PARADO | F10: 80 | G10: 200 | H10: 200 | I10: CERRADA | J10: =IF(tblEjecucion[[#This Row],[orden]]="","",tblEjecucion[[#This Row],[orden]]&IF(tblEjecucion[[#This Row],[operacion]]="","0010",tblEjecucion[[#This Row],[operacion]]))
A11: OT-000003 | B11: 0010 | C11: CERR | D11: 3-BAJA | E11: OPERATIVO | F11: 60 | G11: 150 | H11: 150 | I11: CERRADA | J11: =IF(tblEjecucion[[#This Row],[orden]]="","",tblEjecucion[[#This Row],[orden]]&IF(tblEjecucion[[#This Row],[operacion]]="","0010",tblEjecucion[[#This Row],[operacion]]))
A12: OT-000004 | B12: 0010 | C12: CERR | D12: 1-ALTA | E12: PARADO | F12: 100 | G12: 250 | H12: 250 | I12: CERRADA | J12: =IF(tblEjecucion[[#This Row],[orden]]="","",tblEjecucion[[#This Row],[orden]]&IF(tblEjecucion[[#This Row],[operacion]]="","0010",tblEjecucion[[#This Row],[operacion]]))
A13: OT-000005 | B13: 0010 | C13: CERR | D13: 2-MEDIA | E13: OPERATIVO | F13: 80 | G13: 200 | H13: 200 | I13: CERRADA | J13: =IF(tblEjecucion[[#This Row],[orden]]="","",tblEjecucion[[#This Row],[orden]]&IF(tblEjecucion[[#This Row],[operacion]]="","0010",tblEjecucion[[#This Row],[operacion]]))
A14: OT-000006 | B14: 0010 | C14: CERR | D14: 3-BAJA | E14: PARADO | F14: 60 | G14: 150 | H14: 150 | I14: CERRADA | J14: =IF(tblEjecucion[[#This Row],[orden]]="","",tblEjecucion[[#This Row],[orden]]&IF(tblEjecucion[[#This Row],[operacion]]="","0010",tblEjecucion[[#This Row],[operacion]]))
A15: OT-000007 | B15: 0010 | C15: CERR | D15: 1-ALTA | E15: OPERATIVO | F15: 100 | G15: 250 | H15: 250 | I15: CERRADA | J15: =IF(tblEjecucion[[#This Row],[orden]]="","",tblEjecucion[[#This Row],[orden]]&IF(tblEjecucion[[#This Row],[operacion]]="","0010",tblEjecucion[[#This Row],[operacion]]))
A16: OT-000008 | B16: 0010 | C16: CERR | D16: 2-MEDIA | E16: PARADO | F16: 80 | G16: 200 | H16: 200 | I16: CERRADA | J16: =IF(tblEjecucion[[#This Row],[orden]]="","",tblEjecucion[[#This Row],[orden]]&IF(tblEjecucion[[#This Row],[operacion]]="","0010",tblEjecucion[[#This Row],[operacion]]))
A17: OT-000009 | B17: 0010 | C17: CERR | D17: 3-BAJA | E17: OPERATIVO | F17: 60 | G17: 150 | H17: 150 | I17: CERRADA | J17: =IF(tblEjecucion[[#This Row],[orden]]="","",tblEjecucion[[#This Row],[orden]]&IF(tblEjecucion[[#This Row],[operacion]]="","0010",tblEjecucion[[#This Row],[operacion]]))
A18: OT-000010 | B18: 0010 | C18: CERR | D18: 1-ALTA | E18: PARADO | F18: 80 | G18: 200 | H18: 200 | I18: CERRADA | J18: =IF(tblEjecucion[[#This Row],[orden]]="","",tblEjecucion[[#This Row],[orden]]&IF(tblEjecucion[[#This Row],[operacion]]="","0010",tblEjecucion[[#This Row],[operacion]]))
A19: OT-000011 | B19: 0010 | C19: CERR | D19: 2-MEDIA | E19: OPERATIVO | F19: 160 | G19: 400 | H19: 400 | I19: CERRADA | J19: =IF(tblEjecucion[[#This Row],[orden]]="","",tblEjecucion[[#This Row],[orden]]&IF(tblEjecucion[[#This Row],[operacion]]="","0010",tblEjecucion[[#This Row],[operacion]]))
A20: OT-000012 | B20: 0010 | C20: CERR | D20: 3-BAJA | E20: PARADO | F20: 160 | G20: 400 | H20: 400 | I20: CERRADA | J20: =IF(tblEjecucion[[#This Row],[orden]]="","",tblEjecucion[[#This Row],[orden]]&IF(tblEjecucion[[#This Row],[operacion]]="","0010",tblEjecucion[[#This Row],[operacion]]))
... A169: OT-000992 | B169: 0010 | C169: LIB | D169: 2-MEDIA | E169: OPERATIVO | F169: 50 | G169: 0 | H169: 150 | I169: LIBERADA | J169: =IF(tblEjecucion[[#This Row],[orden]]="","",tblEjecucion[[#This Row],[orden]]&IF(tblEjecucion[[#This Row],[operacion]]="","0010",tblEjecucion[[#This Row],[operacion]]))
J170: =IF(tblEjecucion[[#This Row],[orden]]="","",tblEjecucion[[#This Row],[orden]]&IF(tblEjecucion[[#This Row],[operacion]]="","0010",tblEjecucion[[#This Row],[operacion]]))
J171: =IF(tblEjecucion[[#This Row],[orden]]="","",tblEjecucion[[#This Row],[orden]]&IF(tblEjecucion[[#This Row],[operacion]]="","0010",tblEjecucion[[#This Row],[operacion]]))
J172: =IF(tblEjecucion[[#This Row],[orden]]="","",tblEjecucion[[#This Row],[orden]]&IF(tblEjecucion[[#This Row],[operacion]]="","0010",tblEjecucion[[#This Row],[operacion]]))
J173: =IF(tblEjecucion[[#This Row],[orden]]="","",tblEjecucion[[#This Row],[orden]]&IF(tblEjecucion[[#This Row],[operacion]]="","0010",tblEjecucion[[#This Row],[operacion]]))
J174: =IF(tblEjecucion[[#This Row],[orden]]="","",tblEjecucion[[#This Row],[orden]]&IF(tblEjecucion[[#This Row],[operacion]]="","0010",tblEjecucion[[#This Row],[operacion]]))
J175: =IF(tblEjecucion[[#This Row],[orden]]="","",tblEjecucion[[#This Row],[orden]]&IF(tblEjecucion[[#This Row],[operacion]]="","0010",tblEjecucion[[#This Row],[operacion]]))
J176: =IF(tblEjecucion[[#This Row],[orden]]="","",tblEjecucion[[#This Row],[orden]]&IF(tblEjecucion[[#This Row],[operacion]]="","0010",tblEjecucion[[#This Row],[operacion]]))
J177: =IF(tblEjecucion[[#This Row],[orden]]="","",tblEjecucion[[#This Row],[orden]]&IF(tblEjecucion[[#This Row],[operacion]]="","0010",tblEjecucion[[#This Row],[operacion]]))
J178: =IF(tblEjecucion[[#This Row],[orden]]="","",tblEjecucion[[#This Row],[orden]]&IF(tblEjecucion[[#This Row],[operacion]]="","0010",tblEjecucion[[#This Row],[operacion]]))
J179: =IF(tblEjecucion[[#This Row],[orden]]="","",tblEjecucion[[#This Row],[orden]]&IF(tblEjecucion[[#This Row],[operacion]]="","0010",tblEjecucion[[#This Row],[operacion]]))
J180: =IF(tblEjecucion[[#This Row],[orden]]="","",tblEjecucion[[#This Row],[orden]]&IF(tblEjecucion[[#This Row],[operacion]]="","0010",tblEjecucion[[#This Row],[operacion]]))
J181: =IF(tblEjecucion[[#This Row],[orden]]="","",tblEjecucion[[#This Row],[orden]]&IF(tblEjecucion[[#This Row],[operacion]]="","0010",tblEjecucion[[#This Row],[operacion]]))
... J1208: =IF(tblEjecucion[[#This Row],[orden]]="","",tblEjecucion[[#This Row],[orden]]&IF(tblEjecucion[[#This Row],[operacion]]="","0010",tblEjecucion[[#This Row],[operacion]]))

Sheet ORDENES
A1: ORDENES — tabla madre (tblOrdenes). Azul = editable; el resto se calcula solo.
A3: orden | B3: operacion | C3: descripcion_general | D3: descripcion_operacion | E3: equipo | F3: centro_costo | G3: puesto_trabajo | H3: cod_actividad | I3: tipo_ot | J3: fecha_inicio | K3: horas_estimadas | L3: costo_plan | M3: horas_ajustadas | N3: horas_efectivas | O3: estado | P3: semana | Q3: anio | R3: mes | S3: dia_semana | T3: clasificacion | U3: linea | V3: area | W3: coordinador | X3: especialidad | Y3: actividad | Z3: backlog_dias | AA3: estado_backlog | AB3: en_plan | AC3: tecnico_asignado | AD3: turno_asignado | AE3: HHA | AF3: HHD | AG3: costo_servicio | AH3: costo_materiales | AI3: costo_total | AJ3: permiso_requerido | AK3: bloqueo_energia | AL3: link_checklist | AM3: abrir_checklist | AN3: observaciones | AO3: id_operacion
A4: OT-000001 | B4: 0010 | C4: Lubricación programada — EQ-102 | D4: Lubricación programada en EQ-102 | E4: EQ-102 | F4: CC-110 | G4: PU-MEC | H4: ACT-02 | I4: TIPO-P2 | J4: 46216 | K4: 10 | L4: 250 | N4: =IF(tblOrdenes[[#This Row],[orden]]="","",IF(tblOrdenes[[#This Row],[horas_ajustadas]]<>"",tblOrdenes[[#This Row],[horas_ajustadas]],IF(tblOrdenes[[#This Row],[horas_estimadas]]="","",tblOrdenes[[#This Row],[horas_estimadas]]))) | O4: =IF(tblOrdenes[[#This Row],[orden]]="","",_xlfn.XLOOKUP(_xlfn.XLOOKUP(tblOrdenes[[#This Row],[id_operacion]],tblEjecucion[id_operacion],tblEjecucion[estado_sistema],""),tblEstados[estado_sistema],tblEstados[estado_normalizado],"Pendiente")) | P4: =IF(tblOrdenes[[#This Row],[fecha_inicio]]="","",YEAR(tblOrdenes[[#This Row],[fecha_inicio]]+4-WEEKDAY(tblOrdenes[[#This Row],[fecha_inicio]],2))&"-S"&TEXT(_xlfn.ISOWEEKNUM(tblOrdenes[[#This Row],[fecha_inicio]]),"00")) | Q4: =IF(tblOrdenes[[#This Row],[fecha_inicio]]="","",YEAR(tblOrdenes[[#This Row],[fecha_inicio]])) | R4: =IF(tblOrdenes[[#This Row],[fecha_inicio]]="","",MONTH(tblOrdenes[[#This Row],[fecha_inicio]])) | S4: =IF(tblOrdenes[[#This Row],[fecha_inicio]]="","",INDEX(lista_dias,WEEKDAY(tblOrdenes[[#This Row],[fecha_inicio]],2))) | T4: =IF(tblOrdenes[[#This Row],[tipo_ot]]="","",_xlfn.XLOOKUP(tblOrdenes[[#This Row],[tipo_ot]],tblTiposOT[codigo],tblTiposOT[clasificacion],"sin_clasificar")) | U4: =IF(tblOrdenes[[#This Row],[centro_costo]]="","",_xlfn.XLOOKUP(tblOrdenes[[#This Row],[centro_costo]],tblCECO[codigo],tblCECO[linea],"(sin catálogo)")) | V4: =IF(tblOrdenes[[#This Row],[centro_costo]]="","",_xlfn.XLOOKUP(tblOrdenes[[#This Row],[centro_costo]],tblCECO[codigo],tblCECO[area],"(sin catálogo)")) | W4: =IF(tblOrdenes[[#This Row],[centro_costo]]="","",_xlfn.XLOOKUP(tblOrdenes[[#This Row],[centro_costo]],tblCECO[codigo],tblCECO[coordinador],"(sin catálogo)")) | X4: =IF(tblOrdenes[[#This Row],[puesto_trabajo]]="","",_xlfn.XLOOKUP(tblOrdenes[[#This Row],[puesto_trabajo]],tblPuestos[codigo],tblPuestos[especialidad],"(sin catálogo)")) | Y4: =IF(tblOrdenes[[#This Row],[cod_actividad]]="","",_xlfn.XLOOKUP(tblOrdenes[[#This Row],[cod_actividad]],tblActividades[codigo],tblActividades[descripcion],"(sin catálogo)")) | Z4: =IF(tblOrdenes[[#This Row],[fecha_inicio]]="","",TODAY()-tblOrdenes[[#This Row],[fecha_inicio]]) | AA4: =IF(tblOrdenes[[#This Row],[backlog_dias]]="","",IF(tblOrdenes[[#This Row],[backlog_dias]]<0,"FUTURO",IF(tblOrdenes[[#This Row],[backlog_dias]]>p_dias_backlog_max,"BACKLOG","MES CORRIENTE"))) | AB4: =IF(tblOrdenes[[#This Row],[backlog_dias]]="",FALSE,AND(tblOrdenes[[#This Row],[backlog_dias]]>p_dias_backlog_min,tblOrdenes[[#This Row],[backlog_dias]]<=p_dias_backlog_max)) | AC4: Técnico 01 | AD4: =IF(tblOrdenes[[#This Row],[tecnico_asignado]]="","",_xlfn.XLOOKUP(tblOrdenes[[#This Row],[semana]]&"|"&tblOrdenes[[#This Row],[dia_semana]]&"|"&tblOrdenes[[#This Row],[tecnico_asignado]],tblAsignaciones[clave],tblAsignaciones[turno],"")) | AE4: =IF(tblOrdenes[[#This Row],[tecnico_asignado]]="","",SUMIFS(tblOrdenes[horas_efectivas],tblOrdenes[tecnico_asignado],tblOrdenes[[#This Row],[tecnico_asignado]],tblOrdenes[semana],tblOrdenes[[#This Row],[semana]],tblOrdenes[dia_semana],tblOrdenes[[#This Row],[dia_semana]])) | AF4: =IF(tblOrdenes[[#This Row],[HHA]]="","",p_factor_productividad*_xlfn.XLOOKUP(tblOrdenes[[#This Row],[semana]]&"|"&tblOrdenes[[#This Row],[dia_semana]]&"|"&tblOrdenes[[#This Row],[tecnico_asignado]],tblAsignaciones[clave],tblAsignaciones[horas_disponibles],0)-tblOrdenes[[#This Row],[HHA]]) | AG4: =IF(tblOrdenes[[#This Row],[orden]]="","",_xlfn.XLOOKUP(tblOrdenes[[#This Row],[id_operacion]],tblEjecucion[id_operacion],tblEjecucion[precio],0)) | AH4: =IF(tblOrdenes[[#This Row],[orden]]="","",MAX(0,_xlfn.XLOOKUP(tblOrdenes[[#This Row],[id_operacion]],tblEjecucion[id_operacion],tblEjecucion[costo_plan_total],0)-tblOrdenes[[#This Row],[costo_servicio]])) | AI4: =IF(tblOrdenes[[#This Row],[orden]]="","",tblOrdenes[[#This Row],[costo_servicio]]+tblOrdenes[[#This Row],[costo_materiales]]) | AL4: ACT-02.pdf | AM4: =IF(tblOrdenes[[#This Row],[link_checklist]]="","",HYPERLINK(p_ruta_base_checklists&tblOrdenes[[#This Row],[link_checklist]],"abrir")) | AO4: =IF(tblOrdenes[[#This Row],[orden]]="","",tblOrdenes[[#This Row],[orden]]&IF(tblOrdenes[[#This Row],[operacion]]="","0010",tblOrdenes[[#This Row],[operacion]]))
A5: OT-000002 | B5: 0010 | C5: Análisis predictivo — EQ-108 | D5: Análisis predictivo en EQ-108 | E5: EQ-108 | F5: CC-210 | G5: PU-MEC | H5: ACT-04 | I5: TIPO-P1 | J5: 46217 | K5: 8 | L5: 200 | N5: =IF(tblOrdenes[[#This Row],[orden]]="","",IF(tblOrdenes[[#This Row],[horas_ajustadas]]<>"",tblOrdenes[[#This Row],[horas_ajustadas]],IF(tblOrdenes[[#This Row],[horas_estimadas]]="","",tblOrdenes[[#This Row],[horas_estimadas]]))) | O5: =IF(tblOrdenes[[#This Row],[orden]]="","",_xlfn.XLOOKUP(_xlfn.XLOOKUP(tblOrdenes[[#This Row],[id_operacion]],tblEjecucion[id_operacion],tblEjecucion[estado_sistema],""),tblEstados[estado_sistema],tblEstados[estado_normalizado],"Pendiente")) | P5: =IF(tblOrdenes[[#This Row],[fecha_inicio]]="","",YEAR(tblOrdenes[[#This Row],[fecha_inicio]]+4-WEEKDAY(tblOrdenes[[#This Row],[fecha_inicio]],2))&"-S"&TEXT(_xlfn.ISOWEEKNUM(tblOrdenes[[#This Row],[fecha_inicio]]),"00")) | Q5: =IF(tblOrdenes[[#This Row],[fecha_inicio]]="","",YEAR(tblOrdenes[[#This Row],[fecha_inicio]])) | R5: =IF(tblOrdenes[[#This Row],[fecha_inicio]]="","",MONTH(tblOrdenes[[#This Row],[fecha_inicio]])) | S5: =IF(tblOrdenes[[#This Row],[fecha_inicio]]="","",INDEX(lista_dias,WEEKDAY(tblOrdenes[[#This Row],[fecha_inicio]],2))) | T5: =IF(tblOrdenes[[#This Row],[tipo_ot]]="","",_xlfn.XLOOKUP(tblOrdenes[[#This Row],[tipo_ot]],tblTiposOT[codigo],tblTiposOT[clasificacion],"sin_clasificar")) | U5: =IF(tblOrdenes[[#This Row],[centro_costo]]="","",_xlfn.XLOOKUP(tblOrdenes[[#This Row],[centro_costo]],tblCECO[codigo],tblCECO[linea],"(sin catálogo)")) | V5: =IF(tblOrdenes[[#This Row],[centro_costo]]="","",_xlfn.XLOOKUP(tblOrdenes[[#This Row],[centro_costo]],tblCECO[codigo],tblCECO[area],"(sin catálogo)")) | W5: =IF(tblOrdenes[[#This Row],[centro_costo]]="","",_xlfn.XLOOKUP(tblOrdenes[[#This Row],[centro_costo]],tblCECO[codigo],tblCECO[coordinador],"(sin catálogo)")) | X5: =IF(tblOrdenes[[#This Row],[puesto_trabajo]]="","",_xlfn.XLOOKUP(tblOrdenes[[#This Row],[puesto_trabajo]],tblPuestos[codigo],tblPuestos[especialidad],"(sin catálogo)")) | Y5: =IF(tblOrdenes[[#This Row],[cod_actividad]]="","",_xlfn.XLOOKUP(tblOrdenes[[#This Row],[cod_actividad]],tblActividades[codigo],tblActividades[descripcion],"(sin catálogo)")) | Z5: =IF(tblOrdenes[[#This Row],[fecha_inicio]]="","",TODAY()-tblOrdenes[[#This Row],[fecha_inicio]]) | AA5: =IF(tblOrdenes[[#This Row],[backlog_dias]]="","",IF(tblOrdenes[[#This Row],[backlog_dias]]<0,"FUTURO",IF(tblOrdenes[[#This Row],[backlog_dias]]>p_dias_backlog_max,"BACKLOG","MES CORRIENTE"))) | AB5: =IF(tblOrdenes[[#This Row],[backlog_dias]]="",FALSE,AND(tblOrdenes[[#This Row],[backlog_dias]]>p_dias_backlog_min,tblOrdenes[[#This Row],[backlog_dias]]<=p_dias_backlog_max)) | AC5: Técnico 02 | AD5: =IF(tblOrdenes[[#This Row],[tecnico_asignado]]="","",_xlfn.XLOOKUP(tblOrdenes[[#This Row],[semana]]&"|"&tblOrdenes[[#This Row],[dia_semana]]&"|"&tblOrdenes[[#This Row],[tecnico_asignado]],tblAsignaciones[clave],tblAsignaciones[turno],"")) | AE5: =IF(tblOrdenes[[#This Row],[tecnico_asignado]]="","",SUMIFS(tblOrdenes[horas_efectivas],tblOrdenes[tecnico_asignado],tblOrdenes[[#This Row],[tecnico_asignado]],tblOrdenes[semana],tblOrdenes[[#This Row],[semana]],tblOrdenes[dia_semana],tblOrdenes[[#This Row],[dia_semana]])) | AF5: =IF(tblOrdenes[[#This Row],[HHA]]="","",p_factor_productividad*_xlfn.XLOOKUP(tblOrdenes[[#This Row],[semana]]&"|"&tblOrdenes[[#This Row],[dia_semana]]&"|"&tblOrdenes[[#This Row],[tecnico_asignado]],tblAsignaciones[clave],tblAsignaciones[horas_disponibles],0)-tblOrdenes[[#This Row],[HHA]]) | AG5: =IF(tblOrdenes[[#This Row],[orden]]="","",_xlfn.XLOOKUP(tblOrdenes[[#This Row],[id_operacion]],tblEjecucion[id_operacion],tblEjecucion[precio],0)) | AH5: =IF(tblOrdenes[[#This Row],[orden]]="","",MAX(0,_xlfn.XLOOKUP(tblOrdenes[[#This Row],[id_operacion]],tblEjecucion[id_operacion],tblEjecucion[costo_plan_total],0)-tblOrdenes[[#This Row],[costo_servicio]])) | AI5: =IF(tblOrdenes[[#This Row],[orden]]="","",tblOrdenes[[#This Row],[costo_servicio]]+tblOrdenes[[#This Row],[costo_materiales]]) | AL5: ACT-04.pdf | AM5: =IF(tblOrdenes[[#This Row],[link_checklist]]="","",HYPERLINK(p_ruta_base_checklists&tblOrdenes[[#This Row],[link_checklist]],"abrir")) | AO5: =IF(tblOrdenes[[#This Row],[orden]]="","",tblOrdenes[[#This Row],[orden]]&IF(tblOrdenes[[#This Row],[operacion]]="","0010",tblOrdenes[[#This Row],[operacion]]))
A6: OT-000003 | B6: 0010 | C6: Inspección de rutina — EQ-110 | D6: Inspección de rutina en EQ-110 | E6: EQ-110 | F6: CC-310 | G6: PU-MEC | H6: ACT-01 | I6: TIPO-P2 | J6: 46218 | K6: 6 | L6: 150 | N6: =IF(tblOrdenes[[#This Row],[orden]]="","",IF(tblOrdenes[[#This Row],[horas_ajustadas]]<>"",tblOrdenes[[#This Row],[horas_ajustadas]],IF(tblOrdenes[[#This Row],[horas_estimadas]]="","",tblOrdenes[[#This Row],[horas_estimadas]]))) | O6: =IF(tblOrdenes[[#This Row],[orden]]="","",_xlfn.XLOOKUP(_xlfn.XLOOKUP(tblOrdenes[[#This Row],[id_operacion]],tblEjecucion[id_operacion],tblEjecucion[estado_sistema],""),tblEstados[estado_sistema],tblEstados[estado_normalizado],"Pendiente")) | P6: =IF(tblOrdenes[[#This Row],[fecha_inicio]]="","",YEAR(tblOrdenes[[#This Row],[fecha_inicio]]+4-WEEKDAY(tblOrdenes[[#This Row],[fecha_inicio]],2))&"-S"&TEXT(_xlfn.ISOWEEKNUM(tblOrdenes[[#This Row],[fecha_inicio]]),"00")) | Q6: =IF(tblOrdenes[[#This Row],[fecha_inicio]]="","",YEAR(tblOrdenes[[#This Row],[fecha_inicio]])) | R6: =IF(tblOrdenes[[#This Row],[fecha_inicio]]="","",MONTH(tblOrdenes[[#This Row],[fecha_inicio]])) | S6: =IF(tblOrdenes[[#This Row],[fecha_inicio]]="","",INDEX(lista_dias,WEEKDAY(tblOrdenes[[#This Row],[fecha_inicio]],2))) | T6: =IF(tblOrdenes[[#This Row],[tipo_ot]]="","",_xlfn.XLOOKUP(tblOrdenes[[#This Row],[tipo_ot]],tblTiposOT[codigo],tblTiposOT[clasificacion],"sin_clasificar")) | U6: =IF(tblOrdenes[[#This Row],[centro_costo]]="","",_xlfn.XLOOKUP(tblOrdenes[[#This Row],[centro_costo]],tblCECO[codigo],tblCECO[linea],"(sin catálogo)")) | V6: =IF(tblOrdenes[[#This Row],[centro_costo]]="","",_xlfn.XLOOKUP(tblOrdenes[[#This Row],[centro_costo]],tblCECO[codigo],tblCECO[area],"(sin catálogo)")) | W6: =IF(tblOrdenes[[#This Row],[centro_costo]]="","",_xlfn.XLOOKUP(tblOrdenes[[#This Row],[centro_costo]],tblCECO[codigo],tblCECO[coordinador],"(sin catálogo)")) | X6: =IF(tblOrdenes[[#This Row],[puesto_trabajo]]="","",_xlfn.XLOOKUP(tblOrdenes[[#This Row],[puesto_trabajo]],tblPuestos[codigo],tblPuestos[especialidad],"(sin catálogo)")) | Y6: =IF(tblOrdenes[[#This Row],[cod_actividad]]="","",_xlfn.XLOOKUP(tblOrdenes[[#This Row],[cod_actividad]],tblActividades[codigo],tblActividades[descripcion],"(sin catálogo)")) | Z6: =IF(tblOrdenes[[#This Row],[fecha_inicio]]="","",TODAY()-tblOrdenes[[#This Row],[fecha_inicio]]) | AA6: =IF(tblOrdenes[[#This Row],[backlog_dias]]="","",IF(tblOrdenes[[#This Row],[backlog_dias]]<0,"FUTURO",IF(tblOrdenes[[#This Row],[backlog_dias]]>p_dias_backlog_max,"BACKLOG","MES CORRIENTE"))) | AB6: =IF(tblOrdenes[[#This Row],[backlog_dias]]="",FALSE,AND(tblOrdenes[[#This Row],[backlog_dias]]>p_dias_backlog_min,tblOrdenes[[#This Row],[backlog_dias]]<=p_dias_backlog_max)) | AC6: Técnico 03 | AD6: =IF(tblOrdenes[[#This Row],[tecnico_asignado]]="","",_xlfn.XLOOKUP(tblOrdenes[[#This Row],[semana]]&"|"&tblOrdenes[[#This Row],[dia_semana]]&"|"&tblOrdenes[[#This Row],[tecnico_asignado]],tblAsignaciones[clave],tblAsignaciones[turno],"")) | AE6: =IF(tblOrdenes[[#This Row],[tecnico_asignado]]="","",SUMIFS(tblOrdenes[horas_efectivas],tblOrdenes[tecnico_asignado],tblOrdenes[[#This Row],[tecnico_asignado]],tblOrdenes[semana],tblOrdenes[[#This Row],[semana]],tblOrdenes[dia_semana],tblOrdenes[[#This Row],[dia_semana]])) | AF6: =IF(tblOrdenes[[#This Row],[HHA]]="","",p_factor_productividad*_xlfn.XLOOKUP(tblOrdenes[[#This Row],[semana]]&"|"&tblOrdenes[[#This Row],[dia_semana]]&"|"&tblOrdenes[[#This Row],[tecnico_asignado]],tblAsignaciones[clave],tblAsignaciones[horas_disponibles],0)-tblOrdenes[[#This Row],[HHA]]) | AG6: =IF(tblOrdenes[[#This Row],[orden]]="","",_xlfn.XLOOKUP(tblOrdenes[[#This Row],[id_operacion]],tblEjecucion[id_operacion],tblEjecucion[precio],0)) | AH6: =IF(tblOrdenes[[#This Row],[orden]]="","",MAX(0,_xlfn.XLOOKUP(tblOrdenes[[#This Row],[id_operacion]],tblEjecucion[id_operacion],tblEjecucion[costo_plan_total],0)-tblOrdenes[[#This Row],[costo_servicio]])) | AI6: =IF(tblOrdenes[[#This Row],[orden]]="","",tblOrdenes[[#This Row],[costo_servicio]]+tblOrdenes[[#This Row],[costo_materiales]]) | AL6: ACT-01.pdf | AM6: =IF(tblOrdenes[[#This Row],[link_checklist]]="","",HYPERLINK(p_ruta_base_checklists&tblOrdenes[[#This Row],[link_checklist]],"abrir")) | AO6: =IF(tblOrdenes[[#This Row],[orden]]="","",tblOrdenes[[#This Row],[orden]]&IF(tblOrdenes[[#This Row],[operacion]]="","0010",tblOrdenes[[#This Row],[operacion]]))
A7: OT-000004 | B7: 0010 | C7: Lubricación programada — EQ-105 | D7: Lubricación programada en EQ-105 | E7: EQ-105 | F7: CC-110 | G7: PU-MEC | H7: ACT-02 | I7: TIPO-P1 | J7: 46219 | K7: 10 | L7: 250 | N7: =IF(tblOrdenes[[#This Row],[orden]]="","",IF(tblOrdenes[[#This Row],[horas_ajustadas]]<>"",tblOrdenes[[#This Row],[horas_ajustadas]],IF(tblOrdenes[[#This Row],[horas_estimadas]]="","",tblOrdenes[[#This Row],[horas_estimadas]]))) | O7: =IF(tblOrdenes[[#This Row],[orden]]="","",_xlfn.XLOOKUP(_xlfn.XLOOKUP(tblOrdenes[[#This Row],[id_operacion]],tblEjecucion[id_operacion],tblEjecucion[estado_sistema],""),tblEstados[estado_sistema],tblEstados[estado_normalizado],"Pendiente")) | P7: =IF(tblOrdenes[[#This Row],[fecha_inicio]]="","",YEAR(tblOrdenes[[#This Row],[fecha_inicio]]+4-WEEKDAY(tblOrdenes[[#This Row],[fecha_inicio]],2))&"-S"&TEXT(_xlfn.ISOWEEKNUM(tblOrdenes[[#This Row],[fecha_inicio]]),"00")) | Q7: =IF(tblOrdenes[[#This Row],[fecha_inicio]]="","",YEAR(tblOrdenes[[#This Row],[fecha_inicio]])) | R7: =IF(tblOrdenes[[#This Row],[fecha_inicio]]="","",MONTH(tblOrdenes[[#This Row],[fecha_inicio]])) | S7: =IF(tblOrdenes[[#This Row],[fecha_inicio]]="","",INDEX(lista_dias,WEEKDAY(tblOrdenes[[#This Row],[fecha_inicio]],2))) | T7: =IF(tblOrdenes[[#This Row],[tipo_ot]]="","",_xlfn.XLOOKUP(tblOrdenes[[#This Row],[tipo_ot]],tblTiposOT[codigo],tblTiposOT[clasificacion],"sin_clasificar")) | U7: =IF(tblOrdenes[[#This Row],[centro_costo]]="","",_xlfn.XLOOKUP(tblOrdenes[[#This Row],[centro_costo]],tblCECO[codigo],tblCECO[linea],"(sin catálogo)")) | V7: =IF(tblOrdenes[[#This Row],[centro_costo]]="","",_xlfn.XLOOKUP(tblOrdenes[[#This Row],[centro_costo]],tblCECO[codigo],tblCECO[area],"(sin catálogo)")) | W7: =IF(tblOrdenes[[#This Row],[centro_costo]]="","",_xlfn.XLOOKUP(tblOrdenes[[#This Row],[centro_costo]],tblCECO[codigo],tblCECO[coordinador],"(sin catálogo)")) | X7: =IF(tblOrdenes[[#This Row],[puesto_trabajo]]="","",_xlfn.XLOOKUP(tblOrdenes[[#This Row],[puesto_trabajo]],tblPuestos[codigo],tblPuestos[especialidad],"(sin catálogo)")) | Y7: =IF(tblOrdenes[[#This Row],[cod_actividad]]="","",_xlfn.XLOOKUP(tblOrdenes[[#This Row],[cod_actividad]],tblActividades[codigo],tblActividades[descripcion],"(sin catálogo)")) | Z7: =IF(tblOrdenes[[#This Row],[fecha_inicio]]="","",TODAY()-tblOrdenes[[#This Row],[fecha_inicio]]) | AA7: =IF(tblOrdenes[[#This Row],[backlog_dias]]="","",IF(tblOrdenes[[#This Row],[backlog_dias]]<0,"FUTURO",IF(tblOrdenes[[#This Row],[backlog_dias]]>p_dias_backlog_max,"BACKLOG","MES CORRIENTE"))) | AB7: =IF(tblOrdenes[[#This Row],[backlog_dias]]="",FALSE,AND(tblOrdenes[[#This Row],[backlog_dias]]>p_dias_backlog_min,tblOrdenes[[#This Row],[backlog_dias]]<=p_dias_backlog_max)) | AC7: Técnico 04 | AD7: =IF(tblOrdenes[[#This Row],[tecnico_asignado]]="","",_xlfn.XLOOKUP(tblOrdenes[[#This Row],[semana]]&"|"&tblOrdenes[[#This Row],[dia_semana]]&"|"&tblOrdenes[[#This Row],[tecnico_asignado]],tblAsignaciones[clave],tblAsignaciones[turno],"")) | AE7: =IF(tblOrdenes[[#This Row],[tecnico_asignado]]="","",SUMIFS(tblOrdenes[horas_efectivas],tblOrdenes[tecnico_asignado],tblOrdenes[[#This Row],[tecnico_asignado]],tblOrdenes[semana],tblOrdenes[[#This Row],[semana]],tblOrdenes[dia_semana],tblOrdenes[[#This Row],[dia_semana]])) | AF7: =IF(tblOrdenes[[#This Row],[HHA]]="","",p_factor_productividad*_xlfn.XLOOKUP(tblOrdenes[[#This Row],[semana]]&"|"&tblOrdenes[[#This Row],[dia_semana]]&"|"&tblOrdenes[[#This Row],[tecnico_asignado]],tblAsignaciones[clave],tblAsignaciones[horas_disponibles],0)-tblOrdenes[[#This Row],[HHA]]) | AG7: =IF(tblOrdenes[[#This Row],[orden]]="","",_xlfn.XLOOKUP(tblOrdenes[[#This Row],[id_operacion]],tblEjecucion[id_operacion],tblEjecucion[precio],0)) | AH7: =IF(tblOrdenes[[#This Row],[orden]]="","",MAX(0,_xlfn.XLOOKUP(tblOrdenes[[#This Row],[id_operacion]],tblEjecucion[id_operacion],tblEjecucion[costo_plan_total],0)-tblOrdenes[[#This Row],[costo_servicio]])) | AI7: =IF(tblOrdenes[[#This Row],[orden]]="","",tblOrdenes[[#This Row],[costo_servicio]]+tblOrdenes[[#This Row],[costo_materiales]]) | AL7: ACT-02.pdf | AM7: =IF(tblOrdenes[[#This Row],[link_checklist]]="","",HYPERLINK(p_ruta_base_checklists&tblOrdenes[[#This Row],[link_checklist]],"abrir")) | AO7: =IF(tblOrdenes[[#This Row],[orden]]="","",tblOrdenes[[#This Row],[orden]]&IF(tblOrdenes[[#This Row],[operacion]]="","0010",tblOrdenes[[#This Row],[operacion]]))
A8: OT-000005 | B8: 0010 | C8: Análisis predictivo — EQ-107 | D8: Análisis predictivo en EQ-107 | E8: EQ-107 | F8: CC-210 | G8: PU-MEC | H8: ACT-04 | I8: TIPO-P2 | J8: 46220 | K8: 8 | L8: 200 | N8: =IF(tblOrdenes[[#This Row],[orden]]="","",IF(tblOrdenes[[#This Row],[horas_ajustadas]]<>"",tblOrdenes[[#This Row],[horas_ajustadas]],IF(tblOrdenes[[#This Row],[horas_estimadas]]="","",tblOrdenes[[#This Row],[horas_estimadas]]))) | O8: =IF(tblOrdenes[[#This Row],[orden]]="","",_xlfn.XLOOKUP(_xlfn.XLOOKUP(tblOrdenes[[#This Row],[id_operacion]],tblEjecucion[id_operacion],tblEjecucion[estado_sistema],""),tblEstados[estado_sistema],tblEstados[estado_normalizado],"Pendiente")) | P8: =IF(tblOrdenes[[#This Row],[fecha_inicio]]="","",YEAR(tblOrdenes[[#This Row],[fecha_inicio]]+4-WEEKDAY(tblOrdenes[[#This Row],[fecha_inicio]],2))&"-S"&TEXT(_xlfn.ISOWEEKNUM(tblOrdenes[[#This Row],[fecha_inicio]]),"00")) | Q8: =IF(tblOrdenes[[#This Row],[fecha_inicio]]="","",YEAR(tblOrdenes[[#This Row],[fecha_inicio]])) | R8: =IF(tblOrdenes[[#This Row],[fecha_inicio]]="","",MONTH(tblOrdenes[[#This Row],[fecha_inicio]])) | S8: =IF(tblOrdenes[[#This Row],[fecha_inicio]]="","",INDEX(lista_dias,WEEKDAY(tblOrdenes[[#This Row],[fecha_inicio]],2))) | T8: =IF(tblOrdenes[[#This Row],[tipo_ot]]="","",_xlfn.XLOOKUP(tblOrdenes[[#This Row],[tipo_ot]],tblTiposOT[codigo],tblTiposOT[clasificacion],"sin_clasificar")) | U8: =IF(tblOrdenes[[#This Row],[centro_costo]]="","",_xlfn.XLOOKUP(tblOrdenes[[#This Row],[centro_costo]],tblCECO[codigo],tblCECO[linea],"(sin catálogo)")) | V8: =IF(tblOrdenes[[#This Row],[centro_costo]]="","",_xlfn.XLOOKUP(tblOrdenes[[#This Row],[centro_costo]],tblCECO[codigo],tblCECO[area],"(sin catálogo)")) | W8: =IF(tblOrdenes[[#This Row],[centro_costo]]="","",_xlfn.XLOOKUP(tblOrdenes[[#This Row],[centro_costo]],tblCECO[codigo],tblCECO[coordinador],"(sin catálogo)")) | X8: =IF(tblOrdenes[[#This Row],[puesto_trabajo]]="","",_xlfn.XLOOKUP(tblOrdenes[[#This Row],[puesto_trabajo]],tblPuestos[codigo],tblPuestos[especialidad],"(sin catálogo)")) | Y8: =IF(tblOrdenes[[#This Row],[cod_actividad]]="","",_xlfn.XLOOKUP(tblOrdenes[[#This Row],[cod_actividad]],tblActividades[codigo],tblActividades[descripcion],"(sin catálogo)")) | Z8: =IF(tblOrdenes[[#This Row],[fecha_inicio]]="","",TODAY()-tblOrdenes[[#This Row],[fecha_inicio]]) | AA8: =IF(tblOrdenes[[#This Row],[backlog_dias]]="","",IF(tblOrdenes[[#This Row],[backlog_dias]]<0,"FUTURO",IF(tblOrdenes[[#This Row],[backlog_dias]]>p_dias_backlog_max,"BACKLOG","MES CORRIENTE"))) | AB8: =IF(tblOrdenes[[#This Row],[backlog_dias]]="",FALSE,AND(tblOrdenes[[#This Row],[backlog_dias]]>p_dias_backlog_min,tblOrdenes[[#This Row],[backlog_dias]]<=p_dias_backlog_max)) | AC8: Técnico 01 | AD8: =IF(tblOrdenes[[#This Row],[tecnico_asignado]]="","",_xlfn.XLOOKUP(tblOrdenes[[#This Row],[semana]]&"|"&tblOrdenes[[#This Row],[dia_semana]]&"|"&tblOrdenes[[#This Row],[tecnico_asignado]],tblAsignaciones[clave],tblAsignaciones[turno],"")) | AE8: =IF(tblOrdenes[[#This Row],[tecnico_asignado]]="","",SUMIFS(tblOrdenes[horas_efectivas],tblOrdenes[tecnico_asignado],tblOrdenes[[#This Row],[tecnico_asignado]],tblOrdenes[semana],tblOrdenes[[#This Row],[semana]],tblOrdenes[dia_semana],tblOrdenes[[#This Row],[dia_semana]])) | AF8: =IF(tblOrdenes[[#This Row],[HHA]]="","",p_factor_productividad*_xlfn.XLOOKUP(tblOrdenes[[#This Row],[semana]]&"|"&tblOrdenes[[#This Row],[dia_semana]]&"|"&tblOrdenes[[#This Row],[tecnico_asignado]],tblAsignaciones[clave],tblAsignaciones[horas_disponibles],0)-tblOrdenes[[#This Row],[HHA]]) | AG8: =IF(tblOrdenes[[#This Row],[orden]]="","",_xlfn.XLOOKUP(tblOrdenes[[#This Row],[id_operacion]],tblEjecucion[id_operacion],tblEjecucion[precio],0)) | AH8: =IF(tblOrdenes[[#This Row],[orden]]="","",MAX(0,_xlfn.XLOOKUP(tblOrdenes[[#This Row],[id_operacion]],tblEjecucion[id_operacion],tblEjecucion[costo_plan_total],0)-tblOrdenes[[#This Row],[costo_servicio]])) | AI8: =IF(tblOrdenes[[#This Row],[orden]]="","",tblOrdenes[[#This Row],[costo_servicio]]+tblOrdenes[[#This Row],[costo_materiales]]) | AL8: ACT-04.pdf | AM8: =IF(tblOrdenes[[#This Row],[link_checklist]]="","",HYPERLINK(p_ruta_base_checklists&tblOrdenes[[#This Row],[link_checklist]],"abrir")) | AO8: =IF(tblOrdenes[[#This Row],[orden]]="","",tblOrdenes[[#This Row],[orden]]&IF(tblOrdenes[[#This Row],[operacion]]="","0010",tblOrdenes[[#This Row],[operacion]]))
A9: OT-000006 | B9: 0010 | C9: Inspección de rutina — EQ-110 | D9: Inspección de rutina en EQ-110 | E9: EQ-110 | F9: CC-310 | G9: PU-MEC | H9: ACT-01 | I9: TIPO-P1 | J9: 46216 | K9: 6 | L9: 150 | N9: =IF(tblOrdenes[[#This Row],[orden]]="","",IF(tblOrdenes[[#This Row],[horas_ajustadas]]<>"",tblOrdenes[[#This Row],[horas_ajustadas]],IF(tblOrdenes[[#This Row],[horas_estimadas]]="","",tblOrdenes[[#This Row],[horas_estimadas]]))) | O9: =IF(tblOrdenes[[#This Row],[orden]]="","",_xlfn.XLOOKUP(_xlfn.XLOOKUP(tblOrdenes[[#This Row],[id_operacion]],tblEjecucion[id_operacion],tblEjecucion[estado_sistema],""),tblEstados[estado_sistema],tblEstados[estado_normalizado],"Pendiente")) | P9: =IF(tblOrdenes[[#This Row],[fecha_inicio]]="","",YEAR(tblOrdenes[[#This Row],[fecha_inicio]]+4-WEEKDAY(tblOrdenes[[#This Row],[fecha_inicio]],2))&"-S"&TEXT(_xlfn.ISOWEEKNUM(tblOrdenes[[#This Row],[fecha_inicio]]),"00")) | Q9: =IF(tblOrdenes[[#This Row],[fecha_inicio]]="","",YEAR(tblOrdenes[[#This Row],[fecha_inicio]])) | R9: =IF(tblOrdenes[[#This Row],[fecha_inicio]]="","",MONTH(tblOrdenes[[#This Row],[fecha_inicio]])) | S9: =IF(tblOrdenes[[#This Row],[fecha_inicio]]="","",INDEX(lista_dias,WEEKDAY(tblOrdenes[[#This Row],[fecha_inicio]],2))) | T9: =IF(tblOrdenes[[#This Row],[tipo_ot]]="","",_xlfn.XLOOKUP(tblOrdenes[[#This Row],[tipo_ot]],tblTiposOT[codigo],tblTiposOT[clasificacion],"sin_clasificar")) | U9: =IF(tblOrdenes[[#This Row],[centro_costo]]="","",_xlfn.XLOOKUP(tblOrdenes[[#This Row],[centro_costo]],tblCECO[codigo],tblCECO[linea],"(sin catálogo)")) | V9: =IF(tblOrdenes[[#This Row],[centro_costo]]="","",_xlfn.XLOOKUP(tblOrdenes[[#This Row],[centro_costo]],tblCECO[codigo],tblCECO[area],"(sin catálogo)")) | W9: =IF(tblOrdenes[[#This Row],[centro_costo]]="","",_xlfn.XLOOKUP(tblOrdenes[[#This Row],[centro_costo]],tblCECO[codigo],tblCECO[coordinador],"(sin catálogo)")) | X9: =IF(tblOrdenes[[#This Row],[puesto_trabajo]]="","",_xlfn.XLOOKUP(tblOrdenes[[#This Row],[puesto_trabajo]],tblPuestos[codigo],tblPuestos[especialidad],"(sin catálogo)")) | Y9: =IF(tblOrdenes[[#This Row],[cod_actividad]]="","",_xlfn.XLOOKUP(tblOrdenes[[#This Row],[cod_actividad]],tblActividades[codigo],tblActividades[descripcion],"(sin catálogo)")) | Z9: =IF(tblOrdenes[[#This Row],[fecha_inicio]]="","",TODAY()-tblOrdenes[[#This Row],[fecha_inicio]]) | AA9: =IF(tblOrdenes[[#This Row],[backlog_dias]]="","",IF(tblOrdenes[[#This Row],[backlog_dias]]<0,"FUTURO",IF(tblOrdenes[[#This Row],[backlog_dias]]>p_dias_backlog_max,"BACKLOG","MES CORRIENTE"))) | AB9: =IF(tblOrdenes[[#This Row],[backlog_dias]]="",FALSE,AND(tblOrdenes[[#This Row],[backlog_dias]]>p_dias_backlog_min,tblOrdenes[[#This Row],[backlog_dias]]<=p_dias_backlog_max)) | AC9: Técnico 02 | AD9: =IF(tblOrdenes[[#This Row],[tecnico_asignado]]="","",_xlfn.XLOOKUP(tblOrdenes[[#This Row],[semana]]&"|"&tblOrdenes[[#This Row],[dia_semana]]&"|"&tblOrdenes[[#This Row],[tecnico_asignado]],tblAsignaciones[clave],tblAsignaciones[turno],"")) | AE9: =IF(tblOrdenes[[#This Row],[tecnico_asignado]]="","",SUMIFS(tblOrdenes[horas_efectivas],tblOrdenes[tecnico_asignado],tblOrdenes[[#This Row],[tecnico_asignado]],tblOrdenes[semana],tblOrdenes[[#This Row],[semana]],tblOrdenes[dia_semana],tblOrdenes[[#This Row],[dia_semana]])) | AF9: =IF(tblOrdenes[[#This Row],[HHA]]="","",p_factor_productividad*_xlfn.XLOOKUP(tblOrdenes[[#This Row],[semana]]&"|"&tblOrdenes[[#This Row],[dia_semana]]&"|"&tblOrdenes[[#This Row],[tecnico_asignado]],tblAsignaciones[clave],tblAsignaciones[horas_disponibles],0)-tblOrdenes[[#This Row],[HHA]]) | AG9: =IF(tblOrdenes[[#This Row],[orden]]="","",_xlfn.XLOOKUP(tblOrdenes[[#This Row],[id_operacion]],tblEjecucion[id_operacion],tblEjecucion[precio],0)) | AH9: =IF(tblOrdenes[[#This Row],[orden]]="","",MAX(0,_xlfn.XLOOKUP(tblOrdenes[[#This Row],[id_operacion]],tblEjecucion[id_operacion],tblEjecucion[costo_plan_total],0)-tblOrdenes[[#This Row],[costo_servicio]])) | AI9: =IF(tblOrdenes[[#This Row],[orden]]="","",tblOrdenes[[#This Row],[costo_servicio]]+tblOrdenes[[#This Row],[costo_materiales]]) | AL9: ACT-01.pdf | AM9: =IF(tblOrdenes[[#This Row],[link_checklist]]="","",HYPERLINK(p_ruta_base_checklists&tblOrdenes[[#This Row],[link_checklist]],"abrir")) | AO9: =IF(tblOrdenes[[#This Row],[orden]]="","",tblOrdenes[[#This Row],[orden]]&IF(tblOrdenes[[#This Row],[operacion]]="","0010",tblOrdenes[[#This Row],[operacion]]))
A10: OT-000007 | B10: 0010 | C10: Lubricación programada — EQ-103 | D10: Lubricación programada en EQ-103 | E10: EQ-103 | F10: CC-110 | G10: PU-MEC | H10: ACT-02 | I10: TIPO-P2 | J10: 46217 | K10: 10 | L10: 250 | N10: =IF(tblOrdenes[[#This Row],[orden]]="","",IF(tblOrdenes[[#This Row],[horas_ajustadas]]<>"",tblOrdenes[[#This Row],[horas_ajustadas]],IF(tblOrdenes[[#This Row],[horas_estimadas]]="","",tblOrdenes[[#This Row],[horas_estimadas]]))) | O10: =IF(tblOrdenes[[#This Row],[orden]]="","",_xlfn.XLOOKUP(_xlfn.XLOOKUP(tblOrdenes[[#This Row],[id_operacion]],tblEjecucion[id_operacion],tblEjecucion[estado_sistema],""),tblEstados[estado_sistema],tblEstados[estado_normalizado],"Pendiente")) | P10: =IF(tblOrdenes[[#This Row],[fecha_inicio]]="","",YEAR(tblOrdenes[[#This Row],[fecha_inicio]]+4-WEEKDAY(tblOrdenes[[#This Row],[fecha_inicio]],2))&"-S"&TEXT(_xlfn.ISOWEEKNUM(tblOrdenes[[#This Row],[fecha_inicio]]),"00")) | Q10: =IF(tblOrdenes[[#This Row],[fecha_inicio]]="","",YEAR(tblOrdenes[[#This Row],[fecha_inicio]])) | R10: =IF(tblOrdenes[[#This Row],[fecha_inicio]]="","",MONTH(tblOrdenes[[#This Row],[fecha_inicio]])) | S10: =IF(tblOrdenes[[#This Row],[fecha_inicio]]="","",INDEX(lista_dias,WEEKDAY(tblOrdenes[[#This Row],[fecha_inicio]],2))) | T10: =IF(tblOrdenes[[#This Row],[tipo_ot]]="","",_xlfn.XLOOKUP(tblOrdenes[[#This Row],[tipo_ot]],tblTiposOT[codigo],tblTiposOT[clasificacion],"sin_clasificar")) | U10: =IF(tblOrdenes[[#This Row],[centro_costo]]="","",_xlfn.XLOOKUP(tblOrdenes[[#This Row],[centro_costo]],tblCECO[codigo],tblCECO[linea],"(sin catálogo)")) | V10: =IF(tblOrdenes[[#This Row],[centro_costo]]="","",_xlfn.XLOOKUP(tblOrdenes[[#This Row],[centro_costo]],tblCECO[codigo],tblCECO[area],"(sin catálogo)")) | W10: =IF(tblOrdenes[[#This Row],[centro_costo]]="","",_xlfn.XLOOKUP(tblOrdenes[[#This Row],[centro_costo]],tblCECO[codigo],tblCECO[coordinador],"(sin catálogo)")) | X10: =IF(tblOrdenes[[#This Row],[puesto_trabajo]]="","",_xlfn.XLOOKUP(tblOrdenes[[#This Row],[puesto_trabajo]],tblPuestos[codigo],tblPuestos[especialidad],"(sin catálogo)")) | Y10: =IF(tblOrdenes[[#This Row],[cod_actividad]]="","",_xlfn.XLOOKUP(tblOrdenes[[#This Row],[cod_actividad]],tblActividades[codigo],tblActividades[descripcion],"(sin catálogo)")) | Z10: =IF(tblOrdenes[[#This Row],[fecha_inicio]]="","",TODAY()-tblOrdenes[[#This Row],[fecha_inicio]]) | AA10: =IF(tblOrdenes[[#This Row],[backlog_dias]]="","",IF(tblOrdenes[[#This Row],[backlog_dias]]<0,"FUTURO",IF(tblOrdenes[[#This Row],[backlog_dias]]>p_dias_backlog_max,"BACKLOG","MES CORRIENTE"))) | AB10: =IF(tblOrdenes[[#This Row],[backlog_dias]]="",FALSE,AND(tblOrdenes[[#This Row],[backlog_dias]]>p_dias_backlog_min,tblOrdenes[[#This Row],[backlog_dias]]<=p_dias_backlog_max)) | AC10: Técnico 03 | AD10: =IF(tblOrdenes[[#This Row],[tecnico_asignado]]="","",_xlfn.XLOOKUP(tblOrdenes[[#This Row],[semana]]&"|"&tblOrdenes[[#This Row],[dia_semana]]&"|"&tblOrdenes[[#This Row],[tecnico_asignado]],tblAsignaciones[clave],tblAsignaciones[turno],"")) | AE10: =IF(tblOrdenes[[#This Row],[tecnico_asignado]]="","",SUMIFS(tblOrdenes[horas_efectivas],tblOrdenes[tecnico_asignado],tblOrdenes[[#This Row],[tecnico_asignado]],tblOrdenes[semana],tblOrdenes[[#This Row],[semana]],tblOrdenes[dia_semana],tblOrdenes[[#This Row],[dia_semana]])) | AF10: =IF(tblOrdenes[[#This Row],[HHA]]="","",p_factor_productividad*_xlfn.XLOOKUP(tblOrdenes[[#This Row],[semana]]&"|"&tblOrdenes[[#This Row],[dia_semana]]&"|"&tblOrdenes[[#This Row],[tecnico_asignado]],tblAsignaciones[clave],tblAsignaciones[horas_disponibles],0)-tblOrdenes[[#This Row],[HHA]]) | AG10: =IF(tblOrdenes[[#This Row],[orden]]="","",_xlfn.XLOOKUP(tblOrdenes[[#This Row],[id_operacion]],tblEjecucion[id_operacion],tblEjecucion[precio],0)) | AH10: =IF(tblOrdenes[[#This Row],[orden]]="","",MAX(0,_xlfn.XLOOKUP(tblOrdenes[[#This Row],[id_operacion]],tblEjecucion[id_operacion],tblEjecucion[costo_plan_total],0)-tblOrdenes[[#This Row],[costo_servicio]])) | AI10: =IF(tblOrdenes[[#This Row],[orden]]="","",tblOrdenes[[#This Row],[costo_servicio]]+tblOrdenes[[#This Row],[costo_materiales]]) | AL10: ACT-02.pdf | AM10: =IF(tblOrdenes[[#This Row],[link_checklist]]="","",HYPERLINK(p_ruta_base_checklists&tblOrdenes[[#This Row],[link_checklist]],"abrir")) | AO10: =IF(tblOrdenes[[#This Row],[orden]]="","",tblOrdenes[[#This Row],[orden]]&IF(tblOrdenes[[#This Row],[operacion]]="","0010",tblOrdenes[[#This Row],[operacion]]))
A11: OT-000008 | B11: 0010 | C11: Análisis predictivo — EQ-106 | D11: Análisis predictivo en EQ-106 | E11: EQ-106 | F11: CC-210 | G11: PU-MEC | H11: ACT-04 | I11: TIPO-P1 | J11: 46218 | K11: 8 | L11: 200 | N11: =IF(tblOrdenes[[#This Row],[orden]]="","",IF(tblOrdenes[[#This Row],[horas_ajustadas]]<>"",tblOrdenes[[#This Row],[horas_ajustadas]],IF(tblOrdenes[[#This Row],[horas_estimadas]]="","",tblOrdenes[[#This Row],[horas_estimadas]]))) | O11: =IF(tblOrdenes[[#This Row],[orden]]="","",_xlfn.XLOOKUP(_xlfn.XLOOKUP(tblOrdenes[[#This Row],[id_operacion]],tblEjecucion[id_operacion],tblEjecucion[estado_sistema],""),tblEstados[estado_sistema],tblEstados[estado_normalizado],"Pendiente")) | P11: =IF(tblOrdenes[[#This Row],[fecha_inicio]]="","",YEAR(tblOrdenes[[#This Row],[fecha_inicio]]+4-WEEKDAY(tblOrdenes[[#This Row],[fecha_inicio]],2))&"-S"&TEXT(_xlfn.ISOWEEKNUM(tblOrdenes[[#This Row],[fecha_inicio]]),"00")) | Q11: =IF(tblOrdenes[[#This Row],[fecha_inicio]]="","",YEAR(tblOrdenes[[#This Row],[fecha_inicio]])) | R11: =IF(tblOrdenes[[#This Row],[fecha_inicio]]="","",MONTH(tblOrdenes[[#This Row],[fecha_inicio]])) | S11: =IF(tblOrdenes[[#This Row],[fecha_inicio]]="","",INDEX(lista_dias,WEEKDAY(tblOrdenes[[#This Row],[fecha_inicio]],2))) | T11: =IF(tblOrdenes[[#This Row],[tipo_ot]]="","",_xlfn.XLOOKUP(tblOrdenes[[#This Row],[tipo_ot]],tblTiposOT[codigo],tblTiposOT[clasificacion],"sin_clasificar")) | U11: =IF(tblOrdenes[[#This Row],[centro_costo]]="","",_xlfn.XLOOKUP(tblOrdenes[[#This Row],[centro_costo]],tblCECO[codigo],tblCECO[linea],"(sin catálogo)")) | V11: =IF(tblOrdenes[[#This Row],[centro_costo]]="","",_xlfn.XLOOKUP(tblOrdenes[[#This Row],[centro_costo]],tblCECO[codigo],tblCECO[area],"(sin catálogo)")) | W11: =IF(tblOrdenes[[#This Row],[centro_costo]]="","",_xlfn.XLOOKUP(tblOrdenes[[#This Row],[centro_costo]],tblCECO[codigo],tblCECO[coordinador],"(sin catálogo)")) | X11: =IF(tblOrdenes[[#This Row],[puesto_trabajo]]="","",_xlfn.XLOOKUP(tblOrdenes[[#This Row],[puesto_trabajo]],tblPuestos[codigo],tblPuestos[especialidad],"(sin catálogo)")) | Y11: =IF(tblOrdenes[[#This Row],[cod_actividad]]="","",_xlfn.XLOOKUP(tblOrdenes[[#This Row],[cod_actividad]],tblActividades[codigo],tblActividades[descripcion],"(sin catálogo)")) | Z11: =IF(tblOrdenes[[#This Row],[fecha_inicio]]="","",TODAY()-tblOrdenes[[#This Row],[fecha_inicio]]) | AA11: =IF(tblOrdenes[[#This Row],[backlog_dias]]="","",IF(tblOrdenes[[#This Row],[backlog_dias]]<0,"FUTURO",IF(tblOrdenes[[#This Row],[backlog_dias]]>p_dias_backlog_max,"BACKLOG","MES CORRIENTE"))) | AB11: =IF(tblOrdenes[[#This Row],[backlog_dias]]="",FALSE,AND(tblOrdenes[[#This Row],[backlog_dias]]>p_dias_backlog_min,tblOrdenes[[#This Row],[backlog_dias]]<=p_dias_backlog_max)) | AC11: Técnico 04 | AD11: =IF(tblOrdenes[[#This Row],[tecnico_asignado]]="","",_xlfn.XLOOKUP(tblOrdenes[[#This Row],[semana]]&"|"&tblOrdenes[[#This Row],[dia_semana]]&"|"&tblOrdenes[[#This Row],[tecnico_asignado]],tblAsignaciones[clave],tblAsignaciones[turno],"")) | AE11: =IF(tblOrdenes[[#This Row],[tecnico_asignado]]="","",SUMIFS(tblOrdenes[horas_efectivas],tblOrdenes[tecnico_asignado],tblOrdenes[[#This Row],[tecnico_asignado]],tblOrdenes[semana],tblOrdenes[[#This Row],[semana]],tblOrdenes[dia_semana],tblOrdenes[[#This Row],[dia_semana]])) | AF11: =IF(tblOrdenes[[#This Row],[HHA]]="","",p_factor_productividad*_xlfn.XLOOKUP(tblOrdenes[[#This Row],[semana]]&"|"&tblOrdenes[[#This Row],[dia_semana]]&"|"&tblOrdenes[[#This Row],[tecnico_asignado]],tblAsignaciones[clave],tblAsignaciones[horas_disponibles],0)-tblOrdenes[[#This Row],[HHA]]) | AG11: =IF(tblOrdenes[[#This Row],[orden]]="","",_xlfn.XLOOKUP(tblOrdenes[[#This Row],[id_operacion]],tblEjecucion[id_operacion],tblEjecucion[precio],0)) | AH11: =IF(tblOrdenes[[#This Row],[orden]]="","",MAX(0,_xlfn.XLOOKUP(tblOrdenes[[#This Row],[id_operacion]],tblEjecucion[id_operacion],tblEjecucion[costo_plan_total],0)-tblOrdenes[[#This Row],[costo_servicio]])) | AI11: =IF(tblOrdenes[[#This Row],[orden]]="","",tblOrdenes[[#This Row],[costo_servicio]]+tblOrdenes[[#This Row],[costo_materiales]]) | AL11: ACT-04.pdf | AM11: =IF(tblOrdenes[[#This Row],[link_checklist]]="","",HYPERLINK(p_ruta_base_checklists&tblOrdenes[[#This Row],[link_checklist]],"abrir")) | AO11: =IF(tblOrdenes[[#This Row],[orden]]="","",tblOrdenes[[#This Row],[orden]]&IF(tblOrdenes[[#This Row],[operacion]]="","0010",tblOrdenes[[#This Row],[operacion]]))
A12: OT-000009 | B12: 0010 | C12: Inspección de rutina — EQ-110 | D12: Inspección de rutina en EQ-110 | E12: EQ-110 | F12: CC-310 | G12: PU-MEC | H12: ACT-01 | I12: TIPO-P2 | J12: 46219 | K12: 6 | L12: 150 | N12: =IF(tblOrdenes[[#This Row],[orden]]="","",IF(tblOrdenes[[#This Row],[horas_ajustadas]]<>"",tblOrdenes[[#This Row],[horas_ajustadas]],IF(tblOrdenes[[#This Row],[horas_estimadas]]="","",tblOrdenes[[#This Row],[horas_estimadas]]))) | O12: =IF(tblOrdenes[[#This Row],[orden]]="","",_xlfn.XLOOKUP(_xlfn.XLOOKUP(tblOrdenes[[#This Row],[id_operacion]],tblEjecucion[id_operacion],tblEjecucion[estado_sistema],""),tblEstados[estado_sistema],tblEstados[estado_normalizado],"Pendiente")) | P12: =IF(tblOrdenes[[#This Row],[fecha_inicio]]="","",YEAR(tblOrdenes[[#This Row],[fecha_inicio]]+4-WEEKDAY(tblOrdenes[[#This Row],[fecha_inicio]],2))&"-S"&TEXT(_xlfn.ISOWEEKNUM(tblOrdenes[[#This Row],[fecha_inicio]]),"00")) | Q12: =IF(tblOrdenes[[#This Row],[fecha_inicio]]="","",YEAR(tblOrdenes[[#This Row],[fecha_inicio]])) | R12: =IF(tblOrdenes[[#This Row],[fecha_inicio]]="","",MONTH(tblOrdenes[[#This Row],[fecha_inicio]])) | S12: =IF(tblOrdenes[[#This Row],[fecha_inicio]]="","",INDEX(lista_dias,WEEKDAY(tblOrdenes[[#This Row],[fecha_inicio]],2))) | T12: =IF(tblOrdenes[[#This Row],[tipo_ot]]="","",_xlfn.XLOOKUP(tblOrdenes[[#This Row],[tipo_ot]],tblTiposOT[codigo],tblTiposOT[clasificacion],"sin_clasificar")) | U12: =IF(tblOrdenes[[#This Row],[centro_costo]]="","",_xlfn.XLOOKUP(tblOrdenes[[#This Row],[centro_costo]],tblCECO[codigo],tblCECO[linea],"(sin catálogo)")) | V12: =IF(tblOrdenes[[#This Row],[centro_costo]]="","",_xlfn.XLOOKUP(tblOrdenes[[#This Row],[centro_costo]],tblCECO[codigo],tblCECO[area],"(sin catálogo)")) | W12: =IF(tblOrdenes[[#This Row],[centro_costo]]="","",_xlfn.XLOOKUP(tblOrdenes[[#This Row],[centro_costo]],tblCECO[codigo],tblCECO[coordinador],"(sin catálogo)")) | X12: =IF(tblOrdenes[[#This Row],[puesto_trabajo]]="","",_xlfn.XLOOKUP(tblOrdenes[[#This Row],[puesto_trabajo]],tblPuestos[codigo],tblPuestos[especialidad],"(sin catálogo)")) | Y12: =IF(tblOrdenes[[#This Row],[cod_actividad]]="","",_xlfn.XLOOKUP(tblOrdenes[[#This Row],[cod_actividad]],tblActividades[codigo],tblActividades[descripcion],"(sin catálogo)")) | Z12: =IF(tblOrdenes[[#This Row],[fecha_inicio]]="","",TODAY()-tblOrdenes[[#This Row],[fecha_inicio]]) | AA12: =IF(tblOrdenes[[#This Row],[backlog_dias]]="","",IF(tblOrdenes[[#This Row],[backlog_dias]]<0,"FUTURO",IF(tblOrdenes[[#This Row],[backlog_dias]]>p_dias_backlog_max,"BACKLOG","MES CORRIENTE"))) | AB12: =IF(tblOrdenes[[#This Row],[backlog_dias]]="",FALSE,AND(tblOrdenes[[#This Row],[backlog_dias]]>p_dias_backlog_min,tblOrdenes[[#This Row],[backlog_dias]]<=p_dias_backlog_max)) | AC12: Técnico 01 | AD12: =IF(tblOrdenes[[#This Row],[tecnico_asignado]]="","",_xlfn.XLOOKUP(tblOrdenes[[#This Row],[semana]]&"|"&tblOrdenes[[#This Row],[dia_semana]]&"|"&tblOrdenes[[#This Row],[tecnico_asignado]],tblAsignaciones[clave],tblAsignaciones[turno],"")) | AE12: =IF(tblOrdenes[[#This Row],[tecnico_asignado]]="","",SUMIFS(tblOrdenes[horas_efectivas],tblOrdenes[tecnico_asignado],tblOrdenes[[#This Row],[tecnico_asignado]],tblOrdenes[semana],tblOrdenes[[#This Row],[semana]],tblOrdenes[dia_semana],tblOrdenes[[#This Row],[dia_semana]])) | AF12: =IF(tblOrdenes[[#This Row],[HHA]]="","",p_factor_productividad*_xlfn.XLOOKUP(tblOrdenes[[#This Row],[semana]]&"|"&tblOrdenes[[#This Row],[dia_semana]]&"|"&tblOrdenes[[#This Row],[tecnico_asignado]],tblAsignaciones[clave],tblAsignaciones[horas_disponibles],0)-tblOrdenes[[#This Row],[HHA]]) | AG12: =IF(tblOrdenes[[#This Row],[orden]]="","",_xlfn.XLOOKUP(tblOrdenes[[#This Row],[id_operacion]],tblEjecucion[id_operacion],tblEjecucion[precio],0)) | AH12: =IF(tblOrdenes[[#This Row],[orden]]="","",MAX(0,_xlfn.XLOOKUP(tblOrdenes[[#This Row],[id_operacion]],tblEjecucion[id_operacion],tblEjecucion[costo_plan_total],0)-tblOrdenes[[#This Row],[costo_servicio]])) | AI12: =IF(tblOrdenes[[#This Row],[orden]]="","",tblOrdenes[[#This Row],[costo_servicio]]+tblOrdenes[[#This Row],[costo_materiales]]) | AL12: ACT-01.pdf | AM12: =IF(tblOrdenes[[#This Row],[link_checklist]]="","",HYPERLINK(p_ruta_base_checklists&tblOrdenes[[#This Row],[link_checklist]],"abrir")) | AO12: =IF(tblOrdenes[[#This Row],[orden]]="","",tblOrdenes[[#This Row],[orden]]&IF(tblOrdenes[[#This Row],[operacion]]="","0010",tblOrdenes[[#This Row],[operacion]]))
A13: OT-000010 | B13: 0010 | C13: Lubricación programada — EQ-101 | D13: Lubricación programada en EQ-101 | E13: EQ-101 | F13: CC-110 | G13: PU-MEC | H13: ACT-02 | I13: TIPO-P1 | J13: 46220 | K13: 8 | L13: 200 | N13: =IF(tblOrdenes[[#This Row],[orden]]="","",IF(tblOrdenes[[#This Row],[horas_ajustadas]]<>"",tblOrdenes[[#This Row],[horas_ajustadas]],IF(tblOrdenes[[#This Row],[horas_estimadas]]="","",tblOrdenes[[#This Row],[horas_estimadas]]))) | O13: =IF(tblOrdenes[[#This Row],[orden]]="","",_xlfn.XLOOKUP(_xlfn.XLOOKUP(tblOrdenes[[#This Row],[id_operacion]],tblEjecucion[id_operacion],tblEjecucion[estado_sistema],""),tblEstados[estado_sistema],tblEstados[estado_normalizado],"Pendiente")) | P13: =IF(tblOrdenes[[#This Row],[fecha_inicio]]="","",YEAR(tblOrdenes[[#This Row],[fecha_inicio]]+4-WEEKDAY(tblOrdenes[[#This Row],[fecha_inicio]],2))&"-S"&TEXT(_xlfn.ISOWEEKNUM(tblOrdenes[[#This Row],[fecha_inicio]]),"00")) | Q13: =IF(tblOrdenes[[#This Row],[fecha_inicio]]="","",YEAR(tblOrdenes[[#This Row],[fecha_inicio]])) | R13: =IF(tblOrdenes[[#This Row],[fecha_inicio]]="","",MONTH(tblOrdenes[[#This Row],[fecha_inicio]])) | S13: =IF(tblOrdenes[[#This Row],[fecha_inicio]]="","",INDEX(lista_dias,WEEKDAY(tblOrdenes[[#This Row],[fecha_inicio]],2))) | T13: =IF(tblOrdenes[[#This Row],[tipo_ot]]="","",_xlfn.XLOOKUP(tblOrdenes[[#This Row],[tipo_ot]],tblTiposOT[codigo],tblTiposOT[clasificacion],"sin_clasificar")) | U13: =IF(tblOrdenes[[#This Row],[centro_costo]]="","",_xlfn.XLOOKUP(tblOrdenes[[#This Row],[centro_costo]],tblCECO[codigo],tblCECO[linea],"(sin catálogo)")) | V13: =IF(tblOrdenes[[#This Row],[centro_costo]]="","",_xlfn.XLOOKUP(tblOrdenes[[#This Row],[centro_costo]],tblCECO[codigo],tblCECO[area],"(sin catálogo)")) | W13: =IF(tblOrdenes[[#This Row],[centro_costo]]="","",_xlfn.XLOOKUP(tblOrdenes[[#This Row],[centro_costo]],tblCECO[codigo],tblCECO[coordinador],"(sin catálogo)")) | X13: =IF(tblOrdenes[[#This Row],[puesto_trabajo]]="","",_xlfn.XLOOKUP(tblOrdenes[[#This Row],[puesto_trabajo]],tblPuestos[codigo],tblPuestos[especialidad],"(sin catálogo)")) | Y13: =IF(tblOrdenes[[#This Row],[cod_actividad]]="","",_xlfn.XLOOKUP(tblOrdenes[[#This Row],[cod_actividad]],tblActividades[codigo],tblActividades[descripcion],"(sin catálogo)")) | Z13: =IF(tblOrdenes[[#This Row],[fecha_inicio]]="","",TODAY()-tblOrdenes[[#This Row],[fecha_inicio]]) | AA13: =IF(tblOrdenes[[#This Row],[backlog_dias]]="","",IF(tblOrdenes[[#This Row],[backlog_dias]]<0,"FUTURO",IF(tblOrdenes[[#This Row],[backlog_dias]]>p_dias_backlog_max,"BACKLOG","MES CORRIENTE"))) | AB13: =IF(tblOrdenes[[#This Row],[backlog_dias]]="",FALSE,AND(tblOrdenes[[#This Row],[backlog_dias]]>p_dias_backlog_min,tblOrdenes[[#This Row],[backlog_dias]]<=p_dias_backlog_max)) | AC13: Técnico 02 | AD13: =IF(tblOrdenes[[#This Row],[tecnico_asignado]]="","",_xlfn.XLOOKUP(tblOrdenes[[#This Row],[semana]]&"|"&tblOrdenes[[#This Row],[dia_semana]]&"|"&tblOrdenes[[#This Row],[tecnico_asignado]],tblAsignaciones[clave],tblAsignaciones[turno],"")) | AE13: =IF(tblOrdenes[[#This Row],[tecnico_asignado]]="","",SUMIFS(tblOrdenes[horas_efectivas],tblOrdenes[tecnico_asignado],tblOrdenes[[#This Row],[tecnico_asignado]],tblOrdenes[semana],tblOrdenes[[#This Row],[semana]],tblOrdenes[dia_semana],tblOrdenes[[#This Row],[dia_semana]])) | AF13: =IF(tblOrdenes[[#This Row],[HHA]]="","",p_factor_productividad*_xlfn.XLOOKUP(tblOrdenes[[#This Row],[semana]]&"|"&tblOrdenes[[#This Row],[dia_semana]]&"|"&tblOrdenes[[#This Row],[tecnico_asignado]],tblAsignaciones[clave],tblAsignaciones[horas_disponibles],0)-tblOrdenes[[#This Row],[HHA]]) | AG13: =IF(tblOrdenes[[#This Row],[orden]]="","",_xlfn.XLOOKUP(tblOrdenes[[#This Row],[id_operacion]],tblEjecucion[id_operacion],tblEjecucion[precio],0)) | AH13: =IF(tblOrdenes[[#This Row],[orden]]="","",MAX(0,_xlfn.XLOOKUP(tblOrdenes[[#This Row],[id_operacion]],tblEjecucion[id_operacion],tblEjecucion[costo_plan_total],0)-tblOrdenes[[#This Row],[costo_servicio]])) | AI13: =IF(tblOrdenes[[#This Row],[orden]]="","",tblOrdenes[[#This Row],[costo_servicio]]+tblOrdenes[[#This Row],[costo_materiales]]) | AL13: ACT-02.pdf | AM13: =IF(tblOrdenes[[#This Row],[link_checklist]]="","",HYPERLINK(p_ruta_base_checklists&tblOrdenes[[#This Row],[link_checklist]],"abrir")) | AO13: =IF(tblOrdenes[[#This Row],[orden]]="","",tblOrdenes[[#This Row],[orden]]&IF(tblOrdenes[[#This Row],[operacion]]="","0010",tblOrdenes[[#This Row],[operacion]]))
A14: OT-000011 | B14: 0010 | C14: Reparación de falla — EQ-109 | D14: Reparación de falla en EQ-109 | E14: EQ-109 | F14: CC-210 | G14: PU-MEC | H14: ACT-03 | I14: TIPO-C2 | J14: 46216 | K14: 10 | L14: 400 | N14: =IF(tblOrdenes[[#This Row],[orden]]="","",IF(tblOrdenes[[#This Row],[horas_ajustadas]]<>"",tblOrdenes[[#This Row],[horas_ajustadas]],IF(tblOrdenes[[#This Row],[horas_estimadas]]="","",tblOrdenes[[#This Row],[horas_estimadas]]))) | O14: =IF(tblOrdenes[[#This Row],[orden]]="","",_xlfn.XLOOKUP(_xlfn.XLOOKUP(tblOrdenes[[#This Row],[id_operacion]],tblEjecucion[id_operacion],tblEjecucion[estado_sistema],""),tblEstados[estado_sistema],tblEstados[estado_normalizado],"Pendiente")) | P14: =IF(tblOrdenes[[#This Row],[fecha_inicio]]="","",YEAR(tblOrdenes[[#This Row],[fecha_inicio]]+4-WEEKDAY(tblOrdenes[[#This Row],[fecha_inicio]],2))&"-S"&TEXT(_xlfn.ISOWEEKNUM(tblOrdenes[[#This Row],[fecha_inicio]]),"00")) | Q14: =IF(tblOrdenes[[#This Row],[fecha_inicio]]="","",YEAR(tblOrdenes[[#This Row],[fecha_inicio]])) | R14: =IF(tblOrdenes[[#This Row],[fecha_inicio]]="","",MONTH(tblOrdenes[[#This Row],[fecha_inicio]])) | S14: =IF(tblOrdenes[[#This Row],[fecha_inicio]]="","",INDEX(lista_dias,WEEKDAY(tblOrdenes[[#This Row],[fecha_inicio]],2))) | T14: =IF(tblOrdenes[[#This Row],[tipo_ot]]="","",_xlfn.XLOOKUP(tblOrdenes[[#This Row],[tipo_ot]],tblTiposOT[codigo],tblTiposOT[clasificacion],"sin_clasificar")) | U14: =IF(tblOrdenes[[#This Row],[centro_costo]]="","",_xlfn.XLOOKUP(tblOrdenes[[#This Row],[centro_costo]],tblCECO[codigo],tblCECO[linea],"(sin catálogo)")) | V14: =IF(tblOrdenes[[#This Row],[centro_costo]]="","",_xlfn.XLOOKUP(tblOrdenes[[#This Row],[centro_costo]],tblCECO[codigo],tblCECO[area],"(sin catálogo)")) | W14: =IF(tblOrdenes[[#This Row],[centro_costo]]="","",_xlfn.XLOOKUP(tblOrdenes[[#This Row],[centro_costo]],tblCECO[codigo],tblCECO[coordinador],"(sin catálogo)")) | X14: =IF(tblOrdenes[[#This Row],[puesto_trabajo]]="","",_xlfn.XLOOKUP(tblOrdenes[[#This Row],[puesto_trabajo]],tblPuestos[codigo],tblPuestos[especialidad],"(sin catálogo)")) | Y14: =IF(tblOrdenes[[#This Row],[cod_actividad]]="","",_xlfn.XLOOKUP(tblOrdenes[[#This Row],[cod_actividad]],tblActividades[codigo],tblActividades[descripcion],"(sin catálogo)")) | Z14: =IF(tblOrdenes[[#This Row],[fecha_inicio]]="","",TODAY()-tblOrdenes[[#This Row],[fecha_inicio]]) | AA14: =IF(tblOrdenes[[#This Row],[backlog_dias]]="","",IF(tblOrdenes[[#This Row],[backlog_dias]]<0,"FUTURO",IF(tblOrdenes[[#This Row],[backlog_dias]]>p_dias_backlog_max,"BACKLOG","MES CORRIENTE"))) | AB14: =IF(tblOrdenes[[#This Row],[backlog_dias]]="",FALSE,AND(tblOrdenes[[#This Row],[backlog_dias]]>p_dias_backlog_min,tblOrdenes[[#This Row],[backlog_dias]]<=p_dias_backlog_max)) | AC14: Técnico 03 | AD14: =IF(tblOrdenes[[#This Row],[tecnico_asignado]]="","",_xlfn.XLOOKUP(tblOrdenes[[#This Row],[semana]]&"|"&tblOrdenes[[#This Row],[dia_semana]]&"|"&tblOrdenes[[#This Row],[tecnico_asignado]],tblAsignaciones[clave],tblAsignaciones[turno],"")) | AE14: =IF(tblOrdenes[[#This Row],[tecnico_asignado]]="","",SUMIFS(tblOrdenes[horas_efectivas],tblOrdenes[tecnico_asignado],tblOrdenes[[#This Row],[tecnico_asignado]],tblOrdenes[semana],tblOrdenes[[#This Row],[semana]],tblOrdenes[dia_semana],tblOrdenes[[#This Row],[dia_semana]])) | AF14: =IF(tblOrdenes[[#This Row],[HHA]]="","",p_factor_productividad*_xlfn.XLOOKUP(tblOrdenes[[#This Row],[semana]]&"|"&tblOrdenes[[#This Row],[dia_semana]]&"|"&tblOrdenes[[#This Row],[tecnico_asignado]],tblAsignaciones[clave],tblAsignaciones[horas_disponibles],0)-tblOrdenes[[#This Row],[HHA]]) | AG14: =IF(tblOrdenes[[#This Row],[orden]]="","",_xlfn.XLOOKUP(tblOrdenes[[#This Row],[id_operacion]],tblEjecucion[id_operacion],tblEjecucion[precio],0)) | AH14: =IF(tblOrdenes[[#This Row],[orden]]="","",MAX(0,_xlfn.XLOOKUP(tblOrdenes[[#This Row],[id_operacion]],tblEjecucion[id_operacion],tblEjecucion[costo_plan_total],0)-tblOrdenes[[#This Row],[costo_servicio]])) | AI14: =IF(tblOrdenes[[#This Row],[orden]]="","",tblOrdenes[[#This Row],[costo_servicio]]+tblOrdenes[[#This Row],[costo_materiales]]) | AM14: =IF(tblOrdenes[[#This Row],[link_checklist]]="","",HYPERLINK(p_ruta_base_checklists&tblOrdenes[[#This Row],[link_checklist]],"abrir")) | AO14: =IF(tblOrdenes[[#This Row],[orden]]="","",tblOrdenes[[#This Row],[orden]]&IF(tblOrdenes[[#This Row],[operacion]]="","0010",tblOrdenes[[#This Row],[operacion]]))
A15: OT-000012 | B15: 0010 | C15: Reparación de falla — EQ-110 | D15: Reparación de falla en EQ-110 | E15: EQ-110 | F15: CC-310 | G15: PU-MEC | H15: ACT-03 | I15: TIPO-C1 | J15: 46217 | K15: 10 | L15: 400 | N15: =IF(tblOrdenes[[#This Row],[orden]]="","",IF(tblOrdenes[[#This Row],[horas_ajustadas]]<>"",tblOrdenes[[#This Row],[horas_ajustadas]],IF(tblOrdenes[[#This Row],[horas_estimadas]]="","",tblOrdenes[[#This Row],[horas_estimadas]]))) | O15: =IF(tblOrdenes[[#This Row],[orden]]="","",_xlfn.XLOOKUP(_xlfn.XLOOKUP(tblOrdenes[[#This Row],[id_operacion]],tblEjecucion[id_operacion],tblEjecucion[estado_sistema],""),tblEstados[estado_sistema],tblEstados[estado_normalizado],"Pendiente")) | P15: =IF(tblOrdenes[[#This Row],[fecha_inicio]]="","",YEAR(tblOrdenes[[#This Row],[fecha_inicio]]+4-WEEKDAY(tblOrdenes[[#This Row],[fecha_inicio]],2))&"-S"&TEXT(_xlfn.ISOWEEKNUM(tblOrdenes[[#This Row],[fecha_inicio]]),"00")) | Q15: =IF(tblOrdenes[[#This Row],[fecha_inicio]]="","",YEAR(tblOrdenes[[#This Row],[fecha_inicio]])) | R15: =IF(tblOrdenes[[#This Row],[fecha_inicio]]="","",MONTH(tblOrdenes[[#This Row],[fecha_inicio]])) | S15: =IF(tblOrdenes[[#This Row],[fecha_inicio]]="","",INDEX(lista_dias,WEEKDAY(tblOrdenes[[#This Row],[fecha_inicio]],2))) | T15: =IF(tblOrdenes[[#This Row],[tipo_ot]]="","",_xlfn.XLOOKUP(tblOrdenes[[#This Row],[tipo_ot]],tblTiposOT[codigo],tblTiposOT[clasificacion],"sin_clasificar")) | U15: =IF(tblOrdenes[[#This Row],[centro_costo]]="","",_xlfn.XLOOKUP(tblOrdenes[[#This Row],[centro_costo]],tblCECO[codigo],tblCECO[linea],"(sin catálogo)")) | V15: =IF(tblOrdenes[[#This Row],[centro_costo]]="","",_xlfn.XLOOKUP(tblOrdenes[[#This Row],[centro_costo]],tblCECO[codigo],tblCECO[area],"(sin catálogo)")) | W15: =IF(tblOrdenes[[#This Row],[centro_costo]]="","",_xlfn.XLOOKUP(tblOrdenes[[#This Row],[centro_costo]],tblCECO[codigo],tblCECO[coordinador],"(sin catálogo)")) | X15: =IF(tblOrdenes[[#This Row],[puesto_trabajo]]="","",_xlfn.XLOOKUP(tblOrdenes[[#This Row],[puesto_trabajo]],tblPuestos[codigo],tblPuestos[especialidad],"(sin catálogo)")) | Y15: =IF(tblOrdenes[[#This Row],[cod_actividad]]="","",_xlfn.XLOOKUP(tblOrdenes[[#This Row],[cod_actividad]],tblActividades[codigo],tblActividades[descripcion],"(sin catálogo)")) | Z15: =IF(tblOrdenes[[#This Row],[fecha_inicio]]="","",TODAY()-tblOrdenes[[#This Row],[fecha_inicio]]) | AA15: =IF(tblOrdenes[[#This Row],[backlog_dias]]="","",IF(tblOrdenes[[#This Row],[backlog_dias]]<0,"FUTURO",IF(tblOrdenes[[#This Row],[backlog_dias]]>p_dias_backlog_max,"BACKLOG","MES CORRIENTE"))) | AB15: =IF(tblOrdenes[[#This Row],[backlog_dias]]="",FALSE,AND(tblOrdenes[[#This Row],[backlog_dias]]>p_dias_backlog_min,tblOrdenes[[#This Row],[backlog_dias]]<=p_dias_backlog_max)) | AD15: =IF(tblOrdenes[[#This Row],[tecnico_asignado]]="","",_xlfn.XLOOKUP(tblOrdenes[[#This Row],[semana]]&"|"&tblOrdenes[[#This Row],[dia_semana]]&"|"&tblOrdenes[[#This Row],[tecnico_asignado]],tblAsignaciones[clave],tblAsignaciones[turno],"")) | AE15: =IF(tblOrdenes[[#This Row],[tecnico_asignado]]="","",SUMIFS(tblOrdenes[horas_efectivas],tblOrdenes[tecnico_asignado],tblOrdenes[[#This Row],[tecnico_asignado]],tblOrdenes[semana],tblOrdenes[[#This Row],[semana]],tblOrdenes[dia_semana],tblOrdenes[[#This Row],[dia_semana]])) | AF15: =IF(tblOrdenes[[#This Row],[HHA]]="","",p_factor_productividad*_xlfn.XLOOKUP(tblOrdenes[[#This Row],[semana]]&"|"&tblOrdenes[[#This Row],[dia_semana]]&"|"&tblOrdenes[[#This Row],[tecnico_asignado]],tblAsignaciones[clave],tblAsignaciones[horas_disponibles],0)-tblOrdenes[[#This Row],[HHA]]) | AG15: =IF(tblOrdenes[[#This Row],[orden]]="","",_xlfn.XLOOKUP(tblOrdenes[[#This Row],[id_operacion]],tblEjecucion[id_operacion],tblEjecucion[precio],0)) | AH15: =IF(tblOrdenes[[#This Row],[orden]]="","",MAX(0,_xlfn.XLOOKUP(tblOrdenes[[#This Row],[id_operacion]],tblEjecucion[id_operacion],tblEjecucion[costo_plan_total],0)-tblOrdenes[[#This Row],[costo_servicio]])) | AI15: =IF(tblOrdenes[[#This Row],[orden]]="","",tblOrdenes[[#This Row],[costo_servicio]]+tblOrdenes[[#This Row],[costo_materiales]]) | AJ15: PT-CALIENTE | AK15: LOTO | AM15: =IF(tblOrdenes[[#This Row],[link_checklist]]="","",HYPERLINK(p_ruta_base_checklists&tblOrdenes[[#This Row],[link_checklist]],"abrir")) | AO15: =IF(tblOrdenes[[#This Row],[orden]]="","",tblOrdenes[[#This Row],[orden]]&IF(tblOrdenes[[#This Row],[operacion]]="","0010",tblOrdenes[[#This Row],[operacion]]))
A16: OT-000013 | B16: 0010 | C16: Lubricación programada — EQ-104 | D16: Lubricación programada en EQ-104 | E16: EQ-104 | F16: CC-110 | G16: PU-MEC | H16: ACT-02 | I16: TIPO-P2 | J16: 46225 | K16: 10 | L16: 250 | N16: =IF(tblOrdenes[[#This Row],[orden]]="","",IF(tblOrdenes[[#This Row],[horas_ajustadas]]<>"",tblOrdenes[[#This Row],[horas_ajustadas]],IF(tblOrdenes[[#This Row],[horas_estimadas]]="","",tblOrdenes[[#This Row],[horas_estimadas]]))) | O16: =IF(tblOrdenes[[#This Row],[orden]]="","",_xlfn.XLOOKUP(_xlfn.XLOOKUP(tblOrdenes[[#This Row],[id_operacion]],tblEjecucion[id_operacion],tblEjecucion[estado_sistema],""),tblEstados[estado_sistema],tblEstados[estado_normalizado],"Pendiente")) | P16: =IF(tblOrdenes[[#This Row],[fecha_inicio]]="","",YEAR(tblOrdenes[[#This Row],[fecha_inicio]]+4-WEEKDAY(tblOrdenes[[#This Row],[fecha_inicio]],2))&"-S"&TEXT(_xlfn.ISOWEEKNUM(tblOrdenes[[#This Row],[fecha_inicio]]),"00")) | Q16: =IF(tblOrdenes[[#This Row],[fecha_inicio]]="","",YEAR(tblOrdenes[[#This Row],[fecha_inicio]])) | R16: =IF(tblOrdenes[[#This Row],[fecha_inicio]]="","",MONTH(tblOrdenes[[#This Row],[fecha_inicio]])) | S16: =IF(tblOrdenes[[#This Row],[fecha_inicio]]="","",INDEX(lista_dias,WEEKDAY(tblOrdenes[[#This Row],[fecha_inicio]],2))) | T16: =IF(tblOrdenes[[#This Row],[tipo_ot]]="","",_xlfn.XLOOKUP(tblOrdenes[[#This Row],[tipo_ot]],tblTiposOT[codigo],tblTiposOT[clasificacion],"sin_clasificar")) | U16: =IF(tblOrdenes[[#This Row],[centro_costo]]="","",_xlfn.XLOOKUP(tblOrdenes[[#This Row],[centro_costo]],tblCECO[codigo],tblCECO[linea],"(sin catálogo)")) | V16: =IF(tblOrdenes[[#This Row],[centro_costo]]="","",_xlfn.XLOOKUP(tblOrdenes[[#This Row],[centro_costo]],tblCECO[codigo],tblCECO[area],"(sin catálogo)")) | W16: =IF(tblOrdenes[[#This Row],[centro_costo]]="","",_xlfn.XLOOKUP(tblOrdenes[[#This Row],[centro_costo]],tblCECO[codigo],tblCECO[coordinador],"(sin catálogo)")) | X16: =IF(tblOrdenes[[#This Row],[puesto_trabajo]]="","",_xlfn.XLOOKUP(tblOrdenes[[#This Row],[puesto_trabajo]],tblPuestos[codigo],tblPuestos[especialidad],"(sin catálogo)")) | Y16: =IF(tblOrdenes[[#This Row],[cod_actividad]]="","",_xlfn.XLOOKUP(tblOrdenes[[#This Row],[cod_actividad]],tblActividades[codigo],tblActividades[descripcion],"(sin catálogo)")) | Z16: =IF(tblOrdenes[[#This Row],[fecha_inicio]]="","",TODAY()-tblOrdenes[[#This Row],[fecha_inicio]]) | AA16: =IF(tblOrdenes[[#This Row],[backlog_dias]]="","",IF(tblOrdenes[[#This Row],[backlog_dias]]<0,"FUTURO",IF(tblOrdenes[[#This Row],[backlog_dias]]>p_dias_backlog_max,"BACKLOG","MES CORRIENTE"))) | AB16: =IF(tblOrdenes[[#This Row],[backlog_dias]]="",FALSE,AND(tblOrdenes[[#This Row],[backlog_dias]]>p_dias_backlog_min,tblOrdenes[[#This Row],[backlog_dias]]<=p_dias_backlog_max)) | AC16: Técnico 01 | AD16: =IF(tblOrdenes[[#This Row],[tecnico_asignado]]="","",_xlfn.XLOOKUP(tblOrdenes[[#This Row],[semana]]&"|"&tblOrdenes[[#This Row],[dia_semana]]&"|"&tblOrdenes[[#This Row],[tecnico_asignado]],tblAsignaciones[clave],tblAsignaciones[turno],"")) | AE16: =IF(tblOrdenes[[#This Row],[tecnico_asignado]]="","",SUMIFS(tblOrdenes[horas_efectivas],tblOrdenes[tecnico_asignado],tblOrdenes[[#This Row],[tecnico_asignado]],tblOrdenes[semana],tblOrdenes[[#This Row],[semana]],tblOrdenes[dia_semana],tblOrdenes[[#This Row],[dia_semana]])) | AF16: =IF(tblOrdenes[[#This Row],[HHA]]="","",p_factor_productividad*_xlfn.XLOOKUP(tblOrdenes[[#This Row],[semana]]&"|"&tblOrdenes[[#This Row],[dia_semana]]&"|"&tblOrdenes[[#This Row],[tecnico_asignado]],tblAsignaciones[clave],tblAsignaciones[horas_disponibles],0)-tblOrdenes[[#This Row],[HHA]]) | AG16: =IF(tblOrdenes[[#This Row],[orden]]="","",_xlfn.XLOOKUP(tblOrdenes[[#This Row],[id_operacion]],tblEjecucion[id_operacion],tblEjecucion[precio],0)) | AH16: =IF(tblOrdenes[[#This Row],[orden]]="","",MAX(0,_xlfn.XLOOKUP(tblOrdenes[[#This Row],[id_operacion]],tblEjecucion[id_operacion],tblEjecucion[costo_plan_total],0)-tblOrdenes[[#This Row],[costo_servicio]])) | AI16: =IF(tblOrdenes[[#This Row],[orden]]="","",tblOrdenes[[#This Row],[costo_servicio]]+tblOrdenes[[#This Row],[costo_materiales]]) | AL16: ACT-02.pdf | AM16: =IF(tblOrdenes[[#This Row],[link_checklist]]="","",HYPERLINK(p_ruta_base_checklists&tblOrdenes[[#This Row],[link_checklist]],"abrir")) | AO16: =IF(tblOrdenes[[#This Row],[orden]]="","",tblOrdenes[[#This Row],[orden]]&IF(tblOrdenes[[#This Row],[operacion]]="","0010",tblOrdenes[[#This Row],[operacion]]))
A17: OT-000014 | B17: 0010 | C17: Análisis predictivo — EQ-108 | D17: Análisis predictivo en EQ-108 | E17: EQ-108 | F17: CC-210 | G17: PU-MEC | H17: ACT-04 | I17: TIPO-P1 | J17: 46226 | K17: 8 | L17: 200 | N17: =IF(tblOrdenes[[#This Row],[orden]]="","",IF(tblOrdenes[[#This Row],[horas_ajustadas]]<>"",tblOrdenes[[#This Row],[horas_ajustadas]],IF(tblOrdenes[[#This Row],[horas_estimadas]]="","",tblOrdenes[[#This Row],[horas_estimadas]]))) | O17: =IF(tblOrdenes[[#This Row],[orden]]="","",_xlfn.XLOOKUP(_xlfn.XLOOKUP(tblOrdenes[[#This Row],[id_operacion]],tblEjecucion[id_operacion],tblEjecucion[estado_sistema],""),tblEstados[estado_sistema],tblEstados[estado_normalizado],"Pendiente")) | P17: =IF(tblOrdenes[[#This Row],[fecha_inicio]]="","",YEAR(tblOrdenes[[#This Row],[fecha_inicio]]+4-WEEKDAY(tblOrdenes[[#This Row],[fecha_inicio]],2))&"-S"&TEXT(_xlfn.ISOWEEKNUM(tblOrdenes[[#This Row],[fecha_inicio]]),"00")) | Q17: =IF(tblOrdenes[[#This Row],[fecha_inicio]]="","",YEAR(tblOrdenes[[#This Row],[fecha_inicio]])) | R17: =IF(tblOrdenes[[#This Row],[fecha_inicio]]="","",MONTH(tblOrdenes[[#This Row],[fecha_inicio]])) | S17: =IF(tblOrdenes[[#This Row],[fecha_inicio]]="","",INDEX(lista_dias,WEEKDAY(tblOrdenes[[#This Row],[fecha_inicio]],2))) | T17: =IF(tblOrdenes[[#This Row],[tipo_ot]]="","",_xlfn.XLOOKUP(tblOrdenes[[#This Row],[tipo_ot]],tblTiposOT[codigo],tblTiposOT[clasificacion],"sin_clasificar")) | U17: =IF(tblOrdenes[[#This Row],[centro_costo]]="","",_xlfn.XLOOKUP(tblOrdenes[[#This Row],[centro_costo]],tblCECO[codigo],tblCECO[linea],"(sin catálogo)")) | V17: =IF(tblOrdenes[[#This Row],[centro_costo]]="","",_xlfn.XLOOKUP(tblOrdenes[[#This Row],[centro_costo]],tblCECO[codigo],tblCECO[area],"(sin catálogo)")) | W17: =IF(tblOrdenes[[#This Row],[centro_costo]]="","",_xlfn.XLOOKUP(tblOrdenes[[#This Row],[centro_costo]],tblCECO[codigo],tblCECO[coordinador],"(sin catálogo)")) | X17: =IF(tblOrdenes[[#This Row],[puesto_trabajo]]="","",_xlfn.XLOOKUP(tblOrdenes[[#This Row],[puesto_trabajo]],tblPuestos[codigo],tblPuestos[especialidad],"(sin catálogo)")) | Y17: =IF(tblOrdenes[[#This Row],[cod_actividad]]="","",_xlfn.XLOOKUP(tblOrdenes[[#This Row],[cod_actividad]],tblActividades[codigo],tblActividades[descripcion],"(sin catálogo)")) | Z17: =IF(tblOrdenes[[#This Row],[fecha_inicio]]="","",TODAY()-tblOrdenes[[#This Row],[fecha_inicio]]) | AA17: =IF(tblOrdenes[[#This Row],[backlog_dias]]="","",IF(tblOrdenes[[#This Row],[backlog_dias]]<0,"FUTURO",IF(tblOrdenes[[#This Row],[backlog_dias]]>p_dias_backlog_max,"BACKLOG","MES CORRIENTE"))) | AB17: =IF(tblOrdenes[[#This Row],[backlog_dias]]="",FALSE,AND(tblOrdenes[[#This Row],[backlog_dias]]>p_dias_backlog_min,tblOrdenes[[#This Row],[backlog_dias]]<=p_dias_backlog_max)) | AC17: Técnico 02 | AD17: =IF(tblOrdenes[[#This Row],[tecnico_asignado]]="","",_xlfn.XLOOKUP(tblOrdenes[[#This Row],[semana]]&"|"&tblOrdenes[[#This Row],[dia_semana]]&"|"&tblOrdenes[[#This Row],[tecnico_asignado]],tblAsignaciones[clave],tblAsignaciones[turno],"")) | AE17: =IF(tblOrdenes[[#This Row],[tecnico_asignado]]="","",SUMIFS(tblOrdenes[horas_efectivas],tblOrdenes[tecnico_asignado],tblOrdenes[[#This Row],[tecnico_asignado]],tblOrdenes[semana],tblOrdenes[[#This Row],[semana]],tblOrdenes[dia_semana],tblOrdenes[[#This Row],[dia_semana]])) | AF17: =IF(tblOrdenes[[#This Row],[HHA]]="","",p_factor_productividad*_xlfn.XLOOKUP(tblOrdenes[[#This Row],[semana]]&"|"&tblOrdenes[[#This Row],[dia_semana]]&"|"&tblOrdenes[[#This Row],[tecnico_asignado]],tblAsignaciones[clave],tblAsignaciones[horas_disponibles],0)-tblOrdenes[[#This Row],[HHA]]) | AG17: =IF(tblOrdenes[[#This Row],[orden]]="","",_xlfn.XLOOKUP(tblOrdenes[[#This Row],[id_operacion]],tblEjecucion[id_operacion],tblEjecucion[precio],0)) | AH17: =IF(tblOrdenes[[#This Row],[orden]]="","",MAX(0,_xlfn.XLOOKUP(tblOrdenes[[#This Row],[id_operacion]],tblEjecucion[id_operacion],tblEjecucion[costo_plan_total],0)-tblOrdenes[[#This Row],[costo_servicio]])) | AI17: =IF(tblOrdenes[[#This Row],[orden]]="","",tblOrdenes[[#This Row],[costo_servicio]]+tblOrdenes[[#This Row],[costo_materiales]]) | AL17: ACT-04.pdf | AM17: =IF(tblOrdenes[[#This Row],[link_checklist]]="","",HYPERLINK(p_ruta_base_checklists&tblOrdenes[[#This Row],[link_checklist]],"abrir")) | AO17: =IF(tblOrdenes[[#This Row],[orden]]="","",tblOrdenes[[#This Row],[orden]]&IF(tblOrdenes[[#This Row],[operacion]]="","0010",tblOrdenes[[#This Row],[operacion]]))
A18: OT-000015 | B18: 0010 | C18: Inspección de rutina — EQ-110 | D18: Inspección de rutina en EQ-110 | E18: EQ-110 | F18: CC-310 | G18: PU-MEC | H18: ACT-01 | I18: TIPO-P2 | J18: 46227 | K18: 6 | L18: 150 | N18: =IF(tblOrdenes[[#This Row],[orden]]="","",IF(tblOrdenes[[#This Row],[horas_ajustadas]]<>"",tblOrdenes[[#This Row],[horas_ajustadas]],IF(tblOrdenes[[#This Row],[horas_estimadas]]="","",tblOrdenes[[#This Row],[horas_estimadas]]))) | O18: =IF(tblOrdenes[[#This Row],[orden]]="","",_xlfn.XLOOKUP(_xlfn.XLOOKUP(tblOrdenes[[#This Row],[id_operacion]],tblEjecucion[id_operacion],tblEjecucion[estado_sistema],""),tblEstados[estado_sistema],tblEstados[estado_normalizado],"Pendiente")) | P18: =IF(tblOrdenes[[#This Row],[fecha_inicio]]="","",YEAR(tblOrdenes[[#This Row],[fecha_inicio]]+4-WEEKDAY(tblOrdenes[[#This Row],[fecha_inicio]],2))&"-S"&TEXT(_xlfn.ISOWEEKNUM(tblOrdenes[[#This Row],[fecha_inicio]]),"00")) | Q18: =IF(tblOrdenes[[#This Row],[fecha_inicio]]="","",YEAR(tblOrdenes[[#This Row],[fecha_inicio]])) | R18: =IF(tblOrdenes[[#This Row],[fecha_inicio]]="","",MONTH(tblOrdenes[[#This Row],[fecha_inicio]])) | S18: =IF(tblOrdenes[[#This Row],[fecha_inicio]]="","",INDEX(lista_dias,WEEKDAY(tblOrdenes[[#This Row],[fecha_inicio]],2))) | T18: =IF(tblOrdenes[[#This Row],[tipo_ot]]="","",_xlfn.XLOOKUP(tblOrdenes[[#This Row],[tipo_ot]],tblTiposOT[codigo],tblTiposOT[clasificacion],"sin_clasificar")) | U18: =IF(tblOrdenes[[#This Row],[centro_costo]]="","",_xlfn.XLOOKUP(tblOrdenes[[#This Row],[centro_costo]],tblCECO[codigo],tblCECO[linea],"(sin catálogo)")) | V18: =IF(tblOrdenes[[#This Row],[centro_costo]]="","",_xlfn.XLOOKUP(tblOrdenes[[#This Row],[centro_costo]],tblCECO[codigo],tblCECO[area],"(sin catálogo)")) | W18: =IF(tblOrdenes[[#This Row],[centro_costo]]="","",_xlfn.XLOOKUP(tblOrdenes[[#This Row],[centro_costo]],tblCECO[codigo],tblCECO[coordinador],"(sin catálogo)")) | X18: =IF(tblOrdenes[[#This Row],[puesto_trabajo]]="","",_xlfn.XLOOKUP(tblOrdenes[[#This Row],[puesto_trabajo]],tblPuestos[codigo],tblPuestos[especialidad],"(sin catálogo)")) | Y18: =IF(tblOrdenes[[#This Row],[cod_actividad]]="","",_xlfn.XLOOKUP(tblOrdenes[[#This Row],[cod_actividad]],tblActividades[codigo],tblActividades[descripcion],"(sin catálogo)")) | Z18: =IF(tblOrdenes[[#This Row],[fecha_inicio]]="","",TODAY()-tblOrdenes[[#This Row],[fecha_inicio]]) | AA18: =IF(tblOrdenes[[#This Row],[backlog_dias]]="","",IF(tblOrdenes[[#This Row],[backlog_dias]]<0,"FUTURO",IF(tblOrdenes[[#This Row],[backlog_dias]]>p_dias_backlog_max,"BACKLOG","MES CORRIENTE"))) | AB18: =IF(tblOrdenes[[#This Row],[backlog_dias]]="",FALSE,AND(tblOrdenes[[#This Row],[backlog_dias]]>p_dias_backlog_min,tblOrdenes[[#This Row],[backlog_dias]]<=p_dias_backlog_max)) | AC18: Técnico 03 | AD18: =IF(tblOrdenes[[#This Row],[tecnico_asignado]]="","",_xlfn.XLOOKUP(tblOrdenes[[#This Row],[semana]]&"|"&tblOrdenes[[#This Row],[dia_semana]]&"|"&tblOrdenes[[#This Row],[tecnico_asignado]],tblAsignaciones[clave],tblAsignaciones[turno],"")) | AE18: =IF(tblOrdenes[[#This Row],[tecnico_asignado]]="","",SUMIFS(tblOrdenes[horas_efectivas],tblOrdenes[tecnico_asignado],tblOrdenes[[#This Row],[tecnico_asignado]],tblOrdenes[semana],tblOrdenes[[#This Row],[semana]],tblOrdenes[dia_semana],tblOrdenes[[#This Row],[dia_semana]])) | AF18: =IF(tblOrdenes[[#This Row],[HHA]]="","",p_factor_productividad*_xlfn.XLOOKUP(tblOrdenes[[#This Row],[semana]]&"|"&tblOrdenes[[#This Row],[dia_semana]]&"|"&tblOrdenes[[#This Row],[tecnico_asignado]],tblAsignaciones[clave],tblAsignaciones[horas_disponibles],0)-tblOrdenes[[#This Row],[HHA]]) | AG18: =IF(tblOrdenes[[#This Row],[orden]]="","",_xlfn.XLOOKUP(tblOrdenes[[#This Row],[id_operacion]],tblEjecucion[id_operacion],tblEjecucion[precio],0)) | AH18: =IF(tblOrdenes[[#This Row],[orden]]="","",MAX(0,_xlfn.XLOOKUP(tblOrdenes[[#This Row],[id_operacion]],tblEjecucion[id_operacion],tblEjecucion[costo_plan_total],0)-tblOrdenes[[#This Row],[costo_servicio]])) | AI18: =IF(tblOrdenes[[#This Row],[orden]]="","",tblOrdenes[[#This Row],[costo_servicio]]+tblOrdenes[[#This Row],[costo_materiales]]) | AL18: ACT-01.pdf | AM18: =IF(tblOrdenes[[#This Row],[link_checklist]]="","",HYPERLINK(p_ruta_base_checklists&tblOrdenes[[#This Row],[link_checklist]],"abrir")) | AO18: =IF(tblOrdenes[[#This Row],[orden]]="","",tblOrdenes[[#This Row],[orden]]&IF(tblOrdenes[[#This Row],[operacion]]="","0010",tblOrdenes[[#This Row],[operacion]]))
A19: OT-000016 | B19: 0010 | C19: Lubricación programada — EQ-102 | D19: Lubricación programada en EQ-102 | E19: EQ-102 | F19: CC-110 | G19: PU-MEC | H19: ACT-02 | I19: TIPO-P1 | J19: 46223 | K19: 10 | L19: 250 | N19: =IF(tblOrdenes[[#This Row],[orden]]="","",IF(tblOrdenes[[#This Row],[horas_ajustadas]]<>"",tblOrdenes[[#This Row],[horas_ajustadas]],IF(tblOrdenes[[#This Row],[horas_estimadas]]="","",tblOrdenes[[#This Row],[horas_estimadas]]))) | O19: =IF(tblOrdenes[[#This Row],[orden]]="","",_xlfn.XLOOKUP(_xlfn.XLOOKUP(tblOrdenes[[#This Row],[id_operacion]],tblEjecucion[id_operacion],tblEjecucion[estado_sistema],""),tblEstados[estado_sistema],tblEstados[estado_normalizado],"Pendiente")) | P19: =IF(tblOrdenes[[#This Row],[fecha_inicio]]="","",YEAR(tblOrdenes[[#This Row],[fecha_inicio]]+4-WEEKDAY(tblOrdenes[[#This Row],[fecha_inicio]],2))&"-S"&TEXT(_xlfn.ISOWEEKNUM(tblOrdenes[[#This Row],[fecha_inicio]]),"00")) | Q19: =IF(tblOrdenes[[#This Row],[fecha_inicio]]="","",YEAR(tblOrdenes[[#This Row],[fecha_inicio]])) | R19: =IF(tblOrdenes[[#This Row],[fecha_inicio]]="","",MONTH(tblOrdenes[[#This Row],[fecha_inicio]])) | S19: =IF(tblOrdenes[[#This Row],[fecha_inicio]]="","",INDEX(lista_dias,WEEKDAY(tblOrdenes[[#This Row],[fecha_inicio]],2))) | T19: =IF(tblOrdenes[[#This Row],[tipo_ot]]="","",_xlfn.XLOOKUP(tblOrdenes[[#This Row],[tipo_ot]],tblTiposOT[codigo],tblTiposOT[clasificacion],"sin_clasificar")) | U19: =IF(tblOrdenes[[#This Row],[centro_costo]]="","",_xlfn.XLOOKUP(tblOrdenes[[#This Row],[centro_costo]],tblCECO[codigo],tblCECO[linea],"(sin catálogo)")) | V19: =IF(tblOrdenes[[#This Row],[centro_costo]]="","",_xlfn.XLOOKUP(tblOrdenes[[#This Row],[centro_costo]],tblCECO[codigo],tblCECO[area],"(sin catálogo)")) | W19: =IF(tblOrdenes[[#This Row],[centro_costo]]="","",_xlfn.XLOOKUP(tblOrdenes[[#This Row],[centro_costo]],tblCECO[codigo],tblCECO[coordinador],"(sin catálogo)")) | X19: =IF(tblOrdenes[[#This Row],[puesto_trabajo]]="","",_xlfn.XLOOKUP(tblOrdenes[[#This Row],[puesto_trabajo]],tblPuestos[codigo],tblPuestos[especialidad],"(sin catálogo)")) | Y19: =IF(tblOrdenes[[#This Row],[cod_actividad]]="","",_xlfn.XLOOKUP(tblOrdenes[[#This Row],[cod_actividad]],tblActividades[codigo],tblActividades[descripcion],"(sin catálogo)")) | Z19: =IF(tblOrdenes[[#This Row],[fecha_inicio]]="","",TODAY()-tblOrdenes[[#This Row],[fecha_inicio]]) | AA19: =IF(tblOrdenes[[#This Row],[backlog_dias]]="","",IF(tblOrdenes[[#This Row],[backlog_dias]]<0,"FUTURO",IF(tblOrdenes[[#This Row],[backlog_dias]]>p_dias_backlog_max,"BACKLOG","MES CORRIENTE"))) | AB19: =IF(tblOrdenes[[#This Row],[backlog_dias]]="",FALSE,AND(tblOrdenes[[#This Row],[backlog_dias]]>p_dias_backlog_min,tblOrdenes[[#This Row],[backlog_dias]]<=p_dias_backlog_max)) | AC19: Técnico 04 | AD19: =IF(tblOrdenes[[#This Row],[tecnico_asignado]]="","",_xlfn.XLOOKUP(tblOrdenes[[#This Row],[semana]]&"|"&tblOrdenes[[#This Row],[dia_semana]]&"|"&tblOrdenes[[#This Row],[tecnico_asignado]],tblAsignaciones[clave],tblAsignaciones[turno],"")) | AE19: =IF(tblOrdenes[[#This Row],[tecnico_asignado]]="","",SUMIFS(tblOrdenes[horas_efectivas],tblOrdenes[tecnico_asignado],tblOrdenes[[#This Row],[tecnico_asignado]],tblOrdenes[semana],tblOrdenes[[#This Row],[semana]],tblOrdenes[dia_semana],tblOrdenes[[#This Row],[dia_semana]])) | AF19: =IF(tblOrdenes[[#This Row],[HHA]]="","",p_factor_productividad*_xlfn.XLOOKUP(tblOrdenes[[#This Row],[semana]]&"|"&tblOrdenes[[#This Row],[dia_semana]]&"|"&tblOrdenes[[#This Row],[tecnico_asignado]],tblAsignaciones[clave],tblAsignaciones[horas_disponibles],0)-tblOrdenes[[#This Row],[HHA]]) | AG19: =IF(tblOrdenes[[#This Row],[orden]]="","",_xlfn.XLOOKUP(tblOrdenes[[#This Row],[id_operacion]],tblEjecucion[id_operacion],tblEjecucion[precio],0)) | AH19: =IF(tblOrdenes[[#This Row],[orden]]="","",MAX(0,_xlfn.XLOOKUP(tblOrdenes[[#This Row],[id_operacion]],tblEjecucion[id_operacion],tblEjecucion[costo_plan_total],0)-tblOrdenes[[#This Row],[costo_servicio]])) | AI19: =IF(tblOrdenes[[#This Row],[orden]]="","",tblOrdenes[[#This Row],[costo_servicio]]+tblOrdenes[[#This Row],[costo_materiales]]) | AL19: ACT-02.pdf | AM19: =IF(tblOrdenes[[#This Row],[link_checklist]]="","",HYPERLINK(p_ruta_base_checklists&tblOrdenes[[#This Row],[link_checklist]],"abrir")) | AO19: =IF(tblOrdenes[[#This Row],[orden]]="","",tblOrdenes[[#This Row],[orden]]&IF(tblOrdenes[[#This Row],[operacion]]="","0010",tblOrdenes[[#This Row],[operacion]]))
A20: OT-000017 | B20: 0010 | C20: Análisis predictivo — EQ-107 | D20: Análisis predictivo en EQ-107 | E20: EQ-107 | F20: CC-210 | G20: PU-MEC | H20: ACT-04 | I20: TIPO-P2 | J20: 46224 | K20: 8 | L20: 200 | M20: 12 | N20: =IF(tblOrdenes[[#This Row],[orden]]="","",IF(tblOrdenes[[#This Row],[horas_ajustadas]]<>"",tblOrdenes[[#This Row],[horas_ajustadas]],IF(tblOrdenes[[#This Row],[horas_estimadas]]="","",tblOrdenes[[#This Row],[horas_estimadas]]))) | O20: =IF(tblOrdenes[[#This Row],[orden]]="","",_xlfn.XLOOKUP(_xlfn.XLOOKUP(tblOrdenes[[#This Row],[id_operacion]],tblEjecucion[id_operacion],tblEjecucion[estado_sistema],""),tblEstados[estado_sistema],tblEstados[estado_normalizado],"Pendiente")) | P20: =IF(tblOrdenes[[#This Row],[fecha_inicio]]="","",YEAR(tblOrdenes[[#This Row],[fecha_inicio]]+4-WEEKDAY(tblOrdenes[[#This Row],[fecha_inicio]],2))&"-S"&TEXT(_xlfn.ISOWEEKNUM(tblOrdenes[[#This Row],[fecha_inicio]]),"00")) | Q20: =IF(tblOrdenes[[#This Row],[fecha_inicio]]="","",YEAR(tblOrdenes[[#This Row],[fecha_inicio]])) | R20: =IF(tblOrdenes[[#This Row],[fecha_inicio]]="","",MONTH(tblOrdenes[[#This Row],[fecha_inicio]])) | S20: =IF(tblOrdenes[[#This Row],[fecha_inicio]]="","",INDEX(lista_dias,WEEKDAY(tblOrdenes[[#This Row],[fecha_inicio]],2))) | T20: =IF(tblOrdenes[[#This Row],[tipo_ot]]="","",_xlfn.XLOOKUP(tblOrdenes[[#This Row],[tipo_ot]],tblTiposOT[codigo],tblTiposOT[clasificacion],"sin_clasificar")) | U20: =IF(tblOrdenes[[#This Row],[centro_costo]]="","",_xlfn.XLOOKUP(tblOrdenes[[#This Row],[centro_costo]],tblCECO[codigo],tblCECO[linea],"(sin catálogo)")) | V20: =IF(tblOrdenes[[#This Row],[centro_costo]]="","",_xlfn.XLOOKUP(tblOrdenes[[#This Row],[centro_costo]],tblCECO[codigo],tblCECO[area],"(sin catálogo)")) | W20: =IF(tblOrdenes[[#This Row],[centro_costo]]="","",_xlfn.XLOOKUP(tblOrdenes[[#This Row],[centro_costo]],tblCECO[codigo],tblCECO[coordinador],"(sin catálogo)")) | X20: =IF(tblOrdenes[[#This Row],[puesto_trabajo]]="","",_xlfn.XLOOKUP(tblOrdenes[[#This Row],[puesto_trabajo]],tblPuestos[codigo],tblPuestos[especialidad],"(sin catálogo)")) | Y20: =IF(tblOrdenes[[#This Row],[cod_actividad]]="","",_xlfn.XLOOKUP(tblOrdenes[[#This Row],[cod_actividad]],tblActividades[codigo],tblActividades[descripcion],"(sin catálogo)")) | Z20: =IF(tblOrdenes[[#This Row],[fecha_inicio]]="","",TODAY()-tblOrdenes[[#This Row],[fecha_inicio]]) | AA20: =IF(tblOrdenes[[#This Row],[backlog_dias]]="","",IF(tblOrdenes[[#This Row],[backlog_dias]]<0,"FUTURO",IF(tblOrdenes[[#This Row],[backlog_dias]]>p_dias_backlog_max,"BACKLOG","MES CORRIENTE"))) | AB20: =IF(tblOrdenes[[#This Row],[backlog_dias]]="",FALSE,AND(tblOrdenes[[#This Row],[backlog_dias]]>p_dias_backlog_min,tblOrdenes[[#This Row],[backlog_dias]]<=p_dias_backlog_max)) | AC20: Técnico 01 | AD20: =IF(tblOrdenes[[#This Row],[tecnico_asignado]]="","",_xlfn.XLOOKUP(tblOrdenes[[#This Row],[semana]]&"|"&tblOrdenes[[#This Row],[dia_semana]]&"|"&tblOrdenes[[#This Row],[tecnico_asignado]],tblAsignaciones[clave],tblAsignaciones[turno],"")) | AE20: =IF(tblOrdenes[[#This Row],[tecnico_asignado]]="","",SUMIFS(tblOrdenes[horas_efectivas],tblOrdenes[tecnico_asignado],tblOrdenes[[#This Row],[tecnico_asignado]],tblOrdenes[semana],tblOrdenes[[#This Row],[semana]],tblOrdenes[dia_semana],tblOrdenes[[#This Row],[dia_semana]])) | AF20: =IF(tblOrdenes[[#This Row],[HHA]]="","",p_factor_productividad*_xlfn.XLOOKUP(tblOrdenes[[#This Row],[semana]]&"|"&tblOrdenes[[#This Row],[dia_semana]]&"|"&tblOrdenes[[#This Row],[tecnico_asignado]],tblAsignaciones[clave],tblAsignaciones[horas_disponibles],0)-tblOrdenes[[#This Row],[HHA]]) | AG20: =IF(tblOrdenes[[#This Row],[orden]]="","",_xlfn.XLOOKUP(tblOrdenes[[#This Row],[id_operacion]],tblEjecucion[id_operacion],tblEjecucion[precio],0)) | AH20: =IF(tblOrdenes[[#This Row],[orden]]="","",MAX(0,_xlfn.XLOOKUP(tblOrdenes[[#This Row],[id_operacion]],tblEjecucion[id_operacion],tblEjecucion[costo_plan_total],0)-tblOrdenes[[#This Row],[costo_servicio]])) | AI20: =IF(tblOrdenes[[#This Row],[orden]]="","",tblOrdenes[[#This Row],[costo_servicio]]+tblOrdenes[[#This Row],[costo_materiales]]) | AL20: ACT-04.pdf | AM20: =IF(tblOrdenes[[#This Row],[link_checklist]]="","",HYPERLINK(p_ruta_base_checklists&tblOrdenes[[#This Row],[link_checklist]],"abrir")) | AN20: Ajuste: 8 → 12 h por alcance real | AO20: =IF(tblOrdenes[[#This Row],[orden]]="","",tblOrdenes[[#This Row],[orden]]&IF(tblOrdenes[[#This Row],[operacion]]="","0010",tblOrdenes[[#This Row],[operacion]]))
A21: OT-000018 | B21: 0010 | C21: Inspección de rutina — EQ-110 | D21: Inspección de rutina en EQ-110 | E21: EQ-110 | F21: CC-310 | G21: PU-MEC | H21: ACT-01 | I21: TIPO-P1 | J21: 46225 | K21: 6 | L21: 150 | N21: =IF(tblOrdenes[[#This Row],[orden]]="","",IF(tblOrdenes[[#This Row],[horas_ajustadas]]<>"",tblOrdenes[[#This Row],[horas_ajustadas]],IF(tblOrdenes[[#This Row],[horas_estimadas]]="","",tblOrdenes[[#This Row],[horas_estimadas]]))) | O21: =IF(tblOrdenes[[#This Row],[orden]]="","",_xlfn.XLOOKUP(_xlfn.XLOOKUP(tblOrdenes[[#This Row],[id_operacion]],tblEjecucion[id_operacion],tblEjecucion[estado_sistema],""),tblEstados[estado_sistema],tblEstados[estado_normalizado],"Pendiente")) | P21: =IF(tblOrdenes[[#This Row],[fecha_inicio]]="","",YEAR(tblOrdenes[[#This Row],[fecha_inicio]]+4-WEEKDAY(tblOrdenes[[#This Row],[fecha_inicio]],2))&"-S"&TEXT(_xlfn.ISOWEEKNUM(tblOrdenes[[#This Row],[fecha_inicio]]),"00")) | Q21: =IF(tblOrdenes[[#This Row],[fecha_inicio]]="","",YEAR(tblOrdenes[[#This Row],[fecha_inicio]])) | R21: =IF(tblOrdenes[[#This Row],[fecha_inicio]]="","",MONTH(tblOrdenes[[#This Row],[fecha_inicio]])) | S21: =IF(tblOrdenes[[#This Row],[fecha_inicio]]="","",INDEX(lista_dias,WEEKDAY(tblOrdenes[[#This Row],[fecha_inicio]],2))) | T21: =IF(tblOrdenes[[#This Row],[tipo_ot]]="","",_xlfn.XLOOKUP(tblOrdenes[[#This Row],[tipo_ot]],tblTiposOT[codigo],tblTiposOT[clasificacion],"sin_clasificar")) | U21: =IF(tblOrdenes[[#This Row],[centro_costo]]="","",_xlfn.XLOOKUP(tblOrdenes[[#This Row],[centro_costo]],tblCECO[codigo],tblCECO[linea],"(sin catálogo)")) | V21: =IF(tblOrdenes[[#This Row],[centro_costo]]="","",_xlfn.XLOOKUP(tblOrdenes[[#This Row],[centro_costo]],tblCECO[codigo],tblCECO[area],"(sin catálogo)")) | W21: =IF(tblOrdenes[[#This Row],[centro_costo]]="","",_xlfn.XLOOKUP(tblOrdenes[[#This Row],[centro_costo]],tblCECO[codigo],tblCECO[coordinador],"(sin catálogo)")) | X21: =IF(tblOrdenes[[#This Row],[puesto_trabajo]]="","",_xlfn.XLOOKUP(tblOrdenes[[#This Row],[puesto_trabajo]],tblPuestos[codigo],tblPuestos[especialidad],"(sin catálogo)")) | Y21: =IF(tblOrdenes[[#This Row],[cod_actividad]]="","",_xlfn.XLOOKUP(tblOrdenes[[#This Row],[cod_actividad]],tblActividades[codigo],tblActividades[descripcion],"(sin catálogo)")) | Z21: =IF(tblOrdenes[[#This Row],[fecha_inicio]]="","",TODAY()-tblOrdenes[[#This Row],[fecha_inicio]]) | AA21: =IF(tblOrdenes[[#This Row],[backlog_dias]]="","",IF(tblOrdenes[[#This Row],[backlog_dias]]<0,"FUTURO",IF(tblOrdenes[[#This Row],[backlog_dias]]>p_dias_backlog_max,"BACKLOG","MES CORRIENTE"))) | AB21: =IF(tblOrdenes[[#This Row],[backlog_dias]]="",FALSE,AND(tblOrdenes[[#This Row],[backlog_dias]]>p_dias_backlog_min,tblOrdenes[[#This Row],[backlog_dias]]<=p_dias_backlog_max)) | AC21: Técnico 02 | AD21: =IF(tblOrdenes[[#This Row],[tecnico_asignado]]="","",_xlfn.XLOOKUP(tblOrdenes[[#This Row],[semana]]&"|"&tblOrdenes[[#This Row],[dia_semana]]&"|"&tblOrdenes[[#This Row],[tecnico_asignado]],tblAsignaciones[clave],tblAsignaciones[turno],"")) | AE21: =IF(tblOrdenes[[#This Row],[tecnico_asignado]]="","",SUMIFS(tblOrdenes[horas_efectivas],tblOrdenes[tecnico_asignado],tblOrdenes[[#This Row],[tecnico_asignado]],tblOrdenes[semana],tblOrdenes[[#This Row],[semana]],tblOrdenes[dia_semana],tblOrdenes[[#This Row],[dia_semana]])) | AF21: =IF(tblOrdenes[[#This Row],[HHA]]="","",p_factor_productividad*_xlfn.XLOOKUP(tblOrdenes[[#This Row],[semana]]&"|"&tblOrdenes[[#This Row],[dia_semana]]&"|"&tblOrdenes[[#This Row],[tecnico_asignado]],tblAsignaciones[clave],tblAsignaciones[horas_disponibles],0)-tblOrdenes[[#This Row],[HHA]]) | AG21: =IF(tblOrdenes[[#This Row],[orden]]="","",_xlfn.XLOOKUP(tblOrdenes[[#This Row],[id_operacion]],tblEjecucion[id_operacion],tblEjecucion[precio],0)) | AH21: =IF(tblOrdenes[[#This Row],[orden]]="","",MAX(0,_xlfn.XLOOKUP(tblOrdenes[[#This Row],[id_operacion]],tblEjecucion[id_operacion],tblEjecucion[costo_plan_total],0)-tblOrdenes[[#This Row],[costo_servicio]])) | AI21: =IF(tblOrdenes[[#This Row],[orden]]="","",tblOrdenes[[#This Row],[costo_servicio]]+tblOrdenes[[#This Row],[costo_materiales]]) | AL21: ACT-01.pdf | AM21: =IF(tblOrdenes[[#This Row],[link_checklist]]="","",HYPERLINK(p_ruta_base_checklists&tblOrdenes[[#This Row],[link_checklist]],"abrir")) | AO21: =IF(tblOrdenes[[#This Row],[orden]]="","",tblOrdenes[[#This Row],[orden]]&IF(tblOrdenes[[#This Row],[operacion]]="","0010",tblOrdenes[[#This Row],[operacion]]))
A22: OT-000019 | B22: 0010 | C22: Lubricación programada — EQ-105 | D22: Lubricación programada en EQ-105 | E22: EQ-105 | F22: CC-110 | G22: PU-MEC | H22: ACT-02 | I22: TIPO-P2 | J22: 46226 | K22: 10 | L22: 250 | N22: =IF(tblOrdenes[[#This Row],[orden]]="","",IF(tblOrdenes[[#This Row],[horas_ajustadas]]<>"",tblOrdenes[[#This Row],[horas_ajustadas]],IF(tblOrdenes[[#This Row],[horas_estimadas]]="","",tblOrdenes[[#This Row],[horas_estimadas]]))) | O22: =IF(tblOrdenes[[#This Row],[orden]]="","",_xlfn.XLOOKUP(_xlfn.XLOOKUP(tblOrdenes[[#This Row],[id_operacion]],tblEjecucion[id_operacion],tblEjecucion[estado_sistema],""),tblEstados[estado_sistema],tblEstados[estado_normalizado],"Pendiente")) | P22: =IF(tblOrdenes[[#This Row],[fecha_inicio]]="","",YEAR(tblOrdenes[[#This Row],[fecha_inicio]]+4-WEEKDAY(tblOrdenes[[#This Row],[fecha_inicio]],2))&"-S"&TEXT(_xlfn.ISOWEEKNUM(tblOrdenes[[#This Row],[fecha_inicio]]),"00")) | Q22: =IF(tblOrdenes[[#This Row],[fecha_inicio]]="","",YEAR(tblOrdenes[[#This Row],[fecha_inicio]])) | R22: =IF(tblOrdenes[[#This Row],[fecha_inicio]]="","",MONTH(tblOrdenes[[#This Row],[fecha_inicio]])) | S22: =IF(tblOrdenes[[#This Row],[fecha_inicio]]="","",INDEX(lista_dias,WEEKDAY(tblOrdenes[[#This Row],[fecha_inicio]],2))) | T22: =IF(tblOrdenes[[#This Row],[tipo_ot]]="","",_xlfn.XLOOKUP(tblOrdenes[[#This Row],[tipo_ot]],tblTiposOT[codigo],tblTiposOT[clasificacion],"sin_clasificar")) | U22: =IF(tblOrdenes[[#This Row],[centro_costo]]="","",_xlfn.XLOOKUP(tblOrdenes[[#This Row],[centro_costo]],tblCECO[codigo],tblCECO[linea],"(sin catálogo)")) | V22: =IF(tblOrdenes[[#This Row],[centro_costo]]="","",_xlfn.XLOOKUP(tblOrdenes[[#This Row],[centro_costo]],tblCECO[codigo],tblCECO[area],"(sin catálogo)")) | W22: =IF(tblOrdenes[[#This Row],[centro_costo]]="","",_xlfn.XLOOKUP(tblOrdenes[[#This Row],[centro_costo]],tblCECO[codigo],tblCECO[coordinador],"(sin catálogo)")) | X22: =IF(tblOrdenes[[#This Row],[puesto_trabajo]]="","",_xlfn.XLOOKUP(tblOrdenes[[#This Row],[puesto_trabajo]],tblPuestos[codigo],tblPuestos[especialidad],"(sin catálogo)")) | Y22: =IF(tblOrdenes[[#This Row],[cod_actividad]]="","",_xlfn.XLOOKUP(tblOrdenes[[#This Row],[cod_actividad]],tblActividades[codigo],tblActividades[descripcion],"(sin catálogo)")) | Z22: =IF(tblOrdenes[[#This Row],[fecha_inicio]]="","",TODAY()-tblOrdenes[[#This Row],[fecha_inicio]]) | AA22: =IF(tblOrdenes[[#This Row],[backlog_dias]]="","",IF(tblOrdenes[[#This Row],[backlog_dias]]<0,"FUTURO",IF(tblOrdenes[[#This Row],[backlog_dias]]>p_dias_backlog_max,"BACKLOG","MES CORRIENTE"))) | AB22: =IF(tblOrdenes[[#This Row],[backlog_dias]]="",FALSE,AND(tblOrdenes[[#This Row],[backlog_dias]]>p_dias_backlog_min,tblOrdenes[[#This Row],[backlog_dias]]<=p_dias_backlog_max)) | AC22: Técnico 03 | AD22: =IF(tblOrdenes[[#This Row],[tecnico_asignado]]="","",_xlfn.XLOOKUP(tblOrdenes[[#This Row],[semana]]&"|"&tblOrdenes[[#This Row],[dia_semana]]&"|"&tblOrdenes[[#This Row],[tecnico_asignado]],tblAsignaciones[clave],tblAsignaciones[turno],"")) | AE22: =IF(tblOrdenes[[#This Row],[tecnico_asignado]]="","",SUMIFS(tblOrdenes[horas_efectivas],tblOrdenes[tecnico_asignado],tblOrdenes[[#This Row],[tecnico_asignado]],tblOrdenes[semana],tblOrdenes[[#This Row],[semana]],tblOrdenes[dia_semana],tblOrdenes[[#This Row],[dia_semana]])) | AF22: =IF(tblOrdenes[[#This Row],[HHA]]="","",p_factor_productividad*_xlfn.XLOOKUP(tblOrdenes[[#This Row],[semana]]&"|"&tblOrdenes[[#This Row],[dia_semana]]&"|"&tblOrdenes[[#This Row],[tecnico_asignado]],tblAsignaciones[clave],tblAsignaciones[horas_disponibles],0)-tblOrdenes[[#This Row],[HHA]]) | AG22: =IF(tblOrdenes[[#This Row],[orden]]="","",_xlfn.XLOOKUP(tblOrdenes[[#This Row],[id_operacion]],tblEjecucion[id_operacion],tblEjecucion[precio],0)) | AH22: =IF(tblOrdenes[[#This Row],[orden]]="","",MAX(0,_xlfn.XLOOKUP(tblOrdenes[[#This Row],[id_operacion]],tblEjecucion[id_operacion],tblEjecucion[costo_plan_total],0)-tblOrdenes[[#This Row],[costo_servicio]])) | AI22: =IF(tblOrdenes[[#This Row],[orden]]="","",tblOrdenes[[#This Row],[costo_servicio]]+tblOrdenes[[#This Row],[costo_materiales]]) | AL22: ACT-02.pdf | AM22: =IF(tblOrdenes[[#This Row],[link_checklist]]="","",HYPERLINK(p_ruta_base_checklists&tblOrdenes[[#This Row],[link_checklist]],"abrir")) | AO22: =IF(tblOrdenes[[#This Row],[orden]]="","",tblOrdenes[[#This Row],[orden]]&IF(tblOrdenes[[#This Row],[operacion]]="","0010",tblOrdenes[[#This Row],[operacion]]))
A23: OT-000020 | B23: 0010 | C23: Análisis predictivo — EQ-106 | D23: Análisis predictivo en EQ-106 | E23: EQ-106 | F23: CC-210 | G23: PU-MEC | H23: ACT-04 | I23: TIPO-P1 | J23: 46227 | K23: 8 | L23: 200 | N23: =IF(tblOrdenes[[#This Row],[orden]]="","",IF(tblOrdenes[[#This Row],[horas_ajustadas]]<>"",tblOrdenes[[#This Row],[horas_ajustadas]],IF(tblOrdenes[[#This Row],[horas_estimadas]]="","",tblOrdenes[[#This Row],[horas_estimadas]]))) | O23: =IF(tblOrdenes[[#This Row],[orden]]="","",_xlfn.XLOOKUP(_xlfn.XLOOKUP(tblOrdenes[[#This Row],[id_operacion]],tblEjecucion[id_operacion],tblEjecucion[estado_sistema],""),tblEstados[estado_sistema],tblEstados[estado_normalizado],"Pendiente")) | P23: =IF(tblOrdenes[[#This Row],[fecha_inicio]]="","",YEAR(tblOrdenes[[#This Row],[fecha_inicio]]+4-WEEKDAY(tblOrdenes[[#This Row],[fecha_inicio]],2))&"-S"&TEXT(_xlfn.ISOWEEKNUM(tblOrdenes[[#This Row],[fecha_inicio]]),"00")) | Q23: =IF(tblOrdenes[[#This Row],[fecha_inicio]]="","",YEAR(tblOrdenes[[#This Row],[fecha_inicio]])) | R23: =IF(tblOrdenes[[#This Row],[fecha_inicio]]="","",MONTH(tblOrdenes[[#This Row],[fecha_inicio]])) | S23: =IF(tblOrdenes[[#This Row],[fecha_inicio]]="","",INDEX(lista_dias,WEEKDAY(tblOrdenes[[#This Row],[fecha_inicio]],2))) | T23: =IF(tblOrdenes[[#This Row],[tipo_ot]]="","",_xlfn.XLOOKUP(tblOrdenes[[#This Row],[tipo_ot]],tblTiposOT[codigo],tblTiposOT[clasificacion],"sin_clasificar")) | U23: =IF(tblOrdenes[[#This Row],[centro_costo]]="","",_xlfn.XLOOKUP(tblOrdenes[[#This Row],[centro_costo]],tblCECO[codigo],tblCECO[linea],"(sin catálogo)")) | V23: =IF(tblOrdenes[[#This Row],[centro_costo]]="","",_xlfn.XLOOKUP(tblOrdenes[[#This Row],[centro_costo]],tblCECO[codigo],tblCECO[area],"(sin catálogo)")) | W23: =IF(tblOrdenes[[#This Row],[centro_costo]]="","",_xlfn.XLOOKUP(tblOrdenes[[#This Row],[centro_costo]],tblCECO[codigo],tblCECO[coordinador],"(sin catálogo)")) | X23: =IF(tblOrdenes[[#This Row],[puesto_trabajo]]="","",_xlfn.XLOOKUP(tblOrdenes[[#This Row],[puesto_trabajo]],tblPuestos[codigo],tblPuestos[especialidad],"(sin catálogo)")) | Y23: =IF(tblOrdenes[[#This Row],[cod_actividad]]="","",_xlfn.XLOOKUP(tblOrdenes[[#This Row],[cod_actividad]],tblActividades[codigo],tblActividades[descripcion],"(sin catálogo)")) | Z23: =IF(tblOrdenes[[#This Row],[fecha_inicio]]="","",TODAY()-tblOrdenes[[#This Row],[fecha_inicio]]) | AA23: =IF(tblOrdenes[[#This Row],[backlog_dias]]="","",IF(tblOrdenes[[#This Row],[backlog_dias]]<0,"FUTURO",IF(tblOrdenes[[#This Row],[backlog_dias]]>p_dias_backlog_max,"BACKLOG","MES CORRIENTE"))) | AB23: =IF(tblOrdenes[[#This Row],[backlog_dias]]="",FALSE,AND(tblOrdenes[[#This Row],[backlog_dias]]>p_dias_backlog_min,tblOrdenes[[#This Row],[backlog_dias]]<=p_dias_backlog_max)) | AC23: Técnico 04 | AD23: =IF(tblOrdenes[[#This Row],[tecnico_asignado]]="","",_xlfn.XLOOKUP(tblOrdenes[[#This Row],[semana]]&"|"&tblOrdenes[[#This Row],[dia_semana]]&"|"&tblOrdenes[[#This Row],[tecnico_asignado]],tblAsignaciones[clave],tblAsignaciones[turno],"")) | AE23: =IF(tblOrdenes[[#This Row],[tecnico_asignado]]="","",SUMIFS(tblOrdenes[horas_efectivas],tblOrdenes[tecnico_asignado],tblOrdenes[[#This Row],[tecnico_asignado]],tblOrdenes[semana],tblOrdenes[[#This Row],[semana]],tblOrdenes[dia_semana],tblOrdenes[[#This Row],[dia_semana]])) | AF23: =IF(tblOrdenes[[#This Row],[HHA]]="","",p_factor_productividad*_xlfn.XLOOKUP(tblOrdenes[[#This Row],[semana]]&"|"&tblOrdenes[[#This Row],[dia_semana]]&"|"&tblOrdenes[[#This Row],[tecnico_asignado]],tblAsignaciones[clave],tblAsignaciones[horas_disponibles],0)-tblOrdenes[[#This Row],[HHA]]) | AG23: =IF(tblOrdenes[[#This Row],[orden]]="","",_xlfn.XLOOKUP(tblOrdenes[[#This Row],[id_operacion]],tblEjecucion[id_operacion],tblEjecucion[precio],0)) | AH23: =IF(tblOrdenes[[#This Row],[orden]]="","",MAX(0,_xlfn.XLOOKUP(tblOrdenes[[#This Row],[id_operacion]],tblEjecucion[id_operacion],tblEjecucion[costo_plan_total],0)-tblOrdenes[[#This Row],[costo_servicio]])) | AI23: =IF(tblOrdenes[[#This Row],[orden]]="","",tblOrdenes[[#This Row],[costo_servicio]]+tblOrdenes[[#This Row],[costo_materiales]]) | AL23: ACT-04.pdf | AM23: =IF(tblOrdenes[[#This Row],[link_checklist]]="","",HYPERLINK(p_ruta_base_checklists&tblOrdenes[[#This Row],[link_checklist]],"abrir")) | AO23: =IF(tblOrdenes[[#This Row],[orden]]="","",tblOrdenes[[#This Row],[orden]]&IF(tblOrdenes[[#This Row],[operacion]]="","0010",tblOrdenes[[#This Row],[operacion]]))
A24: OT-000021 | B24: 0010 | C24: Inspección de rutina — EQ-110 | D24: Inspección de rutina en EQ-110 | E24: EQ-110 | F24: CC-310 | G24: PU-MEC | H24: ACT-01 | I24: TIPO-P2 | J24: 46223 | K24: 6 | L24: 150 | N24: =IF(tblOrdenes[[#This Row],[orden]]="","",IF(tblOrdenes[[#This Row],[horas_ajustadas]]<>"",tblOrdenes[[#This Row],[horas_ajustadas]],IF(tblOrdenes[[#This Row],[horas_estimadas]]="","",tblOrdenes[[#This Row],[horas_estimadas]]))) | O24: =IF(tblOrdenes[[#This Row],[orden]]="","",_xlfn.XLOOKUP(_xlfn.XLOOKUP(tblOrdenes[[#This Row],[id_operacion]],tblEjecucion[id_operacion],tblEjecucion[estado_sistema],""),tblEstados[estado_sistema],tblEstados[estado_normalizado],"Pendiente")) | P24: =IF(tblOrdenes[[#This Row],[fecha_inicio]]="","",YEAR(tblOrdenes[[#This Row],[fecha_inicio]]+4-WEEKDAY(tblOrdenes[[#This Row],[fecha_inicio]],2))&"-S"&TEXT(_xlfn.ISOWEEKNUM(tblOrdenes[[#This Row],[fecha_inicio]]),"00")) | Q24: =IF(tblOrdenes[[#This Row],[fecha_inicio]]="","",YEAR(tblOrdenes[[#This Row],[fecha_inicio]])) | R24: =IF(tblOrdenes[[#This Row],[fecha_inicio]]="","",MONTH(tblOrdenes[[#This Row],[fecha_inicio]])) | S24: =IF(tblOrdenes[[#This Row],[fecha_inicio]]="","",INDEX(lista_dias,WEEKDAY(tblOrdenes[[#This Row],[fecha_inicio]],2))) | T24: =IF(tblOrdenes[[#This Row],[tipo_ot]]="","",_xlfn.XLOOKUP(tblOrdenes[[#This Row],[tipo_ot]],tblTiposOT[codigo],tblTiposOT[clasificacion],"sin_clasificar")) | U24: =IF(tblOrdenes[[#This Row],[centro_costo]]="","",_xlfn.XLOOKUP(tblOrdenes[[#This Row],[centro_costo]],tblCECO[codigo],tblCECO[linea],"(sin catálogo)")) | V24: =IF(tblOrdenes[[#This Row],[centro_costo]]="","",_xlfn.XLOOKUP(tblOrdenes[[#This Row],[centro_costo]],tblCECO[codigo],tblCECO[area],"(sin catálogo)")) | W24: =IF(tblOrdenes[[#This Row],[centro_costo]]="","",_xlfn.XLOOKUP(tblOrdenes[[#This Row],[centro_costo]],tblCECO[codigo],tblCECO[coordinador],"(sin catálogo)")) | X24: =IF(tblOrdenes[[#This Row],[puesto_trabajo]]="","",_xlfn.XLOOKUP(tblOrdenes[[#This Row],[puesto_trabajo]],tblPuestos[codigo],tblPuestos[especialidad],"(sin catálogo)")) | Y24: =IF(tblOrdenes[[#This Row],[cod_actividad]]="","",_xlfn.XLOOKUP(tblOrdenes[[#This Row],[cod_actividad]],tblActividades[codigo],tblActividades[descripcion],"(sin catálogo)")) | Z24: =IF(tblOrdenes[[#This Row],[fecha_inicio]]="","",TODAY()-tblOrdenes[[#This Row],[fecha_inicio]]) | AA24: =IF(tblOrdenes[[#This Row],[backlog_dias]]="","",IF(tblOrdenes[[#This Row],[backlog_dias]]<0,"FUTURO",IF(tblOrdenes[[#This Row],[backlog_dias]]>p_dias_backlog_max,"BACKLOG","MES CORRIENTE"))) | AB24: =IF(tblOrdenes[[#This Row],[backlog_dias]]="",FALSE,AND(tblOrdenes[[#This Row],[backlog_dias]]>p_dias_backlog_min,tblOrdenes[[#This Row],[backlog_dias]]<=p_dias_backlog_max)) | AC24: Técnico 01 | AD24: =IF(tblOrdenes[[#This Row],[tecnico_asignado]]="","",_xlfn.XLOOKUP(tblOrdenes[[#This Row],[semana]]&"|"&tblOrdenes[[#This Row],[dia_semana]]&"|"&tblOrdenes[[#This Row],[tecnico_asignado]],tblAsignaciones[clave],tblAsignaciones[turno],"")) | AE24: =IF(tblOrdenes[[#This Row],[tecnico_asignado]]="","",SUMIFS(tblOrdenes[horas_efectivas],tblOrdenes[tecnico_asignado],tblOrdenes[[#This Row],[tecnico_asignado]],tblOrdenes[semana],tblOrdenes[[#This Row],[semana]],tblOrdenes[dia_semana],tblOrdenes[[#This Row],[dia_semana]])) | AF24: =IF(tblOrdenes[[#This Row],[HHA]]="","",p_factor_productividad*_xlfn.XLOOKUP(tblOrdenes[[#This Row],[semana]]&"|"&tblOrdenes[[#This Row],[dia_semana]]&"|"&tblOrdenes[[#This Row],[tecnico_asignado]],tblAsignaciones[clave],tblAsignaciones[horas_disponibles],0)-tblOrdenes[[#This Row],[HHA]]) | AG24: =IF(tblOrdenes[[#This Row],[orden]]="","",_xlfn.XLOOKUP(tblOrdenes[[#This Row],[id_operacion]],tblEjecucion[id_operacion],tblEjecucion[precio],0)) | AH24: =IF(tblOrdenes[[#This Row],[orden]]="","",MAX(0,_xlfn.XLOOKUP(tblOrdenes[[#This Row],[id_operacion]],tblEjecucion[id_operacion],tblEjecucion[costo_plan_total],0)-tblOrdenes[[#This Row],[costo_servicio]])) | AI24: =IF(tblOrdenes[[#This Row],[orden]]="","",tblOrdenes[[#This Row],[costo_servicio]]+tblOrdenes[[#This Row],[costo_materiales]]) | AL24: ACT-01.pdf | AM24: =IF(tblOrdenes[[#This Row],[link_checklist]]="","",HYPERLINK(p_ruta_base_checklists&tblOrdenes[[#This Row],[link_checklist]],"abrir")) | AO24: =IF(tblOrdenes[[#This Row],[orden]]="","",tblOrdenes[[#This Row],[orden]]&IF(tblOrdenes[[#This Row],[operacion]]="","0010",tblOrdenes[[#This Row],[operacion]]))
A25: OT-000022 | B25: 0010 | C25: Lubricación programada — EQ-103 | D25: Lubricación programada en EQ-103 | E25: EQ-103 | F25: CC-110 | G25: PU-MEC | H25: ACT-02 | I25: TIPO-P1 | J25: 46224 | K25: 8 | L25: 200 | N25: =IF(tblOrdenes[[#This Row],[orden]]="","",IF(tblOrdenes[[#This Row],[horas_ajustadas]]<>"",tblOrdenes[[#This Row],[horas_ajustadas]],IF(tblOrdenes[[#This Row],[horas_estimadas]]="","",tblOrdenes[[#This Row],[horas_estimadas]]))) | O25: =IF(tblOrdenes[[#This Row],[orden]]="","",_xlfn.XLOOKUP(_xlfn.XLOOKUP(tblOrdenes[[#This Row],[id_operacion]],tblEjecucion[id_operacion],tblEjecucion[estado_sistema],""),tblEstados[estado_sistema],tblEstados[estado_normalizado],"Pendiente")) | P25: =IF(tblOrdenes[[#This Row],[fecha_inicio]]="","",YEAR(tblOrdenes[[#This Row],[fecha_inicio]]+4-WEEKDAY(tblOrdenes[[#This Row],[fecha_inicio]],2))&"-S"&TEXT(_xlfn.ISOWEEKNUM(tblOrdenes[[#This Row],[fecha_inicio]]),"00")) | Q25: =IF(tblOrdenes[[#This Row],[fecha_inicio]]="","",YEAR(tblOrdenes[[#This Row],[fecha_inicio]])) | R25: =IF(tblOrdenes[[#This Row],[fecha_inicio]]="","",MONTH(tblOrdenes[[#This Row],[fecha_inicio]])) | S25: =IF(tblOrdenes[[#This Row],[fecha_inicio]]="","",INDEX(lista_dias,WEEKDAY(tblOrdenes[[#This Row],[fecha_inicio]],2))) | T25: =IF(tblOrdenes[[#This Row],[tipo_ot]]="","",_xlfn.XLOOKUP(tblOrdenes[[#This Row],[tipo_ot]],tblTiposOT[codigo],tblTiposOT[clasificacion],"sin_clasificar")) | U25: =IF(tblOrdenes[[#This Row],[centro_costo]]="","",_xlfn.XLOOKUP(tblOrdenes[[#This Row],[centro_costo]],tblCECO[codigo],tblCECO[linea],"(sin catálogo)")) | V25: =IF(tblOrdenes[[#This Row],[centro_costo]]="","",_xlfn.XLOOKUP(tblOrdenes[[#This Row],[centro_costo]],tblCECO[codigo],tblCECO[area],"(sin catálogo)")) | W25: =IF(tblOrdenes[[#This Row],[centro_costo]]="","",_xlfn.XLOOKUP(tblOrdenes[[#This Row],[centro_costo]],tblCECO[codigo],tblCECO[coordinador],"(sin catálogo)")) | X25: =IF(tblOrdenes[[#This Row],[puesto_trabajo]]="","",_xlfn.XLOOKUP(tblOrdenes[[#This Row],[puesto_trabajo]],tblPuestos[codigo],tblPuestos[especialidad],"(sin catálogo)")) | Y25: =IF(tblOrdenes[[#This Row],[cod_actividad]]="","",_xlfn.XLOOKUP(tblOrdenes[[#This Row],[cod_actividad]],tblActividades[codigo],tblActividades[descripcion],"(sin catálogo)")) | Z25: =IF(tblOrdenes[[#This Row],[fecha_inicio]]="","",TODAY()-tblOrdenes[[#This Row],[fecha_inicio]]) | AA25: =IF(tblOrdenes[[#This Row],[backlog_dias]]="","",IF(tblOrdenes[[#This Row],[backlog_dias]]<0,"FUTURO",IF(tblOrdenes[[#This Row],[backlog_dias]]>p_dias_backlog_max,"BACKLOG","MES CORRIENTE"))) | AB25: =IF(tblOrdenes[[#This Row],[backlog_dias]]="",FALSE,AND(tblOrdenes[[#This Row],[backlog_dias]]>p_dias_backlog_min,tblOrdenes[[#This Row],[backlog_dias]]<=p_dias_backlog_max)) | AC25: Técnico 02 | AD25: =IF(tblOrdenes[[#This Row],[tecnico_asignado]]="","",_xlfn.XLOOKUP(tblOrdenes[[#This Row],[semana]]&"|"&tblOrdenes[[#This Row],[dia_semana]]&"|"&tblOrdenes[[#This Row],[tecnico_asignado]],tblAsignaciones[clave],tblAsignaciones[turno],"")) | AE25: =IF(tblOrdenes[[#This Row],[tecnico_asignado]]="","",SUMIFS(tblOrdenes[horas_efectivas],tblOrdenes[tecnico_asignado],tblOrdenes[[#This Row],[tecnico_asignado]],tblOrdenes[semana],tblOrdenes[[#This Row],[semana]],tblOrdenes[dia_semana],tblOrdenes[[#This Row],[dia_semana]])) | AF25: =IF(tblOrdenes[[#This Row],[HHA]]="","",p_factor_productividad*_xlfn.XLOOKUP(tblOrdenes[[#This Row],[semana]]&"|"&tblOrdenes[[#This Row],[dia_semana]]&"|"&tblOrdenes[[#This Row],[tecnico_asignado]],tblAsignaciones[clave],tblAsignaciones[horas_disponibles],0)-tblOrdenes[[#This Row],[HHA]]) | AG25: =IF(tblOrdenes[[#This Row],[orden]]="","",_xlfn.XLOOKUP(tblOrdenes[[#This Row],[id_operacion]],tblEjecucion[id_operacion],tblEjecucion[precio],0)) | AH25: =IF(tblOrdenes[[#This Row],[orden]]="","",MAX(0,_xlfn.XLOOKUP(tblOrdenes[[#This Row],[id_operacion]],tblEjecucion[id_operacion],tblEjecucion[costo_plan_total],0)-tblOrdenes[[#This Row],[costo_servicio]])) | AI25: =IF(tblOrdenes[[#This Row],[orden]]="","",tblOrdenes[[#This Row],[costo_servicio]]+tblOrdenes[[#This Row],[costo_materiales]]) | AL25: ACT-02.pdf | AM25: =IF(tblOrdenes[[#This Row],[link_checklist]]="","",HYPERLINK(p_ruta_base_checklists&tblOrdenes[[#This Row],[link_checklist]],"abrir")) | AO25: =IF(tblOrdenes[[#This Row],[orden]]="","",tblOrdenes[[#This Row],[orden]]&IF(tblOrdenes[[#This Row],[operacion]]="","0010",tblOrdenes[[#This Row],[operacion]]))
A26: OT-000023 | B26: 0010 | C26: Reparación de falla — EQ-109 | D26: Reparación de falla en EQ-109 | E26: EQ-109 | F26: CC-210 | G26: PU-MEC | H26: ACT-03 | I26: TIPO-C2 | J26: 46225 | K26: 10 | L26: 400 | N26: =IF(tblOrdenes[[#This Row],[orden]]="","",IF(tblOrdenes[[#This Row],[horas_ajustadas]]<>"",tblOrdenes[[#This Row],[horas_ajustadas]],IF(tblOrdenes[[#This Row],[horas_estimadas]]="","",tblOrdenes[[#This Row],[horas_estimadas]]))) | O26: =IF(tblOrdenes[[#This Row],[orden]]="","",_xlfn.XLOOKUP(_xlfn.XLOOKUP(tblOrdenes[[#This Row],[id_operacion]],tblEjecucion[id_operacion],tblEjecucion[estado_sistema],""),tblEstados[estado_sistema],tblEstados[estado_normalizado],"Pendiente")) | P26: =IF(tblOrdenes[[#This Row],[fecha_inicio]]="","",YEAR(tblOrdenes[[#This Row],[fecha_inicio]]+4-WEEKDAY(tblOrdenes[[#This Row],[fecha_inicio]],2))&"-S"&TEXT(_xlfn.ISOWEEKNUM(tblOrdenes[[#This Row],[fecha_inicio]]),"00")) | Q26: =IF(tblOrdenes[[#This Row],[fecha_inicio]]="","",YEAR(tblOrdenes[[#This Row],[fecha_inicio]])) | R26: =IF(tblOrdenes[[#This Row],[fecha_inicio]]="","",MONTH(tblOrdenes[[#This Row],[fecha_inicio]])) | S26: =IF(tblOrdenes[[#This Row],[fecha_inicio]]="","",INDEX(lista_dias,WEEKDAY(tblOrdenes[[#This Row],[fecha_inicio]],2))) | T26: =IF(tblOrdenes[[#This Row],[tipo_ot]]="","",_xlfn.XLOOKUP(tblOrdenes[[#This Row],[tipo_ot]],tblTiposOT[codigo],tblTiposOT[clasificacion],"sin_clasificar")) | U26: =IF(tblOrdenes[[#This Row],[centro_costo]]="","",_xlfn.XLOOKUP(tblOrdenes[[#This Row],[centro_costo]],tblCECO[codigo],tblCECO[linea],"(sin catálogo)")) | V26: =IF(tblOrdenes[[#This Row],[centro_costo]]="","",_xlfn.XLOOKUP(tblOrdenes[[#This Row],[centro_costo]],tblCECO[codigo],tblCECO[area],"(sin catálogo)")) | W26: =IF(tblOrdenes[[#This Row],[centro_costo]]="","",_xlfn.XLOOKUP(tblOrdenes[[#This Row],[centro_costo]],tblCECO[codigo],tblCECO[coordinador],"(sin catálogo)")) | X26: =IF(tblOrdenes[[#This Row],[puesto_trabajo]]="","",_xlfn.XLOOKUP(tblOrdenes[[#This Row],[puesto_trabajo]],tblPuestos[codigo],tblPuestos[especialidad],"(sin catálogo)")) | Y26: =IF(tblOrdenes[[#This Row],[cod_actividad]]="","",_xlfn.XLOOKUP(tblOrdenes[[#This Row],[cod_actividad]],tblActividades[codigo],tblActividades[descripcion],"(sin catálogo)")) | Z26: =IF(tblOrdenes[[#This Row],[fecha_inicio]]="","",TODAY()-tblOrdenes[[#This Row],[fecha_inicio]]) | AA26: =IF(tblOrdenes[[#This Row],[backlog_dias]]="","",IF(tblOrdenes[[#This Row],[backlog_dias]]<0,"FUTURO",IF(tblOrdenes[[#This Row],[backlog_dias]]>p_dias_backlog_max,"BACKLOG","MES CORRIENTE"))) | AB26: =IF(tblOrdenes[[#This Row],[backlog_dias]]="",FALSE,AND(tblOrdenes[[#This Row],[backlog_dias]]>p_dias_backlog_min,tblOrdenes[[#This Row],[backlog_dias]]<=p_dias_backlog_max)) | AC26: Técnico 03 | AD26: =IF(tblOrdenes[[#This Row],[tecnico_asignado]]="","",_xlfn.XLOOKUP(tblOrdenes[[#This Row],[semana]]&"|"&tblOrdenes[[#This Row],[dia_semana]]&"|"&tblOrdenes[[#This Row],[tecnico_asignado]],tblAsignaciones[clave],tblAsignaciones[turno],"")) | AE26: =IF(tblOrdenes[[#This Row],[tecnico_asignado]]="","",SUMIFS(tblOrdenes[horas_efectivas],tblOrdenes[tecnico_asignado],tblOrdenes[[#This Row],[tecnico_asignado]],tblOrdenes[semana],tblOrdenes[[#This Row],[semana]],tblOrdenes[dia_semana],tblOrdenes[[#This Row],[dia_semana]])) | AF26: =IF(tblOrdenes[[#This Row],[HHA]]="","",p_factor_productividad*_xlfn.XLOOKUP(tblOrdenes[[#This Row],[semana]]&"|"&tblOrdenes[[#This Row],[dia_semana]]&"|"&tblOrdenes[[#This Row],[tecnico_asignado]],tblAsignaciones[clave],tblAsignaciones[horas_disponibles],0)-tblOrdenes[[#This Row],[HHA]]) | AG26: =IF(tblOrdenes[[#This Row],[orden]]="","",_xlfn.XLOOKUP(tblOrdenes[[#This Row],[id_operacion]],tblEjecucion[id_operacion],tblEjecucion[precio],0)) | AH26: =IF(tblOrdenes[[#This Row],[orden]]="","",MAX(0,_xlfn.XLOOKUP(tblOrdenes[[#This Row],[id_operacion]],tblEjecucion[id_operacion],tblEjecucion[costo_plan_total],0)-tblOrdenes[[#This Row],[costo_servicio]])) | AI26: =IF(tblOrdenes[[#This Row],[orden]]="","",tblOrdenes[[#This Row],[costo_servicio]]+tblOrdenes[[#This Row],[costo_materiales]]) | AM26: =IF(tblOrdenes[[#This Row],[link_checklist]]="","",HYPERLINK(p_ruta_base_checklists&tblOrdenes[[#This Row],[link_checklist]],"abrir")) | AO26: =IF(tblOrdenes[[#This Row],[orden]]="","",tblOrdenes[[#This Row],[orden]]&IF(tblOrdenes[[#This Row],[operacion]]="","0010",tblOrdenes[[#This Row],[operacion]]))
A27: OT-000024 | B27: 0010 | C27: Reparación de falla — EQ-110 | D27: Reparación de falla en EQ-110 | E27: EQ-110 | F27: CC-310 | G27: PU-MEC | H27: ACT-03 | I27: TIPO-C1 | J27: 46226 | K27: 8 | L27: 320 | N27: =IF(tblOrdenes[[#This Row],[orden]]="","",IF(tblOrdenes[[#This Row],[horas_ajustadas]]<>"",tblOrdenes[[#This Row],[horas_ajustadas]],IF(tblOrdenes[[#This Row],[horas_estimadas]]="","",tblOrdenes[[#This Row],[horas_estimadas]]))) | O27: =IF(tblOrdenes[[#This Row],[orden]]="","",_xlfn.XLOOKUP(_xlfn.XLOOKUP(tblOrdenes[[#This Row],[id_operacion]],tblEjecucion[id_operacion],tblEjecucion[estado_sistema],""),tblEstados[estado_sistema],tblEstados[estado_normalizado],"Pendiente")) | P27: =IF(tblOrdenes[[#This Row],[fecha_inicio]]="","",YEAR(tblOrdenes[[#This Row],[fecha_inicio]]+4-WEEKDAY(tblOrdenes[[#This Row],[fecha_inicio]],2))&"-S"&TEXT(_xlfn.ISOWEEKNUM(tblOrdenes[[#This Row],[fecha_inicio]]),"00")) | Q27: =IF(tblOrdenes[[#This Row],[fecha_inicio]]="","",YEAR(tblOrdenes[[#This Row],[fecha_inicio]])) | R27: =IF(tblOrdenes[[#This Row],[fecha_inicio]]="","",MONTH(tblOrdenes[[#This Row],[fecha_inicio]])) | S27: =IF(tblOrdenes[[#This Row],[fecha_inicio]]="","",INDEX(lista_dias,WEEKDAY(tblOrdenes[[#This Row],[fecha_inicio]],2))) | T27: =IF(tblOrdenes[[#This Row],[tipo_ot]]="","",_xlfn.XLOOKUP(tblOrdenes[[#This Row],[tipo_ot]],tblTiposOT[codigo],tblTiposOT[clasificacion],"sin_clasificar")) | U27: =IF(tblOrdenes[[#This Row],[centro_costo]]="","",_xlfn.XLOOKUP(tblOrdenes[[#This Row],[centro_costo]],tblCECO[codigo],tblCECO[linea],"(sin catálogo)")) | V27: =IF(tblOrdenes[[#This Row],[centro_costo]]="","",_xlfn.XLOOKUP(tblOrdenes[[#This Row],[centro_costo]],tblCECO[codigo],tblCECO[area],"(sin catálogo)")) | W27: =IF(tblOrdenes[[#This Row],[centro_costo]]="","",_xlfn.XLOOKUP(tblOrdenes[[#This Row],[centro_costo]],tblCECO[codigo],tblCECO[coordinador],"(sin catálogo)")) | X27: =IF(tblOrdenes[[#This Row],[puesto_trabajo]]="","",_xlfn.XLOOKUP(tblOrdenes[[#This Row],[puesto_trabajo]],tblPuestos[codigo],tblPuestos[especialidad],"(sin catálogo)")) | Y27: =IF(tblOrdenes[[#This Row],[cod_actividad]]="","",_xlfn.XLOOKUP(tblOrdenes[[#This Row],[cod_actividad]],tblActividades[codigo],tblActividades[descripcion],"(sin catálogo)")) | Z27: =IF(tblOrdenes[[#This Row],[fecha_inicio]]="","",TODAY()-tblOrdenes[[#This Row],[fecha_inicio]]) | AA27: =IF(tblOrdenes[[#This Row],[backlog_dias]]="","",IF(tblOrdenes[[#This Row],[backlog_dias]]<0,"FUTURO",IF(tblOrdenes[[#This Row],[backlog_dias]]>p_dias_backlog_max,"BACKLOG","MES CORRIENTE"))) | AB27: =IF(tblOrdenes[[#This Row],[backlog_dias]]="",FALSE,AND(tblOrdenes[[#This Row],[backlog_dias]]>p_dias_backlog_min,tblOrdenes[[#This Row],[backlog_dias]]<=p_dias_backlog_max)) | AD27: =IF(tblOrdenes[[#This Row],[tecnico_asignado]]="","",_xlfn.XLOOKUP(tblOrdenes[[#This Row],[semana]]&"|"&tblOrdenes[[#This Row],[dia_semana]]&"|"&tblOrdenes[[#This Row],[tecnico_asignado]],tblAsignaciones[clave],tblAsignaciones[turno],"")) | AE27: =IF(tblOrdenes[[#This Row],[tecnico_asignado]]="","",SUMIFS(tblOrdenes[horas_efectivas],tblOrdenes[tecnico_asignado],tblOrdenes[[#This Row],[tecnico_asignado]],tblOrdenes[semana],tblOrdenes[[#This Row],[semana]],tblOrdenes[dia_semana],tblOrdenes[[#This Row],[dia_semana]])) | AF27: =IF(tblOrdenes[[#This Row],[HHA]]="","",p_factor_productividad*_xlfn.XLOOKUP(tblOrdenes[[#This Row],[semana]]&"|"&tblOrdenes[[#This Row],[dia_semana]]&"|"&tblOrdenes[[#This Row],[tecnico_asignado]],tblAsignaciones[clave],tblAsignaciones[horas_disponibles],0)-tblOrdenes[[#This Row],[HHA]]) | AG27: =IF(tblOrdenes[[#This Row],[orden]]="","",_xlfn.XLOOKUP(tblOrdenes[[#This Row],[id_operacion]],tblEjecucion[id_operacion],tblEjecucion[precio],0)) | AH27: =IF(tblOrdenes[[#This Row],[orden]]="","",MAX(0,_xlfn.XLOOKUP(tblOrdenes[[#This Row],[id_operacion]],tblEjecucion[id_operacion],tblEjecucion[costo_plan_total],0)-tblOrdenes[[#This Row],[costo_servicio]])) | AI27: =IF(tblOrdenes[[#This Row],[orden]]="","",tblOrdenes[[#This Row],[costo_servicio]]+tblOrdenes[[#This Row],[costo_materiales]]) | AJ27: PT-CALIENTE | AK27: LOTO | AM27: =IF(tblOrdenes[[#This Row],[link_checklist]]="","",HYPERLINK(p_ruta_base_checklists&tblOrdenes[[#This Row],[link_checklist]],"abrir")) | AO27: =IF(tblOrdenes[[#This Row],[orden]]="","",tblOrdenes[[#This Row],[orden]]&IF(tblOrdenes[[#This Row],[operacion]]="","0010",tblOrdenes[[#This Row],[operacion]]))
A28: OT-000025 | B28: 0010 | C28: Reparación de falla — EQ-101 | D28: Reparación de falla en EQ-101 | E28: EQ-101 | F28: CC-110 | G28: PU-MEC | H28: ACT-03 | I28: TIPO-C2 | J28: 46227 | K28: 7 | L28: 280 | N28: =IF(tblOrdenes[[#This Row],[orden]]="","",IF(tblOrdenes[[#This Row],[horas_ajustadas]]<>"",tblOrdenes[[#This Row],[horas_ajustadas]],IF(tblOrdenes[[#This Row],[horas_estimadas]]="","",tblOrdenes[[#This Row],[horas_estimadas]]))) | O28: =IF(tblOrdenes[[#This Row],[orden]]="","",_xlfn.XLOOKUP(_xlfn.XLOOKUP(tblOrdenes[[#This Row],[id_operacion]],tblEjecucion[id_operacion],tblEjecucion[estado_sistema],""),tblEstados[estado_sistema],tblEstados[estado_normalizado],"Pendiente")) | P28: =IF(tblOrdenes[[#This Row],[fecha_inicio]]="","",YEAR(tblOrdenes[[#This Row],[fecha_inicio]]+4-WEEKDAY(tblOrdenes[[#This Row],[fecha_inicio]],2))&"-S"&TEXT(_xlfn.ISOWEEKNUM(tblOrdenes[[#This Row],[fecha_inicio]]),"00")) | Q28: =IF(tblOrdenes[[#This Row],[fecha_inicio]]="","",YEAR(tblOrdenes[[#This Row],[fecha_inicio]])) | R28: =IF(tblOrdenes[[#This Row],[fecha_inicio]]="","",MONTH(tblOrdenes[[#This Row],[fecha_inicio]])) | S28: =IF(tblOrdenes[[#This Row],[fecha_inicio]]="","",INDEX(lista_dias,WEEKDAY(tblOrdenes[[#This Row],[fecha_inicio]],2))) | T28: =IF(tblOrdenes[[#This Row],[tipo_ot]]="","",_xlfn.XLOOKUP(tblOrdenes[[#This Row],[tipo_ot]],tblTiposOT[codigo],tblTiposOT[clasificacion],"sin_clasificar")) | U28: =IF(tblOrdenes[[#This Row],[centro_costo]]="","",_xlfn.XLOOKUP(tblOrdenes[[#This Row],[centro_costo]],tblCECO[codigo],tblCECO[linea],"(sin catálogo)")) | V28: =IF(tblOrdenes[[#This Row],[centro_costo]]="","",_xlfn.XLOOKUP(tblOrdenes[[#This Row],[centro_costo]],tblCECO[codigo],tblCECO[area],"(sin catálogo)")) | W28: =IF(tblOrdenes[[#This Row],[centro_costo]]="","",_xlfn.XLOOKUP(tblOrdenes[[#This Row],[centro_costo]],tblCECO[codigo],tblCECO[coordinador],"(sin catálogo)")) | X28: =IF(tblOrdenes[[#This Row],[puesto_trabajo]]="","",_xlfn.XLOOKUP(tblOrdenes[[#This Row],[puesto_trabajo]],tblPuestos[codigo],tblPuestos[especialidad],"(sin catálogo)")) | Y28: =IF(tblOrdenes[[#This Row],[cod_actividad]]="","",_xlfn.XLOOKUP(tblOrdenes[[#This Row],[cod_actividad]],tblActividades[codigo],tblActividades[descripcion],"(sin catálogo)")) | Z28: =IF(tblOrdenes[[#This Row],[fecha_inicio]]="","",TODAY()-tblOrdenes[[#This Row],[fecha_inicio]]) | AA28: =IF(tblOrdenes[[#This Row],[backlog_dias]]="","",IF(tblOrdenes[[#This Row],[backlog_dias]]<0,"FUTURO",IF(tblOrdenes[[#This Row],[backlog_dias]]>p_dias_backlog_max,"BACKLOG","MES CORRIENTE"))) | AB28: =IF(tblOrdenes[[#This Row],[backlog_dias]]="",FALSE,AND(tblOrdenes[[#This Row],[backlog_dias]]>p_dias_backlog_min,tblOrdenes[[#This Row],[backlog_dias]]<=p_dias_backlog_max)) | AC28: Técnico 01 | AD28: =IF(tblOrdenes[[#This Row],[tecnico_asignado]]="","",_xlfn.XLOOKUP(tblOrdenes[[#This Row],[semana]]&"|"&tblOrdenes[[#This Row],[dia_semana]]&"|"&tblOrdenes[[#This Row],[tecnico_asignado]],tblAsignaciones[clave],tblAsignaciones[turno],"")) | AE28: =IF(tblOrdenes[[#This Row],[tecnico_asignado]]="","",SUMIFS(tblOrdenes[horas_efectivas],tblOrdenes[tecnico_asignado],tblOrdenes[[#This Row],[tecnico_asignado]],tblOrdenes[semana],tblOrdenes[[#This Row],[semana]],tblOrdenes[dia_semana],tblOrdenes[[#This Row],[dia_semana]])) | AF28: =IF(tblOrdenes[[#This Row],[HHA]]="","",p_factor_productividad*_xlfn.XLOOKUP(tblOrdenes[[#This Row],[semana]]&"|"&tblOrdenes[[#This Row],[dia_semana]]&"|"&tblOrdenes[[#This Row],[tecnico_asignado]],tblAsignaciones[clave],tblAsignaciones[horas_disponibles],0)-tblOrdenes[[#This Row],[HHA]]) | AG28: =IF(tblOrdenes[[#This Row],[orden]]="","",_xlfn.XLOOKUP(tblOrdenes[[#This Row],[id_operacion]],tblEjecucion[id_operacion],tblEjecucion[precio],0)) | AH28: =IF(tblOrdenes[[#This Row],[orden]]="","",MAX(0,_xlfn.XLOOKUP(tblOrdenes[[#This Row],[id_operacion]],tblEjecucion[id_operacion],tblEjecucion[costo_plan_total],0)-tblOrdenes[[#This Row],[costo_servicio]])) | AI28: =IF(tblOrdenes[[#This Row],[orden]]="","",tblOrdenes[[#This Row],[costo_servicio]]+tblOrdenes[[#This Row],[costo_materiales]]) | AM28: =IF(tblOrdenes[[#This Row],[link_checklist]]="","",HYPERLINK(p_ruta_base_checklists&tblOrdenes[[#This Row],[link_checklist]],"abrir")) | AO28: =IF(tblOrdenes[[#This Row],[orden]]="","",tblOrdenes[[#This Row],[orden]]&IF(tblOrdenes[[#This Row],[operacion]]="","0010",tblOrdenes[[#This Row],[operacion]]))
A29: OT-000026 | B29: 0010 | C29: Análisis predictivo — EQ-108 | D29: Análisis predictivo en EQ-108 | E29: EQ-108 | F29: CC-210 | G29: PU-MEC | H29: ACT-04 | I29: TIPO-P1 | J29: 46230 | K29: 10 | L29: 250 | N29: =IF(tblOrdenes[[#This Row],[orden]]="","",IF(tblOrdenes[[#This Row],[horas_ajustadas]]<>"",tblOrdenes[[#This Row],[horas_ajustadas]],IF(tblOrdenes[[#This Row],[horas_estimadas]]="","",tblOrdenes[[#This Row],[horas_estimadas]]))) | O29: =IF(tblOrdenes[[#This Row],[orden]]="","",_xlfn.XLOOKUP(_xlfn.XLOOKUP(tblOrdenes[[#This Row],[id_operacion]],tblEjecucion[id_operacion],tblEjecucion[estado_sistema],""),tblEstados[estado_sistema],tblEstados[estado_normalizado],"Pendiente")) | P29: =IF(tblOrdenes[[#This Row],[fecha_inicio]]="","",YEAR(tblOrdenes[[#This Row],[fecha_inicio]]+4-WEEKDAY(tblOrdenes[[#This Row],[fecha_inicio]],2))&"-S"&TEXT(_xlfn.ISOWEEKNUM(tblOrdenes[[#This Row],[fecha_inicio]]),"00")) | Q29: =IF(tblOrdenes[[#This Row],[fecha_inicio]]="","",YEAR(tblOrdenes[[#This Row],[fecha_inicio]])) | R29: =IF(tblOrdenes[[#This Row],[fecha_inicio]]="","",MONTH(tblOrdenes[[#This Row],[fecha_inicio]])) | S29: =IF(tblOrdenes[[#This Row],[fecha_inicio]]="","",INDEX(lista_dias,WEEKDAY(tblOrdenes[[#This Row],[fecha_inicio]],2))) | T29: =IF(tblOrdenes[[#This Row],[tipo_ot]]="","",_xlfn.XLOOKUP(tblOrdenes[[#This Row],[tipo_ot]],tblTiposOT[codigo],tblTiposOT[clasificacion],"sin_clasificar")) | U29: =IF(tblOrdenes[[#This Row],[centro_costo]]="","",_xlfn.XLOOKUP(tblOrdenes[[#This Row],[centro_costo]],tblCECO[codigo],tblCECO[linea],"(sin catálogo)")) | V29: =IF(tblOrdenes[[#This Row],[centro_costo]]="","",_xlfn.XLOOKUP(tblOrdenes[[#This Row],[centro_costo]],tblCECO[codigo],tblCECO[area],"(sin catálogo)")) | W29: =IF(tblOrdenes[[#This Row],[centro_costo]]="","",_xlfn.XLOOKUP(tblOrdenes[[#This Row],[centro_costo]],tblCECO[codigo],tblCECO[coordinador],"(sin catálogo)")) | X29: =IF(tblOrdenes[[#This Row],[puesto_trabajo]]="","",_xlfn.XLOOKUP(tblOrdenes[[#This Row],[puesto_trabajo]],tblPuestos[codigo],tblPuestos[especialidad],"(sin catálogo)")) | Y29: =IF(tblOrdenes[[#This Row],[cod_actividad]]="","",_xlfn.XLOOKUP(tblOrdenes[[#This Row],[cod_actividad]],tblActividades[codigo],tblActividades[descripcion],"(sin catálogo)")) | Z29: =IF(tblOrdenes[[#This Row],[fecha_inicio]]="","",TODAY()-tblOrdenes[[#This Row],[fecha_inicio]]) | AA29: =IF(tblOrdenes[[#This Row],[backlog_dias]]="","",IF(tblOrdenes[[#This Row],[backlog_dias]]<0,"FUTURO",IF(tblOrdenes[[#This Row],[backlog_dias]]>p_dias_backlog_max,"BACKLOG","MES CORRIENTE"))) | AB29: =IF(tblOrdenes[[#This Row],[backlog_dias]]="",FALSE,AND(tblOrdenes[[#This Row],[backlog_dias]]>p_dias_backlog_min,tblOrdenes[[#This Row],[backlog_dias]]<=p_dias_backlog_max)) | AC29: Técnico 04 | AD29: =IF(tblOrdenes[[#This Row],[tecnico_asignado]]="","",_xlfn.XLOOKUP(tblOrdenes[[#This Row],[semana]]&"|"&tblOrdenes[[#This Row],[dia_semana]]&"|"&tblOrdenes[[#This Row],[tecnico_asignado]],tblAsignaciones[clave],tblAsignaciones[turno],"")) | AE29: =IF(tblOrdenes[[#This Row],[tecnico_asignado]]="","",SUMIFS(tblOrdenes[horas_efectivas],tblOrdenes[tecnico_asignado],tblOrdenes[[#This Row],[tecnico_asignado]],tblOrdenes[semana],tblOrdenes[[#This Row],[semana]],tblOrdenes[dia_semana],tblOrdenes[[#This Row],[dia_semana]])) | AF29: =IF(tblOrdenes[[#This Row],[HHA]]="","",p_factor_productividad*_xlfn.XLOOKUP(tblOrdenes[[#This Row],[semana]]&"|"&tblOrdenes[[#This Row],[dia_semana]]&"|"&tblOrdenes[[#This Row],[tecnico_asignado]],tblAsignaciones[clave],tblAsignaciones[horas_disponibles],0)-tblOrdenes[[#This Row],[HHA]]) | AG29: =IF(tblOrdenes[[#This Row],[orden]]="","",_xlfn.XLOOKUP(tblOrdenes[[#This Row],[id_operacion]],tblEjecucion[id_operacion],tblEjecucion[precio],0)) | AH29: =IF(tblOrdenes[[#This Row],[orden]]="","",MAX(0,_xlfn.XLOOKUP(tblOrdenes[[#This Row],[id_operacion]],tblEjecucion[id_operacion],tblEjecucion[costo_plan_total],0)-tblOrdenes[[#This Row],[costo_servicio]])) | AI29: =IF(tblOrdenes[[#This Row],[orden]]="","",tblOrdenes[[#This Row],[costo_servicio]]+tblOrdenes[[#This Row],[costo_materiales]]) | AL29: ACT-04.pdf | AM29: =IF(tblOrdenes[[#This Row],[link_checklist]]="","",HYPERLINK(p_ruta_base_checklists&tblOrdenes[[#This Row],[link_checklist]],"abrir")) | AN29: Demo: asignada a técnico de vacaciones (HHD = −HHA) | AO29: =IF(tblOrdenes[[#This Row],[orden]]="","",tblOrdenes[[#This Row],[orden]]&IF(tblOrdenes[[#This Row],[operacion]]="","0010",tblOrdenes[[#This Row],[operacion]]))
A30: OT-000027 | B30: 0010 | C30: Inspección de rutina — EQ-110 | D30: Inspección de rutina en EQ-110 | E30: EQ-110 | F30: CC-310 | G30: PU-MEC | H30: ACT-01 | I30: TIPO-P2 | J30: 46231 | K30: 8 | L30: 200 | N30: =IF(tblOrdenes[[#This Row],[orden]]="","",IF(tblOrdenes[[#This Row],[horas_ajustadas]]<>"",tblOrdenes[[#This Row],[horas_ajustadas]],IF(tblOrdenes[[#This Row],[horas_estimadas]]="","",tblOrdenes[[#This Row],[horas_estimadas]]))) | O30: =IF(tblOrdenes[[#This Row],[orden]]="","",_xlfn.XLOOKUP(_xlfn.XLOOKUP(tblOrdenes[[#This Row],[id_operacion]],tblEjecucion[id_operacion],tblEjecucion[estado_sistema],""),tblEstados[estado_sistema],tblEstados[estado_normalizado],"Pendiente")) | P30: =IF(tblOrdenes[[#This Row],[fecha_inicio]]="","",YEAR(tblOrdenes[[#This Row],[fecha_inicio]]+4-WEEKDAY(tblOrdenes[[#This Row],[fecha_inicio]],2))&"-S"&TEXT(_xlfn.ISOWEEKNUM(tblOrdenes[[#This Row],[fecha_inicio]]),"00")) | Q30: =IF(tblOrdenes[[#This Row],[fecha_inicio]]="","",YEAR(tblOrdenes[[#This Row],[fecha_inicio]])) | R30: =IF(tblOrdenes[[#This Row],[fecha_inicio]]="","",MONTH(tblOrdenes[[#This Row],[fecha_inicio]])) | S30: =IF(tblOrdenes[[#This Row],[fecha_inicio]]="","",INDEX(lista_dias,WEEKDAY(tblOrdenes[[#This Row],[fecha_inicio]],2))) | T30: =IF(tblOrdenes[[#This Row],[tipo_ot]]="","",_xlfn.XLOOKUP(tblOrdenes[[#This Row],[tipo_ot]],tblTiposOT[codigo],tblTiposOT[clasificacion],"sin_clasificar")) | U30: =IF(tblOrdenes[[#This Row],[centro_costo]]="","",_xlfn.XLOOKUP(tblOrdenes[[#This Row],[centro_costo]],tblCECO[codigo],tblCECO[linea],"(sin catálogo)")) | V30: =IF(tblOrdenes[[#This Row],[centro_costo]]="","",_xlfn.XLOOKUP(tblOrdenes[[#This Row],[centro_costo]],tblCECO[codigo],tblCECO[area],"(sin catálogo)")) | W30: =IF(tblOrdenes[[#This Row],[centro_costo]]="","",_xlfn.XLOOKUP(tblOrdenes[[#This Row],[centro_costo]],tblCECO[codigo],tblCECO[coordinador],"(sin catálogo)")) | X30: =IF(tblOrdenes[[#This Row],[puesto_trabajo]]="","",_xlfn.XLOOKUP(tblOrdenes[[#This Row],[puesto_trabajo]],tblPuestos[codigo],tblPuestos[especialidad],"(sin catálogo)")) | Y30: =IF(tblOrdenes[[#This Row],[cod_actividad]]="","",_xlfn.XLOOKUP(tblOrdenes[[#This Row],[cod_actividad]],tblActividades[codigo],tblActividades[descripcion],"(sin catálogo)")) | Z30: =IF(tblOrdenes[[#This Row],[fecha_inicio]]="","",TODAY()-tblOrdenes[[#This Row],[fecha_inicio]]) | AA30: =IF(tblOrdenes[[#This Row],[backlog_dias]]="","",IF(tblOrdenes[[#This Row],[backlog_dias]]<0,"FUTURO",IF(tblOrdenes[[#This Row],[backlog_dias]]>p_dias_backlog_max,"BACKLOG","MES CORRIENTE"))) | AB30: =IF(tblOrdenes[[#This Row],[backlog_dias]]="",FALSE,AND(tblOrdenes[[#This Row],[backlog_dias]]>p_dias_backlog_min,tblOrdenes[[#This Row],[backlog_dias]]<=p_dias_backlog_max)) | AC30: Técnico 03 | AD30: =IF(tblOrdenes[[#This Row],[tecnico_asignado]]="","",_xlfn.XLOOKUP(tblOrdenes[[#This Row],[semana]]&"|"&tblOrdenes[[#This Row],[dia_semana]]&"|"&tblOrdenes[[#This Row],[tecnico_asignado]],tblAsignaciones[clave],tblAsignaciones[turno],"")) | AE30: =IF(tblOrdenes[[#This Row],[tecnico_asignado]]="","",SUMIFS(tblOrdenes[horas_efectivas],tblOrdenes[tecnico_asignado],tblOrdenes[[#This Row],[tecnico_asignado]],tblOrdenes[semana],tblOrdenes[[#This Row],[semana]],tblOrdenes[dia_semana],tblOrdenes[[#This Row],[dia_semana]])) | AF30: =IF(tblOrdenes[[#This Row],[HHA]]="","",p_factor_productividad*_xlfn.XLOOKUP(tblOrdenes[[#This Row],[semana]]&"|"&tblOrdenes[[#This Row],[dia_semana]]&"|"&tblOrdenes[[#This Row],[tecnico_asignado]],tblAsignaciones[clave],tblAsignaciones[horas_disponibles],0)-tblOrdenes[[#This Row],[HHA]]) | AG30: =IF(tblOrdenes[[#This Row],[orden]]="","",_xlfn.XLOOKUP(tblOrdenes[[#This Row],[id_operacion]],tblEjecucion[id_operacion],tblEjecucion[precio],0)) | AH30: =IF(tblOrdenes[[#This Row],[orden]]="","",MAX(0,_xlfn.XLOOKUP(tblOrdenes[[#This Row],[id_operacion]],tblEjecucion[id_operacion],tblEjecucion[costo_plan_total],0)-tblOrdenes[[#This Row],[costo_servicio]])) | AI30: =IF(tblOrdenes[[#This Row],[orden]]="","",tblOrdenes[[#This Row],[costo_servicio]]+tblOrdenes[[#This Row],[costo_materiales]]) | AL30: ACT-01.pdf | AM30: =IF(tblOrdenes[[#This Row],[link_checklist]]="","",HYPERLINK(p_ruta_base_checklists&tblOrdenes[[#This Row],[link_checklist]],"abrir")) | AO30: =IF(tblOrdenes[[#This Row],[orden]]="","",tblOrdenes[[#This Row],[orden]]&IF(tblOrdenes[[#This Row],[operacion]]="","0010",tblOrdenes[[#This Row],[operacion]]))
A31: OT-000028 | B31: 0010 | C31: Lubricación programada — EQ-104 | D31: Lubricación programada en EQ-104 | E31: EQ-104 | F31: CC-110 | G31: PU-MEC | H31: ACT-02 | I31: TIPO-P1 | J31: 46232 | K31: 6 | L31: 150 | N31: =IF(tblOrdenes[[#This Row],[orden]]="","",IF(tblOrdenes[[#This Row],[horas_ajustadas]]<>"",tblOrdenes[[#This Row],[horas_ajustadas]],IF(tblOrdenes[[#This Row],[horas_estimadas]]="","",tblOrdenes[[#This Row],[horas_estimadas]]))) | O31: =IF(tblOrdenes[[#This Row],[orden]]="","",_xlfn.XLOOKUP(_xlfn.XLOOKUP(tblOrdenes[[#This Row],[id_operacion]],tblEjecucion[id_operacion],tblEjecucion[estado_sistema],""),tblEstados[estado_sistema],tblEstados[estado_normalizado],"Pendiente")) | P31: =IF(tblOrdenes[[#This Row],[fecha_inicio]]="","",YEAR(tblOrdenes[[#This Row],[fecha_inicio]]+4-WEEKDAY(tblOrdenes[[#This Row],[fecha_inicio]],2))&"-S"&TEXT(_xlfn.ISOWEEKNUM(tblOrdenes[[#This Row],[fecha_inicio]]),"00")) | Q31: =IF(tblOrdenes[[#This Row],[fecha_inicio]]="","",YEAR(tblOrdenes[[#This Row],[fecha_inicio]])) | R31: =IF(tblOrdenes[[#This Row],[fecha_inicio]]="","",MONTH(tblOrdenes[[#This Row],[fecha_inicio]])) | S31: =IF(tblOrdenes[[#This Row],[fecha_inicio]]="","",INDEX(lista_dias,WEEKDAY(tblOrdenes[[#This Row],[fecha_inicio]],2))) | T31: =IF(tblOrdenes[[#This Row],[tipo_ot]]="","",_xlfn.XLOOKUP(tblOrdenes[[#This Row],[tipo_ot]],tblTiposOT[codigo],tblTiposOT[clasificacion],"sin_clasificar")) | U31: =IF(tblOrdenes[[#This Row],[centro_costo]]="","",_xlfn.XLOOKUP(tblOrdenes[[#This Row],[centro_costo]],tblCECO[codigo],tblCECO[linea],"(sin catálogo)")) | V31: =IF(tblOrdenes[[#This Row],[centro_costo]]="","",_xlfn.XLOOKUP(tblOrdenes[[#This Row],[centro_costo]],tblCECO[codigo],tblCECO[area],"(sin catálogo)")) | W31: =IF(tblOrdenes[[#This Row],[centro_costo]]="","",_xlfn.XLOOKUP(tblOrdenes[[#This Row],[centro_costo]],tblCECO[codigo],tblCECO[coordinador],"(sin catálogo)")) | X31: =IF(tblOrdenes[[#This Row],[puesto_trabajo]]="","",_xlfn.XLOOKUP(tblOrdenes[[#This Row],[puesto_trabajo]],tblPuestos[codigo],tblPuestos[especialidad],"(sin catálogo)")) | Y31: =IF(tblOrdenes[[#This Row],[cod_actividad]]="","",_xlfn.XLOOKUP(tblOrdenes[[#This Row],[cod_actividad]],tblActividades[codigo],tblActividades[descripcion],"(sin catálogo)")) | Z31: =IF(tblOrdenes[[#This Row],[fecha_inicio]]="","",TODAY()-tblOrdenes[[#This Row],[fecha_inicio]]) | AA31: =IF(tblOrdenes[[#This Row],[backlog_dias]]="","",IF(tblOrdenes[[#This Row],[backlog_dias]]<0,"FUTURO",IF(tblOrdenes[[#This Row],[backlog_dias]]>p_dias_backlog_max,"BACKLOG","MES CORRIENTE"))) | AB31: =IF(tblOrdenes[[#This Row],[backlog_dias]]="",FALSE,AND(tblOrdenes[[#This Row],[backlog_dias]]>p_dias_backlog_min,tblOrdenes[[#This Row],[backlog_dias]]<=p_dias_backlog_max)) | AC31: Técnico 01 | AD31: =IF(tblOrdenes[[#This Row],[tecnico_asignado]]="","",_xlfn.XLOOKUP(tblOrdenes[[#This Row],[semana]]&"|"&tblOrdenes[[#This Row],[dia_semana]]&"|"&tblOrdenes[[#This Row],[tecnico_asignado]],tblAsignaciones[clave],tblAsignaciones[turno],"")) | AE31: =IF(tblOrdenes[[#This Row],[tecnico_asignado]]="","",SUMIFS(tblOrdenes[horas_efectivas],tblOrdenes[tecnico_asignado],tblOrdenes[[#This Row],[tecnico_asignado]],tblOrdenes[semana],tblOrdenes[[#This Row],[semana]],tblOrdenes[dia_semana],tblOrdenes[[#This Row],[dia_semana]])) | AF31: =IF(tblOrdenes[[#This Row],[HHA]]="","",p_factor_productividad*_xlfn.XLOOKUP(tblOrdenes[[#This Row],[semana]]&"|"&tblOrdenes[[#This Row],[dia_semana]]&"|"&tblOrdenes[[#This Row],[tecnico_asignado]],tblAsignaciones[clave],tblAsignaciones[horas_disponibles],0)-tblOrdenes[[#This Row],[HHA]]) | AG31: =IF(tblOrdenes[[#This Row],[orden]]="","",_xlfn.XLOOKUP(tblOrdenes[[#This Row],[id_operacion]],tblEjecucion[id_operacion],tblEjecucion[precio],0)) | AH31: =IF(tblOrdenes[[#This Row],[orden]]="","",MAX(0,_xlfn.XLOOKUP(tblOrdenes[[#This Row],[id_operacion]],tblEjecucion[id_operacion],tblEjecucion[costo_plan_total],0)-tblOrdenes[[#This Row],[costo_servicio]])) | AI31: =IF(tblOrdenes[[#This Row],[orden]]="","",tblOrdenes[[#This Row],[costo_servicio]]+tblOrdenes[[#This Row],[costo_materiales]]) | AL31: ACT-02.pdf | AM31: =IF(tblOrdenes[[#This Row],[link_checklist]]="","",HYPERLINK(p_ruta_base_checklists&tblOrdenes[[#This Row],[link_checklist]],"abrir")) | AO31: =IF(tblOrdenes[[#This Row],[orden]]="","",tblOrdenes[[#This Row],[orden]]&IF(tblOrdenes[[#This Row],[operacion]]="","0010",tblOrdenes[[#This Row],[operacion]]))
A32: OT-000029 | B32: 0010 | C32: Análisis predictivo — EQ-107 | D32: Análisis predictivo en EQ-107 | E32: EQ-107 | F32: CC-210 | G32: PU-MEC | H32: ACT-04 | I32: TIPO-P2 | J32: 46233 | K32: 10 | L32: 250 | N32: =IF(tblOrdenes[[#This Row],[orden]]="","",IF(tblOrdenes[[#This Row],[horas_ajustadas]]<>"",tblOrdenes[[#This Row],[horas_ajustadas]],IF(tblOrdenes[[#This Row],[horas_estimadas]]="","",tblOrdenes[[#This Row],[horas_estimadas]]))) | O32: =IF(tblOrdenes[[#This Row],[orden]]="","",_xlfn.XLOOKUP(_xlfn.XLOOKUP(tblOrdenes[[#This Row],[id_operacion]],tblEjecucion[id_operacion],tblEjecucion[estado_sistema],""),tblEstados[estado_sistema],tblEstados[estado_normalizado],"Pendiente")) | P32: =IF(tblOrdenes[[#This Row],[fecha_inicio]]="","",YEAR(tblOrdenes[[#This Row],[fecha_inicio]]+4-WEEKDAY(tblOrdenes[[#This Row],[fecha_inicio]],2))&"-S"&TEXT(_xlfn.ISOWEEKNUM(tblOrdenes[[#This Row],[fecha_inicio]]),"00")) | Q32: =IF(tblOrdenes[[#This Row],[fecha_inicio]]="","",YEAR(tblOrdenes[[#This Row],[fecha_inicio]])) | R32: =IF(tblOrdenes[[#This Row],[fecha_inicio]]="","",MONTH(tblOrdenes[[#This Row],[fecha_inicio]])) | S32: =IF(tblOrdenes[[#This Row],[fecha_inicio]]="","",INDEX(lista_dias,WEEKDAY(tblOrdenes[[#This Row],[fecha_inicio]],2))) | T32: =IF(tblOrdenes[[#This Row],[tipo_ot]]="","",_xlfn.XLOOKUP(tblOrdenes[[#This Row],[tipo_ot]],tblTiposOT[codigo],tblTiposOT[clasificacion],"sin_clasificar")) | U32: =IF(tblOrdenes[[#This Row],[centro_costo]]="","",_xlfn.XLOOKUP(tblOrdenes[[#This Row],[centro_costo]],tblCECO[codigo],tblCECO[linea],"(sin catálogo)")) | V32: =IF(tblOrdenes[[#This Row],[centro_costo]]="","",_xlfn.XLOOKUP(tblOrdenes[[#This Row],[centro_costo]],tblCECO[codigo],tblCECO[area],"(sin catálogo)")) | W32: =IF(tblOrdenes[[#This Row],[centro_costo]]="","",_xlfn.XLOOKUP(tblOrdenes[[#This Row],[centro_costo]],tblCECO[codigo],tblCECO[coordinador],"(sin catálogo)")) | X32: =IF(tblOrdenes[[#This Row],[puesto_trabajo]]="","",_xlfn.XLOOKUP(tblOrdenes[[#This Row],[puesto_trabajo]],tblPuestos[codigo],tblPuestos[especialidad],"(sin catálogo)")) | Y32: =IF(tblOrdenes[[#This Row],[cod_actividad]]="","",_xlfn.XLOOKUP(tblOrdenes[[#This Row],[cod_actividad]],tblActividades[codigo],tblActividades[descripcion],"(sin catálogo)")) | Z32: =IF(tblOrdenes[[#This Row],[fecha_inicio]]="","",TODAY()-tblOrdenes[[#This Row],[fecha_inicio]]) | AA32: =IF(tblOrdenes[[#This Row],[backlog_dias]]="","",IF(tblOrdenes[[#This Row],[backlog_dias]]<0,"FUTURO",IF(tblOrdenes[[#This Row],[backlog_dias]]>p_dias_backlog_max,"BACKLOG","MES CORRIENTE"))) | AB32: =IF(tblOrdenes[[#This Row],[backlog_dias]]="",FALSE,AND(tblOrdenes[[#This Row],[backlog_dias]]>p_dias_backlog_min,tblOrdenes[[#This Row],[backlog_dias]]<=p_dias_backlog_max)) | AC32: Técnico 02 | AD32: =IF(tblOrdenes[[#This Row],[tecnico_asignado]]="","",_xlfn.XLOOKUP(tblOrdenes[[#This Row],[semana]]&"|"&tblOrdenes[[#This Row],[dia_semana]]&"|"&tblOrdenes[[#This Row],[tecnico_asignado]],tblAsignaciones[clave],tblAsignaciones[turno],"")) | AE32: =IF(tblOrdenes[[#This Row],[tecnico_asignado]]="","",SUMIFS(tblOrdenes[horas_efectivas],tblOrdenes[tecnico_asignado],tblOrdenes[[#This Row],[tecnico_asignado]],tblOrdenes[semana],tblOrdenes[[#This Row],[semana]],tblOrdenes[dia_semana],tblOrdenes[[#This Row],[dia_semana]])) | AF32: =IF(tblOrdenes[[#This Row],[HHA]]="","",p_factor_productividad*_xlfn.XLOOKUP(tblOrdenes[[#This Row],[semana]]&"|"&tblOrdenes[[#This Row],[dia_semana]]&"|"&tblOrdenes[[#This Row],[tecnico_asignado]],tblAsignaciones[clave],tblAsignaciones[horas_disponibles],0)-tblOrdenes[[#This Row],[HHA]]) | AG32: =IF(tblOrdenes[[#This Row],[orden]]="","",_xlfn.XLOOKUP(tblOrdenes[[#This Row],[id_operacion]],tblEjecucion[id_operacion],tblEjecucion[precio],0)) | AH32: =IF(tblOrdenes[[#This Row],[orden]]="","",MAX(0,_xlfn.XLOOKUP(tblOrdenes[[#This Row],[id_operacion]],tblEjecucion[id_operacion],tblEjecucion[costo_plan_total],0)-tblOrdenes[[#This Row],[costo_servicio]])) | AI32: =IF(tblOrdenes[[#This Row],[orden]]="","",tblOrdenes[[#This Row],[costo_servicio]]+tblOrdenes[[#This Row],[costo_materiales]]) | AL32: ACT-04.pdf | AM32: =IF(tblOrdenes[[#This Row],[link_checklist]]="","",HYPERLINK(p_ruta_base_checklists&tblOrdenes[[#This Row],[link_checklist]],"abrir")) | AO32: =IF(tblOrdenes[[#This Row],[orden]]="","",tblOrdenes[[#This Row],[orden]]&IF(tblOrdenes[[#This Row],[operacion]]="","0010",tblOrdenes[[#This Row],[operacion]]))
A33: OT-000030 | B33: 0010 | C33: Inspección de rutina — EQ-110 | D33: Inspección de rutina en EQ-110 | E33: EQ-110 | F33: CC-310 | G33: PU-MEC | H33: ACT-01 | I33: TIPO-P1 | J33: 46234 | K33: 8 | L33: 200 | N33: =IF(tblOrdenes[[#This Row],[orden]]="","",IF(tblOrdenes[[#This Row],[horas_ajustadas]]<>"",tblOrdenes[[#This Row],[horas_ajustadas]],IF(tblOrdenes[[#This Row],[horas_estimadas]]="","",tblOrdenes[[#This Row],[horas_estimadas]]))) | O33: =IF(tblOrdenes[[#This Row],[orden]]="","",_xlfn.XLOOKUP(_xlfn.XLOOKUP(tblOrdenes[[#This Row],[id_operacion]],tblEjecucion[id_operacion],tblEjecucion[estado_sistema],""),tblEstados[estado_sistema],tblEstados[estado_normalizado],"Pendiente")) | P33: =IF(tblOrdenes[[#This Row],[fecha_inicio]]="","",YEAR(tblOrdenes[[#This Row],[fecha_inicio]]+4-WEEKDAY(tblOrdenes[[#This Row],[fecha_inicio]],2))&"-S"&TEXT(_xlfn.ISOWEEKNUM(tblOrdenes[[#This Row],[fecha_inicio]]),"00")) | Q33: =IF(tblOrdenes[[#This Row],[fecha_inicio]]="","",YEAR(tblOrdenes[[#This Row],[fecha_inicio]])) | R33: =IF(tblOrdenes[[#This Row],[fecha_inicio]]="","",MONTH(tblOrdenes[[#This Row],[fecha_inicio]])) | S33: =IF(tblOrdenes[[#This Row],[fecha_inicio]]="","",INDEX(lista_dias,WEEKDAY(tblOrdenes[[#This Row],[fecha_inicio]],2))) | T33: =IF(tblOrdenes[[#This Row],[tipo_ot]]="","",_xlfn.XLOOKUP(tblOrdenes[[#This Row],[tipo_ot]],tblTiposOT[codigo],tblTiposOT[clasificacion],"sin_clasificar")) | U33: =IF(tblOrdenes[[#This Row],[centro_costo]]="","",_xlfn.XLOOKUP(tblOrdenes[[#This Row],[centro_costo]],tblCECO[codigo],tblCECO[linea],"(sin catálogo)")) | V33: =IF(tblOrdenes[[#This Row],[centro_costo]]="","",_xlfn.XLOOKUP(tblOrdenes[[#This Row],[centro_costo]],tblCECO[codigo],tblCECO[area],"(sin catálogo)")) | W33: =IF(tblOrdenes[[#This Row],[centro_costo]]="","",_xlfn.XLOOKUP(tblOrdenes[[#This Row],[centro_costo]],tblCECO[codigo],tblCECO[coordinador],"(sin catálogo)")) | X33: =IF(tblOrdenes[[#This Row],[puesto_trabajo]]="","",_xlfn.XLOOKUP(tblOrdenes[[#This Row],[puesto_trabajo]],tblPuestos[codigo],tblPuestos[especialidad],"(sin catálogo)")) | Y33: =IF(tblOrdenes[[#This Row],[cod_actividad]]="","",_xlfn.XLOOKUP(tblOrdenes[[#This Row],[cod_actividad]],tblActividades[codigo],tblActividades[descripcion],"(sin catálogo)")) | Z33: =IF(tblOrdenes[[#This Row],[fecha_inicio]]="","",TODAY()-tblOrdenes[[#This Row],[fecha_inicio]]) | AA33: =IF(tblOrdenes[[#This Row],[backlog_dias]]="","",IF(tblOrdenes[[#This Row],[backlog_dias]]<0,"FUTURO",IF(tblOrdenes[[#This Row],[backlog_dias]]>p_dias_backlog_max,"BACKLOG","MES CORRIENTE"))) | AB33: =IF(tblOrdenes[[#This Row],[backlog_dias]]="",FALSE,AND(tblOrdenes[[#This Row],[backlog_dias]]>p_dias_backlog_min,tblOrdenes[[#This Row],[backlog_dias]]<=p_dias_backlog_max)) | AC33: Técnico 03 | AD33: =IF(tblOrdenes[[#This Row],[tecnico_asignado]]="","",_xlfn.XLOOKUP(tblOrdenes[[#This Row],[semana]]&"|"&tblOrdenes[[#This Row],[dia_semana]]&"|"&tblOrdenes[[#This Row],[tecnico_asignado]],tblAsignaciones[clave],tblAsignaciones[turno],"")) | AE33: =IF(tblOrdenes[[#This Row],[tecnico_asignado]]="","",SUMIFS(tblOrdenes[horas_efectivas],tblOrdenes[tecnico_asignado],tblOrdenes[[#This Row],[tecnico_asignado]],tblOrdenes[semana],tblOrdenes[[#This Row],[semana]],tblOrdenes[dia_semana],tblOrdenes[[#This Row],[dia_semana]])) | AF33: =IF(tblOrdenes[[#This Row],[HHA]]="","",p_factor_productividad*_xlfn.XLOOKUP(tblOrdenes[[#This Row],[semana]]&"|"&tblOrdenes[[#This Row],[dia_semana]]&"|"&tblOrdenes[[#This Row],[tecnico_asignado]],tblAsignaciones[clave],tblAsignaciones[horas_disponibles],0)-tblOrdenes[[#This Row],[HHA]]) | AG33: =IF(tblOrdenes[[#This Row],[orden]]="","",_xlfn.XLOOKUP(tblOrdenes[[#This Row],[id_operacion]],tblEjecucion[id_operacion],tblEjecucion[precio],0)) | AH33: =IF(tblOrdenes[[#This Row],[orden]]="","",MAX(0,_xlfn.XLOOKUP(tblOrdenes[[#This Row],[id_operacion]],tblEjecucion[id_operacion],tblEjecucion[costo_plan_total],0)-tblOrdenes[[#This Row],[costo_servicio]])) | AI33: =IF(tblOrdenes[[#This Row],[orden]]="","",tblOrdenes[[#This Row],[costo_servicio]]+tblOrdenes[[#This Row],[costo_materiales]]) | AL33: ACT-01.pdf | AM33: =IF(tblOrdenes[[#This Row],[link_checklist]]="","",HYPERLINK(p_ruta_base_checklists&tblOrdenes[[#This Row],[link_checklist]],"abrir")) | AO33: =IF(tblOrdenes[[#This Row],[orden]]="","",tblOrdenes[[#This Row],[orden]]&IF(tblOrdenes[[#This Row],[operacion]]="","0010",tblOrdenes[[#This Row],[operacion]]))
A34: OT-000031 | B34: 0010 | C34: Lubricación programada — EQ-102 | D34: Lubricación programada en EQ-102 | E34: EQ-102 | F34: CC-110 | G34: PU-MEC | H34: ACT-02 | I34: TIPO-P2 | J34: 46230 | K34: 6 | L34: 150 | N34: =IF(tblOrdenes[[#This Row],[orden]]="","",IF(tblOrdenes[[#This Row],[horas_ajustadas]]<>"",tblOrdenes[[#This Row],[horas_ajustadas]],IF(tblOrdenes[[#This Row],[horas_estimadas]]="","",tblOrdenes[[#This Row],[horas_estimadas]]))) | O34: =IF(tblOrdenes[[#This Row],[orden]]="","",_xlfn.XLOOKUP(_xlfn.XLOOKUP(tblOrdenes[[#This Row],[id_operacion]],tblEjecucion[id_operacion],tblEjecucion[estado_sistema],""),tblEstados[estado_sistema],tblEstados[estado_normalizado],"Pendiente")) | P34: =IF(tblOrdenes[[#This Row],[fecha_inicio]]="","",YEAR(tblOrdenes[[#This Row],[fecha_inicio]]+4-WEEKDAY(tblOrdenes[[#This Row],[fecha_inicio]],2))&"-S"&TEXT(_xlfn.ISOWEEKNUM(tblOrdenes[[#This Row],[fecha_inicio]]),"00")) | Q34: =IF(tblOrdenes[[#This Row],[fecha_inicio]]="","",YEAR(tblOrdenes[[#This Row],[fecha_inicio]])) | R34: =IF(tblOrdenes[[#This Row],[fecha_inicio]]="","",MONTH(tblOrdenes[[#This Row],[fecha_inicio]])) | S34: =IF(tblOrdenes[[#This Row],[fecha_inicio]]="","",INDEX(lista_dias,WEEKDAY(tblOrdenes[[#This Row],[fecha_inicio]],2))) | T34: =IF(tblOrdenes[[#This Row],[tipo_ot]]="","",_xlfn.XLOOKUP(tblOrdenes[[#This Row],[tipo_ot]],tblTiposOT[codigo],tblTiposOT[clasificacion],"sin_clasificar")) | U34: =IF(tblOrdenes[[#This Row],[centro_costo]]="","",_xlfn.XLOOKUP(tblOrdenes[[#This Row],[centro_costo]],tblCECO[codigo],tblCECO[linea],"(sin catálogo)")) | V34: =IF(tblOrdenes[[#This Row],[centro_costo]]="","",_xlfn.XLOOKUP(tblOrdenes[[#This Row],[centro_costo]],tblCECO[codigo],tblCECO[area],"(sin catálogo)")) | W34: =IF(tblOrdenes[[#This Row],[centro_costo]]="","",_xlfn.XLOOKUP(tblOrdenes[[#This Row],[centro_costo]],tblCECO[codigo],tblCECO[coordinador],"(sin catálogo)")) | X34: =IF(tblOrdenes[[#This Row],[puesto_trabajo]]="","",_xlfn.XLOOKUP(tblOrdenes[[#This Row],[puesto_trabajo]],tblPuestos[codigo],tblPuestos[especialidad],"(sin catálogo)")) | Y34: =IF(tblOrdenes[[#This Row],[cod_actividad]]="","",_xlfn.XLOOKUP(tblOrdenes[[#This Row],[cod_actividad]],tblActividades[codigo],tblActividades[descripcion],"(sin catálogo)")) | Z34: =IF(tblOrdenes[[#This Row],[fecha_inicio]]="","",TODAY()-tblOrdenes[[#This Row],[fecha_inicio]]) | AA34: =IF(tblOrdenes[[#This Row],[backlog_dias]]="","",IF(tblOrdenes[[#This Row],[backlog_dias]]<0,"FUTURO",IF(tblOrdenes[[#This Row],[backlog_dias]]>p_dias_backlog_max,"BACKLOG","MES CORRIENTE"))) | AB34: =IF(tblOrdenes[[#This Row],[backlog_dias]]="",FALSE,AND(tblOrdenes[[#This Row],[backlog_dias]]>p_dias_backlog_min,tblOrdenes[[#This Row],[backlog_dias]]<=p_dias_backlog_max)) | AC34: Técnico 01 | AD34: =IF(tblOrdenes[[#This Row],[tecnico_asignado]]="","",_xlfn.XLOOKUP(tblOrdenes[[#This Row],[semana]]&"|"&tblOrdenes[[#This Row],[dia_semana]]&"|"&tblOrdenes[[#This Row],[tecnico_asignado]],tblAsignaciones[clave],tblAsignaciones[turno],"")) | AE34: =IF(tblOrdenes[[#This Row],[tecnico_asignado]]="","",SUMIFS(tblOrdenes[horas_efectivas],tblOrdenes[tecnico_asignado],tblOrdenes[[#This Row],[tecnico_asignado]],tblOrdenes[semana],tblOrdenes[[#This Row],[semana]],tblOrdenes[dia_semana],tblOrdenes[[#This Row],[dia_semana]])) | AF34: =IF(tblOrdenes[[#This Row],[HHA]]="","",p_factor_productividad*_xlfn.XLOOKUP(tblOrdenes[[#This Row],[semana]]&"|"&tblOrdenes[[#This Row],[dia_semana]]&"|"&tblOrdenes[[#This Row],[tecnico_asignado]],tblAsignaciones[clave],tblAsignaciones[horas_disponibles],0)-tblOrdenes[[#This Row],[HHA]]) | AG34: =IF(tblOrdenes[[#This Row],[orden]]="","",_xlfn.XLOOKUP(tblOrdenes[[#This Row],[id_operacion]],tblEjecucion[id_operacion],tblEjecucion[precio],0)) | AH34: =IF(tblOrdenes[[#This Row],[orden]]="","",MAX(0,_xlfn.XLOOKUP(tblOrdenes[[#This Row],[id_operacion]],tblEjecucion[id_operacion],tblEjecucion[costo_plan_total],0)-tblOrdenes[[#This Row],[costo_servicio]])) | AI34: =IF(tblOrdenes[[#This Row],[orden]]="","",tblOrdenes[[#This Row],[costo_servicio]]+tblOrdenes[[#This Row],[costo_materiales]]) | AL34: ACT-02.pdf | AM34: =IF(tblOrdenes[[#This Row],[link_checklist]]="","",HYPERLINK(p_ruta_base_checklists&tblOrdenes[[#This Row],[link_checklist]],"abrir")) | AO34: =IF(tblOrdenes[[#This Row],[orden]]="","",tblOrdenes[[#This Row],[orden]]&IF(tblOrdenes[[#This Row],[operacion]]="","0010",tblOrdenes[[#This Row],[operacion]]))
A35: OT-000032 | B35: 0010 | C35: Análisis predictivo — EQ-106 | D35: Análisis predictivo en EQ-106 | E35: EQ-106 | F35: CC-210 | G35: PU-MEC | H35: ACT-04 | I35: TIPO-P1 | J35: 46231 | K35: 10 | L35: 250 | N35: =IF(tblOrdenes[[#This Row],[orden]]="","",IF(tblOrdenes[[#This Row],[horas_ajustadas]]<>"",tblOrdenes[[#This Row],[horas_ajustadas]],IF(tblOrdenes[[#This Row],[horas_estimadas]]="","",tblOrdenes[[#This Row],[horas_estimadas]]))) | O35: =IF(tblOrdenes[[#This Row],[orden]]="","",_xlfn.XLOOKUP(_xlfn.XLOOKUP(tblOrdenes[[#This Row],[id_operacion]],tblEjecucion[id_operacion],tblEjecucion[estado_sistema],""),tblEstados[estado_sistema],tblEstados[estado_normalizado],"Pendiente")) | P35: =IF(tblOrdenes[[#This Row],[fecha_inicio]]="","",YEAR(tblOrdenes[[#This Row],[fecha_inicio]]+4-WEEKDAY(tblOrdenes[[#This Row],[fecha_inicio]],2))&"-S"&TEXT(_xlfn.ISOWEEKNUM(tblOrdenes[[#This Row],[fecha_inicio]]),"00")) | Q35: =IF(tblOrdenes[[#This Row],[fecha_inicio]]="","",YEAR(tblOrdenes[[#This Row],[fecha_inicio]])) | R35: =IF(tblOrdenes[[#This Row],[fecha_inicio]]="","",MONTH(tblOrdenes[[#This Row],[fecha_inicio]])) | S35: =IF(tblOrdenes[[#This Row],[fecha_inicio]]="","",INDEX(lista_dias,WEEKDAY(tblOrdenes[[#This Row],[fecha_inicio]],2))) | T35: =IF(tblOrdenes[[#This Row],[tipo_ot]]="","",_xlfn.XLOOKUP(tblOrdenes[[#This Row],[tipo_ot]],tblTiposOT[codigo],tblTiposOT[clasificacion],"sin_clasificar")) | U35: =IF(tblOrdenes[[#This Row],[centro_costo]]="","",_xlfn.XLOOKUP(tblOrdenes[[#This Row],[centro_costo]],tblCECO[codigo],tblCECO[linea],"(sin catálogo)")) | V35: =IF(tblOrdenes[[#This Row],[centro_costo]]="","",_xlfn.XLOOKUP(tblOrdenes[[#This Row],[centro_costo]],tblCECO[codigo],tblCECO[area],"(sin catálogo)")) | W35: =IF(tblOrdenes[[#This Row],[centro_costo]]="","",_xlfn.XLOOKUP(tblOrdenes[[#This Row],[centro_costo]],tblCECO[codigo],tblCECO[coordinador],"(sin catálogo)")) | X35: =IF(tblOrdenes[[#This Row],[puesto_trabajo]]="","",_xlfn.XLOOKUP(tblOrdenes[[#This Row],[puesto_trabajo]],tblPuestos[codigo],tblPuestos[especialidad],"(sin catálogo)")) | Y35: =IF(tblOrdenes[[#This Row],[cod_actividad]]="","",_xlfn.XLOOKUP(tblOrdenes[[#This Row],[cod_actividad]],tblActividades[codigo],tblActividades[descripcion],"(sin catálogo)")) | Z35: =IF(tblOrdenes[[#This Row],[fecha_inicio]]="","",TODAY()-tblOrdenes[[#This Row],[fecha_inicio]]) | AA35: =IF(tblOrdenes[[#This Row],[backlog_dias]]="","",IF(tblOrdenes[[#This Row],[backlog_dias]]<0,"FUTURO",IF(tblOrdenes[[#This Row],[backlog_dias]]>p_dias_backlog_max,"BACKLOG","MES CORRIENTE"))) | AB35: =IF(tblOrdenes[[#This Row],[backlog_dias]]="",FALSE,AND(tblOrdenes[[#This Row],[backlog_dias]]>p_dias_backlog_min,tblOrdenes[[#This Row],[backlog_dias]]<=p_dias_backlog_max)) | AC35: Técnico 02 | AD35: =IF(tblOrdenes[[#This Row],[tecnico_asignado]]="","",_xlfn.XLOOKUP(tblOrdenes[[#This Row],[semana]]&"|"&tblOrdenes[[#This Row],[dia_semana]]&"|"&tblOrdenes[[#This Row],[tecnico_asignado]],tblAsignaciones[clave],tblAsignaciones[turno],"")) | AE35: =IF(tblOrdenes[[#This Row],[tecnico_asignado]]="","",SUMIFS(tblOrdenes[horas_efectivas],tblOrdenes[tecnico_asignado],tblOrdenes[[#This Row],[tecnico_asignado]],tblOrdenes[semana],tblOrdenes[[#This Row],[semana]],tblOrdenes[dia_semana],tblOrdenes[[#This Row],[dia_semana]])) | AF35: =IF(tblOrdenes[[#This Row],[HHA]]="","",p_factor_productividad*_xlfn.XLOOKUP(tblOrdenes[[#This Row],[semana]]&"|"&tblOrdenes[[#This Row],[dia_semana]]&"|"&tblOrdenes[[#This Row],[tecnico_asignado]],tblAsignaciones[clave],tblAsignaciones[horas_disponibles],0)-tblOrdenes[[#This Row],[HHA]]) | AG35: =IF(tblOrdenes[[#This Row],[orden]]="","",_xlfn.XLOOKUP(tblOrdenes[[#This Row],[id_operacion]],tblEjecucion[id_operacion],tblEjecucion[precio],0)) | AH35: =IF(tblOrdenes[[#This Row],[orden]]="","",MAX(0,_xlfn.XLOOKUP(tblOrdenes[[#This Row],[id_operacion]],tblEjecucion[id_operacion],tblEjecucion[costo_plan_total],0)-tblOrdenes[[#This Row],[costo_servicio]])) | AI35: =IF(tblOrdenes[[#This Row],[orden]]="","",tblOrdenes[[#This Row],[costo_servicio]]+tblOrdenes[[#This Row],[costo_materiales]]) | AL35: ACT-04.pdf | AM35: =IF(tblOrdenes[[#This Row],[link_checklist]]="","",HYPERLINK(p_ruta_base_checklists&tblOrdenes[[#This Row],[link_checklist]],"abrir")) | AO35: =IF(tblOrdenes[[#This Row],[orden]]="","",tblOrdenes[[#This Row],[orden]]&IF(tblOrdenes[[#This Row],[operacion]]="","0010",tblOrdenes[[#This Row],[operacion]]))
A36: OT-000033 | B36: 0010 | C36: Inspección de rutina — EQ-110 | D36: Inspección de rutina en EQ-110 | E36: EQ-110 | F36: CC-310 | G36: PU-MEC | H36: ACT-01 | I36: TIPO-P2 | J36: 46232 | K36: 8 | L36: 200 | N36: =IF(tblOrdenes[[#This Row],[orden]]="","",IF(tblOrdenes[[#This Row],[horas_ajustadas]]<>"",tblOrdenes[[#This Row],[horas_ajustadas]],IF(tblOrdenes[[#This Row],[horas_estimadas]]="","",tblOrdenes[[#This Row],[horas_estimadas]]))) | O36: =IF(tblOrdenes[[#This Row],[orden]]="","",_xlfn.XLOOKUP(_xlfn.XLOOKUP(tblOrdenes[[#This Row],[id_operacion]],tblEjecucion[id_operacion],tblEjecucion[estado_sistema],""),tblEstados[estado_sistema],tblEstados[estado_normalizado],"Pendiente")) | P36: =IF(tblOrdenes[[#This Row],[fecha_inicio]]="","",YEAR(tblOrdenes[[#This Row],[fecha_inicio]]+4-WEEKDAY(tblOrdenes[[#This Row],[fecha_inicio]],2))&"-S"&TEXT(_xlfn.ISOWEEKNUM(tblOrdenes[[#This Row],[fecha_inicio]]),"00")) | Q36: =IF(tblOrdenes[[#This Row],[fecha_inicio]]="","",YEAR(tblOrdenes[[#This Row],[fecha_inicio]])) | R36: =IF(tblOrdenes[[#This Row],[fecha_inicio]]="","",MONTH(tblOrdenes[[#This Row],[fecha_inicio]])) | S36: =IF(tblOrdenes[[#This Row],[fecha_inicio]]="","",INDEX(lista_dias,WEEKDAY(tblOrdenes[[#This Row],[fecha_inicio]],2))) | T36: =IF(tblOrdenes[[#This Row],[tipo_ot]]="","",_xlfn.XLOOKUP(tblOrdenes[[#This Row],[tipo_ot]],tblTiposOT[codigo],tblTiposOT[clasificacion],"sin_clasificar")) | U36: =IF(tblOrdenes[[#This Row],[centro_costo]]="","",_xlfn.XLOOKUP(tblOrdenes[[#This Row],[centro_costo]],tblCECO[codigo],tblCECO[linea],"(sin catálogo)")) | V36: =IF(tblOrdenes[[#This Row],[centro_costo]]="","",_xlfn.XLOOKUP(tblOrdenes[[#This Row],[centro_costo]],tblCECO[codigo],tblCECO[area],"(sin catálogo)")) | W36: =IF(tblOrdenes[[#This Row],[centro_costo]]="","",_xlfn.XLOOKUP(tblOrdenes[[#This Row],[centro_costo]],tblCECO[codigo],tblCECO[coordinador],"(sin catálogo)")) | X36: =IF(tblOrdenes[[#This Row],[puesto_trabajo]]="","",_xlfn.XLOOKUP(tblOrdenes[[#This Row],[puesto_trabajo]],tblPuestos[codigo],tblPuestos[especialidad],"(sin catálogo)")) | Y36: =IF(tblOrdenes[[#This Row],[cod_actividad]]="","",_xlfn.XLOOKUP(tblOrdenes[[#This Row],[cod_actividad]],tblActividades[codigo],tblActividades[descripcion],"(sin catálogo)")) | Z36: =IF(tblOrdenes[[#This Row],[fecha_inicio]]="","",TODAY()-tblOrdenes[[#This Row],[fecha_inicio]]) | AA36: =IF(tblOrdenes[[#This Row],[backlog_dias]]="","",IF(tblOrdenes[[#This Row],[backlog_dias]]<0,"FUTURO",IF(tblOrdenes[[#This Row],[backlog_dias]]>p_dias_backlog_max,"BACKLOG","MES CORRIENTE"))) | AB36: =IF(tblOrdenes[[#This Row],[backlog_dias]]="",FALSE,AND(tblOrdenes[[#This Row],[backlog_dias]]>p_dias_backlog_min,tblOrdenes[[#This Row],[backlog_dias]]<=p_dias_backlog_max)) | AC36: Técnico 03 | AD36: =IF(tblOrdenes[[#This Row],[tecnico_asignado]]="","",_xlfn.XLOOKUP(tblOrdenes[[#This Row],[semana]]&"|"&tblOrdenes[[#This Row],[dia_semana]]&"|"&tblOrdenes[[#This Row],[tecnico_asignado]],tblAsignaciones[clave],tblAsignaciones[turno],"")) | AE36: =IF(tblOrdenes[[#This Row],[tecnico_asignado]]="","",SUMIFS(tblOrdenes[horas_efectivas],tblOrdenes[tecnico_asignado],tblOrdenes[[#This Row],[tecnico_asignado]],tblOrdenes[semana],tblOrdenes[[#This Row],[semana]],tblOrdenes[dia_semana],tblOrdenes[[#This Row],[dia_semana]])) | AF36: =IF(tblOrdenes[[#This Row],[HHA]]="","",p_factor_productividad*_xlfn.XLOOKUP(tblOrdenes[[#This Row],[semana]]&"|"&tblOrdenes[[#This Row],[dia_semana]]&"|"&tblOrdenes[[#This Row],[tecnico_asignado]],tblAsignaciones[clave],tblAsignaciones[horas_disponibles],0)-tblOrdenes[[#This Row],[HHA]]) | AG36: =IF(tblOrdenes[[#This Row],[orden]]="","",_xlfn.XLOOKUP(tblOrdenes[[#This Row],[id_operacion]],tblEjecucion[id_operacion],tblEjecucion[precio],0)) | AH36: =IF(tblOrdenes[[#This Row],[orden]]="","",MAX(0,_xlfn.XLOOKUP(tblOrdenes[[#This Row],[id_operacion]],tblEjecucion[id_operacion],tblEjecucion[costo_plan_total],0)-tblOrdenes[[#This Row],[costo_servicio]])) | AI36: =IF(tblOrdenes[[#This Row],[orden]]="","",tblOrdenes[[#This Row],[costo_servicio]]+tblOrdenes[[#This Row],[costo_materiales]]) | AL36: ACT-01.pdf | AM36: =IF(tblOrdenes[[#This Row],[link_checklist]]="","",HYPERLINK(p_ruta_base_checklists&tblOrdenes[[#This Row],[link_checklist]],"abrir")) | AO36: =IF(tblOrdenes[[#This Row],[orden]]="","",tblOrdenes[[#This Row],[orden]]&IF(tblOrdenes[[#This Row],[operacion]]="","0010",tblOrdenes[[#This Row],[operacion]]))
A37: OT-000034 | B37: 0010 | C37: Lubricación programada — EQ-105 | D37: Lubricación programada en EQ-105 | E37: EQ-105 | F37: CC-110 | G37: PU-MEC | H37: ACT-02 | I37: TIPO-P1 | J37: 46233 | K37: 6 | L37: 150 | N37: =IF(tblOrdenes[[#This Row],[orden]]="","",IF(tblOrdenes[[#This Row],[horas_ajustadas]]<>"",tblOrdenes[[#This Row],[horas_ajustadas]],IF(tblOrdenes[[#This Row],[horas_estimadas]]="","",tblOrdenes[[#This Row],[horas_estimadas]]))) | O37: =IF(tblOrdenes[[#This Row],[orden]]="","",_xlfn.XLOOKUP(_xlfn.XLOOKUP(tblOrdenes[[#This Row],[id_operacion]],tblEjecucion[id_operacion],tblEjecucion[estado_sistema],""),tblEstados[estado_sistema],tblEstados[estado_normalizado],"Pendiente")) | P37: =IF(tblOrdenes[[#This Row],[fecha_inicio]]="","",YEAR(tblOrdenes[[#This Row],[fecha_inicio]]+4-WEEKDAY(tblOrdenes[[#This Row],[fecha_inicio]],2))&"-S"&TEXT(_xlfn.ISOWEEKNUM(tblOrdenes[[#This Row],[fecha_inicio]]),"00")) | Q37: =IF(tblOrdenes[[#This Row],[fecha_inicio]]="","",YEAR(tblOrdenes[[#This Row],[fecha_inicio]])) | R37: =IF(tblOrdenes[[#This Row],[fecha_inicio]]="","",MONTH(tblOrdenes[[#This Row],[fecha_inicio]])) | S37: =IF(tblOrdenes[[#This Row],[fecha_inicio]]="","",INDEX(lista_dias,WEEKDAY(tblOrdenes[[#This Row],[fecha_inicio]],2))) | T37: =IF(tblOrdenes[[#This Row],[tipo_ot]]="","",_xlfn.XLOOKUP(tblOrdenes[[#This Row],[tipo_ot]],tblTiposOT[codigo],tblTiposOT[clasificacion],"sin_clasificar")) | U37: =IF(tblOrdenes[[#This Row],[centro_costo]]="","",_xlfn.XLOOKUP(tblOrdenes[[#This Row],[centro_costo]],tblCECO[codigo],tblCECO[linea],"(sin catálogo)")) | V37: =IF(tblOrdenes[[#This Row],[centro_costo]]="","",_xlfn.XLOOKUP(tblOrdenes[[#This Row],[centro_costo]],tblCECO[codigo],tblCECO[area],"(sin catálogo)")) | W37: =IF(tblOrdenes[[#This Row],[centro_costo]]="","",_xlfn.XLOOKUP(tblOrdenes[[#This Row],[centro_costo]],tblCECO[codigo],tblCECO[coordinador],"(sin catálogo)")) | X37: =IF(tblOrdenes[[#This Row],[puesto_trabajo]]="","",_xlfn.XLOOKUP(tblOrdenes[[#This Row],[puesto_trabajo]],tblPuestos[codigo],tblPuestos[especialidad],"(sin catálogo)")) | Y37: =IF(tblOrdenes[[#This Row],[cod_actividad]]="","",_xlfn.XLOOKUP(tblOrdenes[[#This Row],[cod_actividad]],tblActividades[codigo],tblActividades[descripcion],"(sin catálogo)")) | Z37: =IF(tblOrdenes[[#This Row],[fecha_inicio]]="","",TODAY()-tblOrdenes[[#This Row],[fecha_inicio]]) | AA37: =IF(tblOrdenes[[#This Row],[backlog_dias]]="","",IF(tblOrdenes[[#This Row],[backlog_dias]]<0,"FUTURO",IF(tblOrdenes[[#This Row],[backlog_dias]]>p_dias_backlog_max,"BACKLOG","MES CORRIENTE"))) | AB37: =IF(tblOrdenes[[#This Row],[backlog_dias]]="",FALSE,AND(tblOrdenes[[#This Row],[backlog_dias]]>p_dias_backlog_min,tblOrdenes[[#This Row],[backlog_dias]]<=p_dias_backlog_max)) | AC37: Técnico 01 | AD37: =IF(tblOrdenes[[#This Row],[tecnico_asignado]]="","",_xlfn.XLOOKUP(tblOrdenes[[#This Row],[semana]]&"|"&tblOrdenes[[#This Row],[dia_semana]]&"|"&tblOrdenes[[#This Row],[tecnico_asignado]],tblAsignaciones[clave],tblAsignaciones[turno],"")) | AE37: =IF(tblOrdenes[[#This Row],[tecnico_asignado]]="","",SUMIFS(tblOrdenes[horas_efectivas],tblOrdenes[tecnico_asignado],tblOrdenes[[#This Row],[tecnico_asignado]],tblOrdenes[semana],tblOrdenes[[#This Row],[semana]],tblOrdenes[dia_semana],tblOrdenes[[#This Row],[dia_semana]])) | AF37: =IF(tblOrdenes[[#This Row],[HHA]]="","",p_factor_productividad*_xlfn.XLOOKUP(tblOrdenes[[#This Row],[semana]]&"|"&tblOrdenes[[#This Row],[dia_semana]]&"|"&tblOrdenes[[#This Row],[tecnico_asignado]],tblAsignaciones[clave],tblAsignaciones[horas_disponibles],0)-tblOrdenes[[#This Row],[HHA]]) | AG37: =IF(tblOrdenes[[#This Row],[orden]]="","",_xlfn.XLOOKUP(tblOrdenes[[#This Row],[id_operacion]],tblEjecucion[id_operacion],tblEjecucion[precio],0)) | AH37: =IF(tblOrdenes[[#This Row],[orden]]="","",MAX(0,_xlfn.XLOOKUP(tblOrdenes[[#This Row],[id_operacion]],tblEjecucion[id_operacion],tblEjecucion[costo_plan_total],0)-tblOrdenes[[#This Row],[costo_servicio]])) | AI37: =IF(tblOrdenes[[#This Row],[orden]]="","",tblOrdenes[[#This Row],[costo_servicio]]+tblOrdenes[[#This Row],[costo_materiales]]) | AL37: ACT-02.pdf | AM37: =IF(tblOrdenes[[#This Row],[link_checklist]]="","",HYPERLINK(p_ruta_base_checklists&tblOrdenes[[#This Row],[link_checklist]],"abrir")) | AO37: =IF(tblOrdenes[[#This Row],[orden]]="","",tblOrdenes[[#This Row],[orden]]&IF(tblOrdenes[[#This Row],[operacion]]="","0010",tblOrdenes[[#This Row],[operacion]]))
A38: OT-000035 | B38: 0010 | C38: Análisis predictivo — EQ-109 | D38: Análisis predictivo en EQ-109 | E38: EQ-109 | F38: CC-210 | G38: PU-MEC | H38: ACT-04 | I38: TIPO-P2 | J38: 46234 | K38: 8 | L38: 200 | N38: =IF(tblOrdenes[[#This Row],[orden]]="","",IF(tblOrdenes[[#This Row],[horas_ajustadas]]<>"",tblOrdenes[[#This Row],[horas_ajustadas]],IF(tblOrdenes[[#This Row],[horas_estimadas]]="","",tblOrdenes[[#This Row],[horas_estimadas]]))) | O38: =IF(tblOrdenes[[#This Row],[orden]]="","",_xlfn.XLOOKUP(_xlfn.XLOOKUP(tblOrdenes[[#This Row],[id_operacion]],tblEjecucion[id_operacion],tblEjecucion[estado_sistema],""),tblEstados[estado_sistema],tblEstados[estado_normalizado],"Pendiente")) | P38: =IF(tblOrdenes[[#This Row],[fecha_inicio]]="","",YEAR(tblOrdenes[[#This Row],[fecha_inicio]]+4-WEEKDAY(tblOrdenes[[#This Row],[fecha_inicio]],2))&"-S"&TEXT(_xlfn.ISOWEEKNUM(tblOrdenes[[#This Row],[fecha_inicio]]),"00")) | Q38: =IF(tblOrdenes[[#This Row],[fecha_inicio]]="","",YEAR(tblOrdenes[[#This Row],[fecha_inicio]])) | R38: =IF(tblOrdenes[[#This Row],[fecha_inicio]]="","",MONTH(tblOrdenes[[#This Row],[fecha_inicio]])) | S38: =IF(tblOrdenes[[#This Row],[fecha_inicio]]="","",INDEX(lista_dias,WEEKDAY(tblOrdenes[[#This Row],[fecha_inicio]],2))) | T38: =IF(tblOrdenes[[#This Row],[tipo_ot]]="","",_xlfn.XLOOKUP(tblOrdenes[[#This Row],[tipo_ot]],tblTiposOT[codigo],tblTiposOT[clasificacion],"sin_clasificar")) | U38: =IF(tblOrdenes[[#This Row],[centro_costo]]="","",_xlfn.XLOOKUP(tblOrdenes[[#This Row],[centro_costo]],tblCECO[codigo],tblCECO[linea],"(sin catálogo)")) | V38: =IF(tblOrdenes[[#This Row],[centro_costo]]="","",_xlfn.XLOOKUP(tblOrdenes[[#This Row],[centro_costo]],tblCECO[codigo],tblCECO[area],"(sin catálogo)")) | W38: =IF(tblOrdenes[[#This Row],[centro_costo]]="","",_xlfn.XLOOKUP(tblOrdenes[[#This Row],[centro_costo]],tblCECO[codigo],tblCECO[coordinador],"(sin catálogo)")) | X38: =IF(tblOrdenes[[#This Row],[puesto_trabajo]]="","",_xlfn.XLOOKUP(tblOrdenes[[#This Row],[puesto_trabajo]],tblPuestos[codigo],tblPuestos[especialidad],"(sin catálogo)")) | Y38: =IF(tblOrdenes[[#This Row],[cod_actividad]]="","",_xlfn.XLOOKUP(tblOrdenes[[#This Row],[cod_actividad]],tblActividades[codigo],tblActividades[descripcion],"(sin catálogo)")) | Z38: =IF(tblOrdenes[[#This Row],[fecha_inicio]]="","",TODAY()-tblOrdenes[[#This Row],[fecha_inicio]]) | AA38: =IF(tblOrdenes[[#This Row],[backlog_dias]]="","",IF(tblOrdenes[[#This Row],[backlog_dias]]<0,"FUTURO",IF(tblOrdenes[[#This Row],[backlog_dias]]>p_dias_backlog_max,"BACKLOG","MES CORRIENTE"))) | AB38: =IF(tblOrdenes[[#This Row],[backlog_dias]]="",FALSE,AND(tblOrdenes[[#This Row],[backlog_dias]]>p_dias_backlog_min,tblOrdenes[[#This Row],[backlog_dias]]<=p_dias_backlog_max)) | AC38: Técnico 02 | AD38: =IF(tblOrdenes[[#This Row],[tecnico_asignado]]="","",_xlfn.XLOOKUP(tblOrdenes[[#This Row],[semana]]&"|"&tblOrdenes[[#This Row],[dia_semana]]&"|"&tblOrdenes[[#This Row],[tecnico_asignado]],tblAsignaciones[clave],tblAsignaciones[turno],"")) | AE38: =IF(tblOrdenes[[#This Row],[tecnico_asignado]]="","",SUMIFS(tblOrdenes[horas_efectivas],tblOrdenes[tecnico_asignado],tblOrdenes[[#This Row],[tecnico_asignado]],tblOrdenes[semana],tblOrdenes[[#This Row],[semana]],tblOrdenes[dia_semana],tblOrdenes[[#This Row],[dia_semana]])) | AF38: =IF(tblOrdenes[[#This Row],[HHA]]="","",p_factor_productividad*_xlfn.XLOOKUP(tblOrdenes[[#This Row],[semana]]&"|"&tblOrdenes[[#This Row],[dia_semana]]&"|"&tblOrdenes[[#This Row],[tecnico_asignado]],tblAsignaciones[clave],tblAsignaciones[horas_disponibles],0)-tblOrdenes[[#This Row],[HHA]]) | AG38: =IF(tblOrdenes[[#This Row],[orden]]="","",_xlfn.XLOOKUP(tblOrdenes[[#This Row],[id_operacion]],tblEjecucion[id_operacion],tblEjecucion[precio],0)) | AH38: =IF(tblOrdenes[[#This Row],[orden]]="","",MAX(0,_xlfn.XLOOKUP(tblOrdenes[[#This Row],[id_operacion]],tblEjecucion[id_operacion],tblEjecucion[costo_plan_total],0)-tblOrdenes[[#This Row],[costo_servicio]])) | AI38: =IF(tblOrdenes[[#This Row],[orden]]="","",tblOrdenes[[#This Row],[costo_servicio]]+tblOrdenes[[#This Row],[costo_materiales]]) | AL38: ACT-04.pdf | AM38: =IF(tblOrdenes[[#This Row],[link_checklist]]="","",HYPERLINK(p_ruta_base_checklists&tblOrdenes[[#This Row],[link_checklist]],"abrir")) | AO38: =IF(tblOrdenes[[#This Row],[orden]]="","",tblOrdenes[[#This Row],[orden]]&IF(tblOrdenes[[#This Row],[operacion]]="","0010",tblOrdenes[[#This Row],[operacion]]))
A39: OT-000036 | B39: 0010 | C39: Reparación de falla — EQ-110 | D39: Reparación de falla en EQ-110 | E39: EQ-110 | F39: CC-310 | G39: PU-MEC | H39: ACT-03 | I39: TIPO-C1 | J39: 46230 | K39: 10 | L39: 400 | N39: =IF(tblOrdenes[[#This Row],[orden]]="","",IF(tblOrdenes[[#This Row],[horas_ajustadas]]<>"",tblOrdenes[[#This Row],[horas_ajustadas]],IF(tblOrdenes[[#This Row],[horas_estimadas]]="","",tblOrdenes[[#This Row],[horas_estimadas]]))) | O39: =IF(tblOrdenes[[#This Row],[orden]]="","",_xlfn.XLOOKUP(_xlfn.XLOOKUP(tblOrdenes[[#This Row],[id_operacion]],tblEjecucion[id_operacion],tblEjecucion[estado_sistema],""),tblEstados[estado_sistema],tblEstados[estado_normalizado],"Pendiente")) | P39: =IF(tblOrdenes[[#This Row],[fecha_inicio]]="","",YEAR(tblOrdenes[[#This Row],[fecha_inicio]]+4-WEEKDAY(tblOrdenes[[#This Row],[fecha_inicio]],2))&"-S"&TEXT(_xlfn.ISOWEEKNUM(tblOrdenes[[#This Row],[fecha_inicio]]),"00")) | Q39: =IF(tblOrdenes[[#This Row],[fecha_inicio]]="","",YEAR(tblOrdenes[[#This Row],[fecha_inicio]])) | R39: =IF(tblOrdenes[[#This Row],[fecha_inicio]]="","",MONTH(tblOrdenes[[#This Row],[fecha_inicio]])) | S39: =IF(tblOrdenes[[#This Row],[fecha_inicio]]="","",INDEX(lista_dias,WEEKDAY(tblOrdenes[[#This Row],[fecha_inicio]],2))) | T39: =IF(tblOrdenes[[#This Row],[tipo_ot]]="","",_xlfn.XLOOKUP(tblOrdenes[[#This Row],[tipo_ot]],tblTiposOT[codigo],tblTiposOT[clasificacion],"sin_clasificar")) | U39: =IF(tblOrdenes[[#This Row],[centro_costo]]="","",_xlfn.XLOOKUP(tblOrdenes[[#This Row],[centro_costo]],tblCECO[codigo],tblCECO[linea],"(sin catálogo)")) | V39: =IF(tblOrdenes[[#This Row],[centro_costo]]="","",_xlfn.XLOOKUP(tblOrdenes[[#This Row],[centro_costo]],tblCECO[codigo],tblCECO[area],"(sin catálogo)")) | W39: =IF(tblOrdenes[[#This Row],[centro_costo]]="","",_xlfn.XLOOKUP(tblOrdenes[[#This Row],[centro_costo]],tblCECO[codigo],tblCECO[coordinador],"(sin catálogo)")) | X39: =IF(tblOrdenes[[#This Row],[puesto_trabajo]]="","",_xlfn.XLOOKUP(tblOrdenes[[#This Row],[puesto_trabajo]],tblPuestos[codigo],tblPuestos[especialidad],"(sin catálogo)")) | Y39: =IF(tblOrdenes[[#This Row],[cod_actividad]]="","",_xlfn.XLOOKUP(tblOrdenes[[#This Row],[cod_actividad]],tblActividades[codigo],tblActividades[descripcion],"(sin catálogo)")) | Z39: =IF(tblOrdenes[[#This Row],[fecha_inicio]]="","",TODAY()-tblOrdenes[[#This Row],[fecha_inicio]]) | AA39: =IF(tblOrdenes[[#This Row],[backlog_dias]]="","",IF(tblOrdenes[[#This Row],[backlog_dias]]<0,"FUTURO",IF(tblOrdenes[[#This Row],[backlog_dias]]>p_dias_backlog_max,"BACKLOG","MES CORRIENTE"))) | AB39: =IF(tblOrdenes[[#This Row],[backlog_dias]]="",FALSE,AND(tblOrdenes[[#This Row],[backlog_dias]]>p_dias_backlog_min,tblOrdenes[[#This Row],[backlog_dias]]<=p_dias_backlog_max)) | AD39: =IF(tblOrdenes[[#This Row],[tecnico_asignado]]="","",_xlfn.XLOOKUP(tblOrdenes[[#This Row],[semana]]&"|"&tblOrdenes[[#This Row],[dia_semana]]&"|"&tblOrdenes[[#This Row],[tecnico_asignado]],tblAsignaciones[clave],tblAsignaciones[turno],"")) | AE39: =IF(tblOrdenes[[#This Row],[tecnico_asignado]]="","",SUMIFS(tblOrdenes[horas_efectivas],tblOrdenes[tecnico_asignado],tblOrdenes[[#This Row],[tecnico_asignado]],tblOrdenes[semana],tblOrdenes[[#This Row],[semana]],tblOrdenes[dia_semana],tblOrdenes[[#This Row],[dia_semana]])) | AF39: =IF(tblOrdenes[[#This Row],[HHA]]="","",p_factor_productividad*_xlfn.XLOOKUP(tblOrdenes[[#This Row],[semana]]&"|"&tblOrdenes[[#This Row],[dia_semana]]&"|"&tblOrdenes[[#This Row],[tecnico_asignado]],tblAsignaciones[clave],tblAsignaciones[horas_disponibles],0)-tblOrdenes[[#This Row],[HHA]]) | AG39: =IF(tblOrdenes[[#This Row],[orden]]="","",_xlfn.XLOOKUP(tblOrdenes[[#This Row],[id_operacion]],tblEjecucion[id_operacion],tblEjecucion[precio],0)) | AH39: =IF(tblOrdenes[[#This Row],[orden]]="","",MAX(0,_xlfn.XLOOKUP(tblOrdenes[[#This Row],[id_operacion]],tblEjecucion[id_operacion],tblEjecucion[costo_plan_total],0)-tblOrdenes[[#This Row],[costo_servicio]])) | AI39: =IF(tblOrdenes[[#This Row],[orden]]="","",tblOrdenes[[#This Row],[costo_servicio]]+tblOrdenes[[#This Row],[costo_materiales]]) | AJ39: PT-CALIENTE | AK39: LOTO | AM39: =IF(tblOrdenes[[#This Row],[link_checklist]]="","",HYPERLINK(p_ruta_base_checklists&tblOrdenes[[#This Row],[link_checklist]],"abrir")) | AO39: =IF(tblOrdenes[[#This Row],[orden]]="","",tblOrdenes[[#This Row],[orden]]&IF(tblOrdenes[[#This Row],[operacion]]="","0010",tblOrdenes[[#This Row],[operacion]]))
A40: OT-000037 | B40: 0010 | C40: Reparación de falla — EQ-103 | D40: Reparación de falla en EQ-103 | E40: EQ-103 | F40: CC-110 | G40: PU-MEC | H40: ACT-03 | I40: TIPO-C2 | J40: 46231 | K40: 10 | L40: 400 | N40: =IF(tblOrdenes[[#This Row],[orden]]="","",IF(tblOrdenes[[#This Row],[horas_ajustadas]]<>"",tblOrdenes[[#This Row],[horas_ajustadas]],IF(tblOrdenes[[#This Row],[horas_estimadas]]="","",tblOrdenes[[#This Row],[horas_estimadas]]))) | O40: =IF(tblOrdenes[[#This Row],[orden]]="","",_xlfn.XLOOKUP(_xlfn.XLOOKUP(tblOrdenes[[#This Row],[id_operacion]],tblEjecucion[id_operacion],tblEjecucion[estado_sistema],""),tblEstados[estado_sistema],tblEstados[estado_normalizado],"Pendiente")) | P40: =IF(tblOrdenes[[#This Row],[fecha_inicio]]="","",YEAR(tblOrdenes[[#This Row],[fecha_inicio]]+4-WEEKDAY(tblOrdenes[[#This Row],[fecha_inicio]],2))&"-S"&TEXT(_xlfn.ISOWEEKNUM(tblOrdenes[[#This Row],[fecha_inicio]]),"00")) | Q40: =IF(tblOrdenes[[#This Row],[fecha_inicio]]="","",YEAR(tblOrdenes[[#This Row],[fecha_inicio]])) | R40: =IF(tblOrdenes[[#This Row],[fecha_inicio]]="","",MONTH(tblOrdenes[[#This Row],[fecha_inicio]])) | S40: =IF(tblOrdenes[[#This Row],[fecha_inicio]]="","",INDEX(lista_dias,WEEKDAY(tblOrdenes[[#This Row],[fecha_inicio]],2))) | T40: =IF(tblOrdenes[[#This Row],[tipo_ot]]="","",_xlfn.XLOOKUP(tblOrdenes[[#This Row],[tipo_ot]],tblTiposOT[codigo],tblTiposOT[clasificacion],"sin_clasificar")) | U40: =IF(tblOrdenes[[#This Row],[centro_costo]]="","",_xlfn.XLOOKUP(tblOrdenes[[#This Row],[centro_costo]],tblCECO[codigo],tblCECO[linea],"(sin catálogo)")) | V40: =IF(tblOrdenes[[#This Row],[centro_costo]]="","",_xlfn.XLOOKUP(tblOrdenes[[#This Row],[centro_costo]],tblCECO[codigo],tblCECO[area],"(sin catálogo)")) | W40: =IF(tblOrdenes[[#This Row],[centro_costo]]="","",_xlfn.XLOOKUP(tblOrdenes[[#This Row],[centro_costo]],tblCECO[codigo],tblCECO[coordinador],"(sin catálogo)")) | X40: =IF(tblOrdenes[[#This Row],[puesto_trabajo]]="","",_xlfn.XLOOKUP(tblOrdenes[[#This Row],[puesto_trabajo]],tblPuestos[codigo],tblPuestos[especialidad],"(sin catálogo)")) | Y40: =IF(tblOrdenes[[#This Row],[cod_actividad]]="","",_xlfn.XLOOKUP(tblOrdenes[[#This Row],[cod_actividad]],tblActividades[codigo],tblActividades[descripcion],"(sin catálogo)")) | Z40: =IF(tblOrdenes[[#This Row],[fecha_inicio]]="","",TODAY()-tblOrdenes[[#This Row],[fecha_inicio]]) | AA40: =IF(tblOrdenes[[#This Row],[backlog_dias]]="","",IF(tblOrdenes[[#This Row],[backlog_dias]]<0,"FUTURO",IF(tblOrdenes[[#This Row],[backlog_dias]]>p_dias_backlog_max,"BACKLOG","MES CORRIENTE"))) | AB40: =IF(tblOrdenes[[#This Row],[backlog_dias]]="",FALSE,AND(tblOrdenes[[#This Row],[backlog_dias]]>p_dias_backlog_min,tblOrdenes[[#This Row],[backlog_dias]]<=p_dias_backlog_max)) | AC40: Técnico 01 | AD40: =IF(tblOrdenes[[#This Row],[tecnico_asignado]]="","",_xlfn.XLOOKUP(tblOrdenes[[#This Row],[semana]]&"|"&tblOrdenes[[#This Row],[dia_semana]]&"|"&tblOrdenes[[#This Row],[tecnico_asignado]],tblAsignaciones[clave],tblAsignaciones[turno],"")) | AE40: =IF(tblOrdenes[[#This Row],[tecnico_asignado]]="","",SUMIFS(tblOrdenes[horas_efectivas],tblOrdenes[tecnico_asignado],tblOrdenes[[#This Row],[tecnico_asignado]],tblOrdenes[semana],tblOrdenes[[#This Row],[semana]],tblOrdenes[dia_semana],tblOrdenes[[#This Row],[dia_semana]])) | AF40: =IF(tblOrdenes[[#This Row],[HHA]]="","",p_factor_productividad*_xlfn.XLOOKUP(tblOrdenes[[#This Row],[semana]]&"|"&tblOrdenes[[#This Row],[dia_semana]]&"|"&tblOrdenes[[#This Row],[tecnico_asignado]],tblAsignaciones[clave],tblAsignaciones[horas_disponibles],0)-tblOrdenes[[#This Row],[HHA]]) | AG40: =IF(tblOrdenes[[#This Row],[orden]]="","",_xlfn.XLOOKUP(tblOrdenes[[#This Row],[id_operacion]],tblEjecucion[id_operacion],tblEjecucion[precio],0)) | AH40: =IF(tblOrdenes[[#This Row],[orden]]="","",MAX(0,_xlfn.XLOOKUP(tblOrdenes[[#This Row],[id_operacion]],tblEjecucion[id_operacion],tblEjecucion[costo_plan_total],0)-tblOrdenes[[#This Row],[costo_servicio]])) | AI40: =IF(tblOrdenes[[#This Row],[orden]]="","",tblOrdenes[[#This Row],[costo_servicio]]+tblOrdenes[[#This Row],[costo_materiales]]) | AM40: =IF(tblOrdenes[[#This Row],[link_checklist]]="","",HYPERLINK(p_ruta_base_checklists&tblOrdenes[[#This Row],[link_checklist]],"abrir")) | AO40: =IF(tblOrdenes[[#This Row],[orden]]="","",tblOrdenes[[#This Row],[orden]]&IF(tblOrdenes[[#This Row],[operacion]]="","0010",tblOrdenes[[#This Row],[operacion]]))
A41: OT-000038 | B41: 0010 | C41: Análisis predictivo — EQ-108 | D41: Análisis predictivo en EQ-108 | E41: EQ-108 | F41: CC-210 | G41: PU-MEC | H41: ACT-04 | I41: TIPO-P1 | J41: 46239 | K41: 10 | L41: 250 | N41: =IF(tblOrdenes[[#This Row],[orden]]="","",IF(tblOrdenes[[#This Row],[horas_ajustadas]]<>"",tblOrdenes[[#This Row],[horas_ajustadas]],IF(tblOrdenes[[#This Row],[horas_estimadas]]="","",tblOrdenes[[#This Row],[horas_estimadas]]))) | O41: =IF(tblOrdenes[[#This Row],[orden]]="","",_xlfn.XLOOKUP(_xlfn.XLOOKUP(tblOrdenes[[#This Row],[id_operacion]],tblEjecucion[id_operacion],tblEjecucion[estado_sistema],""),tblEstados[estado_sistema],tblEstados[estado_normalizado],"Pendiente")) | P41: =IF(tblOrdenes[[#This Row],[fecha_inicio]]="","",YEAR(tblOrdenes[[#This Row],[fecha_inicio]]+4-WEEKDAY(tblOrdenes[[#This Row],[fecha_inicio]],2))&"-S"&TEXT(_xlfn.ISOWEEKNUM(tblOrdenes[[#This Row],[fecha_inicio]]),"00")) | Q41: =IF(tblOrdenes[[#This Row],[fecha_inicio]]="","",YEAR(tblOrdenes[[#This Row],[fecha_inicio]])) | R41: =IF(tblOrdenes[[#This Row],[fecha_inicio]]="","",MONTH(tblOrdenes[[#This Row],[fecha_inicio]])) | S41: =IF(tblOrdenes[[#This Row],[fecha_inicio]]="","",INDEX(lista_dias,WEEKDAY(tblOrdenes[[#This Row],[fecha_inicio]],2))) | T41: =IF(tblOrdenes[[#This Row],[tipo_ot]]="","",_xlfn.XLOOKUP(tblOrdenes[[#This Row],[tipo_ot]],tblTiposOT[codigo],tblTiposOT[clasificacion],"sin_clasificar")) | U41: =IF(tblOrdenes[[#This Row],[centro_costo]]="","",_xlfn.XLOOKUP(tblOrdenes[[#This Row],[centro_costo]],tblCECO[codigo],tblCECO[linea],"(sin catálogo)")) | V41: =IF(tblOrdenes[[#This Row],[centro_costo]]="","",_xlfn.XLOOKUP(tblOrdenes[[#This Row],[centro_costo]],tblCECO[codigo],tblCECO[area],"(sin catálogo)")) | W41: =IF(tblOrdenes[[#This Row],[centro_costo]]="","",_xlfn.XLOOKUP(tblOrdenes[[#This Row],[centro_costo]],tblCECO[codigo],tblCECO[coordinador],"(sin catálogo)")) | X41: =IF(tblOrdenes[[#This Row],[puesto_trabajo]]="","",_xlfn.XLOOKUP(tblOrdenes[[#This Row],[puesto_trabajo]],tblPuestos[codigo],tblPuestos[especialidad],"(sin catálogo)")) | Y41: =IF(tblOrdenes[[#This Row],[cod_actividad]]="","",_xlfn.XLOOKUP(tblOrdenes[[#This Row],[cod_actividad]],tblActividades[codigo],tblActividades[descripcion],"(sin catálogo)")) | Z41: =IF(tblOrdenes[[#This Row],[fecha_inicio]]="","",TODAY()-tblOrdenes[[#This Row],[fecha_inicio]]) | AA41: =IF(tblOrdenes[[#This Row],[backlog_dias]]="","",IF(tblOrdenes[[#This Row],[backlog_dias]]<0,"FUTURO",IF(tblOrdenes[[#This Row],[backlog_dias]]>p_dias_backlog_max,"BACKLOG","MES CORRIENTE"))) | AB41: =IF(tblOrdenes[[#This Row],[backlog_dias]]="",FALSE,AND(tblOrdenes[[#This Row],[backlog_dias]]>p_dias_backlog_min,tblOrdenes[[#This Row],[backlog_dias]]<=p_dias_backlog_max)) | AC41: Técnico 02 | AD41: =IF(tblOrdenes[[#This Row],[tecnico_asignado]]="","",_xlfn.XLOOKUP(tblOrdenes[[#This Row],[semana]]&"|"&tblOrdenes[[#This Row],[dia_semana]]&"|"&tblOrdenes[[#This Row],[tecnico_asignado]],tblAsignaciones[clave],tblAsignaciones[turno],"")) | AE41: =IF(tblOrdenes[[#This Row],[tecnico_asignado]]="","",SUMIFS(tblOrdenes[horas_efectivas],tblOrdenes[tecnico_asignado],tblOrdenes[[#This Row],[tecnico_asignado]],tblOrdenes[semana],tblOrdenes[[#This Row],[semana]],tblOrdenes[dia_semana],tblOrdenes[[#This Row],[dia_semana]])) | AF41: =IF(tblOrdenes[[#This Row],[HHA]]="","",p_factor_productividad*_xlfn.XLOOKUP(tblOrdenes[[#This Row],[semana]]&"|"&tblOrdenes[[#This Row],[dia_semana]]&"|"&tblOrdenes[[#This Row],[tecnico_asignado]],tblAsignaciones[clave],tblAsignaciones[horas_disponibles],0)-tblOrdenes[[#This Row],[HHA]]) | AG41: =IF(tblOrdenes[[#This Row],[orden]]="","",_xlfn.XLOOKUP(tblOrdenes[[#This Row],[id_operacion]],tblEjecucion[id_operacion],tblEjecucion[precio],0)) | AH41: =IF(tblOrdenes[[#This Row],[orden]]="","",MAX(0,_xlfn.XLOOKUP(tblOrdenes[[#This Row],[id_operacion]],tblEjecucion[id_operacion],tblEjecucion[costo_plan_total],0)-tblOrdenes[[#This Row],[costo_servicio]])) | AI41: =IF(tblOrdenes[[#This Row],[orden]]="","",tblOrdenes[[#This Row],[costo_servicio]]+tblOrdenes[[#This Row],[costo_materiales]]) | AL41: ACT-04.pdf | AM41: =IF(tblOrdenes[[#This Row],[link_checklist]]="","",HYPERLINK(p_ruta_base_checklists&tblOrdenes[[#This Row],[link_checklist]],"abrir")) | AO41: =IF(tblOrdenes[[#This Row],[orden]]="","",tblOrdenes[[#This Row],[orden]]&IF(tblOrdenes[[#This Row],[operacion]]="","0010",tblOrdenes[[#This Row],[operacion]]))
A42: OT-000039 | B42: 0010 | C42: Inspección de rutina — EQ-110 | D42: Inspección de rutina en EQ-110 | E42: EQ-110 | F42: CC-310 | G42: PU-MEC | H42: ACT-01 | I42: TIPO-P2 | J42: 46240 | K42: 8 | L42: 200 | N42: =IF(tblOrdenes[[#This Row],[orden]]="","",IF(tblOrdenes[[#This Row],[horas_ajustadas]]<>"",tblOrdenes[[#This Row],[horas_ajustadas]],IF(tblOrdenes[[#This Row],[horas_estimadas]]="","",tblOrdenes[[#This Row],[horas_estimadas]]))) | O42: =IF(tblOrdenes[[#This Row],[orden]]="","",_xlfn.XLOOKUP(_xlfn.XLOOKUP(tblOrdenes[[#This Row],[id_operacion]],tblEjecucion[id_operacion],tblEjecucion[estado_sistema],""),tblEstados[estado_sistema],tblEstados[estado_normalizado],"Pendiente")) | P42: =IF(tblOrdenes[[#This Row],[fecha_inicio]]="","",YEAR(tblOrdenes[[#This Row],[fecha_inicio]]+4-WEEKDAY(tblOrdenes[[#This Row],[fecha_inicio]],2))&"-S"&TEXT(_xlfn.ISOWEEKNUM(tblOrdenes[[#This Row],[fecha_inicio]]),"00")) | Q42: =IF(tblOrdenes[[#This Row],[fecha_inicio]]="","",YEAR(tblOrdenes[[#This Row],[fecha_inicio]])) | R42: =IF(tblOrdenes[[#This Row],[fecha_inicio]]="","",MONTH(tblOrdenes[[#This Row],[fecha_inicio]])) | S42: =IF(tblOrdenes[[#This Row],[fecha_inicio]]="","",INDEX(lista_dias,WEEKDAY(tblOrdenes[[#This Row],[fecha_inicio]],2))) | T42: =IF(tblOrdenes[[#This Row],[tipo_ot]]="","",_xlfn.XLOOKUP(tblOrdenes[[#This Row],[tipo_ot]],tblTiposOT[codigo],tblTiposOT[clasificacion],"sin_clasificar")) | U42: =IF(tblOrdenes[[#This Row],[centro_costo]]="","",_xlfn.XLOOKUP(tblOrdenes[[#This Row],[centro_costo]],tblCECO[codigo],tblCECO[linea],"(sin catálogo)")) | V42: =IF(tblOrdenes[[#This Row],[centro_costo]]="","",_xlfn.XLOOKUP(tblOrdenes[[#This Row],[centro_costo]],tblCECO[codigo],tblCECO[area],"(sin catálogo)")) | W42: =IF(tblOrdenes[[#This Row],[centro_costo]]="","",_xlfn.XLOOKUP(tblOrdenes[[#This Row],[centro_costo]],tblCECO[codigo],tblCECO[coordinador],"(sin catálogo)")) | X42: =IF(tblOrdenes[[#This Row],[puesto_trabajo]]="","",_xlfn.XLOOKUP(tblOrdenes[[#This Row],[puesto_trabajo]],tblPuestos[codigo],tblPuestos[especialidad],"(sin catálogo)")) | Y42: =IF(tblOrdenes[[#This Row],[cod_actividad]]="","",_xlfn.XLOOKUP(tblOrdenes[[#This Row],[cod_actividad]],tblActividades[codigo],tblActividades[descripcion],"(sin catálogo)")) | Z42: =IF(tblOrdenes[[#This Row],[fecha_inicio]]="","",TODAY()-tblOrdenes[[#This Row],[fecha_inicio]]) | AA42: =IF(tblOrdenes[[#This Row],[backlog_dias]]="","",IF(tblOrdenes[[#This Row],[backlog_dias]]<0,"FUTURO",IF(tblOrdenes[[#This Row],[backlog_dias]]>p_dias_backlog_max,"BACKLOG","MES CORRIENTE"))) | AB42: =IF(tblOrdenes[[#This Row],[backlog_dias]]="",FALSE,AND(tblOrdenes[[#This Row],[backlog_dias]]>p_dias_backlog_min,tblOrdenes[[#This Row],[backlog_dias]]<=p_dias_backlog_max)) | AC42: Técnico 03 | AD42: =IF(tblOrdenes[[#This Row],[tecnico_asignado]]="","",_xlfn.XLOOKUP(tblOrdenes[[#This Row],[semana]]&"|"&tblOrdenes[[#This Row],[dia_semana]]&"|"&tblOrdenes[[#This Row],[tecnico_asignado]],tblAsignaciones[clave],tblAsignaciones[turno],"")) | AE42: =IF(tblOrdenes[[#This Row],[tecnico_asignado]]="","",SUMIFS(tblOrdenes[horas_efectivas],tblOrdenes[tecnico_asignado],tblOrdenes[[#This Row],[tecnico_asignado]],tblOrdenes[semana],tblOrdenes[[#This Row],[semana]],tblOrdenes[dia_semana],tblOrdenes[[#This Row],[dia_semana]])) | AF42: =IF(tblOrdenes[[#This Row],[HHA]]="","",p_factor_productividad*_xlfn.XLOOKUP(tblOrdenes[[#This Row],[semana]]&"|"&tblOrdenes[[#This Row],[dia_semana]]&"|"&tblOrdenes[[#This Row],[tecnico_asignado]],tblAsignaciones[clave],tblAsignaciones[horas_disponibles],0)-tblOrdenes[[#This Row],[HHA]]) | AG42: =IF(tblOrdenes[[#This Row],[orden]]="","",_xlfn.XLOOKUP(tblOrdenes[[#This Row],[id_operacion]],tblEjecucion[id_operacion],tblEjecucion[precio],0)) | AH42: =IF(tblOrdenes[[#This Row],[orden]]="","",MAX(0,_xlfn.XLOOKUP(tblOrdenes[[#This Row],[id_operacion]],tblEjecucion[id_operacion],tblEjecucion[costo_plan_total],0)-tblOrdenes[[#This Row],[costo_servicio]])) | AI42: =IF(tblOrdenes[[#This Row],[orden]]="","",tblOrdenes[[#This Row],[costo_servicio]]+tblOrdenes[[#This Row],[costo_materiales]]) | AL42: ACT-01.pdf | AM42: =IF(tblOrdenes[[#This Row],[link_checklist]]="","",HYPERLINK(p_ruta_base_checklists&tblOrdenes[[#This Row],[link_checklist]],"abrir")) | AO42: =IF(tblOrdenes[[#This Row],[orden]]="","",tblOrdenes[[#This Row],[orden]]&IF(tblOrdenes[[#This Row],[operacion]]="","0010",tblOrdenes[[#This Row],[operacion]]))
A43: OT-000040 | B43: 0010 | C43: Lubricación programada — EQ-101 | D43: Lubricación programada en EQ-101 | E43: EQ-101 | F43: CC-110 | G43: PU-MEC | H43: ACT-02 | I43: TIPO-P1 | J43: 46241 | K43: 6 | L43: 150 | N43: =IF(tblOrdenes[[#This Row],[orden]]="","",IF(tblOrdenes[[#This Row],[horas_ajustadas]]<>"",tblOrdenes[[#This Row],[horas_ajustadas]],IF(tblOrdenes[[#This Row],[horas_estimadas]]="","",tblOrdenes[[#This Row],[horas_estimadas]]))) | O43: =IF(tblOrdenes[[#This Row],[orden]]="","",_xlfn.XLOOKUP(_xlfn.XLOOKUP(tblOrdenes[[#This Row],[id_operacion]],tblEjecucion[id_operacion],tblEjecucion[estado_sistema],""),tblEstados[estado_sistema],tblEstados[estado_normalizado],"Pendiente")) | P43: =IF(tblOrdenes[[#This Row],[fecha_inicio]]="","",YEAR(tblOrdenes[[#This Row],[fecha_inicio]]+4-WEEKDAY(tblOrdenes[[#This Row],[fecha_inicio]],2))&"-S"&TEXT(_xlfn.ISOWEEKNUM(tblOrdenes[[#This Row],[fecha_inicio]]),"00")) | Q43: =IF(tblOrdenes[[#This Row],[fecha_inicio]]="","",YEAR(tblOrdenes[[#This Row],[fecha_inicio]])) | R43: =IF(tblOrdenes[[#This Row],[fecha_inicio]]="","",MONTH(tblOrdenes[[#This Row],[fecha_inicio]])) | S43: =IF(tblOrdenes[[#This Row],[fecha_inicio]]="","",INDEX(lista_dias,WEEKDAY(tblOrdenes[[#This Row],[fecha_inicio]],2))) | T43: =IF(tblOrdenes[[#This Row],[tipo_ot]]="","",_xlfn.XLOOKUP(tblOrdenes[[#This Row],[tipo_ot]],tblTiposOT[codigo],tblTiposOT[clasificacion],"sin_clasificar")) | U43: =IF(tblOrdenes[[#This Row],[centro_costo]]="","",_xlfn.XLOOKUP(tblOrdenes[[#This Row],[centro_costo]],tblCECO[codigo],tblCECO[linea],"(sin catálogo)")) | V43: =IF(tblOrdenes[[#This Row],[centro_costo]]="","",_xlfn.XLOOKUP(tblOrdenes[[#This Row],[centro_costo]],tblCECO[codigo],tblCECO[area],"(sin catálogo)")) | W43: =IF(tblOrdenes[[#This Row],[centro_costo]]="","",_xlfn.XLOOKUP(tblOrdenes[[#This Row],[centro_costo]],tblCECO[codigo],tblCECO[coordinador],"(sin catálogo)")) | X43: =IF(tblOrdenes[[#This Row],[puesto_trabajo]]="","",_xlfn.XLOOKUP(tblOrdenes[[#This Row],[puesto_trabajo]],tblPuestos[codigo],tblPuestos[especialidad],"(sin catálogo)")) | Y43: =IF(tblOrdenes[[#This Row],[cod_actividad]]="","",_xlfn.XLOOKUP(tblOrdenes[[#This Row],[cod_actividad]],tblActividades[codigo],tblActividades[descripcion],"(sin catálogo)")) | Z43: =IF(tblOrdenes[[#This Row],[fecha_inicio]]="","",TODAY()-tblOrdenes[[#This Row],[fecha_inicio]]) | AA43: =IF(tblOrdenes[[#This Row],[backlog_dias]]="","",IF(tblOrdenes[[#This Row],[backlog_dias]]<0,"FUTURO",IF(tblOrdenes[[#This Row],[backlog_dias]]>p_dias_backlog_max,"BACKLOG","MES CORRIENTE"))) | AB43: =IF(tblOrdenes[[#This Row],[backlog_dias]]="",FALSE,AND(tblOrdenes[[#This Row],[backlog_dias]]>p_dias_backlog_min,tblOrdenes[[#This Row],[backlog_dias]]<=p_dias_backlog_max)) | AC43: Técnico 04 | AD43: =IF(tblOrdenes[[#This Row],[tecnico_asignado]]="","",_xlfn.XLOOKUP(tblOrdenes[[#This Row],[semana]]&"|"&tblOrdenes[[#This Row],[dia_semana]]&"|"&tblOrdenes[[#This Row],[tecnico_asignado]],tblAsignaciones[clave],tblAsignaciones[turno],"")) | AE43: =IF(tblOrdenes[[#This Row],[tecnico_asignado]]="","",SUMIFS(tblOrdenes[horas_efectivas],tblOrdenes[tecnico_asignado],tblOrdenes[[#This Row],[tecnico_asignado]],tblOrdenes[semana],tblOrdenes[[#This Row],[semana]],tblOrdenes[dia_semana],tblOrdenes[[#This Row],[dia_semana]])) | AF43: =IF(tblOrdenes[[#This Row],[HHA]]="","",p_factor_productividad*_xlfn.XLOOKUP(tblOrdenes[[#This Row],[semana]]&"|"&tblOrdenes[[#This Row],[dia_semana]]&"|"&tblOrdenes[[#This Row],[tecnico_asignado]],tblAsignaciones[clave],tblAsignaciones[horas_disponibles],0)-tblOrdenes[[#This Row],[HHA]]) | AG43: =IF(tblOrdenes[[#This Row],[orden]]="","",_xlfn.XLOOKUP(tblOrdenes[[#This Row],[id_operacion]],tblEjecucion[id_operacion],tblEjecucion[precio],0)) | AH43: =IF(tblOrdenes[[#This Row],[orden]]="","",MAX(0,_xlfn.XLOOKUP(tblOrdenes[[#This Row],[id_operacion]],tblEjecucion[id_operacion],tblEjecucion[costo_plan_total],0)-tblOrdenes[[#This Row],[costo_servicio]])) | AI43: =IF(tblOrdenes[[#This Row],[orden]]="","",tblOrdenes[[#This Row],[costo_servicio]]+tblOrdenes[[#This Row],[costo_materiales]]) | AL43: ACT-02.pdf | AM43: =IF(tblOrdenes[[#This Row],[link_checklist]]="","",HYPERLINK(p_ruta_base_checklists&tblOrdenes[[#This Row],[link_checklist]],"abrir")) | AO43: =IF(tblOrdenes[[#This Row],[orden]]="","",tblOrdenes[[#This Row],[orden]]&IF(tblOrdenes[[#This Row],[operacion]]="","0010",tblOrdenes[[#This Row],[operacion]]))
A44: OT-000041 | B44: 0010 | C44: Análisis predictivo — EQ-107 | D44: Análisis predictivo en EQ-107 | E44: EQ-107 | F44: CC-210 | G44: PU-MEC | H44: ACT-04 | I44: TIPO-P2 | J44: 46237 | K44: 10 | L44: 250 | N44: =IF(tblOrdenes[[#This Row],[orden]]="","",IF(tblOrdenes[[#This Row],[horas_ajustadas]]<>"",tblOrdenes[[#This Row],[horas_ajustadas]],IF(tblOrdenes[[#This Row],[horas_estimadas]]="","",tblOrdenes[[#This Row],[horas_estimadas]]))) | O44: =IF(tblOrdenes[[#This Row],[orden]]="","",_xlfn.XLOOKUP(_xlfn.XLOOKUP(tblOrdenes[[#This Row],[id_operacion]],tblEjecucion[id_operacion],tblEjecucion[estado_sistema],""),tblEstados[estado_sistema],tblEstados[estado_normalizado],"Pendiente")) | P44: =IF(tblOrdenes[[#This Row],[fecha_inicio]]="","",YEAR(tblOrdenes[[#This Row],[fecha_inicio]]+4-WEEKDAY(tblOrdenes[[#This Row],[fecha_inicio]],2))&"-S"&TEXT(_xlfn.ISOWEEKNUM(tblOrdenes[[#This Row],[fecha_inicio]]),"00")) | Q44: =IF(tblOrdenes[[#This Row],[fecha_inicio]]="","",YEAR(tblOrdenes[[#This Row],[fecha_inicio]])) | R44: =IF(tblOrdenes[[#This Row],[fecha_inicio]]="","",MONTH(tblOrdenes[[#This Row],[fecha_inicio]])) | S44: =IF(tblOrdenes[[#This Row],[fecha_inicio]]="","",INDEX(lista_dias,WEEKDAY(tblOrdenes[[#This Row],[fecha_inicio]],2))) | T44: =IF(tblOrdenes[[#This Row],[tipo_ot]]="","",_xlfn.XLOOKUP(tblOrdenes[[#This Row],[tipo_ot]],tblTiposOT[codigo],tblTiposOT[clasificacion],"sin_clasificar")) | U44: =IF(tblOrdenes[[#This Row],[centro_costo]]="","",_xlfn.XLOOKUP(tblOrdenes[[#This Row],[centro_costo]],tblCECO[codigo],tblCECO[linea],"(sin catálogo)")) | V44: =IF(tblOrdenes[[#This Row],[centro_costo]]="","",_xlfn.XLOOKUP(tblOrdenes[[#This Row],[centro_costo]],tblCECO[codigo],tblCECO[area],"(sin catálogo)")) | W44: =IF(tblOrdenes[[#This Row],[centro_costo]]="","",_xlfn.XLOOKUP(tblOrdenes[[#This Row],[centro_costo]],tblCECO[codigo],tblCECO[coordinador],"(sin catálogo)")) | X44: =IF(tblOrdenes[[#This Row],[puesto_trabajo]]="","",_xlfn.XLOOKUP(tblOrdenes[[#This Row],[puesto_trabajo]],tblPuestos[codigo],tblPuestos[especialidad],"(sin catálogo)")) | Y44: =IF(tblOrdenes[[#This Row],[cod_actividad]]="","",_xlfn.XLOOKUP(tblOrdenes[[#This Row],[cod_actividad]],tblActividades[codigo],tblActividades[descripcion],"(sin catálogo)")) | Z44: =IF(tblOrdenes[[#This Row],[fecha_inicio]]="","",TODAY()-tblOrdenes[[#This Row],[fecha_inicio]]) | AA44: =IF(tblOrdenes[[#This Row],[backlog_dias]]="","",IF(tblOrdenes[[#This Row],[backlog_dias]]<0,"FUTURO",IF(tblOrdenes[[#This Row],[backlog_dias]]>p_dias_backlog_max,"BACKLOG","MES CORRIENTE"))) | AB44: =IF(tblOrdenes[[#This Row],[backlog_dias]]="",FALSE,AND(tblOrdenes[[#This Row],[backlog_dias]]>p_dias_backlog_min,tblOrdenes[[#This Row],[backlog_dias]]<=p_dias_backlog_max)) | AC44: Técnico 01 | AD44: =IF(tblOrdenes[[#This Row],[tecnico_asignado]]="","",_xlfn.XLOOKUP(tblOrdenes[[#This Row],[semana]]&"|"&tblOrdenes[[#This Row],[dia_semana]]&"|"&tblOrdenes[[#This Row],[tecnico_asignado]],tblAsignaciones[clave],tblAsignaciones[turno],"")) | AE44: =IF(tblOrdenes[[#This Row],[tecnico_asignado]]="","",SUMIFS(tblOrdenes[horas_efectivas],tblOrdenes[tecnico_asignado],tblOrdenes[[#This Row],[tecnico_asignado]],tblOrdenes[semana],tblOrdenes[[#This Row],[semana]],tblOrdenes[dia_semana],tblOrdenes[[#This Row],[dia_semana]])) | AF44: =IF(tblOrdenes[[#This Row],[HHA]]="","",p_factor_productividad*_xlfn.XLOOKUP(tblOrdenes[[#This Row],[semana]]&"|"&tblOrdenes[[#This Row],[dia_semana]]&"|"&tblOrdenes[[#This Row],[tecnico_asignado]],tblAsignaciones[clave],tblAsignaciones[horas_disponibles],0)-tblOrdenes[[#This Row],[HHA]]) | AG44: =IF(tblOrdenes[[#This Row],[orden]]="","",_xlfn.XLOOKUP(tblOrdenes[[#This Row],[id_operacion]],tblEjecucion[id_operacion],tblEjecucion[precio],0)) | AH44: =IF(tblOrdenes[[#This Row],[orden]]="","",MAX(0,_xlfn.XLOOKUP(tblOrdenes[[#This Row],[id_operacion]],tblEjecucion[id_operacion],tblEjecucion[costo_plan_total],0)-tblOrdenes[[#This Row],[costo_servicio]])) | AI44: =IF(tblOrdenes[[#This Row],[orden]]="","",tblOrdenes[[#This Row],[costo_servicio]]+tblOrdenes[[#This Row],[costo_materiales]]) | AL44: ACT-04.pdf | AM44: =IF(tblOrdenes[[#This Row],[link_checklist]]="","",HYPERLINK(p_ruta_base_checklists&tblOrdenes[[#This Row],[link_checklist]],"abrir")) | AO44: =IF(tblOrdenes[[#This Row],[orden]]="","",tblOrdenes[[#This Row],[orden]]&IF(tblOrdenes[[#This Row],[operacion]]="","0010",tblOrdenes[[#This Row],[operacion]]))
A45: OT-000042 | B45: 0010 | C45: Inspección de rutina — EQ-110 | D45: Inspección de rutina en EQ-110 | E45: EQ-110 | F45: CC-310 | G45: PU-MEC | H45: ACT-01 | I45: TIPO-P1 | J45: 46238 | K45: 8 | L45: 200 | N45: =IF(tblOrdenes[[#This Row],[orden]]="","",IF(tblOrdenes[[#This Row],[horas_ajustadas]]<>"",tblOrdenes[[#This Row],[horas_ajustadas]],IF(tblOrdenes[[#This Row],[horas_estimadas]]="","",tblOrdenes[[#This Row],[horas_estimadas]]))) | O45: =IF(tblOrdenes[[#This Row],[orden]]="","",_xlfn.XLOOKUP(_xlfn.XLOOKUP(tblOrdenes[[#This Row],[id_operacion]],tblEjecucion[id_operacion],tblEjecucion[estado_sistema],""),tblEstados[estado_sistema],tblEstados[estado_normalizado],"Pendiente")) | P45: =IF(tblOrdenes[[#This Row],[fecha_inicio]]="","",YEAR(tblOrdenes[[#This Row],[fecha_inicio]]+4-WEEKDAY(tblOrdenes[[#This Row],[fecha_inicio]],2))&"-S"&TEXT(_xlfn.ISOWEEKNUM(tblOrdenes[[#This Row],[fecha_inicio]]),"00")) | Q45: =IF(tblOrdenes[[#This Row],[fecha_inicio]]="","",YEAR(tblOrdenes[[#This Row],[fecha_inicio]])) | R45: =IF(tblOrdenes[[#This Row],[fecha_inicio]]="","",MONTH(tblOrdenes[[#This Row],[fecha_inicio]])) | S45: =IF(tblOrdenes[[#This Row],[fecha_inicio]]="","",INDEX(lista_dias,WEEKDAY(tblOrdenes[[#This Row],[fecha_inicio]],2))) | T45: =IF(tblOrdenes[[#This Row],[tipo_ot]]="","",_xlfn.XLOOKUP(tblOrdenes[[#This Row],[tipo_ot]],tblTiposOT[codigo],tblTiposOT[clasificacion],"sin_clasificar")) | U45: =IF(tblOrdenes[[#This Row],[centro_costo]]="","",_xlfn.XLOOKUP(tblOrdenes[[#This Row],[centro_costo]],tblCECO[codigo],tblCECO[linea],"(sin catálogo)")) | V45: =IF(tblOrdenes[[#This Row],[centro_costo]]="","",_xlfn.XLOOKUP(tblOrdenes[[#This Row],[centro_costo]],tblCECO[codigo],tblCECO[area],"(sin catálogo)")) | W45: =IF(tblOrdenes[[#This Row],[centro_costo]]="","",_xlfn.XLOOKUP(tblOrdenes[[#This Row],[centro_costo]],tblCECO[codigo],tblCECO[coordinador],"(sin catálogo)")) | X45: =IF(tblOrdenes[[#This Row],[puesto_trabajo]]="","",_xlfn.XLOOKUP(tblOrdenes[[#This Row],[puesto_trabajo]],tblPuestos[codigo],tblPuestos[especialidad],"(sin catálogo)")) | Y45: =IF(tblOrdenes[[#This Row],[cod_actividad]]="","",_xlfn.XLOOKUP(tblOrdenes[[#This Row],[cod_actividad]],tblActividades[codigo],tblActividades[descripcion],"(sin catálogo)")) | Z45: =IF(tblOrdenes[[#This Row],[fecha_inicio]]="","",TODAY()-tblOrdenes[[#This Row],[fecha_inicio]]) | AA45: =IF(tblOrdenes[[#This Row],[backlog_dias]]="","",IF(tblOrdenes[[#This Row],[backlog_dias]]<0,"FUTURO",IF(tblOrdenes[[#This Row],[backlog_dias]]>p_dias_backlog_max,"BACKLOG","MES CORRIENTE"))) | AB45: =IF(tblOrdenes[[#This Row],[backlog_dias]]="",FALSE,AND(tblOrdenes[[#This Row],[backlog_dias]]>p_dias_backlog_min,tblOrdenes[[#This Row],[backlog_dias]]<=p_dias_backlog_max)) | AC45: Técnico 02 | AD45: =IF(tblOrdenes[[#This Row],[tecnico_asignado]]="","",_xlfn.XLOOKUP(tblOrdenes[[#This Row],[semana]]&"|"&tblOrdenes[[#This Row],[dia_semana]]&"|"&tblOrdenes[[#This Row],[tecnico_asignado]],tblAsignaciones[clave],tblAsignaciones[turno],"")) | AE45: =IF(tblOrdenes[[#This Row],[tecnico_asignado]]="","",SUMIFS(tblOrdenes[horas_efectivas],tblOrdenes[tecnico_asignado],tblOrdenes[[#This Row],[tecnico_asignado]],tblOrdenes[semana],tblOrdenes[[#This Row],[semana]],tblOrdenes[dia_semana],tblOrdenes[[#This Row],[dia_semana]])) | AF45: =IF(tblOrdenes[[#This Row],[HHA]]="","",p_factor_productividad*_xlfn.XLOOKUP(tblOrdenes[[#This Row],[semana]]&"|"&tblOrdenes[[#This Row],[dia_semana]]&"|"&tblOrdenes[[#This Row],[tecnico_asignado]],tblAsignaciones[clave],tblAsignaciones[horas_disponibles],0)-tblOrdenes[[#This Row],[HHA]]) | AG45: =IF(tblOrdenes[[#This Row],[orden]]="","",_xlfn.XLOOKUP(tblOrdenes[[#This Row],[id_operacion]],tblEjecucion[id_operacion],tblEjecucion[precio],0)) | AH45: =IF(tblOrdenes[[#This Row],[orden]]="","",MAX(0,_xlfn.XLOOKUP(tblOrdenes[[#This Row],[id_operacion]],tblEjecucion[id_operacion],tblEjecucion[costo_plan_total],0)-tblOrdenes[[#This Row],[costo_servicio]])) | AI45: =IF(tblOrdenes[[#This Row],[orden]]="","",tblOrdenes[[#This Row],[costo_servicio]]+tblOrdenes[[#This Row],[costo_materiales]]) | AL45: ACT-01.pdf | AM45: =IF(tblOrdenes[[#This Row],[link_checklist]]="","",HYPERLINK(p_ruta_base_checklists&tblOrdenes[[#This Row],[link_checklist]],"abrir")) | AO45: =IF(tblOrdenes[[#This Row],[orden]]="","",tblOrdenes[[#This Row],[orden]]&IF(tblOrdenes[[#This Row],[operacion]]="","0010",tblOrdenes[[#This Row],[operacion]]))
